Workbook

Sheet Data
A1: =((1200000/30)*14)+1200000 -> 1760000 | B1: =12/30 -> 0.4 | C1: =10/31 -> 0.32258065 | D1: 2 | E1: 3 | G1: 5 | H1: 6 | I1: 7 | J1: 8 | K1: 9 | L1: 10 | M1: 11 | N1: 12 | O1: 13 | P1: 14 | Q1: 15 | R1: 16 | S1: 17 | T1: 18 | U1: 19 | V1: 20 | W1: 21 | X1: 22 | Y1: 23 | Z1: 24 | AA1: 25 | AB1: 26 | AC1: 27 | AD1: 28 | AE1: 29 | AF1: 30 | AG1: 31 | AH1: 32 | AI1: 33 | AJ1: 34 | AK1: 35 | AL1: 36 | AM1: 37 | AN1: 38 | AO1: 39 | AP1: 39 | AQ1: 41 | AR1: 42 | AS1: 43 | AT1: 44 | AU1: 45 | AY1: 46 | AZ1: 47 | BB1: 45747 | BD1: Salary month / target count | BI1: =BE160*3 -> #VALUE! | BO1: Order Booking 2024-2025 | CM1: =COUNTIF(CM3:CM243,">0") -> 26 | CQ1: =SUM(CQ3:CQ29) -> 148 | CR1: =SUM(CR3:CR29) -> 12
A2: State Head | B2: State | C2: Name | D2: Working State | E2: Headquarter | F2: D.O.J | G2: Primary Target | H2: Target | I2: Achievement | J2: Direct Dealers order | K2: Total Old Retailers | L2: Visited in a Month | M2: New Retailers | N2: Total Retailers | O2: Non Visited Retailers | P2: Old Party Business Order Booking | Q2: New Party Order Booking | R2: Business Achived By No. of Old Parties | S2: Business Achived By No. of New Parties | T2: Business Achieved By | U2: Business Achieved By Direct Dealer | V2: Total Lead Counters | W2: Total Lead Visits | X2: Total Non Lead Visits | Y2: Distributor Counter | Z2: Distributor Visits | AA2: Direct Dealer Counter | AB2: Direct Dealer Visits | AC2: Distributor/Direct Dealer Lead Counter | AD2: Distributor/Direct Dealer Lead Visits | AE2: Active Parties Visits | AF2: Total Visits | AG2: Working Days | AH2: Average Sales Per Day | AI2: Average Visit Per Day | AJ2: CTC Monthly | AK2: CTC | AL2: T.A. Bill ST. Cost | AM2: Cost Ratio (%) | AN2: Business Per Retailer | AO2: Target Achievement (%) | AP2: Direct Dealer/Primary target achievement (%) | AQ2: No of Orders | AR2: Total Working Hours | AS2: Total GPS KM | AT2: New Party Orders | AU2: Avg Distance (KM) | AV2: Business Received Parties Visits | AW2: Visited But No Business Received | AX2: No Visit No Business Received | AY2: Sale Report 25-26 | AZ2: Left Date | BA2: Active/ Left | BB2: old new | BC2: Target range | BD2: mar | BE2: Target monthly | BG2: Secondary / Primary | BH2: Sale 24-25 | BI2: Total Order 24-25 | BJ2: days calculation | BK2: Monthy Direct Dealer Primary Target | BL2: Direct Dealer Primary Target | BM2: Total target | BN2: rEMARKS | BO2: q1 | BP2: q2 | BQ2: q3 | BR2: q4 | BS2: Target Achievement (%) (Sale) | BT2: Cost Ratio (%)Sale | BV2: ctc 2025 | BW2: designation | BX2: emp code | CB2: Old | CC2: New | CD2: Left | CE2: Total | CG2: BELOW 60 DEALER | CH2: BUSINESS Achieved 50% AND ABOVE | CJ2: BUSINESS RECEIVED TOTAL VISITS | CK2: VISITED BUT BUSINESS NOT RECEIVED TOTAL VISITS | CL2: PARTIES NOT VISITED | CM2: Varitaion | CN2: Remarks | CO2: State Head | CP2: State | CQ2: Secon | CR2: prima
A3: Sandeep Dadheech | B3: West Bengal | C3: Monmon Paul | D3: WEST BENGAL | E3: KOLKATA | F3: 39859 | G3: 0 | H3: 0 | I3: 1199546.8 | J3: 0 | K3: 194 | L3: 185 | M3: 11 | N3: 205 | O3: 20 | P3: 1199546.8 | Q3: 0 | R3: 12 | S3: 0 | T3: 12 | U3: 0 | V3: 13 | W3: 19 | X3: 75 | Y3: 10 | Z3: 228 | AA3: 1 | AB3: 34 | AC3: 1 | AD3: 16 | AE3: 862 | AF3: 1159 | AG3: 297 | AH3: =IFERROR(SUM(I3:J3)/AG3,"") -> 4038.8782 | AI3: =IFERROR(AF3/AG3,"") -> 3.9023569 | AJ3: 70400 | AK3: =AJ3*BD3 -> 844800 | AL3: 263642 | AM3: =IFERROR(SUM(AK3:AL3)/SUM(I3:J3),"") -> 0.92405063 | AN3: =IFERROR(I3/T3,"") -> 99962.235 | AO3: No Target | AP3: 0 | AQ3: 21 | AR3: 3515 | AS3: 4573.56 | AT3: 0 | AU3: 25 | AV3: 12 | AW3: 173 | AX3: 20 | AY3: =IFERROR(VLOOKUP(C3,#REF!,13,0),"") | BA3: =IF(ISBLANK(AZ3),"Active","LEFT" ) -> Active | BB3: =_xludf.ifs(F3<$BB$1,"Old",F3>$BB$1,"New") -> #NAME? | BC3: No Target | BD3: =MATCH($BD$2,{"Apr","May","Jun","Jul","Aug","Sep","Oct","Nov","Dec","Jan","Feb","Mar"},0) -> 12 | BE3: {=IFERROR(VLOOKUP($C$3:$C243,#REF!,8,0),"")} | BF3: =M3-AT3 -> 11 | BG3: Primary | BH3: =IFERROR(__xludf.DUMMYFUNCTION("iferror(ArrayFormula(VLOOKUP($C$3:$C243,importrange(""1MwNMVzWE3QBVOyJjKr3eFX-Sq1Ng0Q1sghWJbgbE_8g"",""ORDER BOOKING REPORT 2024-25!C:O""),13,0)))"),28690782.84) -> 28690783 | BI3: =IFERROR(__xludf.DUMMYFUNCTION("iferror(ArrayFormula(VLOOKUP($C$3:$C243,importrange(""1MwNMVzWE3QBVOyJjKr3eFX-Sq1Ng0Q1sghWJbgbE_8g"",""ORDER BOOKING REPORT 2024-25!C:O""),11,0)))"),32790753.08) -> 32790753 | BL3: =BK3*BD3 -> 0 | BM3: =H3+BL3 -> 0 | BO3: =IFERROR(__xludf.DUMMYFUNCTION("IFERROR(ArrayFormula(SUM(VLOOKUP($C3,importrange(""1MwNMVzWE3QBVOyJjKr3eFX-Sq1Ng0Q1sghWJbgbE_8g"",""ORDER BOOKING REPORT 2024-25!C:CV""),{16,23,30},0))))"),6963375.6) -> 6963375.6 | BP3: =IFERROR(__xludf.DUMMYFUNCTION("IFERROR(ArrayFormula(SUM(VLOOKUP($C3,importrange(""1MwNMVzWE3QBVOyJjKr3eFX-Sq1Ng0Q1sghWJbgbE_8g"",""ORDER BOOKING REPORT 2024-25!C:CV""),{37,44,51},0))))"),9095913.7) -> 9095913.7 | BQ3: =IFERROR(__xludf.DUMMYFUNCTION("IFERROR(ArrayFormula(SUM(VLOOKUP($C3,importrange(""1MwNMVzWE3QBVOyJjKr3eFX-Sq1Ng0Q1sghWJbgbE_8g"",""ORDER BOOKING REPORT 2024-25!C:CV""),{58,65,72},0))))"),7698254.58) -> 7698254.6 | BR3: =IFERROR(__xludf.DUMMYFUNCTION("IFERROR(ArrayFormula(SUM(VLOOKUP($C3,importrange(""1MwNMVzWE3QBVOyJjKr3eFX-Sq1Ng0Q1sghWJbgbE_8g"",""ORDER BOOKING REPORT 2024-25!C:CV""),{79,86,93},0))))"),9033209.2) -> 9033209.2 | BS3: =IFERROR(AY3/BM3,"") | BT3: =IFERROR(SUM(AK3:AL3)/AY3,"") | BU3: =BL3-G3 -> 0 | BV3: 70400 | BW3: Sr. Area Sales Manager | BX3: 535 | BY3: =BV3-AJ3 -> 0 | CA3: Apr | CB3: =COUNTIF($F:$F, "<=" & DATE(2025,3,30)) -> 170 | CC3: =COUNTIFS(F:F, ">=" & DATE(2025,4,1), F:F, "<=" & DATE(2025,4,30)) -> 4 | CD3: =COUNTIFS(AZ:AZ, ">=" & DATE(2025,4,1), AZ:AZ, "<=" & DATE(2025,4,30)) -> 7 | CE3: =CB3+CC3 -> 174 | CF3: =SUM(CB3:CD3) -> 181 | CG3: =IF(N3<60,"Below 60"," ") | CH3: =IF(T3 = 0, "Not 50%", IF(T3 >= 0.5 * N3, "Business Achieved EXACT 50%", "Not 50%")) -> Not 50% | CI3: =IFERROR((T3/N3),) -> 0.058536585 | CJ3: =IFERROR(__xludf.DUMMYFUNCTION("IFERROR(ArrayFormula(VLOOKUP($C$3:$C243,IMPORTRANGE(""https://docs.google.com/spreadsheets/d/1OkdrCquHuVNXRsEZ16AzawxA5ZUvzmc454rG7C6Xzg0/edit?gid=548125645#gid=548125645"",""Sheet8!B:U""),{6,8,10},0)))"),100) -> 100 | CK3: =IFERROR(__xludf.DUMMYFUNCTION("""COMPUTED_VALUE"""),743) -> 743 | CL3: =IFERROR(__xludf.DUMMYFUNCTION("""COMPUTED_VALUE"""),0) -> 0 | CM3: =AE3-SUM(CJ3:CL3) -> 19 | CN3: =IFERROR(__xludf.DUMMYFUNCTION("IFERROR(ArrayFormula(VLOOKUP($C$3:$C243,IMPORTRANGE(""https://docs.google.com/spreadsheets/d/1OkdrCquHuVNXRsEZ16AzawxA5ZUvzmc454rG7C6Xzg0/edit?gid=548125645#gid=548125645"",""Sheet8!B:U""),20,0)))"),"") | CP3: Andhra Pradesh | CQ3: =COUNTIFS($B:$B,$CP3,$BG:$BG,"Secondary",$BA:$BA,"Active") -> 3 | CR3: =COUNTIFS($B:$B,$CP3,$BG:$BG,"Primary",$BA:$BA,"Active") -> 0 | CS3: {=_xludf.UNIQUE(A3:A243)} -> #NAME? | CT3: =COUNTIFS(A:A,CS3,BA:BA,"Active") -> 0
A4: Sandeep Dadheech | B4: West Bengal | C4: Sujan Ghata | D4: WEST BENGAL | E4: KOLKATA | F4: 39859 | G4: 0 | H4: 60600000 | I4: 41352930 | J4: 0 | K4: 111 | L4: 106 | M4: 13 | N4: 124 | O4: 18 | P4: 36872573 | Q4: 4480356.8 | R4: 85 | S4: 11 | T4: 96 | U4: 0 | V4: 9 | W4: 9 | X4: 79 | Y4: 9 | Z4: 121 | AA4: 0 | AB4: 0 | AC4: 0 | AD4: 0 | AE4: 1023 | AF4: 1153 | AG4: 291 | AH4: =IFERROR(SUM(I4:J4)/AG4,"") -> 142106.29 | AI4: =IFERROR(AF4/AG4,"") -> 3.9621993 | AJ4: 60500 | AK4: =AJ4*BD4 -> 726000 | AL4: 91425 | AM4: =IFERROR(SUM(AK4:AL4)/SUM(I4:J4),"") -> 0.01976704 | AN4: =IFERROR(I4/T4,"") -> 430759.68 | AO4: =IFERROR(SUM(I4:J4)/SUM(G4:H4),"") -> 0.68239158 | AP4: 0 | AQ4: 466 | AR4: 3035 | AS4: 4088.66 | AT4: 11 | AU4: 39 | AV4: 96 | AW4: 19 | AX4: 9 | AY4: =IFERROR(VLOOKUP(C4,#REF!,13,0),"") | BA4: =IF(ISBLANK(AZ4),"Active","LEFT" ) -> Active | BB4: =_xludf.ifs(F4<$BB$1,"Old",F4>$BB$1,"New") -> #NAME? | BC4: =_xludf.ifs(AO4<50%,"Below 50%",AO4<70%,"50%-70%",AO4<90%,"70%-90%",AO4<100%,"90%-100%",AO4>100%,"Above 100%") -> #NAME? | BD4: =MATCH($BD$2,{"Apr","May","Jun","Jul","Aug","Sep","Oct","Nov","Dec","Jan","Feb","Mar"},0) -> 12 | BF4: =M4-AT4 -> 2 | BG4: Secondary | BH4: =IFERROR(__xludf.DUMMYFUNCTION("""COMPUTED_VALUE"""),38475930.54) -> 38475931 | BI4: =IFERROR(__xludf.DUMMYFUNCTION("""COMPUTED_VALUE"""),37705783.88) -> 37705784 | BL4: =BK4*BD4 -> 0 | BM4: =H4+BL4 -> 60600000 | BO4: =IFERROR(__xludf.DUMMYFUNCTION("IFERROR(ArrayFormula(SUM(VLOOKUP($C4,importrange(""1MwNMVzWE3QBVOyJjKr3eFX-Sq1Ng0Q1sghWJbgbE_8g"",""ORDER BOOKING REPORT 2024-25!C:CV""),{16,23,30},0))))"),7373008.92) -> 7373008.9 | BP4: =IFERROR(__xludf.DUMMYFUNCTION("IFERROR(ArrayFormula(SUM(VLOOKUP($C4,importrange(""1MwNMVzWE3QBVOyJjKr3eFX-Sq1Ng0Q1sghWJbgbE_8g"",""ORDER BOOKING REPORT 2024-25!C:CV""),{37,44,51},0))))"),9026880) -> 9026880 | BQ4: =IFERROR(__xludf.DUMMYFUNCTION("IFERROR(ArrayFormula(SUM(VLOOKUP($C4,importrange(""1MwNMVzWE3QBVOyJjKr3eFX-Sq1Ng0Q1sghWJbgbE_8g"",""ORDER BOOKING REPORT 2024-25!C:CV""),{58,65,72},0))))"),8248527.6) -> 8248527.6 | BR4: =IFERROR(__xludf.DUMMYFUNCTION("IFERROR(ArrayFormula(SUM(VLOOKUP($C4,importrange(""1MwNMVzWE3QBVOyJjKr3eFX-Sq1Ng0Q1sghWJbgbE_8g"",""ORDER BOOKING REPORT 2024-25!C:CV""),{79,86,93},0))))"),13057367.36) -> 13057367 | BS4: =IFERROR(AY4/BM4,"") | BT4: =IFERROR(SUM(AK4:AL4)/AY4,"") | BU4: =BL4-G4 -> 0 | BV4: 60500 | BW4: Area Sales Manager | BX4: 536 | BY4: =BV4-AJ4 -> 0 | CA4: May | CB4: =COUNTIF($F:$F, "<=" & DATE(2025,4,30))-COUNTIFS(AZ:AZ, ">=" & DATE(2025,4,1), AZ:AZ, "<=" & DATE(2025,4,30)) -> 167 | CC4: =COUNTIFS(F:F, ">=" & DATE(2025,5,1), F:F, "<=" & DATE(2025,5,31)) -> 9 | CD4: =COUNTIFS(AZ:AZ, ">=" & DATE(2025,5,1), AZ:AZ, "<=" & DATE(2025,5,31)) -> 5 | CE4: =CB4+CC4 -> 176 | CF4: =SUM(CB4:CD4) -> 181 | CG4: =IF(N4<60,"Below 60"," ") | CH4: =IF(T4 = 0, "Not 50%", IF(T4 >= 0.5 * N4, "Business Achieved 50%", "Not 50%")) -> Business Achieved 50% | CI4: =IFERROR((T4/N4),) -> 0.77419355 | CJ4: =IFERROR(__xludf.DUMMYFUNCTION("""COMPUTED_VALUE"""),955) -> 955 | CK4: =IFERROR(__xludf.DUMMYFUNCTION("""COMPUTED_VALUE"""),68) -> 68 | CL4: =IFERROR(__xludf.DUMMYFUNCTION("""COMPUTED_VALUE"""),0) -> 0 | CM4: =AE4-SUM(CJ4:CL4) -> 0 | CP4: Bihar | CQ4: =COUNTIFS($B:$B,$CP4,$BG:$BG,"Secondary",$BA:$BA,"Active") -> 8 | CR4: =COUNTIFS($B:$B,$CP4,$BG:$BG,"Primary",$BA:$BA,"Active") -> 1 | CS4: #NAME? | CT4: =COUNTIFS(A:A,CS4,BA:BA,"Active") -> 0
A5: Syed Aqil Rizvi | B5: East U.P | C5: Rajan Srivastava | D5: East U.P, MADHYA PRADESH | E5: Varanasi | F5: 41004 | G5: 3600000 | H5: 46400004 | I5: 39826983 | J5: 3804037.1 | K5: 59 | L5: 70 | M5: 15 | N5: 74 | O5: 4 | P5: 32519279 | Q5: 7307704 | R5: 41 | S5: 11 | T5: 52 | U5: 8 | V5: 14 | W5: 21 | X5: 19 | Y5: 11 | Z5: 408 | AA5: 9 | AB5: 118 | AC5: 3 | AD5: 6 | AE5: 619 | AF5: 1172 | AG5: 254 | AH5: =IFERROR(SUM(I5:J5)/AG5,"") -> 171775.67 | AI5: =IFERROR(AF5/AG5,"") -> 4.6141732 | AJ5: =BV5 -> 95834 | AK5: =AJ5*BD5 -> 1150008 | AL5: 239916 | AM5: =IFERROR(SUM(AK5:AL5)/SUM(I5:J5),"") -> 0.031856326 | AN5: =IFERROR(I5/T5,"") -> 765903.53 | AO5: =IFERROR(SUM(I5:J5)/SUM(G5:H5),"") -> 0.87262034 | AP5: 1.06 | AQ5: 578 | AR5: 1986 | AS5: 2254.73 | AT5: 11 | AU5: 32 | AV5: 52 | AW5: 18 | AX5: 4 | AY5: =IFERROR(VLOOKUP(C5,#REF!,13,0),"") | BA5: =IF(ISBLANK(AZ5),"Active","LEFT" ) -> Active | BB5: =_xludf.ifs(F5<$BB$1,"Old",F5>$BB$1,"New") -> #NAME? | BC5: =_xludf.ifs(AO5<50%,"Below 50%",AO5<70%,"50%-70%",AO5<90%,"70%-90%",AO5<100%,"90%-100%",AO5>100%,"Above 100%") -> #NAME? | BD5: =MATCH($BD$2,{"Apr","May","Jun","Jul","Aug","Sep","Oct","Nov","Dec","Jan","Feb","Mar"},0) -> 12 | BF5: =M5-AT5 -> 4 | BG5: Secondary | BH5: =IFERROR(__xludf.DUMMYFUNCTION("""COMPUTED_VALUE"""),45381670) -> 45381670 | BI5: =IFERROR(__xludf.DUMMYFUNCTION("""COMPUTED_VALUE"""),44623264.94) -> 44623265 | BK5: 300000 | BL5: =BK5*BD5 -> 3600000 | BM5: =H5+BL5 -> 50000004 | BO5: =IFERROR(__xludf.DUMMYFUNCTION("IFERROR(ArrayFormula(SUM(VLOOKUP($C5,importrange(""1MwNMVzWE3QBVOyJjKr3eFX-Sq1Ng0Q1sghWJbgbE_8g"",""ORDER BOOKING REPORT 2024-25!C:CV""),{16,23,30},0))))"),13609862.56) -> 13609863 | BP5: =IFERROR(__xludf.DUMMYFUNCTION("IFERROR(ArrayFormula(SUM(VLOOKUP($C5,importrange(""1MwNMVzWE3QBVOyJjKr3eFX-Sq1Ng0Q1sghWJbgbE_8g"",""ORDER BOOKING REPORT 2024-25!C:CV""),{37,44,51},0))))"),7145309.5) -> 7145309.5 | BQ5: =IFERROR(__xludf.DUMMYFUNCTION("IFERROR(ArrayFormula(SUM(VLOOKUP($C5,importrange(""1MwNMVzWE3QBVOyJjKr3eFX-Sq1Ng0Q1sghWJbgbE_8g"",""ORDER BOOKING REPORT 2024-25!C:CV""),{58,65,72},0))))"),11508289.34) -> 11508289 | BR5: =IFERROR(__xludf.DUMMYFUNCTION("IFERROR(ArrayFormula(SUM(VLOOKUP($C5,importrange(""1MwNMVzWE3QBVOyJjKr3eFX-Sq1Ng0Q1sghWJbgbE_8g"",""ORDER BOOKING REPORT 2024-25!C:CV""),{79,86,93},0))))"),12359803.54) -> 12359804 | BS5: =IFERROR(AY5/BM5,"") | BT5: =IFERROR(SUM(AK5:AL5)/AY5,"") | BU5: =BL5-G5 -> 0 | BV5: 95834 | BW5: Regional Sales Manager | BX5: 15 | BY5: =BV5-AJ5 -> 0 | CA5: Jun | CB5: =COUNTIF($F:$F, "<=" & DATE(2025,5,31))-COUNTIFS(AZ:AZ, ">=" & DATE(2025,4,1), AZ:AZ, "<=" & DATE(2025,5,31)) -> 171 | CC5: =COUNTIFS(F:F, ">=" & DATE(2025,6,1), F:F, "<=" & DATE(2025,6,30)) -> 9 | CD5: =COUNTIFS(AZ:AZ, ">=" & DATE(2025,6,1), AZ:AZ, "<=" & DATE(2025,6,30)) -> 4 | CE5: =CB5+CC5 -> 180 | CF5: =SUM(CB5:CD5) -> 184 | CG5: =IF(N5<60,"Below 60"," ") | CH5: =IF(T5 = 0, "Not 50%", IF(T5 >= 0.5 * N5, "Business Achieved 50%", "Not 50%")) -> Business Achieved 50% | CI5: =IFERROR((T5/N5),) -> 0.7027027 | CJ5: =IFERROR(__xludf.DUMMYFUNCTION("""COMPUTED_VALUE"""),590) -> 590 | CK5: =IFERROR(__xludf.DUMMYFUNCTION("""COMPUTED_VALUE"""),28) -> 28 | CL5: =IFERROR(__xludf.DUMMYFUNCTION("""COMPUTED_VALUE"""),0) -> 0 | CM5: =AE5-SUM(CJ5:CL5) -> 1 | CN5: =IFERROR(__xludf.DUMMYFUNCTION("""COMPUTED_VALUE"""),"Retailer Convert as a direct dealer") -> Retailer Convert as a direct dealer | CP5: Chattisgarh | CQ5: =COUNTIFS($B:$B,$CP5,$BG:$BG,"Secondary",$BA:$BA,"Active") -> 2 | CR5: =COUNTIFS($B:$B,$CP5,$BG:$BG,"Primary",$BA:$BA,"Active") -> 0 | CS5: #NAME? | CT5: =COUNTIFS(A:A,CS5,BA:BA,"Active") -> 0
A6: Sandeep Dadheech | B6: West Bengal | C6: Surojit Mondal | D6: WEST BENGAL | E6: ANDAL | F6: 41159 | G6: 0 | H6: 81999996 | I6: 34910047 | J6: 0 | K6: 149 | L6: 143 | M6: 4 | N6: 153 | O6: 10 | P6: 33231270 | Q6: 1678777.6 | R6: 78 | S6: 3 | T6: 81 | U6: 0 | V6: 51 | W6: 124 | X6: 22 | Y6: 3 | Z6: 37 | AA6: 0 | AB6: 0 | AC6: 0 | AD6: 0 | AE6: 1386 | AF6: 1547 | AG6: 301 | AH6: =IFERROR(SUM(I6:J6)/AG6,"") -> 115980.22 | AI6: =IFERROR(AF6/AG6,"") -> 5.1395349 | AJ6: 78125 | AK6: =AJ6*BD6 -> 937500 | AL6: 243987 | AM6: =IFERROR(SUM(AK6:AL6)/SUM(I6:J6),"") -> 0.033843752 | AN6: =IFERROR(I6/T6,"") -> 430988.24 | AO6: =IFERROR(SUM(I6:J6)/SUM(G6:H6),"") -> 0.42573231 | AP6: 0 | AQ6: 306 | AR6: 3433 | AS6: 1481.26 | AT6: 3 | AU6: 10 | AV6: 81 | AW6: 62 | AX6: 10 | AY6: =IFERROR(VLOOKUP(C6,#REF!,13,0),"") | BA6: =IF(ISBLANK(AZ6),"Active","LEFT" ) -> Active | BB6: =_xludf.ifs(F6<$BB$1,"Old",F6>$BB$1,"New") -> #NAME? | BC6: =_xludf.ifs(AO6<50%,"Below 50%",AO6<70%,"50%-70%",AO6<90%,"70%-90%",AO6<100%,"90%-100%",AO6>100%,"Above 100%") -> #NAME? | BD6: =MATCH($BD$2,{"Apr","May","Jun","Jul","Aug","Sep","Oct","Nov","Dec","Jan","Feb","Mar"},0) -> 12 | BF6: =M6-AT6 -> 1 | BG6: Secondary | BH6: =IFERROR(__xludf.DUMMYFUNCTION("""COMPUTED_VALUE"""),63090460) -> 63090460 | BI6: =IFERROR(__xludf.DUMMYFUNCTION("""COMPUTED_VALUE"""),63695685.6) -> 63695686 | BL6: =BK6*BD6 -> 0 | BM6: =H6+BL6 -> 81999996 | BO6: =IFERROR(__xludf.DUMMYFUNCTION("IFERROR(ArrayFormula(SUM(VLOOKUP($C6,importrange(""1MwNMVzWE3QBVOyJjKr3eFX-Sq1Ng0Q1sghWJbgbE_8g"",""ORDER BOOKING REPORT 2024-25!C:CV""),{16,23,30},0))))"),15537153.4) -> 15537153 | BP6: =IFERROR(__xludf.DUMMYFUNCTION("IFERROR(ArrayFormula(SUM(VLOOKUP($C6,importrange(""1MwNMVzWE3QBVOyJjKr3eFX-Sq1Ng0Q1sghWJbgbE_8g"",""ORDER BOOKING REPORT 2024-25!C:CV""),{37,44,51},0))))"),13951117.7) -> 13951118 | BQ6: =IFERROR(__xludf.DUMMYFUNCTION("IFERROR(ArrayFormula(SUM(VLOOKUP($C6,importrange(""1MwNMVzWE3QBVOyJjKr3eFX-Sq1Ng0Q1sghWJbgbE_8g"",""ORDER BOOKING REPORT 2024-25!C:CV""),{58,65,72},0))))"),18425749.8) -> 18425750 | BR6: =IFERROR(__xludf.DUMMYFUNCTION("IFERROR(ArrayFormula(SUM(VLOOKUP($C6,importrange(""1MwNMVzWE3QBVOyJjKr3eFX-Sq1Ng0Q1sghWJbgbE_8g"",""ORDER BOOKING REPORT 2024-25!C:CV""),{79,86,93},0))))"),15781664.7) -> 15781665 | BS6: =IFERROR(AY6/BM6,"") | BT6: =IFERROR(SUM(AK6:AL6)/AY6,"") | BU6: =BL6-G6 -> 0 | BV6: 78125 | BW6: Area Sales Manager | BX6: 33 | BY6: =BV6-AJ6 -> 0 | CA6: Jul | CB6: =COUNTIF($F:$F, "<=" & DATE(2025,6,30))-COUNTIFS(AZ:AZ, ">=" & DATE(2025,4,1), AZ:AZ, "<=" & DATE(2025,6,30)) -> 176 | CC6: =COUNTIFS(F:F, ">=" & DATE(2025,7,1), F:F, "<=" & DATE(2025,7,31)) -> 12 | CD6: =COUNTIFS(AZ:AZ, ">=" & DATE(2025,7,1), AZ:AZ, "<=" & DATE(2025,7,31)) -> 9 | CE6: =CB6+CC6 -> 188 | CF6: =SUM(CB6:CD6) -> 197 | CG6: =IF(N6<60,"Below 60"," ") | CH6: =IF(T6 = 0, "Not 50%", IF(T6 >= 0.5 * N6, "Business Achieved 50%", "Not 50%")) -> Business Achieved 50% | CI6: =IFERROR((T6/N6),) -> 0.52941176 | CJ6: =IFERROR(__xludf.DUMMYFUNCTION("""COMPUTED_VALUE"""),991) -> 991 | CK6: =IFERROR(__xludf.DUMMYFUNCTION("""COMPUTED_VALUE"""),395) -> 395 | CL6: =IFERROR(__xludf.DUMMYFUNCTION("""COMPUTED_VALUE"""),0) -> 0 | CM6: =AE6-SUM(CJ6:CL6) -> 0 | CP6: Delhi | CQ6: =COUNTIFS($B:$B,$CP6,$BG:$BG,"Secondary",$BA:$BA,"Active") -> 2 | CR6: =COUNTIFS($B:$B,$CP6,$BG:$BG,"Primary",$BA:$BA,"Active") -> 0 | CS6: #NAME? | CT6: =COUNTIFS(A:A,CS6,BA:BA,"Active") -> 0
A7: Sandeep Dadheech | B7: West Bengal | C7: Suven Sengupta | D7: WEST BENGAL | E7: KOLKATA | F7: 41400 | G7: 0 | H7: 102000000 | I7: 61300488 | J7: 0 | K7: 54 | L7: 53 | M7: 4 | N7: 58 | O7: 5 | P7: 61245045 | Q7: 55443 | R7: 47 | S7: 2 | T7: 49 | U7: 0 | V7: 2 | W7: 4 | X7: 17 | Y7: 3 | Z7: 174 | AA7: 0 | AB7: 0 | AC7: 0 | AD7: 0 | AE7: 1633 | AF7: 1811 | AG7: 245 | AH7: =IFERROR(SUM(I7:J7)/AG7,"") -> 250206.07 | AI7: =IFERROR(AF7/AG7,"") -> 7.3918367 | AJ7: 83075 | AK7: =AJ7*BD7 -> 996900 | AL7: 72733 | AM7: =IFERROR(SUM(AK7:AL7)/SUM(I7:J7),"") -> 0.017449013 | AN7: =IFERROR(I7/T7,"") -> 1251030.4 | AO7: =IFERROR(SUM(I7:J7)/SUM(G7:H7),"") -> 0.60098517 | AP7: 0 | AQ7: 1005 | AR7: 2357 | AS7: 807.74 | AT7: 2 | AU7: 15 | AV7: 49 | AW7: 6 | AX7: 3 | AY7: =IFERROR(VLOOKUP(C7,#REF!,13,0),"") | BA7: =IF(ISBLANK(AZ7),"Active","LEFT" ) -> Active | BB7: =_xludf.ifs(F7<$BB$1,"Old",F7>$BB$1,"New") -> #NAME? | BC7: =_xludf.ifs(AO7<50%,"Below 50%",AO7<70%,"50%-70%",AO7<90%,"70%-90%",AO7<100%,"90%-100%",AO7>100%,"Above 100%") -> #NAME? | BD7: =MATCH($BD$2,{"Apr","May","Jun","Jul","Aug","Sep","Oct","Nov","Dec","Jan","Feb","Mar"},0) -> 12 | BF7: =M7-AT7 -> 2 | BG7: Secondary | BH7: =IFERROR(__xludf.DUMMYFUNCTION("""COMPUTED_VALUE"""),67969652.42) -> 67969652 | BI7: =IFERROR(__xludf.DUMMYFUNCTION("""COMPUTED_VALUE"""),66863516.29) -> 66863516 | BL7: =BK7*BD7 -> 0 | BM7: =H7+BL7 -> 102000000 | BO7: =IFERROR(__xludf.DUMMYFUNCTION("IFERROR(ArrayFormula(SUM(VLOOKUP($C7,importrange(""1MwNMVzWE3QBVOyJjKr3eFX-Sq1Ng0Q1sghWJbgbE_8g"",""ORDER BOOKING REPORT 2024-25!C:CV""),{16,23,30},0))))"),13545550.98) -> 13545551 | BP7: =IFERROR(__xludf.DUMMYFUNCTION("IFERROR(ArrayFormula(SUM(VLOOKUP($C7,importrange(""1MwNMVzWE3QBVOyJjKr3eFX-Sq1Ng0Q1sghWJbgbE_8g"",""ORDER BOOKING REPORT 2024-25!C:CV""),{37,44,51},0))))"),15540769.1399999) -> 15540769 | BQ7: =IFERROR(__xludf.DUMMYFUNCTION("IFERROR(ArrayFormula(SUM(VLOOKUP($C7,importrange(""1MwNMVzWE3QBVOyJjKr3eFX-Sq1Ng0Q1sghWJbgbE_8g"",""ORDER BOOKING REPORT 2024-25!C:CV""),{58,65,72},0))))"),15171394.53) -> 15171395 | BR7: =IFERROR(__xludf.DUMMYFUNCTION("IFERROR(ArrayFormula(SUM(VLOOKUP($C7,importrange(""1MwNMVzWE3QBVOyJjKr3eFX-Sq1Ng0Q1sghWJbgbE_8g"",""ORDER BOOKING REPORT 2024-25!C:CV""),{79,86,93},0))))"),22605801.64) -> 22605802 | BS7: =IFERROR(AY7/BM7,"") | BT7: =IFERROR(SUM(AK7:AL7)/AY7,"") | BU7: =BL7-G7 -> 0 | BV7: 83075 | BW7: Area Sales Manager | BX7: 82 | BY7: =BV7-AJ7 -> 0 | CA7: Aug | CB7: =COUNTIF($F:$F, "<=" & DATE(2025,7,31))-COUNTIFS(AZ:AZ, ">=" & DATE(2025,4,1), AZ:AZ, "<=" & DATE(2025,7,31)) -> 179 | CC7: =COUNTIFS(F:F, ">=" & DATE(2025,8,1), F:F, "<=" & DATE(2025,8,31)) -> 6 | CD7: =COUNTIFS(AZ:AZ, ">=" & DATE(2025,8,1), AZ:AZ, "<=" & DATE(2025,8,31)) -> 12 | CE7: =CB7+CC7 -> 185 | CF7: =SUM(CB7:CD7) -> 197 | CG7: =IF(N7<60,"Below 60"," ") -> Below 60 | CH7: =IF(T7 = 0, "Not 50%", IF(T7 >= 0.5 * N7, "Business Achieved 50%", "Not 50%")) -> Business Achieved 50% | CI7: =IFERROR((T7/N7),) -> 0.84482759 | CJ7: =IFERROR(__xludf.DUMMYFUNCTION("""COMPUTED_VALUE"""),1620) -> 1620 | CK7: =IFERROR(__xludf.DUMMYFUNCTION("""COMPUTED_VALUE"""),13) -> 13 | CL7: =IFERROR(__xludf.DUMMYFUNCTION("""COMPUTED_VALUE"""),0) -> 0 | CM7: =AE7-SUM(CJ7:CL7) -> 0 | CP7: Delhi NCR | CQ7: =COUNTIFS($B:$B,$CP7,$BG:$BG,"Secondary",$BA:$BA,"Active") -> 1 | CR7: =COUNTIFS($B:$B,$CP7,$BG:$BG,"Primary",$BA:$BA,"Active") -> 0 | CS7: #NAME? | CT7: =COUNTIFS(A:A,CS7,BA:BA,"Active") -> 0
A8: Sandeep Dadheech | B8: Odisha | C8: Kailash Ch. Ghadei | D8: ODISHA | E8: CUTTACK | F8: 41563 | G8: 0 | H8: 25200000 | I8: 22853663 | J8: 0 | K8: 38 | L8: 39 | M8: 2 | N8: 40 | O8: 1 | P8: 22820007 | Q8: 33656 | R8: 26 | S8: 1 | T8: 27 | U8: 0 | V8: 3 | W8: 6 | X8: 30 | Y8: 1 | Z8: 17 | AA8: 0 | AB8: 0 | AC8: 0 | AD8: 0 | AE8: 821 | AF8: 844 | AG8: 292 | AH8: =IFERROR(SUM(I8:J8)/AG8,"") -> 78265.969 | AI8: =IFERROR(AF8/AG8,"") -> 2.890411 | AJ8: 48500 | AK8: =AJ8*BD8 -> 582000 | AL8: 225701 | AM8: =IFERROR(SUM(AK8:AL8)/SUM(I8:J8),"") -> 0.035342299 | AN8: =IFERROR(I8/T8,"") -> 846431.96 | AO8: =IFERROR(SUM(I8:J8)/SUM(G8:H8),"") -> 0.90689139 | AP8: 0 | AQ8: 314 | AR8: 3477 | AS8: 3895.5 | AT8: 1 | AU8: 100 | AV8: 27 | AW8: 12 | AX8: 1 | AY8: =IFERROR(VLOOKUP(C8,#REF!,13,0),"") | BA8: =IF(ISBLANK(AZ8),"Active","LEFT" ) -> Active | BB8: =_xludf.ifs(F8<$BB$1,"Old",F8>$BB$1,"New") -> #NAME? | BC8: =_xludf.ifs(AO8<50%,"Below 50%",AO8<70%,"50%-70%",AO8<90%,"70%-90%",AO8<100%,"90%-100%",AO8>100%,"Above 100%") -> #NAME? | BD8: =MATCH($BD$2,{"Apr","May","Jun","Jul","Aug","Sep","Oct","Nov","Dec","Jan","Feb","Mar"},0) -> 12 | BF8: =M8-AT8 -> 1 | BG8: Secondary | BH8: =IFERROR(__xludf.DUMMYFUNCTION("""COMPUTED_VALUE"""),17275853.09) -> 17275853 | BI8: =IFERROR(__xludf.DUMMYFUNCTION("""COMPUTED_VALUE"""),19757187.56) -> 19757188 | BL8: =BK8*BD8 -> 0 | BM8: =H8+BL8 -> 25200000 | BO8: =IFERROR(__xludf.DUMMYFUNCTION("IFERROR(ArrayFormula(SUM(VLOOKUP($C8,importrange(""1MwNMVzWE3QBVOyJjKr3eFX-Sq1Ng0Q1sghWJbgbE_8g"",""ORDER BOOKING REPORT 2024-25!C:CV""),{16,23,30},0))))"),4426946.2) -> 4426946.2 | BP8: =IFERROR(__xludf.DUMMYFUNCTION("IFERROR(ArrayFormula(SUM(VLOOKUP($C8,importrange(""1MwNMVzWE3QBVOyJjKr3eFX-Sq1Ng0Q1sghWJbgbE_8g"",""ORDER BOOKING REPORT 2024-25!C:CV""),{37,44,51},0))))"),4924133.03999999) -> 4924133 | BQ8: =IFERROR(__xludf.DUMMYFUNCTION("IFERROR(ArrayFormula(SUM(VLOOKUP($C8,importrange(""1MwNMVzWE3QBVOyJjKr3eFX-Sq1Ng0Q1sghWJbgbE_8g"",""ORDER BOOKING REPORT 2024-25!C:CV""),{58,65,72},0))))"),4739381.66) -> 4739381.7 | BR8: =IFERROR(__xludf.DUMMYFUNCTION("IFERROR(ArrayFormula(SUM(VLOOKUP($C8,importrange(""1MwNMVzWE3QBVOyJjKr3eFX-Sq1Ng0Q1sghWJbgbE_8g"",""ORDER BOOKING REPORT 2024-25!C:CV""),{79,86,93},0))))"),5666726.66) -> 5666726.7 | BS8: =IFERROR(AY8/BM8,"") | BT8: =IFERROR(SUM(AK8:AL8)/AY8,"") | BU8: =BL8-G8 -> 0 | BV8: 48500 | BW8: Sr. Executive - Sales & Mktg. | BX8: 111 | BY8: =BV8-AJ8 -> 0 | CA8: Sep | CB8: =COUNTIF($F:$F, "<=" & DATE(2025,8,31))-COUNTIFS(AZ:AZ, ">=" & DATE(2025,4,1), AZ:AZ, "<=" & DATE(2025,8,31)) -> 173 | CC8: =COUNTIFS(F:F, ">=" & DATE(2025,9,1), F:F, "<=" & DATE(2025,9,30)) -> 3 | CD8: =COUNTIFS(AZ:AZ, ">=" & DATE(2025,9,1), AZ:AZ, "<=" & DATE(2025,9,30)) -> 7 | CE8: =CB8+CC8 -> 176 | CF8: =SUM(CB8:CD8) -> 183 | CG8: =IF(N8<60,"Below 60"," ") -> Below 60 | CH8: =IF(T8 = 0, "Not 50%", IF(T8 >= 0.5 * N8, "Business Achieved 50%", "Not 50%")) -> Business Achieved 50% | CI8: =IFERROR((T8/N8),) -> 0.675 | CJ8: =IFERROR(__xludf.DUMMYFUNCTION("""COMPUTED_VALUE"""),654) -> 654 | CK8: =IFERROR(__xludf.DUMMYFUNCTION("""COMPUTED_VALUE"""),167) -> 167 | CL8: =IFERROR(__xludf.DUMMYFUNCTION("""COMPUTED_VALUE"""),0) -> 0 | CM8: =AE8-SUM(CJ8:CL8) -> 0 | CP8: East U.P | CQ8: =COUNTIFS($B:$B,$CP8,$BG:$BG,"Secondary",$BA:$BA,"Active") -> 15 | CR8: =COUNTIFS($B:$B,$CP8,$BG:$BG,"Primary",$BA:$BA,"Active") -> 0 | CS8: #NAME? | CT8: =COUNTIFS(A:A,CS8,BA:BA,"Active") -> 0
A9: Sandeep Dadheech | B9: Bihar | C9: Sujeet Singh | D9: BIHAR | E9: Motihari | F9: 41719 | G9: 0 | H9: 0 | I9: 0 | J9: 0 | K9: 167 | L9: 79 | M9: 17 | N9: 184 | O9: 105 | P9: 0 | Q9: 0 | R9: 0 | S9: 0 | T9: 0 | U9: 0 | V9: 62 | W9: 98 | X9: 220 | Y9: 20 | Z9: 263 | AA9: 4 | AB9: 45 | AC9: 9 | AD9: 24 | AE9: 184 | AF9: 614 | AG9: 287 | AH9: =IFERROR(SUM(I9:J9)/AG9,"") -> 0 | AI9: =IFERROR(AF9/AG9,"") -> 2.1393728 | AJ9: 88170 | AK9: =AJ9*BD9 -> 1058040 | AL9: 367576 | AM9: =IFERROR(SUM(AK9:AL9)/SUM(I9:J9),"") | AN9: =IFERROR(I9/T9,"") | AO9: No Target | AP9: 0 | AQ9: 0 | AR9: 2790 | AS9: 1334.02 | AT9: 0 | AU9: 17 | AV9: 0 | AW9: 79 | AX9: 105 | AY9: =IFERROR(VLOOKUP(C9,#REF!,13,0),"") | BA9: =IF(ISBLANK(AZ9),"Active","LEFT" ) -> Active | BB9: =_xludf.ifs(F9<$BB$1,"Old",F9>$BB$1,"New") -> #NAME? | BC9: No Target | BD9: =MATCH($BD$2,{"Apr","May","Jun","Jul","Aug","Sep","Oct","Nov","Dec","Jan","Feb","Mar"},0) -> 12 | BF9: =M9-AT9 -> 17 | BG9: Primary | BL9: =BK9*BD9 -> 0 | BM9: =H9+BL9 -> 0 | BO9: =IFERROR(__xludf.DUMMYFUNCTION("IFERROR(ArrayFormula(SUM(VLOOKUP($C9,importrange(""1MwNMVzWE3QBVOyJjKr3eFX-Sq1Ng0Q1sghWJbgbE_8g"",""ORDER BOOKING REPORT 2024-25!C:CV""),{16,23,30},0))))"),"") | BP9: =IFERROR(__xludf.DUMMYFUNCTION("IFERROR(ArrayFormula(SUM(VLOOKUP($C9,importrange(""1MwNMVzWE3QBVOyJjKr3eFX-Sq1Ng0Q1sghWJbgbE_8g"",""ORDER BOOKING REPORT 2024-25!C:CV""),{37,44,51},0))))"),"") | BQ9: =IFERROR(__xludf.DUMMYFUNCTION("IFERROR(ArrayFormula(SUM(VLOOKUP($C9,importrange(""1MwNMVzWE3QBVOyJjKr3eFX-Sq1Ng0Q1sghWJbgbE_8g"",""ORDER BOOKING REPORT 2024-25!C:CV""),{58,65,72},0))))"),"") | BR9: =IFERROR(__xludf.DUMMYFUNCTION("IFERROR(ArrayFormula(SUM(VLOOKUP($C9,importrange(""1MwNMVzWE3QBVOyJjKr3eFX-Sq1Ng0Q1sghWJbgbE_8g"",""ORDER BOOKING REPORT 2024-25!C:CV""),{79,86,93},0))))"),"") | BS9: =IFERROR(AY9/BM9,"") | BT9: =IFERROR(SUM(AK9:AL9)/AY9,"") | BU9: =BL9-G9 -> 0 | BV9: 88170 | BW9: Sr. Area Sales Manager | BX9: 130 | BY9: =BV9-AJ9 -> 0 | CA9: Oct | CB9: =COUNTIF($F:$F, "<=" & DATE(2025,9,30))-COUNTIFS(AZ:AZ, ">=" & DATE(2025,4,1), AZ:AZ, "<=" & DATE(2025,9,30)) -> 169 | CC9: =COUNTIFS(F:F, ">=" & DATE(2025,10,1), F:F, "<=" & DATE(2025,10,31)) -> 3 | CD9: =COUNTIFS(AZ:AZ, ">=" & DATE(2025,10,1), AZ:AZ, "<=" & DATE(2025,10,31)) -> 7 | CE9: =CB9+CC9 -> 172 | CF9: =SUM(CB9:CD9) -> 179 | CG9: =IF(N9<60,"Below 60"," ") | CH9: =IF(T9 = 0, "Not 50%", IF(T9 >= 0.5 * N9, "Business Achieved 50%", "Not 50%")) -> Not 50% | CI9: =IFERROR((T9/N9),) -> 0 | CM9: =AE9-SUM(CJ9:CL9) -> 184 | CP9: Gujarat | CQ9: =COUNTIFS($B:$B,$CP9,$BG:$BG,"Secondary",$BA:$BA,"Active") -> 5 | CR9: =COUNTIFS($B:$B,$CP9,$BG:$BG,"Primary",$BA:$BA,"Active") -> 0 | CS9: #NAME? | CT9: =COUNTIFS(A:A,CS9,BA:BA,"Active") -> 0
A10: Sandeep Dadheech | B10: West Bengal | C10: Debasish Adhikary | D10: WEST BENGAL | E10: MEDNIPORE | F10: 41791 | G10: 0 | H10: 150000000 | I10: 80016578 | J10: 0 | K10: 100 | L10: 82 | M10: 2 | N10: 102 | O10: 20 | P10: 80016578 | Q10: 0 | R10: 74 | S10: 0 | T10: 74 | U10: 0 | V10: 7 | W10: 7 | X10: 24 | Y10: 4 | Z10: 160 | AA10: 0 | AB10: 0 | AC10: 0 | AD10: 0 | AE10: 1021 | AF10: 1188 | AG10: 269 | AH10: =IFERROR(SUM(I10:J10)/AG10,"") -> 297459.4 | AI10: =IFERROR(AF10/AG10,"") -> 4.4163569 | AJ10: 87460 | AK10: =AJ10*BD10 -> 1027655 | AL10: 163196 | AM10: =IFERROR(SUM(AK10:AL10)/SUM(I10:J10),"") -> 0.014882554 | AN10: =IFERROR(I10/T10,"") -> 1081305.1 | AO10: =IFERROR(SUM(I10:J10)/SUM(G10:H10),"") -> 0.53344385 | AP10: 0 | AQ10: 765 | AR10: 3246 | AS10: 2691.5 | AT10: 0 | AU10: 33 | AV10: 74 | AW10: 8 | AX10: 20 | AY10: =IFERROR(VLOOKUP(C10,#REF!,13,0),"") | BA10: =IF(ISBLANK(AZ10),"Active","LEFT" ) -> Active | BB10: =_xludf.ifs(F10<$BB$1,"Old",F10>$BB$1,"New") -> #NAME? | BC10: =_xludf.ifs(AO10<50%,"Below 50%",AO10<70%,"50%-70%",AO10<90%,"70%-90%",AO10<100%,"90%-100%",AO10>100%,"Above 100%") -> #NAME? | BD10: 11.75 | BF10: =M10-AT10 -> 2 | BG10: Secondary | BH10: =IFERROR(__xludf.DUMMYFUNCTION("""COMPUTED_VALUE"""),103680911.2) -> 1.0368091e+08 | BI10: =IFERROR(__xludf.DUMMYFUNCTION("""COMPUTED_VALUE"""),101906858.6) -> 1.0190686e+08 | BL10: =BK10*BD10 -> 0 | BM10: =H10+BL10 -> 150000000 | BO10: =IFERROR(__xludf.DUMMYFUNCTION("IFERROR(ArrayFormula(SUM(VLOOKUP($C10,importrange(""1MwNMVzWE3QBVOyJjKr3eFX-Sq1Ng0Q1sghWJbgbE_8g"",""ORDER BOOKING REPORT 2024-25!C:CV""),{16,23,30},0))))"),22922417.2) -> 22922417 | BP10: =IFERROR(__xludf.DUMMYFUNCTION("IFERROR(ArrayFormula(SUM(VLOOKUP($C10,importrange(""1MwNMVzWE3QBVOyJjKr3eFX-Sq1Ng0Q1sghWJbgbE_8g"",""ORDER BOOKING REPORT 2024-25!C:CV""),{37,44,51},0))))"),25515495.7999999) -> 25515496 | BQ10: =IFERROR(__xludf.DUMMYFUNCTION("IFERROR(ArrayFormula(SUM(VLOOKUP($C10,importrange(""1MwNMVzWE3QBVOyJjKr3eFX-Sq1Ng0Q1sghWJbgbE_8g"",""ORDER BOOKING REPORT 2024-25!C:CV""),{58,65,72},0))))"),23428766.5) -> 23428766 | BR10: =IFERROR(__xludf.DUMMYFUNCTION("IFERROR(ArrayFormula(SUM(VLOOKUP($C10,importrange(""1MwNMVzWE3QBVOyJjKr3eFX-Sq1Ng0Q1sghWJbgbE_8g"",""ORDER BOOKING REPORT 2024-25!C:CV""),{79,86,93},0))))"),30040179.0999999) -> 30040179 | BS10: =IFERROR(AY10/BM10,"") | BT10: =IFERROR(SUM(AK10:AL10)/AY10,"") | BU10: =BL10-G10 -> 0 | BV10: 87460 | BW10: Sr. Area Sales Manager | BX10: 148 | BY10: =BV10-AJ10 -> 0 | CA10: Nov | CB10: =COUNTIF($F:$F, "<=" & DATE(2025,10,31))-COUNTIFS(AZ:AZ, ">=" & DATE(2025,4,1), AZ:AZ, "<=" & DATE(2025,10,31)) -> 165 | CC10: =COUNTIFS(F:F, ">=" & DATE(2025,11,1), F:F, "<=" & DATE(2025,11,30)) -> 6 | CD10: =COUNTIFS(AZ:AZ, ">=" & DATE(2025,11,1), AZ:AZ, "<=" & DATE(2025,11,30)) -> 8 | CE10: =CB10+CC10 -> 171 | CF10: =SUM(CB10:CD10) -> 179 | CG10: =IF(N10<60,"Below 60"," ") | CH10: =IF(T10 = 0, "Not 50%", IF(T10 >= 0.5 * N10, "Business Achieved 50%", "Not 50%")) -> Business Achieved 50% | CI10: =IFERROR((T10/N10),) -> 0.7254902 | CJ10: =IFERROR(__xludf.DUMMYFUNCTION("""COMPUTED_VALUE"""),981) -> 981 | CK10: =IFERROR(__xludf.DUMMYFUNCTION("""COMPUTED_VALUE"""),40) -> 40 | CL10: =IFERROR(__xludf.DUMMYFUNCTION("""COMPUTED_VALUE"""),0) -> 0 | CM10: =AE10-SUM(CJ10:CL10) -> 0 | CP10: Haryana | CQ10: =COUNTIFS($B:$B,$CP10,$BG:$BG,"Secondary",$BA:$BA,"Active") -> 4 | CR10: =COUNTIFS($B:$B,$CP10,$BG:$BG,"Primary",$BA:$BA,"Active") -> 0 | CS10: #NAME? | CT10: =COUNTIFS(A:A,CS10,BA:BA,"Active") -> 0
A11: Sandeep Dadheech | B11: Odisha | C11: Pravat Kumar Dash | D11: ODISHA | E11: BALASORE | F11: 42125 | G11: 0 | H11: 78696000 | I11: 72128325 | J11: 0 | K11: 125 | L11: 137 | M11: 13 | N11: 138 | O11: 1 | P11: 69031739 | Q11: 3096586.3 | R11: 78 | S11: 8 | T11: 86 | U11: 0 | V11: 1 | W11: 1 | X11: 3 | Y11: 5 | Z11: 184 | AA11: 0 | AB11: 0 | AC11: 0 | AD11: 0 | AE11: 1397 | AF11: 1582 | AG11: 303 | AH11: =IFERROR(SUM(I11:J11)/AG11,"") -> 238047.28 | AI11: =IFERROR(AF11/AG11,"") -> 5.2211221 | AJ11: 79340 | AK11: =AJ11*BD11 -> 952080 | AL11: 219017 | AM11: =IFERROR(SUM(AK11:AL11)/SUM(I11:J11),"") -> 0.016236298 | AN11: =IFERROR(I11/T11,"") -> 838701.45 | AO11: =IFERROR(SUM(I11:J11)/SUM(G11:H11),"") -> 0.91654373 | AP11: 0 | AQ11: 1469 | AR11: 3663 | AS11: 2880.47 | AT11: 8 | AU11: 21 | AV11: 86 | AW11: 51 | AX11: 1 | AY11: =IFERROR(VLOOKUP(C11,#REF!,13,0),"") | BA11: =IF(ISBLANK(AZ11),"Active","LEFT" ) -> Active | BB11: =_xludf.ifs(F11<$BB$1,"Old",F11>$BB$1,"New") -> #NAME? | BC11: =_xludf.ifs(AO11<50%,"Below 50%",AO11<70%,"50%-70%",AO11<90%,"70%-90%",AO11<100%,"90%-100%",AO11>100%,"Above 100%") -> #NAME? | BD11: =MATCH($BD$2,{"Apr","May","Jun","Jul","Aug","Sep","Oct","Nov","Dec","Jan","Feb","Mar"},0) -> 12 | BF11: =M11-AT11 -> 5 | BG11: Secondary | BH11: =IFERROR(__xludf.DUMMYFUNCTION("""COMPUTED_VALUE"""),60223274.44) -> 60223274 | BI11: =IFERROR(__xludf.DUMMYFUNCTION("""COMPUTED_VALUE"""),61970724.91) -> 61970725 | BL11: =BK11*BD11 -> 0 | BM11: =H11+BL11 -> 78696000 | BO11: =IFERROR(__xludf.DUMMYFUNCTION("IFERROR(ArrayFormula(SUM(VLOOKUP($C11,importrange(""1MwNMVzWE3QBVOyJjKr3eFX-Sq1Ng0Q1sghWJbgbE_8g"",""ORDER BOOKING REPORT 2024-25!C:CV""),{16,23,30},0))))"),16487834.6799999) -> 16487835 | BP11: =IFERROR(__xludf.DUMMYFUNCTION("IFERROR(ArrayFormula(SUM(VLOOKUP($C11,importrange(""1MwNMVzWE3QBVOyJjKr3eFX-Sq1Ng0Q1sghWJbgbE_8g"",""ORDER BOOKING REPORT 2024-25!C:CV""),{37,44,51},0))))"),14456037.66) -> 14456038 | BQ11: =IFERROR(__xludf.DUMMYFUNCTION("IFERROR(ArrayFormula(SUM(VLOOKUP($C11,importrange(""1MwNMVzWE3QBVOyJjKr3eFX-Sq1Ng0Q1sghWJbgbE_8g"",""ORDER BOOKING REPORT 2024-25!C:CV""),{58,65,72},0))))"),14904938.15) -> 14904938 | BR11: =IFERROR(__xludf.DUMMYFUNCTION("IFERROR(ArrayFormula(SUM(VLOOKUP($C11,importrange(""1MwNMVzWE3QBVOyJjKr3eFX-Sq1Ng0Q1sghWJbgbE_8g"",""ORDER BOOKING REPORT 2024-25!C:CV""),{79,86,93},0))))"),16121914.42) -> 16121914 | BS11: =IFERROR(AY11/BM11,"") | BT11: =IFERROR(SUM(AK11:AL11)/AY11,"") | BU11: =BL11-G11 -> 0 | BV11: 79340 | BW11: Area Sales Manager | BX11: 221 | BY11: =BV11-AJ11 -> 0 | CA11: Dec | CB11: =COUNTIF($F:$F, "<=" & DATE(2025,11,30))-COUNTIFS(AZ:AZ, ">=" & DATE(2025,4,1), AZ:AZ, "<=" & DATE(2025,11,30)) -> 163 | CC11: =COUNTIFS(F:F, ">=" & DATE(2025,12,1), F:F, "<=" & DATE(2025,12,31)) -> 4 | CD11: =COUNTIFS(AZ:AZ, ">=" & DATE(2025,12,1), AZ:AZ, "<=" & DATE(2025,12,31)) -> 7 | CE11: =CB11+CC11 -> 167 | CF11: =SUM(CB11:CD11) -> 174 | CG11: =IF(N11<60,"Below 60"," ") | CH11: =IF(T11 = 0, "Not 50%", IF(T11 >= 0.5 * N11, "Business Achieved 50%", "Not 50%")) -> Business Achieved 50% | CI11: =IFERROR((T11/N11),) -> 0.62318841 | CJ11: =IFERROR(__xludf.DUMMYFUNCTION("""COMPUTED_VALUE"""),1294) -> 1294 | CK11: =IFERROR(__xludf.DUMMYFUNCTION("""COMPUTED_VALUE"""),103) -> 103 | CL11: =IFERROR(__xludf.DUMMYFUNCTION("""COMPUTED_VALUE"""),0) -> 0 | CM11: =AE11-SUM(CJ11:CL11) -> 0 | CP11: Himachal Pradesh | CQ11: =COUNTIFS($B:$B,$CP11,$BG:$BG,"Secondary",$BA:$BA,"Active") -> 0 | CR11: =COUNTIFS($B:$B,$CP11,$BG:$BG,"Primary",$BA:$BA,"Active") -> 2 | CS11: #NAME? | CT11: =COUNTIFS(A:A,CS11,BA:BA,"Active") -> 0
A12: Syed Aqil Rizvi | B12: East U.P | C12: Ravi Kumar Verma | D12: East U.P | E12: Faizbad | F12: 42530 | G12: 6000000 | H12: 31500000 | I12: 20294789 | J12: 0 | K12: 75 | L12: 92 | M12: 29 | N12: 104 | O12: 12 | P12: 18477281 | Q12: 1817507.9 | R12: 48 | S12: 10 | T12: 58 | U12: 0 | V12: 97 | W12: 158 | X12: 104 | Y12: 7 | Z12: 152 | AA12: 0 | AB12: 0 | AC12: 0 | AD12: 0 | AE12: 639 | AF12: 949 | AG12: 281 | AH12: =IFERROR(SUM(I12:J12)/AG12,"") -> 72223.45 | AI12: =IFERROR(AF12/AG12,"") -> 3.3772242 | AJ12: =BV12 -> 76210 | AK12: =AJ12*BD12 -> 914520 | AL12: 250348 | AM12: =IFERROR(SUM(AK12:AL12)/SUM(I12:J12),"") -> 0.057397393 | AN12: =IFERROR(I12/T12,"") -> 349910.16 | AO12: =IFERROR(SUM(I12:J12)/SUM(G12:H12),"") -> 0.54119438 | AP12: 0 | AQ12: 222 | AR12: 2398 | AS12: 2080.46 | AT12: 10 | AU12: 23 | AV12: 58 | AW12: 36 | AX12: 10 | AY12: =IFERROR(VLOOKUP(C12,#REF!,13,0),"") | BA12: =IF(ISBLANK(AZ12),"Active","LEFT" ) -> Active | BB12: =_xludf.ifs(F12<$BB$1,"Old",F12>$BB$1,"New") -> #NAME? | BC12: =_xludf.ifs(AO12<50%,"Below 50%",AO12<70%,"50%-70%",AO12<90%,"70%-90%",AO12<100%,"90%-100%",AO12>100%,"Above 100%") -> #NAME? | BD12: =MATCH($BD$2,{"Apr","May","Jun","Jul","Aug","Sep","Oct","Nov","Dec","Jan","Feb","Mar"},0) -> 12 | BF12: =M12-AT12 -> 19 | BG12: Secondary | BH12: =IFERROR(__xludf.DUMMYFUNCTION("""COMPUTED_VALUE"""),21287274) -> 21287274 | BI12: =IFERROR(__xludf.DUMMYFUNCTION("""COMPUTED_VALUE"""),20392999.86) -> 20393000 | BK12: 500000 | BL12: =BK12*BD12 -> 6000000 | BM12: =H12+BL12 -> 37500000 | BO12: =IFERROR(__xludf.DUMMYFUNCTION("IFERROR(ArrayFormula(SUM(VLOOKUP($C12,importrange(""1MwNMVzWE3QBVOyJjKr3eFX-Sq1Ng0Q1sghWJbgbE_8g"",""ORDER BOOKING REPORT 2024-25!C:CV""),{16,23,30},0))))"),3572895.8) -> 3572895.8 | BP12: =IFERROR(__xludf.DUMMYFUNCTION("IFERROR(ArrayFormula(SUM(VLOOKUP($C12,importrange(""1MwNMVzWE3QBVOyJjKr3eFX-Sq1Ng0Q1sghWJbgbE_8g"",""ORDER BOOKING REPORT 2024-25!C:CV""),{37,44,51},0))))"),5092431.5) -> 5092431.5 | BQ12: =IFERROR(__xludf.DUMMYFUNCTION("IFERROR(ArrayFormula(SUM(VLOOKUP($C12,importrange(""1MwNMVzWE3QBVOyJjKr3eFX-Sq1Ng0Q1sghWJbgbE_8g"",""ORDER BOOKING REPORT 2024-25!C:CV""),{58,65,72},0))))"),4695979.26) -> 4695979.3 | BR12: =IFERROR(__xludf.DUMMYFUNCTION("IFERROR(ArrayFormula(SUM(VLOOKUP($C12,importrange(""1MwNMVzWE3QBVOyJjKr3eFX-Sq1Ng0Q1sghWJbgbE_8g"",""ORDER BOOKING REPORT 2024-25!C:CV""),{79,86,93},0))))"),7031693.3) -> 7031693.3 | BS12: =IFERROR(AY12/BM12,"") | BT12: =IFERROR(SUM(AK12:AL12)/AY12,"") | BU12: =BL12-G12 -> 0 | BV12: 76210 | BW12: Assistant Area Sales Manager | BX12: 304 | BY12: =BV12-AJ12 -> 0 | CA12: Jan | CB12: =COUNTIF($F:$F, "<=" & DATE(2025,12,31))-COUNTIFS(AZ:AZ, ">=" & DATE(2025,4,1), AZ:AZ, "<=" & DATE(2025,12,31)) -> 160 | CC12: =COUNTIFS(F:F, ">=" & DATE(2026,1,1), F:F, "<=" & DATE(2026,1,31)) -> 7 | CD12: =COUNTIFS(AZ:AZ, ">=" & DATE(2026,1,1), AZ:AZ, "<=" & DATE(2026,1,31)) -> 7 | CE12: =CB12+CC12 -> 167 | CF12: =SUM(CB12:CD12) -> 174 | CG12: =IF(N12<60,"Below 60"," ") | CH12: =IF(T12 = 0, "Not 50%", IF(T12 >= 0.5 * N12, "Business Achieved 50%", "Not 50%")) -> Business Achieved 50% | CI12: =IFERROR((T12/N12),) -> 0.55769231 | CJ12: =IFERROR(__xludf.DUMMYFUNCTION("""COMPUTED_VALUE"""),510) -> 510 | CK12: =IFERROR(__xludf.DUMMYFUNCTION("""COMPUTED_VALUE"""),129) -> 129 | CL12: =IFERROR(__xludf.DUMMYFUNCTION("""COMPUTED_VALUE"""),0) -> 0 | CM12: =AE12-SUM(CJ12:CL12) -> 0 | CP12: JAMMU AND KASHMIR | CQ12: =COUNTIFS($B:$B,$CP12,$BG:$BG,"Secondary",$BA:$BA,"Active") -> 5 | CR12: =COUNTIFS($B:$B,$CP12,$BG:$BG,"Primary",$BA:$BA,"Active") -> 0 | CS12: #NAME? | CT12: =COUNTIFS(A:A,CS12,BA:BA,"Active") -> 0
A13: Sandeep Dadheech | B13: West Bengal | C13: Priyabrata Biswas | D13: WEST BENGAL | E13: BANKURA | F13: 42660 | G13: 0 | H13: 40599996 | I13: 33140270 | J13: 0 | K13: 56 | L13: 58 | M13: 6 | N13: 62 | O13: 4 | P13: 32421767 | Q13: 718502.3 | R13: 38 | S13: 6 | T13: 44 | U13: 0 | V13: 3 | W13: 6 | X13: 4 | Y13: 3 | Z13: 264 | AA13: 0 | AB13: 0 | AC13: 0 | AD13: 0 | AE13: 858 | AF13: 1128 | AG13: 283 | AH13: =IFERROR(SUM(I13:J13)/AG13,"") -> 117103.43 | AI13: =IFERROR(AF13/AG13,"") -> 3.9858657 | AJ13: 48608 | AK13: =AJ13*BD13 -> 583296 | AL13: 187741 | AM13: =IFERROR(SUM(AK13:AL13)/SUM(I13:J13),"") -> 0.023265864 | AN13: =IFERROR(I13/T13,"") -> 753187.95 | AO13: =IFERROR(SUM(I13:J13)/SUM(G13:H13),"") -> 0.81626288 | AP13: 0 | AQ13: 408 | AR13: 3089 | AS13: 1927.17 | AT13: 6 | AU13: 33 | AV13: 44 | AW13: 15 | AX13: 3 | AY13: =IFERROR(VLOOKUP(C13,#REF!,13,0),"") | BA13: =IF(ISBLANK(AZ13),"Active","LEFT" ) -> Active | BB13: =_xludf.ifs(F13<$BB$1,"Old",F13>$BB$1,"New") -> #NAME? | BC13: =_xludf.ifs(AO13<50%,"Below 50%",AO13<70%,"50%-70%",AO13<90%,"70%-90%",AO13<100%,"90%-100%",AO13>100%,"Above 100%") -> #NAME? | BD13: =MATCH($BD$2,{"Apr","May","Jun","Jul","Aug","Sep","Oct","Nov","Dec","Jan","Feb","Mar"},0) -> 12 | BF13: =M13-AT13 -> 0 | BG13: Secondary | BH13: =IFERROR(__xludf.DUMMYFUNCTION("""COMPUTED_VALUE"""),27594897) -> 27594897 | BI13: =IFERROR(__xludf.DUMMYFUNCTION("""COMPUTED_VALUE"""),27934642.2) -> 27934642 | BL13: =BK13*BD13 -> 0 | BM13: =H13+BL13 -> 40599996 | BO13: =IFERROR(__xludf.DUMMYFUNCTION("IFERROR(ArrayFormula(SUM(VLOOKUP($C13,importrange(""1MwNMVzWE3QBVOyJjKr3eFX-Sq1Ng0Q1sghWJbgbE_8g"",""ORDER BOOKING REPORT 2024-25!C:CV""),{16,23,30},0))))"),6726878.5) -> 6726878.5 | BP13: =IFERROR(__xludf.DUMMYFUNCTION("IFERROR(ArrayFormula(SUM(VLOOKUP($C13,importrange(""1MwNMVzWE3QBVOyJjKr3eFX-Sq1Ng0Q1sghWJbgbE_8g"",""ORDER BOOKING REPORT 2024-25!C:CV""),{37,44,51},0))))"),7101797.49999999) -> 7101797.5 | BQ13: =IFERROR(__xludf.DUMMYFUNCTION("IFERROR(ArrayFormula(SUM(VLOOKUP($C13,importrange(""1MwNMVzWE3QBVOyJjKr3eFX-Sq1Ng0Q1sghWJbgbE_8g"",""ORDER BOOKING REPORT 2024-25!C:CV""),{58,65,72},0))))"),6808447.79999999) -> 6808447.8 | BR13: =IFERROR(__xludf.DUMMYFUNCTION("IFERROR(ArrayFormula(SUM(VLOOKUP($C13,importrange(""1MwNMVzWE3QBVOyJjKr3eFX-Sq1Ng0Q1sghWJbgbE_8g"",""ORDER BOOKING REPORT 2024-25!C:CV""),{79,86,93},0))))"),7297518.4) -> 7297518.4 | BS13: =IFERROR(AY13/BM13,"") | BT13: =IFERROR(SUM(AK13:AL13)/AY13,"") | BU13: =BL13-G13 -> 0 | BV13: 48608 | BW13: Assistant Area Sales Manager | BX13: 438 | BY13: =BV13-AJ13 -> 0 | CA13: Feb | CB13: =COUNTIF($F:$F, "<=" & DATE(2026,1,31))-COUNTIFS(AZ:AZ, ">=" & DATE(2025,4,1), AZ:AZ, "<=" & DATE(2026,1,31)) -> 160 | CC13: =COUNTIFS(F:F, ">=" & DATE(2026,2,1), F:F, "<=" & DATE(2026,2,28)) -> 1 | CD13: =COUNTIFS(AZ:AZ, ">=" & DATE(2026,2,1), AZ:AZ, "<=" & DATE(2026,2,28)) -> 3 | CE13: =CB13+CC13 -> 161 | CF13: =SUM(CB13:CD13) -> 164 | CG13: =IF(N13<60,"Below 60"," ") | CH13: =IF(T13 = 0, "Not 50%", IF(T13 >= 0.5 * N13, "Business Achieved 50%", "Not 50%")) -> Business Achieved 50% | CI13: =IFERROR((T13/N13),) -> 0.70967742 | CJ13: =IFERROR(__xludf.DUMMYFUNCTION("""COMPUTED_VALUE"""),781) -> 781 | CK13: =IFERROR(__xludf.DUMMYFUNCTION("""COMPUTED_VALUE"""),77) -> 77 | CL13: =IFERROR(__xludf.DUMMYFUNCTION("""COMPUTED_VALUE"""),0) -> 0 | CM13: =AE13-SUM(CJ13:CL13) -> 0 | CP13: Jharkhand | CQ13: =COUNTIFS($B:$B,$CP13,$BG:$BG,"Secondary",$BA:$BA,"Active") -> 7 | CR13: =COUNTIFS($B:$B,$CP13,$BG:$BG,"Primary",$BA:$BA,"Active") -> 1 | CS13: #NAME? | CT13: =COUNTIFS(A:A,CS13,BA:BA,"Active") -> 0
A14: Syed Aqil Rizvi | B14: Madhya Pradesh | C14: Jitender Birla | D14: MADHYA PRADESH | E14: Indore | F14: 42720 | G14: 5028000 | H14: 32472000 | I14: 23497643 | J14: =2302523.38+1470312.5 -> 3772835.9 | K14: 68 | L14: 81 | M14: 32 | N14: 100 | O14: 19 | P14: 15192121 | Q14: 8305522 | R14: 47 | S14: 24 | T14: 71 | U14: 3 | V14: 61 | W14: 121 | X14: 136 | Y14: 3 | Z14: 82 | AA14: 4 | AB14: 42 | AC14: 1 | AD14: 48 | AE14: 816 | AF14: 1109 | AG14: 296 | AH14: =IFERROR(SUM(I14:J14)/AG14,"") -> 92129.996 | AI14: =IFERROR(AF14/AG14,"") -> 3.7466216 | AJ14: =BV14 -> 61850 | AK14: =AJ14*BD14 -> 742200 | AL14: 279525 | AM14: =IFERROR(SUM(AK14:AL14)/SUM(I14:J14),"") -> 0.037466339 | AN14: =IFERROR(I14/T14,"") -> 330952.72 | AO14: =IFERROR(SUM(I14:J14)/SUM(G14:H14),"") -> 0.72721277 | AP14: 0.75 | AQ14: 528 | AR14: 2088 | AS14: 3658.44 | AT14: 24 | AU14: 45 | AV14: 71 | AW14: 16 | AX14: 13 | AY14: =IFERROR(VLOOKUP(C14,#REF!,13,0),"") | BA14: =IF(ISBLANK(AZ14),"Active","LEFT" ) -> Active | BB14: =_xludf.ifs(F14<$BB$1,"Old",F14>$BB$1,"New") -> #NAME? | BC14: =_xludf.ifs(AO14<50%,"Below 50%",AO14<70%,"50%-70%",AO14<90%,"70%-90%",AO14<100%,"90%-100%",AO14>100%,"Above 100%") -> #NAME? | BD14: =MATCH($BD$2,{"Apr","May","Jun","Jul","Aug","Sep","Oct","Nov","Dec","Jan","Feb","Mar"},0) -> 12 | BF14: =M14-AT14 -> 8 | BG14: Secondary | BH14: =IFERROR(__xludf.DUMMYFUNCTION("""COMPUTED_VALUE"""),19644499) -> 19644499 | BI14: =IFERROR(__xludf.DUMMYFUNCTION("""COMPUTED_VALUE"""),19561872.2599999) -> 19561872 | BK14: 419000 | BL14: =BK14*BD14 -> 5028000 | BM14: =H14+BL14 -> 37500000 | BO14: =IFERROR(__xludf.DUMMYFUNCTION("IFERROR(ArrayFormula(SUM(VLOOKUP($C14,importrange(""1MwNMVzWE3QBVOyJjKr3eFX-Sq1Ng0Q1sghWJbgbE_8g"",""ORDER BOOKING REPORT 2024-25!C:CV""),{16,23,30},0))))"),4285421.91) -> 4285421.9 | BP14: =IFERROR(__xludf.DUMMYFUNCTION("IFERROR(ArrayFormula(SUM(VLOOKUP($C14,importrange(""1MwNMVzWE3QBVOyJjKr3eFX-Sq1Ng0Q1sghWJbgbE_8g"",""ORDER BOOKING REPORT 2024-25!C:CV""),{37,44,51},0))))"),5088733.93999999) -> 5088733.9 | BQ14: =IFERROR(__xludf.DUMMYFUNCTION("IFERROR(ArrayFormula(SUM(VLOOKUP($C14,importrange(""1MwNMVzWE3QBVOyJjKr3eFX-Sq1Ng0Q1sghWJbgbE_8g"",""ORDER BOOKING REPORT 2024-25!C:CV""),{58,65,72},0))))"),4523058.39) -> 4523058.4 | BR14: =IFERROR(__xludf.DUMMYFUNCTION("IFERROR(ArrayFormula(SUM(VLOOKUP($C14,importrange(""1MwNMVzWE3QBVOyJjKr3eFX-Sq1Ng0Q1sghWJbgbE_8g"",""ORDER BOOKING REPORT 2024-25!C:CV""),{79,86,93},0))))"),5664658.02) -> 5664658 | BS14: =IFERROR(AY14/BM14,"") | BT14: =IFERROR(SUM(AK14:AL14)/AY14,"") | BU14: =BL14-G14 -> 0 | BV14: 61850 | BW14: Sr. Area Sales Manager | BX14: 323 | BY14: =BV14-AJ14 -> 0 | CA14: Mar | CB14: =COUNTIF($F:$F, "<=" & DATE(2026,2,28))-COUNTIFS(AZ:AZ, ">=" & DATE(2025,4,1), AZ:AZ, "<=" & DATE(2026,2,28)) -> 158 | CC14: =COUNTIFS(F:F, ">=" & DATE(2026,3,1), F:F, "<=" & DATE(2026,3,31)) -> 7 | CD14: =COUNTIFS(AZ:AZ, ">=" & DATE(2026,3,1), AZ:AZ, "<=" & DATE(2026,3,31)) -> 5 | CE14: =CB14+CC14 -> 165 | CF14: =SUM(CB14:CD14) -> 170 | CG14: =IF(N14<60,"Below 60"," ") | CH14: =IF(T14 = 0, "Not 50%", IF(T14 >= 0.5 * N14, "Business Achieved 50%", "Not 50%")) -> Business Achieved 50% | CI14: =IFERROR((T14/N14),) -> 0.71 | CJ14: =IFERROR(__xludf.DUMMYFUNCTION("""COMPUTED_VALUE"""),764) -> 764 | CK14: =IFERROR(__xludf.DUMMYFUNCTION("""COMPUTED_VALUE"""),52) -> 52 | CL14: =IFERROR(__xludf.DUMMYFUNCTION("""COMPUTED_VALUE"""),0) -> 0 | CM14: =AE14-SUM(CJ14:CL14) -> 0 | CP14: Karnataka | CQ14: =COUNTIFS($B:$B,$CP14,$BG:$BG,"Secondary",$BA:$BA,"Active") -> 2 | CR14: =COUNTIFS($B:$B,$CP14,$BG:$BG,"Primary",$BA:$BA,"Active") -> 2 | CT14: =COUNTIFS(A:A,CS14,BA:BA,"Active") -> 0
A15: Sandeep Dadheech | B15: Andhra Pradesh | C15: S.Tirumala Rao | D15: ANDHRA PRADESH | E15: Srikakulam | F15: 42769 | G15: 0 | H15: 11200000 | I15: 3645541.3 | J15: 0 | K15: 44 | L15: 45 | M15: 1 | N15: 45 | O15: 0 | P15: 3626768.2 | Q15: 18773.1 | R15: 33 | S15: 1 | T15: 34 | U15: 0 | V15: 12 | W15: 27 | X15: 66 | Y15: 2 | Z15: 18 | AA15: 0 | AB15: 0 | AC15: 0 | AD15: 0 | AE15: 812 | AF15: 857 | AG15: 204 | AH15: =IFERROR(SUM(I15:J15)/AG15,"") -> 17870.3 | AI15: =IFERROR(AF15/AG15,"") -> 4.2009804 | AJ15: =BV15 -> 37355 | AK15: =AJ15*BD15 -> 298840 | AL15: 138168 | AM15: =IFERROR(SUM(AK15:AL15)/SUM(I15:J15),"") -> 0.11987465 | AN15: =IFERROR(I15/T15,"") -> 107221.8 | AO15: =IFERROR(SUM(I15:J15)/SUM(G15:H15),"") -> 0.32549476 | AP15: 0 | AQ15: 136 | AR15: 2241 | AS15: 0 | AT15: 1 | AU15: 0 | AV15: 34 | AW15: 11 | AX15: 0 | AY15: =IFERROR(VLOOKUP(C15,#REF!,13,0),"") | AZ15: 45991 | BA15: =IF(ISBLANK(AZ15),"Active","LEFT" ) -> LEFT | BB15: =_xludf.ifs(F15<$BB$1,"Old",F15>$BB$1,"New") -> #NAME? | BC15: =_xludf.ifs(AO15<50%,"Below 50%",AO15<70%,"50%-70%",AO15<90%,"70%-90%",AO15<100%,"90%-100%",AO15>100%,"Above 100%") -> #NAME? | BD15: 8 | BF15: =M15-AT15 -> 0 | BG15: Secondary | BH15: =IFERROR(__xludf.DUMMYFUNCTION("""COMPUTED_VALUE"""),8136889) -> 8136889 | BI15: =IFERROR(__xludf.DUMMYFUNCTION("""COMPUTED_VALUE"""),8549887.04) -> 8549887 | BL15: =BK15*BD15 -> 0 | BM15: =H15+BL15 -> 11200000 | BO15: =IFERROR(__xludf.DUMMYFUNCTION("IFERROR(ArrayFormula(SUM(VLOOKUP($C15,importrange(""1MwNMVzWE3QBVOyJjKr3eFX-Sq1Ng0Q1sghWJbgbE_8g"",""ORDER BOOKING REPORT 2024-25!C:CV""),{16,23,30},0))))"),2883632.9) -> 2883632.9 | BP15: =IFERROR(__xludf.DUMMYFUNCTION("IFERROR(ArrayFormula(SUM(VLOOKUP($C15,importrange(""1MwNMVzWE3QBVOyJjKr3eFX-Sq1Ng0Q1sghWJbgbE_8g"",""ORDER BOOKING REPORT 2024-25!C:CV""),{37,44,51},0))))"),1822099.32) -> 1822099.3 | BQ15: =IFERROR(__xludf.DUMMYFUNCTION("IFERROR(ArrayFormula(SUM(VLOOKUP($C15,importrange(""1MwNMVzWE3QBVOyJjKr3eFX-Sq1Ng0Q1sghWJbgbE_8g"",""ORDER BOOKING REPORT 2024-25!C:CV""),{58,65,72},0))))"),1985247.96) -> 1985248 | BR15: =IFERROR(__xludf.DUMMYFUNCTION("IFERROR(ArrayFormula(SUM(VLOOKUP($C15,importrange(""1MwNMVzWE3QBVOyJjKr3eFX-Sq1Ng0Q1sghWJbgbE_8g"",""ORDER BOOKING REPORT 2024-25!C:CV""),{79,86,93},0))))"),1858906.86) -> 1858906.9 | BS15: =IFERROR(AY15/BM15,"") | BT15: =IFERROR(SUM(AK15:AL15)/AY15,"") | BU15: =BL15-G15 -> 0 | BV15: 37355 | BW15: Executive - Sales & Mkt. | BX15: 341 | BY15: =BV15-AJ15 -> 0 | CB15: =COUNTIF($F:$F, "<=" & DATE(2026,3,31))-COUNTIFS(AZ:AZ, ">=" & DATE(2025,4,1), AZ:AZ, "<=" & DATE(2026,3,31)) -> 160 | CG15: =IF(N15<60,"Below 60"," ") -> Below 60 | CH15: =IF(T15 = 0, "Not 50%", IF(T15 >= 0.5 * N15, "Business Achieved 50%", "Not 50%")) -> Business Achieved 50% | CI15: =IFERROR((T15/N15),) -> 0.75555556 | CJ15: =IFERROR(__xludf.DUMMYFUNCTION("""COMPUTED_VALUE"""),632) -> 632 | CK15: =IFERROR(__xludf.DUMMYFUNCTION("""COMPUTED_VALUE"""),180) -> 180 | CL15: =IFERROR(__xludf.DUMMYFUNCTION("""COMPUTED_VALUE"""),0) -> 0 | CM15: =AE15-SUM(CJ15:CL15) -> 0 | CP15: Kerala | CQ15: =COUNTIFS($B:$B,$CP15,$BG:$BG,"Secondary",$BA:$BA,"Active") -> 7 | CR15: =COUNTIFS($B:$B,$CP15,$BG:$BG,"Primary",$BA:$BA,"Active") -> 0 | CT15: =COUNTIFS(A:A,CS15,BA:BA,"Active") -> 0
A16: Sandeep Dadheech | B16: Odisha | C16: Arijit Roychowdhury | D16: ODISHA | E16: BHUBANESWAR | F16: 42826 | G16: 0 | H16: 24000000 | I16: 6304004.2 | J16: 0 | K16: 73 | L16: 86 | M16: 21 | N16: 94 | O16: 8 | P16: 4934942 | Q16: 1369062.2 | R16: 49 | S16: 21 | T16: 70 | U16: 0 | V16: 2 | W16: 6 | X16: 9 | Y16: 3 | Z16: 143 | AA16: 0 | AB16: 0 | AC16: 0 | AD16: 0 | AE16: 1011 | AF16: 1160 | AG16: 235 | AH16: =IFERROR(SUM(I16:J16)/AG16,"") -> 26825.55 | AI16: =IFERROR(AF16/AG16,"") -> 4.9361702 | AJ16: 76300 | AK16: =AJ16*BD16 -> 763000 | AL16: 101548 | AM16: =IFERROR(SUM(AK16:AL16)/SUM(I16:J16),"") -> 0.13714267 | AN16: =IFERROR(I16/T16,"") -> 90057.203 | AO16: =IFERROR(SUM(I16:J16)/SUM(G16:H16),"") -> 0.26266684 | AP16: 0 | AQ16: 250 | AR16: 2035 | AS16: 0 | AT16: 21 | AU16: 0 | AV16: 70 | AW16: 17 | AX16: 7 | AY16: =IFERROR(VLOOKUP(C16,#REF!,13,0),"") | AZ16: 46053 | BA16: =IF(ISBLANK(AZ16),"Active","LEFT" ) -> LEFT | BB16: =_xludf.ifs(F16<$BB$1,"Old",F16>$BB$1,"New") -> #NAME? | BC16: =_xludf.ifs(AO16<50%,"Below 50%",AO16<70%,"50%-70%",AO16<90%,"70%-90%",AO16<100%,"90%-100%",AO16>100%,"Above 100%") -> #NAME? | BD16: 10 | BF16: =M16-AT16 -> 0 | BG16: Secondary | BH16: =IFERROR(__xludf.DUMMYFUNCTION("""COMPUTED_VALUE"""),5631228.72) -> 5631228.7 | BI16: =IFERROR(__xludf.DUMMYFUNCTION("""COMPUTED_VALUE"""),4942730.67) -> 4942730.7 | BL16: =BK16*BD16 -> 0 | BM16: =H16+BL16 -> 24000000 | BO16: =IFERROR(__xludf.DUMMYFUNCTION("IFERROR(ArrayFormula(SUM(VLOOKUP($C16,importrange(""1MwNMVzWE3QBVOyJjKr3eFX-Sq1Ng0Q1sghWJbgbE_8g"",""ORDER BOOKING REPORT 2024-25!C:CV""),{16,23,30},0))))"),1698763.63) -> 1698763.6 | BP16: =IFERROR(__xludf.DUMMYFUNCTION("IFERROR(ArrayFormula(SUM(VLOOKUP($C16,importrange(""1MwNMVzWE3QBVOyJjKr3eFX-Sq1Ng0Q1sghWJbgbE_8g"",""ORDER BOOKING REPORT 2024-25!C:CV""),{37,44,51},0))))"),399087.1) -> 399087.1 | BQ16: =IFERROR(__xludf.DUMMYFUNCTION("IFERROR(ArrayFormula(SUM(VLOOKUP($C16,importrange(""1MwNMVzWE3QBVOyJjKr3eFX-Sq1Ng0Q1sghWJbgbE_8g"",""ORDER BOOKING REPORT 2024-25!C:CV""),{58,65,72},0))))"),1345957.72) -> 1345957.7 | BR16: =IFERROR(__xludf.DUMMYFUNCTION("IFERROR(ArrayFormula(SUM(VLOOKUP($C16,importrange(""1MwNMVzWE3QBVOyJjKr3eFX-Sq1Ng0Q1sghWJbgbE_8g"",""ORDER BOOKING REPORT 2024-25!C:CV""),{79,86,93},0))))"),1498922.21999999) -> 1498922.2 | BS16: =IFERROR(AY16/BM16,"") | BT16: =IFERROR(SUM(AK16:AL16)/AY16,"") | BU16: =BL16-G16 -> 0 | BV16: 76300 | BW16: Sr. Area Sales Manager | BX16: 354 | BY16: =BV16-AJ16 -> 0 | CG16: =IF(N16<60,"Below 60"," ") | CH16: =IF(T16 = 0, "Not 50%", IF(T16 >= 0.5 * N16, "Business Achieved 50%", "Not 50%")) -> Business Achieved 50% | CI16: =IFERROR((T16/N16),) -> 0.74468085 | CJ16: =IFERROR(__xludf.DUMMYFUNCTION("""COMPUTED_VALUE"""),940) -> 940 | CK16: =IFERROR(__xludf.DUMMYFUNCTION("""COMPUTED_VALUE"""),71) -> 71 | CL16: =IFERROR(__xludf.DUMMYFUNCTION("""COMPUTED_VALUE"""),0) -> 0 | CM16: =AE16-SUM(CJ16:CL16) -> 0 | CP16: Madhya Pradesh | CQ16: =COUNTIFS($B:$B,$CP16,$BG:$BG,"Secondary",$BA:$BA,"Active") -> 10 | CR16: =COUNTIFS($B:$B,$CP16,$BG:$BG,"Primary",$BA:$BA,"Active") -> 0 | CT16: =COUNTIFS(A:A,CS16,BA:BA,"Active") -> 0
A17: Sandeep Dadheech | B17: West Bengal | C17: Sarbjit Singh Chawla | D17: WEST BENGAL | E17: ANDAL | F17: 42826 | G17: 0 | H17: 45600000 | I17: 38462589 | J17: 0 | K17: 129 | L17: 94 | M17: 9 | N17: 138 | O17: 44 | P17: 38462589 | Q17: 0 | R17: 20 | S17: 0 | T17: 20 | U17: 0 | V17: 13 | W17: 19 | X17: 28 | Y17: 4 | Z17: 99 | AA17: 0 | AB17: 0 | AC17: 0 | AD17: 0 | AE17: 852 | AF17: 970 | AG17: 300 | AH17: =IFERROR(SUM(I17:J17)/AG17,"") -> 128208.63 | AI17: =IFERROR(AF17/AG17,"") -> 3.2333333 | AJ17: 63250 | AK17: =AJ17*BD17 -> 759000 | AL17: 264598 | AM17: =IFERROR(SUM(AK17:AL17)/SUM(I17:J17),"") -> 0.026612821 | AN17: =IFERROR(I17/T17,"") -> 1923129.4 | AO17: =IFERROR(SUM(I17:J17)/SUM(G17:H17),"") -> 0.84347783 | AP17: 0 | AQ17: 116 | AR17: 3649 | AS17: 1702.39 | AT17: 0 | AU17: 18 | AV17: 20 | AW17: 74 | AX17: 44 | AY17: =IFERROR(VLOOKUP(C17,#REF!,13,0),"") | BA17: =IF(ISBLANK(AZ17),"Active","LEFT" ) -> Active | BB17: =_xludf.ifs(F17<$BB$1,"Old",F17>$BB$1,"New") -> #NAME? | BC17: =_xludf.ifs(AO17<50%,"Below 50%",AO17<70%,"50%-70%",AO17<90%,"70%-90%",AO17<100%,"90%-100%",AO17>100%,"Above 100%") -> #NAME? | BD17: =MATCH($BD$2,{"Apr","May","Jun","Jul","Aug","Sep","Oct","Nov","Dec","Jan","Feb","Mar"},0) -> 12 | BF17: =M17-AT17 -> 9 | BG17: Secondary | BH17: =IFERROR(__xludf.DUMMYFUNCTION("""COMPUTED_VALUE"""),44970678.61) -> 44970679 | BI17: =IFERROR(__xludf.DUMMYFUNCTION("""COMPUTED_VALUE"""),68311270.3) -> 68311270 | BL17: =BK17*BD17 -> 0 | BM17: =H17+BL17 -> 45600000 | BO17: =IFERROR(__xludf.DUMMYFUNCTION("IFERROR(ArrayFormula(SUM(VLOOKUP($C17,importrange(""1MwNMVzWE3QBVOyJjKr3eFX-Sq1Ng0Q1sghWJbgbE_8g"",""ORDER BOOKING REPORT 2024-25!C:CV""),{16,23,30},0))))"),16343405) -> 16343405 | BP17: =IFERROR(__xludf.DUMMYFUNCTION("IFERROR(ArrayFormula(SUM(VLOOKUP($C17,importrange(""1MwNMVzWE3QBVOyJjKr3eFX-Sq1Ng0Q1sghWJbgbE_8g"",""ORDER BOOKING REPORT 2024-25!C:CV""),{37,44,51},0))))"),15567088.4) -> 15567088 | BQ17: =IFERROR(__xludf.DUMMYFUNCTION("IFERROR(ArrayFormula(SUM(VLOOKUP($C17,importrange(""1MwNMVzWE3QBVOyJjKr3eFX-Sq1Ng0Q1sghWJbgbE_8g"",""ORDER BOOKING REPORT 2024-25!C:CV""),{58,65,72},0))))"),17148584.3) -> 17148584 | BR17: =IFERROR(__xludf.DUMMYFUNCTION("IFERROR(ArrayFormula(SUM(VLOOKUP($C17,importrange(""1MwNMVzWE3QBVOyJjKr3eFX-Sq1Ng0Q1sghWJbgbE_8g"",""ORDER BOOKING REPORT 2024-25!C:CV""),{79,86,93},0))))"),19252192.6) -> 19252193 | BS17: =IFERROR(AY17/BM17,"") | BT17: =IFERROR(SUM(AK17:AL17)/AY17,"") | BU17: =BL17-G17 -> 0 | BV17: 63250 | BW17: Area Sales Manager | BX17: 360 | BY17: =BV17-AJ17 -> 0 | CG17: =IF(N17<60,"Below 60"," ") | CH17: =IF(T17 = 0, "Not 50%", IF(T17 >= 0.5 * N17, "Business Achieved 50%", "Not 50%")) -> Not 50% | CI17: =IFERROR((T17/N17),) -> 0.14492754 | CJ17: =IFERROR(__xludf.DUMMYFUNCTION("""COMPUTED_VALUE"""),382) -> 382 | CK17: =IFERROR(__xludf.DUMMYFUNCTION("""COMPUTED_VALUE"""),470) -> 470 | CL17: =IFERROR(__xludf.DUMMYFUNCTION("""COMPUTED_VALUE"""),0) -> 0 | CM17: =AE17-SUM(CJ17:CL17) -> 0 | CP17: Maharashtra | CQ17: =COUNTIFS($B:$B,$CP17,$BG:$BG,"Secondary",$BA:$BA,"Active") -> 12 | CR17: =COUNTIFS($B:$B,$CP17,$BG:$BG,"Primary",$BA:$BA,"Active") -> 0 | CT17: =COUNTIFS(A:A,CS17,BA:BA,"Active") -> 0
A18: Lalan Kumar | B18: Maharashtra | C18: Amey Deodhar | D18: KARNATAKA, MAHARASHTRA | E18: Miraj (Mh) | F18: 42926 | G18: 0 | H18: 24000000 | I18: 20796267 | J18: 0 | K18: 156 | L18: 134 | M18: 16 | N18: 172 | O18: 38 | P18: 20102077 | Q18: 694190.5 | R18: 88 | S18: 9 | T18: 97 | U18: 0 | V18: 17 | W18: 25 | X18: 42 | Y18: 3 | Z18: 106 | AA18: 0 | AB18: 0 | AC18: 0 | AD18: 0 | AE18: 812 | AF18: 943 | AG18: 293 | AH18: =IFERROR(SUM(I18:J18)/AG18,"") -> 70977.021 | AI18: =IFERROR(AF18/AG18,"") -> 3.21843 | AJ18: 44575 | AK18: =AJ18*BD18 -> 534900 | AL18: 284111 | AM18: =IFERROR(SUM(AK18:AL18)/SUM(I18:J18),"") -> 0.039382597 | AN18: =IFERROR(I18/T18,"") -> 214394.51 | AO18: =IFERROR(SUM(I18:J18)/SUM(G18:H18),"") -> 0.86651113 | AP18: 0 | AQ18: 665 | AR18: 2219 | AS18: 4875.51 | AT18: 9 | AU18: 36 | AV18: 97 | AW18: 48 | AX18: 27 | AY18: =IFERROR(VLOOKUP(C18,#REF!,13,0),"") | BA18: =IF(ISBLANK(AZ18),"Active","LEFT" ) -> Active | BB18: =_xludf.ifs(F18<$BB$1,"Old",F18>$BB$1,"New") -> #NAME? | BC18: =_xludf.ifs(AO18<50%,"Below 50%",AO18<70%,"50%-70%",AO18<90%,"70%-90%",AO18<100%,"90%-100%",AO18>100%,"Above 100%") -> #NAME? | BD18: =MATCH($BD$2,{"Apr","May","Jun","Jul","Aug","Sep","Oct","Nov","Dec","Jan","Feb","Mar"},0) -> 12 | BF18: =M18-AT18 -> 7 | BG18: Secondary | BH18: =IFERROR(__xludf.DUMMYFUNCTION("""COMPUTED_VALUE"""),20081138) -> 20081138 | BI18: =IFERROR(__xludf.DUMMYFUNCTION("""COMPUTED_VALUE"""),16655458.01) -> 16655458 | BL18: =BK18*BD18 -> 0 | BM18: =H18+BL18 -> 24000000 | BO18: =IFERROR(__xludf.DUMMYFUNCTION("IFERROR(ArrayFormula(SUM(VLOOKUP($C18,importrange(""1MwNMVzWE3QBVOyJjKr3eFX-Sq1Ng0Q1sghWJbgbE_8g"",""ORDER BOOKING REPORT 2024-25!C:CV""),{16,23,30},0))))"),3414186.4) -> 3414186.4 | BP18: =IFERROR(__xludf.DUMMYFUNCTION("IFERROR(ArrayFormula(SUM(VLOOKUP($C18,importrange(""1MwNMVzWE3QBVOyJjKr3eFX-Sq1Ng0Q1sghWJbgbE_8g"",""ORDER BOOKING REPORT 2024-25!C:CV""),{37,44,51},0))))"),3785622.06) -> 3785622.1 | BQ18: =IFERROR(__xludf.DUMMYFUNCTION("IFERROR(ArrayFormula(SUM(VLOOKUP($C18,importrange(""1MwNMVzWE3QBVOyJjKr3eFX-Sq1Ng0Q1sghWJbgbE_8g"",""ORDER BOOKING REPORT 2024-25!C:CV""),{58,65,72},0))))"),4615195.56999999) -> 4615195.6 | BR18: =IFERROR(__xludf.DUMMYFUNCTION("IFERROR(ArrayFormula(SUM(VLOOKUP($C18,importrange(""1MwNMVzWE3QBVOyJjKr3eFX-Sq1Ng0Q1sghWJbgbE_8g"",""ORDER BOOKING REPORT 2024-25!C:CV""),{79,86,93},0))))"),4840453.98) -> 4840454 | BS18: =IFERROR(AY18/BM18,"") | BT18: =IFERROR(SUM(AK18:AL18)/AY18,"") | BU18: =BL18-G18 -> 0 | BV18: 44575 | BW18: Executive - Sales & Mkt. | BX18: 371 | BY18: =BV18-AJ18 -> 0 | CG18: =IF(N18<60,"Below 60"," ") | CH18: =IF(T18 = 0, "Not 50%", IF(T18 >= 0.5 * N18, "Business Achieved 50%", "Not 50%")) -> Business Achieved 50% | CI18: =IFERROR((T18/N18),) -> 0.56395349 | CJ18: =IFERROR(__xludf.DUMMYFUNCTION("""COMPUTED_VALUE"""),710) -> 710 | CK18: =IFERROR(__xludf.DUMMYFUNCTION("""COMPUTED_VALUE"""),102) -> 102 | CL18: =IFERROR(__xludf.DUMMYFUNCTION("""COMPUTED_VALUE"""),0) -> 0 | CM18: =AE18-SUM(CJ18:CL18) -> 0 | CP18: Maharashtra 2 | CQ18: =COUNTIFS($B:$B,$CP18,$BG:$BG,"Secondary",$BA:$BA,"Active") -> 3 | CR18: =COUNTIFS($B:$B,$CP18,$BG:$BG,"Primary",$BA:$BA,"Active") -> 0 | CT18: =COUNTIFS(A:A,CS18,BA:BA,"Active") -> 0
A19: Sunil Patel | B19: Gujarat | C19: Devdutt Joshi | D19: GUJARAT | E19: Baroda | F19: 42993 | G19: 0 | H19: 15000000 | I19: 10972000 | J19: 0 | K19: 133 | L19: 118 | M19: 10 | N19: 143 | O19: 25 | P19: 8655366.7 | Q19: 2316633.1 | R19: 100 | S19: 10 | T19: 110 | U19: 0 | V19: 334 | W19: 508 | X19: 400 | Y19: 8 | Z19: 359 | AA19: 0 | AB19: 0 | AC19: 1 | AD19: 1 | AE19: 732 | AF19: 1600 | AG19: 300 | AH19: =IFERROR(SUM(I19:J19)/AG19,"") -> 36573.333 | AI19: =IFERROR(AF19/AG19,"") -> 5.3333333 | AJ19: 51335 | AK19: =AJ19*BD19 -> 616020 | AL19: 148141 | AM19: =IFERROR(SUM(AK19:AL19)/SUM(I19:J19),"") -> 0.069646465 | AN19: =IFERROR(I19/T19,"") -> 99745.453 | AO19: =IFERROR(SUM(I19:J19)/SUM(G19:H19),"") -> 0.73146665 | AP19: 0 | AQ19: 642 | AR19: 2841 | AS19: 3497.37 | AT19: 10 | AU19: 30 | AV19: 110 | AW19: 17 | AX19: 16 | AY19: =IFERROR(VLOOKUP(C19,#REF!,13,0),"") | BA19: =IF(ISBLANK(AZ19),"Active","LEFT" ) -> Active | BB19: =_xludf.ifs(F19<$BB$1,"Old",F19>$BB$1,"New") -> #NAME? | BC19: =_xludf.ifs(AO19<50%,"Below 50%",AO19<70%,"50%-70%",AO19<90%,"70%-90%",AO19<100%,"90%-100%",AO19>100%,"Above 100%") -> #NAME? | BD19: =MATCH($BD$2,{"Apr","May","Jun","Jul","Aug","Sep","Oct","Nov","Dec","Jan","Feb","Mar"},0) -> 12 | BF19: =M19-AT19 -> 0 | BG19: Secondary | BH19: =IFERROR(__xludf.DUMMYFUNCTION("""COMPUTED_VALUE"""),8386751) -> 8386751 | BI19: =IFERROR(__xludf.DUMMYFUNCTION("""COMPUTED_VALUE"""),8640560.62) -> 8640560.6 | BL19: =BK19*BD19 -> 0 | BM19: =H19+BL19 -> 15000000 | BO19: =IFERROR(__xludf.DUMMYFUNCTION("IFERROR(ArrayFormula(SUM(VLOOKUP($C19,importrange(""1MwNMVzWE3QBVOyJjKr3eFX-Sq1Ng0Q1sghWJbgbE_8g"",""ORDER BOOKING REPORT 2024-25!C:CV""),{16,23,30},0))))"),3133686.62) -> 3133686.6 | BP19: =IFERROR(__xludf.DUMMYFUNCTION("IFERROR(ArrayFormula(SUM(VLOOKUP($C19,importrange(""1MwNMVzWE3QBVOyJjKr3eFX-Sq1Ng0Q1sghWJbgbE_8g"",""ORDER BOOKING REPORT 2024-25!C:CV""),{37,44,51},0))))"),1494036.87) -> 1494036.9 | BQ19: =IFERROR(__xludf.DUMMYFUNCTION("IFERROR(ArrayFormula(SUM(VLOOKUP($C19,importrange(""1MwNMVzWE3QBVOyJjKr3eFX-Sq1Ng0Q1sghWJbgbE_8g"",""ORDER BOOKING REPORT 2024-25!C:CV""),{58,65,72},0))))"),2049835.06) -> 2049835.1 | BR19: =IFERROR(__xludf.DUMMYFUNCTION("IFERROR(ArrayFormula(SUM(VLOOKUP($C19,importrange(""1MwNMVzWE3QBVOyJjKr3eFX-Sq1Ng0Q1sghWJbgbE_8g"",""ORDER BOOKING REPORT 2024-25!C:CV""),{79,86,93},0))))"),1963002.06999999) -> 1963002.1 | BS19: =IFERROR(AY19/BM19,"") | BT19: =IFERROR(SUM(AK19:AL19)/AY19,"") | BU19: =BL19-G19 -> 0 | BV19: 51335 | BW19: Area Sales Manager | BX19: 386 | BY19: =BV19-AJ19 -> 0 | CG19: =IF(N19<60,"Below 60"," ") | CH19: =IF(T19 = 0, "Not 50%", IF(T19 >= 0.5 * N19, "Business Achieved 50%", "Not 50%")) -> Business Achieved 50% | CI19: =IFERROR((T19/N19),) -> 0.76923077 | CJ19: =IFERROR(__xludf.DUMMYFUNCTION("""COMPUTED_VALUE"""),691) -> 691 | CK19: =IFERROR(__xludf.DUMMYFUNCTION("""COMPUTED_VALUE"""),41) -> 41 | CL19: =IFERROR(__xludf.DUMMYFUNCTION("""COMPUTED_VALUE"""),0) -> 0 | CM19: =AE19-SUM(CJ19:CL19) -> 0 | CP19: North East | CQ19: =COUNTIFS($B:$B,$CP19,$BG:$BG,"Secondary",$BA:$BA,"Active") -> 7 | CR19: =COUNTIFS($B:$B,$CP19,$BG:$BG,"Primary",$BA:$BA,"Active") -> 0 | CT19: =COUNTIFS(A:A,CS19,BA:BA,"Active") -> 0
A20: Sandeep Dadheech | B20: West Bengal | C20: Soumen Ghosh | D20: WEST BENGAL | E20: MECHADA | F20: 43009 | G20: 0 | H20: 0 | I20: 1259297.3 | J20: 0 | K20: 199 | L20: 162 | M20: 27 | N20: 226 | O20: 64 | P20: 966367 | Q20: 292930.28 | R20: 7 | S20: 1 | T20: 8 | U20: 0 | V20: 14 | W20: 18 | X20: 24 | Y20: 3 | Z20: 167 | AA20: 0 | AB20: 0 | AC20: 0 | AD20: 0 | AE20: 814 | AF20: 999 | AG20: 303 | AH20: =IFERROR(SUM(I20:J20)/AG20,"") -> 4156.0966 | AI20: =IFERROR(AF20/AG20,"") -> 3.2970297 | AJ20: 54455 | AK20: =AJ20*BD20 -> 653460 | AL20: 186147 | AM20: =IFERROR(SUM(AK20:AL20)/SUM(I20:J20),"") -> 0.6667266 | AN20: =IFERROR(I20/T20,"") -> 157412.16 | AO20: No Target | AP20: 0 | AQ20: 11 | AR20: 3123 | AS20: 3220.77 | AT20: 1 | AU20: 20 | AV20: 8 | AW20: 154 | AX20: 64 | AY20: =IFERROR(VLOOKUP(C20,#REF!,13,0),"") | BA20: =IF(ISBLANK(AZ20),"Active","LEFT" ) -> Active | BB20: =_xludf.ifs(F20<$BB$1,"Old",F20>$BB$1,"New") -> #NAME? | BC20: No Target | BD20: =MATCH($BD$2,{"Apr","May","Jun","Jul","Aug","Sep","Oct","Nov","Dec","Jan","Feb","Mar"},0) -> 12 | BF20: =M20-AT20 -> 26 | BG20: Primary | BH20: =IFERROR(__xludf.DUMMYFUNCTION("""COMPUTED_VALUE"""),131748574.1) -> 1.3174857e+08 | BI20: =IFERROR(__xludf.DUMMYFUNCTION("""COMPUTED_VALUE"""),92290520.9) -> 92290521 | BL20: =BK20*BD20 -> 0 | BM20: =H20+BL20 -> 0 | BO20: =IFERROR(__xludf.DUMMYFUNCTION("IFERROR(ArrayFormula(SUM(VLOOKUP($C20,importrange(""1MwNMVzWE3QBVOyJjKr3eFX-Sq1Ng0Q1sghWJbgbE_8g"",""ORDER BOOKING REPORT 2024-25!C:CV""),{16,23,30},0))))"),18653492.3) -> 18653492 | BP20: =IFERROR(__xludf.DUMMYFUNCTION("IFERROR(ArrayFormula(SUM(VLOOKUP($C20,importrange(""1MwNMVzWE3QBVOyJjKr3eFX-Sq1Ng0Q1sghWJbgbE_8g"",""ORDER BOOKING REPORT 2024-25!C:CV""),{37,44,51},0))))"),20690039.2) -> 20690039 | BQ20: =IFERROR(__xludf.DUMMYFUNCTION("IFERROR(ArrayFormula(SUM(VLOOKUP($C20,importrange(""1MwNMVzWE3QBVOyJjKr3eFX-Sq1Ng0Q1sghWJbgbE_8g"",""ORDER BOOKING REPORT 2024-25!C:CV""),{58,65,72},0))))"),22893689.2999999) -> 22893689 | BR20: =IFERROR(__xludf.DUMMYFUNCTION("IFERROR(ArrayFormula(SUM(VLOOKUP($C20,importrange(""1MwNMVzWE3QBVOyJjKr3eFX-Sq1Ng0Q1sghWJbgbE_8g"",""ORDER BOOKING REPORT 2024-25!C:CV""),{79,86,93},0))))"),30053300.1) -> 30053300 | BS20: =IFERROR(AY20/BM20,"") | BT20: =IFERROR(SUM(AK20:AL20)/AY20,"") | BU20: =BL20-G20 -> 0 | BV20: 54455 | BW20: Area Sales Manager | BX20: 439 | BY20: =BV20-AJ20 -> 0 | CG20: =IF(N20<60,"Below 60"," ") | CH20: =IF(T20 = 0, "Not 50%", IF(T20 >= 0.5 * N20, "Business Achieved 50%", "Not 50%")) -> Not 50% | CI20: =IFERROR((T20/N20),) -> 0.03539823 | CJ20: =IFERROR(__xludf.DUMMYFUNCTION("""COMPUTED_VALUE"""),88) -> 88 | CK20: =IFERROR(__xludf.DUMMYFUNCTION("""COMPUTED_VALUE"""),726) -> 726 | CL20: =IFERROR(__xludf.DUMMYFUNCTION("""COMPUTED_VALUE"""),0) -> 0 | CM20: =AE20-SUM(CJ20:CL20) -> 0 | CP20: Odisha | CQ20: =COUNTIFS($B:$B,$CP20,$BG:$BG,"Secondary",$BA:$BA,"Active") -> 6 | CR20: =COUNTIFS($B:$B,$CP20,$BG:$BG,"Primary",$BA:$BA,"Active") -> 0 | CT20: =COUNTIFS(A:A,CS20,BA:BA,"Active") -> 0
A21: Sandeep Dadheech | B21: West Bengal | C21: Sudipta Thom | D21: WEST BENGAL | E21: ANDAL | F21: 43119 | G21: 0 | H21: 45999996 | I21: 22746837 | J21: 0 | K21: 60 | L21: 41 | M21: 8 | N21: 68 | O21: 27 | P21: 21992735 | Q21: 754101.84 | R21: 8 | S21: 1 | T21: 9 | U21: 0 | V21: 11 | W21: 18 | X21: 66 | Y21: 4 | Z21: 89 | AA21: 0 | AB21: 0 | AC21: 0 | AD21: 0 | AE21: 336 | AF21: 443 | AG21: 282 | AH21: =IFERROR(SUM(I21:J21)/AG21,"") -> 80662.543 | AI21: =IFERROR(AF21/AG21,"") -> 1.570922 | AJ21: 56700 | AK21: =AJ21*BD21 -> 680400 | AL21: 199030 | AM21: =IFERROR(SUM(AK21:AL21)/SUM(I21:J21),"") -> 0.038661639 | AN21: =IFERROR(I21/T21,"") -> 2527426.3 | AO21: =IFERROR(SUM(I21:J21)/SUM(G21:H21),"") -> 0.4944965 | AP21: 0 | AQ21: 25 | AR21: 2327 | AS21: 2468.57 | AT21: 1 | AU21: 60 | AV21: 9 | AW21: 32 | AX21: 27 | AY21: =IFERROR(VLOOKUP(C21,#REF!,13,0),"") | BA21: =IF(ISBLANK(AZ21),"Active","LEFT" ) -> Active | BB21: =_xludf.ifs(F21<$BB$1,"Old",F21>$BB$1,"New") -> #NAME? | BC21: =_xludf.ifs(AO21<50%,"Below 50%",AO21<70%,"50%-70%",AO21<90%,"70%-90%",AO21<100%,"90%-100%",AO21>100%,"Above 100%") -> #NAME? | BD21: =MATCH($BD$2,{"Apr","May","Jun","Jul","Aug","Sep","Oct","Nov","Dec","Jan","Feb","Mar"},0) -> 12 | BF21: =M21-AT21 -> 7 | BG21: Secondary | BH21: =IFERROR(__xludf.DUMMYFUNCTION("""COMPUTED_VALUE"""),83333921.83) -> 83333922 | BI21: =IFERROR(__xludf.DUMMYFUNCTION("""COMPUTED_VALUE"""),51201429.4) -> 51201429 | BL21: =BK21*BD21 -> 0 | BM21: =H21+BL21 -> 45999996 | BO21: =IFERROR(__xludf.DUMMYFUNCTION("IFERROR(ArrayFormula(SUM(VLOOKUP($C21,importrange(""1MwNMVzWE3QBVOyJjKr3eFX-Sq1Ng0Q1sghWJbgbE_8g"",""ORDER BOOKING REPORT 2024-25!C:CV""),{16,23,30},0))))"),8987476.7) -> 8987476.7 | BP21: =IFERROR(__xludf.DUMMYFUNCTION("IFERROR(ArrayFormula(SUM(VLOOKUP($C21,importrange(""1MwNMVzWE3QBVOyJjKr3eFX-Sq1Ng0Q1sghWJbgbE_8g"",""ORDER BOOKING REPORT 2024-25!C:CV""),{37,44,51},0))))"),9986998.8) -> 9986998.8 | BQ21: =IFERROR(__xludf.DUMMYFUNCTION("IFERROR(ArrayFormula(SUM(VLOOKUP($C21,importrange(""1MwNMVzWE3QBVOyJjKr3eFX-Sq1Ng0Q1sghWJbgbE_8g"",""ORDER BOOKING REPORT 2024-25!C:CV""),{58,65,72},0))))"),19759840.9) -> 19759841 | BR21: =IFERROR(__xludf.DUMMYFUNCTION("IFERROR(ArrayFormula(SUM(VLOOKUP($C21,importrange(""1MwNMVzWE3QBVOyJjKr3eFX-Sq1Ng0Q1sghWJbgbE_8g"",""ORDER BOOKING REPORT 2024-25!C:CV""),{79,86,93},0))))"),12467113) -> 12467113 | BS21: =IFERROR(AY21/BM21,"") | BT21: =IFERROR(SUM(AK21:AL21)/AY21,"") | BU21: =BL21-G21 -> 0 | BV21: 56700 | BW21: Area Sales Manager | BX21: 437 | BY21: =BV21-AJ21 -> 0 | CG21: =IF(N21<60,"Below 60"," ") | CH21: =IF(T21 = 0, "Not 50%", IF(T21 >= 0.5 * N21, "Business Achieved 50%", "Not 50%")) -> Not 50% | CI21: =IFERROR((T21/N21),) -> 0.13235294 | CJ21: =IFERROR(__xludf.DUMMYFUNCTION("""COMPUTED_VALUE"""),242) -> 242 | CK21: =IFERROR(__xludf.DUMMYFUNCTION("""COMPUTED_VALUE"""),94) -> 94 | CL21: =IFERROR(__xludf.DUMMYFUNCTION("""COMPUTED_VALUE"""),0) -> 0 | CM21: =AE21-SUM(CJ21:CL21) -> 0 | CP21: Punjab | CQ21: =COUNTIFS($B:$B,$CP21,$BG:$BG,"Secondary",$BA:$BA,"Active") -> 2 | CR21: =COUNTIFS($B:$B,$CP21,$BG:$BG,"Primary",$BA:$BA,"Active") -> 1 | CT21: =COUNTIFS(A:A,CS21,BA:BA,"Active") -> 0
A22: Sandeep Dadheech | B22: Telangana | C22: Jithender Reddy Katukuri | D22: TELANGANA | E22: Warangal | F22: 43185 | G22: 3541667 | H22: 12600000 | I22: 4732528.9 | J22: 0 | K22: 109 | L22: 105 | M22: 7 | N22: 116 | O22: 11 | P22: 4523552.4 | Q22: 208976.54 | R22: 57 | S22: 4 | T22: 61 | U22: 0 | V22: 22 | W22: 46 | X22: 88 | Y22: 1 | Z22: 1 | AA22: 1 | AB22: 6 | AC22: 0 | AD22: 0 | AE22: 858 | AF22: 911 | AG22: 166 | AH22: =IFERROR(SUM(I22:J22)/AG22,"") -> 28509.21 | AI22: =IFERROR(AF22/AG22,"") -> 5.4879518 | AJ22: =BV22 -> 34650 | AK22: =AJ22*0.5 -> 17325 | AL22: 112040 | AM22: =IFERROR(SUM(AK22:AL22)/SUM(I22:J22),"") -> 0.027335279 | AN22: =IFERROR(I22/T22,"") -> 77582.441 | AO22: =IFERROR(SUM(I22:J22)/SUM(G22:H22),"") -> 0.29318712 | AP22: 0 | AQ22: 147 | AR22: 1699 | AS22: 2370.92 | AT22: 4 | AU22: 23 | AV22: 61 | AW22: 44 | AX22: 11 | AY22: =IFERROR(VLOOKUP(C22,#REF!,13,0),"") | BA22: =IF(ISBLANK(AZ22),"Active","LEFT" ) -> Active | BB22: =_xludf.ifs(F22<$BB$1,"Old",F22>$BB$1,"New") -> #NAME? | BC22: =_xludf.ifs(AO22<50%,"Below 50%",AO22<70%,"50%-70%",AO22<90%,"70%-90%",AO22<100%,"90%-100%",AO22>100%,"Above 100%") -> #NAME? | BD22: 8.5 | BF22: =M22-AT22 -> 3 | BG22: Secondary | BH22: =IFERROR(__xludf.DUMMYFUNCTION("""COMPUTED_VALUE"""),7359568.47) -> 7359568.5 | BI22: =IFERROR(__xludf.DUMMYFUNCTION("""COMPUTED_VALUE"""),8371547.44999999) -> 8371547.4 | BJ22: =15/30 -> 0.5 | BK22: 416666.67 | BL22: =BK22*BD22 -> 3541666.7 | BM22: =H22+BL22 -> 16141667 | BN22: On leave after 15th April to 5th Aug Due to Accident | BO22: =IFERROR(__xludf.DUMMYFUNCTION("IFERROR(ArrayFormula(SUM(VLOOKUP($C22,importrange(""1MwNMVzWE3QBVOyJjKr3eFX-Sq1Ng0Q1sghWJbgbE_8g"",""ORDER BOOKING REPORT 2024-25!C:CV""),{16,23,30},0))))"),3121686.5) -> 3121686.5 | BP22: =IFERROR(__xludf.DUMMYFUNCTION("IFERROR(ArrayFormula(SUM(VLOOKUP($C22,importrange(""1MwNMVzWE3QBVOyJjKr3eFX-Sq1Ng0Q1sghWJbgbE_8g"",""ORDER BOOKING REPORT 2024-25!C:CV""),{37,44,51},0))))"),1406274.7) -> 1406274.7 | BQ22: =IFERROR(__xludf.DUMMYFUNCTION("IFERROR(ArrayFormula(SUM(VLOOKUP($C22,importrange(""1MwNMVzWE3QBVOyJjKr3eFX-Sq1Ng0Q1sghWJbgbE_8g"",""ORDER BOOKING REPORT 2024-25!C:CV""),{58,65,72},0))))"),2098338.44999999) -> 2098338.4 | BR22: =IFERROR(__xludf.DUMMYFUNCTION("IFERROR(ArrayFormula(SUM(VLOOKUP($C22,importrange(""1MwNMVzWE3QBVOyJjKr3eFX-Sq1Ng0Q1sghWJbgbE_8g"",""ORDER BOOKING REPORT 2024-25!C:CV""),{79,86,93},0))))"),1745247.79999999) -> 1745247.8 | BS22: =IFERROR(AY22/BM22,"") | BT22: =IFERROR(SUM(AK22:AL22)/AY22,"") | BU22: =BL22-G22 -> -0.33305 | BV22: 34650 | BW22: Executive - Sales & Mkt. | BX22: 427 | BY22: =BV22-AJ22 -> 0 | CG22: =IF(N22<60,"Below 60"," ") | CH22: =IF(T22 = 0, "Not 50%", IF(T22 >= 0.5 * N22, "Business Achieved 50%", "Not 50%")) -> Business Achieved 50% | CI22: =IFERROR((T22/N22),) -> 0.52586207 | CJ22: =IFERROR(__xludf.DUMMYFUNCTION("""COMPUTED_VALUE"""),497) -> 497 | CK22: =IFERROR(__xludf.DUMMYFUNCTION("""COMPUTED_VALUE"""),361) -> 361 | CL22: =IFERROR(__xludf.DUMMYFUNCTION("""COMPUTED_VALUE"""),0) -> 0 | CM22: =AE22-SUM(CJ22:CL22) -> 0 | CP22: Rajasthan | CQ22: =COUNTIFS($B:$B,$CP22,$BG:$BG,"Secondary",$BA:$BA,"Active") -> 5 | CR22: =COUNTIFS($B:$B,$CP22,$BG:$BG,"Primary",$BA:$BA,"Active") -> 1 | CT22: =COUNTIFS(A:A,CS22,BA:BA,"Active") -> 0
A23: Sandeep Dadheech | B23: West Bengal | C23: Sudip Guha Roy | D23: WEST BENGAL | E23: Andal | F23: 43255 | G23: 0 | H23: 63999996 | I23: 32017276 | J23: 0 | K23: 145 | L23: 135 | M23: 6 | N23: 151 | O23: 16 | P23: 30960554 | Q23: 1056722 | R23: 49 | S23: 6 | T23: 55 | U23: 0 | V23: 17 | W23: 34 | X23: 33 | Y23: 3 | Z23: 62 | AA23: 0 | AB23: 0 | AC23: 0 | AD23: 0 | AE23: 1242 | AF23: 1338 | AG23: 299 | AH23: =IFERROR(SUM(I23:J23)/AG23,"") -> 107081.19 | AI23: =IFERROR(AF23/AG23,"") -> 4.4749164 | AJ23: 46670 | AK23: =AJ23*BD23 -> 560040 | AL23: 266780 | AM23: =IFERROR(SUM(AK23:AL23)/SUM(I23:J23),"") -> 0.025824183 | AN23: =IFERROR(I23/T23,"") -> 582132.29 | AO23: =IFERROR(SUM(I23:J23)/SUM(G23:H23),"") -> 0.50026997 | AP23: 0 | AQ23: 304 | AR23: 3183 | AS23: 1060.31 | AT23: 6 | AU23: 8 | AV23: 55 | AW23: 80 | AX23: 16 | AY23: =IFERROR(VLOOKUP(C23,#REF!,13,0),"") | BA23: =IF(ISBLANK(AZ23),"Active","LEFT" ) -> Active | BB23: =_xludf.ifs(F23<$BB$1,"Old",F23>$BB$1,"New") -> #NAME? | BC23: =_xludf.ifs(AO23<50%,"Below 50%",AO23<70%,"50%-70%",AO23<90%,"70%-90%",AO23<100%,"90%-100%",AO23>100%,"Above 100%") -> #NAME? | BD23: =MATCH($BD$2,{"Apr","May","Jun","Jul","Aug","Sep","Oct","Nov","Dec","Jan","Feb","Mar"},0) -> 12 | BF23: =M23-AT23 -> 0 | BG23: Secondary | BH23: =IFERROR(__xludf.DUMMYFUNCTION("""COMPUTED_VALUE"""),42903046) -> 42903046 | BI23: =IFERROR(__xludf.DUMMYFUNCTION("""COMPUTED_VALUE"""),39910377.05) -> 39910377 | BL23: =BK23*BD23 -> 0 | BM23: =H23+BL23 -> 63999996 | BO23: =IFERROR(__xludf.DUMMYFUNCTION("IFERROR(ArrayFormula(SUM(VLOOKUP($C23,importrange(""1MwNMVzWE3QBVOyJjKr3eFX-Sq1Ng0Q1sghWJbgbE_8g"",""ORDER BOOKING REPORT 2024-25!C:CV""),{16,23,30},0))))"),6376634.3) -> 6376634.3 | BP23: =IFERROR(__xludf.DUMMYFUNCTION("IFERROR(ArrayFormula(SUM(VLOOKUP($C23,importrange(""1MwNMVzWE3QBVOyJjKr3eFX-Sq1Ng0Q1sghWJbgbE_8g"",""ORDER BOOKING REPORT 2024-25!C:CV""),{37,44,51},0))))"),9433170.5) -> 9433170.5 | BQ23: =IFERROR(__xludf.DUMMYFUNCTION("IFERROR(ArrayFormula(SUM(VLOOKUP($C23,importrange(""1MwNMVzWE3QBVOyJjKr3eFX-Sq1Ng0Q1sghWJbgbE_8g"",""ORDER BOOKING REPORT 2024-25!C:CV""),{58,65,72},0))))"),12909662.55) -> 12909663 | BR23: =IFERROR(__xludf.DUMMYFUNCTION("IFERROR(ArrayFormula(SUM(VLOOKUP($C23,importrange(""1MwNMVzWE3QBVOyJjKr3eFX-Sq1Ng0Q1sghWJbgbE_8g"",""ORDER BOOKING REPORT 2024-25!C:CV""),{79,86,93},0))))"),11190909.7) -> 11190910 | BS23: =IFERROR(AY23/BM23,"") | BT23: =IFERROR(SUM(AK23:AL23)/AY23,"") | BU23: =BL23-G23 -> 0 | BV23: 46670 | BW23: Assistant Area Sales Manager | BX23: 477 | BY23: =BV23-AJ23 -> 0 | CG23: =IF(N23<60,"Below 60"," ") | CH23: =IF(T23 = 0, "Not 50%", IF(T23 >= 0.5 * N23, "Business Achieved 50%", "Not 50%")) -> Not 50% | CI23: =IFERROR((T23/N23),) -> 0.36423841 | CJ23: =IFERROR(__xludf.DUMMYFUNCTION("""COMPUTED_VALUE"""),696) -> 696 | CK23: =IFERROR(__xludf.DUMMYFUNCTION("""COMPUTED_VALUE"""),546) -> 546 | CL23: =IFERROR(__xludf.DUMMYFUNCTION("""COMPUTED_VALUE"""),0) -> 0 | CM23: =AE23-SUM(CJ23:CL23) -> 0 | CP23: Tamil Nadu | CQ23: =COUNTIFS($B:$B,$CP23,$BG:$BG,"Secondary",$BA:$BA,"Active") -> 4 | CR23: =COUNTIFS($B:$B,$CP23,$BG:$BG,"Primary",$BA:$BA,"Active") -> 0 | CT23: =COUNTIFS(A:A,CS23,BA:BA,"Active") -> 0
A24: Syed Aqil Rizvi | B24: Madhya Pradesh | C24: Faraz Khan | D24: MADHYA PRADESH | E24: Bhopal | F24: 43315 | G24: 3600000 | H24: 46400004 | I24: 47014465 | J24: 298483.24 | K24: 106 | L24: 122 | M24: 21 | N24: 127 | O24: 5 | P24: 45115570 | Q24: 1898894.2 | R24: 85 | S24: 15 | T24: 100 | U24: 2 | V24: 14 | W24: 18 | X24: 11 | Y24: 10 | Z24: 63 | AA24: 2 | AB24: 2 | AC24: 3 | AD24: 3 | AE24: 1288 | AF24: 1374 | AG24: 294 | AH24: =IFERROR(SUM(I24:J24)/AG24,"") -> 160928.39 | AI24: =IFERROR(AF24/AG24,"") -> 4.6734694 | AJ24: =BV24 -> 140000 | AK24: =AJ24*BD24 -> 1680000 | AL24: 290356 | AM24: =IFERROR(SUM(AK24:AL24)/SUM(I24:J24),"") -> 0.041645175 | AN24: =IFERROR(I24/T24,"") -> 470144.65 | AO24: =IFERROR(SUM(I24:J24)/SUM(G24:H24),"") -> 0.94625888 | AP24: 0.08 | AQ24: 1348 | AR24: 2273 | AS24: 1239.02 | AT24: 15 | AU24: 10 | AV24: 100 | AW24: 23 | AX24: 4 | AY24: =IFERROR(VLOOKUP(C24,#REF!,13,0),"") | BA24: =IF(ISBLANK(AZ24),"Active","LEFT" ) -> Active | BB24: =_xludf.ifs(F24<$BB$1,"Old",F24>$BB$1,"New") -> #NAME? | BC24: =_xludf.ifs(AO24<50%,"Below 50%",AO24<70%,"50%-70%",AO24<90%,"70%-90%",AO24<100%,"90%-100%",AO24>100%,"Above 100%") -> #NAME? | BD24: =MATCH($BD$2,{"Apr","May","Jun","Jul","Aug","Sep","Oct","Nov","Dec","Jan","Feb","Mar"},0) -> 12 | BF24: =M24-AT24 -> 6 | BG24: Secondary | BH24: =IFERROR(__xludf.DUMMYFUNCTION("""COMPUTED_VALUE"""),42196144) -> 42196144 | BI24: =IFERROR(__xludf.DUMMYFUNCTION("""COMPUTED_VALUE"""),44050491.0099999) -> 44050491 | BK24: 300000 | BL24: =BK24*BD24 -> 3600000 | BM24: =H24+BL24 -> 50000004 | BO24: =IFERROR(__xludf.DUMMYFUNCTION("IFERROR(ArrayFormula(SUM(VLOOKUP($C24,importrange(""1MwNMVzWE3QBVOyJjKr3eFX-Sq1Ng0Q1sghWJbgbE_8g"",""ORDER BOOKING REPORT 2024-25!C:CV""),{16,23,30},0))))"),11035728.9299999) -> 11035729 | BP24: =IFERROR(__xludf.DUMMYFUNCTION("IFERROR(ArrayFormula(SUM(VLOOKUP($C24,importrange(""1MwNMVzWE3QBVOyJjKr3eFX-Sq1Ng0Q1sghWJbgbE_8g"",""ORDER BOOKING REPORT 2024-25!C:CV""),{37,44,51},0))))"),10533376.48) -> 10533376 | BQ24: =IFERROR(__xludf.DUMMYFUNCTION("IFERROR(ArrayFormula(SUM(VLOOKUP($C24,importrange(""1MwNMVzWE3QBVOyJjKr3eFX-Sq1Ng0Q1sghWJbgbE_8g"",""ORDER BOOKING REPORT 2024-25!C:CV""),{58,65,72},0))))"),10290973.34) -> 10290973 | BR24: =IFERROR(__xludf.DUMMYFUNCTION("IFERROR(ArrayFormula(SUM(VLOOKUP($C24,importrange(""1MwNMVzWE3QBVOyJjKr3eFX-Sq1Ng0Q1sghWJbgbE_8g"",""ORDER BOOKING REPORT 2024-25!C:CV""),{79,86,93},0))))"),12190412.2599999) -> 12190412 | BS24: =IFERROR(AY24/BM24,"") | BT24: =IFERROR(SUM(AK24:AL24)/AY24,"") | BU24: =BL24-G24 -> 0 | BV24: 140000 | BW24: Regional Sales Manager | BX24: 464 | BY24: =BV24-AJ24 -> 0 | CG24: =IF(N24<60,"Below 60"," ") | CH24: =IF(T24 = 0, "Not 50%", IF(T24 >= 0.5 * N24, "Business Achieved 50%", "Not 50%")) -> Business Achieved 50% | CI24: =IFERROR((T24/N24),) -> 0.78740157 | CJ24: =IFERROR(__xludf.DUMMYFUNCTION("""COMPUTED_VALUE"""),1250) -> 1250 | CK24: =IFERROR(__xludf.DUMMYFUNCTION("""COMPUTED_VALUE"""),38) -> 38 | CL24: =IFERROR(__xludf.DUMMYFUNCTION("""COMPUTED_VALUE"""),0) -> 0 | CM24: =AE24-SUM(CJ24:CL24) -> 0 | CP24: Telangana | CQ24: =COUNTIFS($B:$B,$CP24,$BG:$BG,"Secondary",$BA:$BA,"Active") -> 3 | CR24: =COUNTIFS($B:$B,$CP24,$BG:$BG,"Primary",$BA:$BA,"Active") -> 0 | CT24: =COUNTIFS(A:A,CS24,BA:BA,"Active") -> 0
A25: Sandeep Dadheech | B25: Andhra Pradesh | C25: Shaik Jani basha | D25: ANDHRA PRADESH | E25: Vijayawada | F25: 43424 | G25: 9999996 | H25: 25200000 | I25: 12739177 | J25: 550029.48 | K25: 124 | L25: 96 | M25: 10 | N25: 134 | O25: 38 | P25: 11851446 | Q25: 887731.71 | R25: 91 | S25: 10 | T25: 101 | U25: 2 | V25: 3 | W25: 7 | X25: 16 | Y25: 8 | Z25: 123 | AA25: 3 | AB25: 63 | AC25: 0 | AD25: 0 | AE25: 1108 | AF25: 1301 | AG25: 276 | AH25: =IFERROR(SUM(I25:J25)/AG25,"") -> 48149.301 | AI25: =IFERROR(AF25/AG25,"") -> 4.7137681 | AJ25: =BV25 -> 41430 | AK25: =AJ25*BD25 -> 497160 | AL25: 183012 | AM25: =IFERROR(SUM(AK25:AL25)/SUM(I25:J25),"") -> 0.051182287 | AN25: =IFERROR(I25/T25,"") -> 126130.47 | AO25: =IFERROR(SUM(I25:J25)/SUM(G25:H25),"") -> 0.37753433 | AP25: 0.05 | AQ25: 658 | AR25: 2300 | AS25: 2131.73 | AT25: 10 | AU25: 22 | AV25: 101 | AW25: 23 | AX25: 10 | AY25: =IFERROR(VLOOKUP(C25,#REF!,13,0),"") | BA25: =IF(ISBLANK(AZ25),"Active","LEFT" ) -> Active | BB25: =_xludf.ifs(F25<$BB$1,"Old",F25>$BB$1,"New") -> #NAME? | BC25: =_xludf.ifs(AO25<50%,"Below 50%",AO25<70%,"50%-70%",AO25<90%,"70%-90%",AO25<100%,"90%-100%",AO25>100%,"Above 100%") -> #NAME? | BD25: =MATCH($BD$2,{"Apr","May","Jun","Jul","Aug","Sep","Oct","Nov","Dec","Jan","Feb","Mar"},0) -> 12 | BF25: =M25-AT25 -> 0 | BG25: Secondary | BH25: =IFERROR(__xludf.DUMMYFUNCTION("""COMPUTED_VALUE"""),11767268.16) -> 11767268 | BI25: =IFERROR(__xludf.DUMMYFUNCTION("""COMPUTED_VALUE"""),11100724.15) -> 11100724 | BK25: 833333.33 | BL25: =BK25*BD25 -> 10000000 | BM25: =H25+BL25 -> 35200000 | BO25: =IFERROR(__xludf.DUMMYFUNCTION("IFERROR(ArrayFormula(SUM(VLOOKUP($C25,importrange(""1MwNMVzWE3QBVOyJjKr3eFX-Sq1Ng0Q1sghWJbgbE_8g"",""ORDER BOOKING REPORT 2024-25!C:CV""),{16,23,30},0))))"),2692764.63999999) -> 2692764.6 | BP25: =IFERROR(__xludf.DUMMYFUNCTION("IFERROR(ArrayFormula(SUM(VLOOKUP($C25,importrange(""1MwNMVzWE3QBVOyJjKr3eFX-Sq1Ng0Q1sghWJbgbE_8g"",""ORDER BOOKING REPORT 2024-25!C:CV""),{37,44,51},0))))"),2815892.24) -> 2815892.2 | BQ25: =IFERROR(__xludf.DUMMYFUNCTION("IFERROR(ArrayFormula(SUM(VLOOKUP($C25,importrange(""1MwNMVzWE3QBVOyJjKr3eFX-Sq1Ng0Q1sghWJbgbE_8g"",""ORDER BOOKING REPORT 2024-25!C:CV""),{58,65,72},0))))"),3100280.98) -> 3100281 | BR25: =IFERROR(__xludf.DUMMYFUNCTION("IFERROR(ArrayFormula(SUM(VLOOKUP($C25,importrange(""1MwNMVzWE3QBVOyJjKr3eFX-Sq1Ng0Q1sghWJbgbE_8g"",""ORDER BOOKING REPORT 2024-25!C:CV""),{79,86,93},0))))"),2491786.29) -> 2491786.3 | BS25: =IFERROR(AY25/BM25,"") | BT25: =IFERROR(SUM(AK25:AL25)/AY25,"") | BU25: =BL25-G25 -> 3.9996 | BV25: 41430 | BW25: Area Sales Manager | BX25: 485 | BY25: =BV25-AJ25 -> 0 | CG25: =IF(N25<60,"Below 60"," ") | CH25: =IF(T25 = 0, "Not 50%", IF(T25 >= 0.5 * N25, "Business Achieved 50%", "Not 50%")) -> Business Achieved 50% | CI25: =IFERROR((T25/N25),) -> 0.75373134 | CJ25: =IFERROR(__xludf.DUMMYFUNCTION("""COMPUTED_VALUE"""),1028) -> 1028 | CK25: =IFERROR(__xludf.DUMMYFUNCTION("""COMPUTED_VALUE"""),80) -> 80 | CL25: =IFERROR(__xludf.DUMMYFUNCTION("""COMPUTED_VALUE"""),0) -> 0 | CM25: =AE25-SUM(CJ25:CL25) -> 0 | CP25: Uttarakhand | CQ25: =COUNTIFS($B:$B,$CP25,$BG:$BG,"Secondary",$BA:$BA,"Active") -> 2 | CR25: =COUNTIFS($B:$B,$CP25,$BG:$BG,"Primary",$BA:$BA,"Active") -> 0 | CT25: =COUNTIFS(A:A,CS25,BA:BA,"Active") -> 0
A26: Sandeep Dadheech | B26: Odisha | C26: Sunil Kumar Pani | D26: ODISHA | E26: Balasore | F26: 43556 | G26: 0 | H26: 24000000 | I26: 19321509 | J26: 0 | K26: 70 | L26: 71 | M26: 6 | N26: 76 | O26: 5 | P26: 18865364 | Q26: 456145.07 | R26: 42 | S26: 4 | T26: 46 | U26: 0 | V26: 0 | W26: 0 | X26: 0 | Y26: 2 | Z26: 163 | AA26: 0 | AB26: 0 | AC26: 0 | AD26: 0 | AE26: 1229 | AF26: 1392 | AG26: 302 | AH26: =IFERROR(SUM(I26:J26)/AG26,"") -> 63978.507 | AI26: =IFERROR(AF26/AG26,"") -> 4.6092715 | AJ26: 39070 | AK26: =AJ26*BD26 -> 468840 | AL26: 153075 | AM26: =IFERROR(SUM(AK26:AL26)/SUM(I26:J26),"") -> 0.032187703 | AN26: =IFERROR(I26/T26,"") -> 420032.81 | AO26: =IFERROR(SUM(I26:J26)/SUM(G26:H26),"") -> 0.80506288 | AP26: 0 | AQ26: 282 | AR26: 2565 | AS26: 1571.7 | AT26: 4 | AU26: 22 | AV26: 46 | AW26: 26 | AX26: 4 | AY26: =IFERROR(VLOOKUP(C26,#REF!,13,0),"") | BA26: =IF(ISBLANK(AZ26),"Active","LEFT" ) -> Active | BB26: =_xludf.ifs(F26<$BB$1,"Old",F26>$BB$1,"New") -> #NAME? | BC26: =_xludf.ifs(AO26<50%,"Below 50%",AO26<70%,"50%-70%",AO26<90%,"70%-90%",AO26<100%,"90%-100%",AO26>100%,"Above 100%") -> #NAME? | BD26: =MATCH($BD$2,{"Apr","May","Jun","Jul","Aug","Sep","Oct","Nov","Dec","Jan","Feb","Mar"},0) -> 12 | BF26: =M26-AT26 -> 2 | BG26: Secondary | BH26: =IFERROR(__xludf.DUMMYFUNCTION("""COMPUTED_VALUE"""),16969894.6) -> 16969895 | BI26: =IFERROR(__xludf.DUMMYFUNCTION("""COMPUTED_VALUE"""),15818502.7) -> 15818503 | BL26: =BK26*BD26 -> 0 | BM26: =H26+BL26 -> 24000000 | BO26: =IFERROR(__xludf.DUMMYFUNCTION("IFERROR(ArrayFormula(SUM(VLOOKUP($C26,importrange(""1MwNMVzWE3QBVOyJjKr3eFX-Sq1Ng0Q1sghWJbgbE_8g"",""ORDER BOOKING REPORT 2024-25!C:CV""),{16,23,30},0))))"),3763058.5) -> 3763058.5 | BP26: =IFERROR(__xludf.DUMMYFUNCTION("IFERROR(ArrayFormula(SUM(VLOOKUP($C26,importrange(""1MwNMVzWE3QBVOyJjKr3eFX-Sq1Ng0Q1sghWJbgbE_8g"",""ORDER BOOKING REPORT 2024-25!C:CV""),{37,44,51},0))))"),4721427.7) -> 4721427.7 | BQ26: =IFERROR(__xludf.DUMMYFUNCTION("IFERROR(ArrayFormula(SUM(VLOOKUP($C26,importrange(""1MwNMVzWE3QBVOyJjKr3eFX-Sq1Ng0Q1sghWJbgbE_8g"",""ORDER BOOKING REPORT 2024-25!C:CV""),{58,65,72},0))))"),2887047.17999999) -> 2887047.2 | BR26: =IFERROR(__xludf.DUMMYFUNCTION("IFERROR(ArrayFormula(SUM(VLOOKUP($C26,importrange(""1MwNMVzWE3QBVOyJjKr3eFX-Sq1Ng0Q1sghWJbgbE_8g"",""ORDER BOOKING REPORT 2024-25!C:CV""),{79,86,93},0))))"),4446969.32) -> 4446969.3 | BS26: =IFERROR(AY26/BM26,"") | BT26: =IFERROR(SUM(AK26:AL26)/AY26,"") | BU26: =BL26-G26 -> 0 | BV26: 39070 | BW26: Sr. Executive - Sales & Mktg. | BX26: 518 | BY26: =BV26-AJ26 -> 0 | CG26: =IF(N26<60,"Below 60"," ") | CH26: =IF(T26 = 0, "Not 50%", IF(T26 >= 0.5 * N26, "Business Achieved 50%", "Not 50%")) -> Business Achieved 50% | CI26: =IFERROR((T26/N26),) -> 0.60526316 | CJ26: =IFERROR(__xludf.DUMMYFUNCTION("""COMPUTED_VALUE"""),851) -> 851 | CK26: =IFERROR(__xludf.DUMMYFUNCTION("""COMPUTED_VALUE"""),378) -> 378 | CL26: =IFERROR(__xludf.DUMMYFUNCTION("""COMPUTED_VALUE"""),0) -> 0 | CM26: =AE26-SUM(CJ26:CL26) -> 0 | CP26: West Bengal | CQ26: =COUNTIFS($B:$B,$CP26,$BG:$BG,"Secondary",$BA:$BA,"Active") -> 28 | CR26: =COUNTIFS($B:$B,$CP26,$BG:$BG,"Primary",$BA:$BA,"Active") -> 4 | CT26: =COUNTIFS(A:A,CS26,BA:BA,"Active") -> 0
A27: Sandeep Dadheech | B27: Tamil Nadu | C27: M. Raman | D27: PONDICHERRY, TAMIL NADU | E27: Trichy | F27: 43557 | G27: 0 | H27: 20000004 | I27: 13110227 | J27: 0 | K27: 156 | L27: 163 | M27: 16 | N27: 172 | O27: 9 | P27: 11204322 | Q27: 1905905.7 | R27: 83 | S27: 14 | T27: 97 | U27: 0 | V27: 56 | W27: 114 | X27: 14 | Y27: 7 | Z27: 78 | AA27: 0 | AB27: 0 | AC27: 0 | AD27: 0 | AE27: 1647 | AF27: 1839 | AG27: 295 | AH27: =IFERROR(SUM(I27:J27)/AG27,"") -> 44441.448 | AI27: =IFERROR(AF27/AG27,"") -> 6.2338983 | AJ27: =BV27 -> 54510 | AK27: =AJ27*BD27 -> 654120 | AL27: 287915 | AM27: =IFERROR(SUM(AK27:AL27)/SUM(I27:J27),"") -> 0.071854971 | AN27: =IFERROR(I27/T27,"") -> 135156.98 | AO27: =IFERROR(SUM(I27:J27)/SUM(G27:H27),"") -> 0.65551123 | AP27: 0 | AQ27: 557 | AR27: 3077 | AS27: 3857.52 | AT27: 14 | AU27: 24 | AV27: 97 | AW27: 67 | AX27: 8 | AY27: =IFERROR(VLOOKUP(C27,#REF!,13,0),"") | BA27: =IF(ISBLANK(AZ27),"Active","LEFT" ) -> Active | BB27: =_xludf.ifs(F27<$BB$1,"Old",F27>$BB$1,"New") -> #NAME? | BC27: =_xludf.ifs(AO27<50%,"Below 50%",AO27<70%,"50%-70%",AO27<90%,"70%-90%",AO27<100%,"90%-100%",AO27>100%,"Above 100%") -> #NAME? | BD27: =MATCH($BD$2,{"Apr","May","Jun","Jul","Aug","Sep","Oct","Nov","Dec","Jan","Feb","Mar"},0) -> 12 | BF27: =M27-AT27 -> 2 | BG27: Secondary | BH27: =IFERROR(__xludf.DUMMYFUNCTION("""COMPUTED_VALUE"""),13932526) -> 13932526 | BI27: =IFERROR(__xludf.DUMMYFUNCTION("""COMPUTED_VALUE"""),13777186.43) -> 13777186 | BL27: =BK27*BD27 -> 0 | BM27: =H27+BL27 -> 20000004 | BO27: =IFERROR(__xludf.DUMMYFUNCTION("IFERROR(ArrayFormula(SUM(VLOOKUP($C27,importrange(""1MwNMVzWE3QBVOyJjKr3eFX-Sq1Ng0Q1sghWJbgbE_8g"",""ORDER BOOKING REPORT 2024-25!C:CV""),{16,23,30},0))))"),3550408.39999999) -> 3550408.4 | BP27: =IFERROR(__xludf.DUMMYFUNCTION("IFERROR(ArrayFormula(SUM(VLOOKUP($C27,importrange(""1MwNMVzWE3QBVOyJjKr3eFX-Sq1Ng0Q1sghWJbgbE_8g"",""ORDER BOOKING REPORT 2024-25!C:CV""),{37,44,51},0))))"),3380054.98) -> 3380055 | BQ27: =IFERROR(__xludf.DUMMYFUNCTION("IFERROR(ArrayFormula(SUM(VLOOKUP($C27,importrange(""1MwNMVzWE3QBVOyJjKr3eFX-Sq1Ng0Q1sghWJbgbE_8g"",""ORDER BOOKING REPORT 2024-25!C:CV""),{58,65,72},0))))"),3554315.25) -> 3554315.2 | BR27: =IFERROR(__xludf.DUMMYFUNCTION("IFERROR(ArrayFormula(SUM(VLOOKUP($C27,importrange(""1MwNMVzWE3QBVOyJjKr3eFX-Sq1Ng0Q1sghWJbgbE_8g"",""ORDER BOOKING REPORT 2024-25!C:CV""),{79,86,93},0))))"),3292407.8) -> 3292407.8 | BS27: =IFERROR(AY27/BM27,"") | BT27: =IFERROR(SUM(AK27:AL27)/AY27,"") | BU27: =BL27-G27 -> 0 | BV27: 54510 | BW27: Area Sales Manager | BX27: 510 | BY27: =BV27-AJ27 -> 0 | CG27: =IF(N27<60,"Below 60"," ") | CH27: =IF(T27 = 0, "Not 50%", IF(T27 >= 0.5 * N27, "Business Achieved 50%", "Not 50%")) -> Business Achieved 50% | CI27: =IFERROR((T27/N27),) -> 0.56395349 | CJ27: =IFERROR(__xludf.DUMMYFUNCTION("""COMPUTED_VALUE"""),1276) -> 1276 | CK27: =IFERROR(__xludf.DUMMYFUNCTION("""COMPUTED_VALUE"""),371) -> 371 | CL27: =IFERROR(__xludf.DUMMYFUNCTION("""COMPUTED_VALUE"""),0) -> 0 | CM27: =AE27-SUM(CJ27:CL27) -> 0 | CP27: West U.P | CQ27: =COUNTIFS($B:$B,$CP27,$BG:$BG,"Secondary",$BA:$BA,"Active") -> 5 | CR27: =COUNTIFS($B:$B,$CP27,$BG:$BG,"Primary",$BA:$BA,"Active") -> 0 | CT27: =COUNTIFS(A:A,CS27,BA:BA,"Active") -> 0
A28: Sandeep Dadheech | B28: Bihar | C28: Pramod Kumar | D28: BIHAR | E28: Purnea | F28: 43647 | G28: 0 | H28: 75000000 | I28: 64945604 | J28: 0 | K28: 90 | L28: 106 | M28: 17 | N28: 107 | O28: 1 | P28: 54329707 | Q28: 10615897 | R28: 68 | S28: 16 | T28: 84 | U28: 0 | V28: 28 | W28: 60 | X28: 24 | Y28: 1 | Z28: 78 | AA28: 0 | AB28: 0 | AC28: 0 | AD28: 0 | AE28: 1317 | AF28: 1455 | AG28: 296 | AH28: =IFERROR(SUM(I28:J28)/AG28,"") -> 219410.82 | AI28: =IFERROR(AF28/AG28,"") -> 4.9155405 | AJ28: 32605 | AK28: =AJ28*BD28 -> 391260 | AL28: 170669 | AM28: =IFERROR(SUM(AK28:AL28)/SUM(I28:J28),"") -> 0.0086523024 | AN28: =IFERROR(I28/T28,"") -> 773161.95 | AO28: =IFERROR(SUM(I28:J28)/SUM(G28:H28),"") -> 0.86594138 | AP28: 0 | AQ28: 739 | AR28: 3126 | AS28: 3757.43 | AT28: 16 | AU28: 35 | AV28: 84 | AW28: 23 | AX28: 0 | AY28: =IFERROR(VLOOKUP(C28,#REF!,13,0),"") | BA28: =IF(ISBLANK(AZ28),"Active","LEFT" ) -> Active | BB28: =_xludf.ifs(F28<$BB$1,"Old",F28>$BB$1,"New") -> #NAME? | BC28: =_xludf.ifs(AO28<50%,"Below 50%",AO28<70%,"50%-70%",AO28<90%,"70%-90%",AO28<100%,"90%-100%",AO28>100%,"Above 100%") -> #NAME? | BD28: =MATCH($BD$2,{"Apr","May","Jun","Jul","Aug","Sep","Oct","Nov","Dec","Jan","Feb","Mar"},0) -> 12 | BF28: =M28-AT28 -> 1 | BG28: Secondary | BH28: =IFERROR(__xludf.DUMMYFUNCTION("""COMPUTED_VALUE"""),71069534.32) -> 71069534 | BI28: =IFERROR(__xludf.DUMMYFUNCTION("""COMPUTED_VALUE"""),60822384.19) -> 60822384 | BL28: =BK28*BD28 -> 0 | BM28: =H28+BL28 -> 75000000 | BO28: =IFERROR(__xludf.DUMMYFUNCTION("IFERROR(ArrayFormula(SUM(VLOOKUP($C28,importrange(""1MwNMVzWE3QBVOyJjKr3eFX-Sq1Ng0Q1sghWJbgbE_8g"",""ORDER BOOKING REPORT 2024-25!C:CV""),{16,23,30},0))))"),12063804.6699999) -> 12063805 | BP28: =IFERROR(__xludf.DUMMYFUNCTION("IFERROR(ArrayFormula(SUM(VLOOKUP($C28,importrange(""1MwNMVzWE3QBVOyJjKr3eFX-Sq1Ng0Q1sghWJbgbE_8g"",""ORDER BOOKING REPORT 2024-25!C:CV""),{37,44,51},0))))"),18014454.7) -> 18014455 | BQ28: =IFERROR(__xludf.DUMMYFUNCTION("IFERROR(ArrayFormula(SUM(VLOOKUP($C28,importrange(""1MwNMVzWE3QBVOyJjKr3eFX-Sq1Ng0Q1sghWJbgbE_8g"",""ORDER BOOKING REPORT 2024-25!C:CV""),{58,65,72},0))))"),12537991.32) -> 12537991 | BR28: =IFERROR(__xludf.DUMMYFUNCTION("IFERROR(ArrayFormula(SUM(VLOOKUP($C28,importrange(""1MwNMVzWE3QBVOyJjKr3eFX-Sq1Ng0Q1sghWJbgbE_8g"",""ORDER BOOKING REPORT 2024-25!C:CV""),{79,86,93},0))))"),18206133.5) -> 18206134 | BS28: =IFERROR(AY28/BM28,"") | BT28: =IFERROR(SUM(AK28:AL28)/AY28,"") | BU28: =BL28-G28 -> 0 | BV28: 32605 | BW28: Sr. Executive - Sales & Mktg. | BX28: 627 | BY28: =BV28-AJ28 -> 0 | CG28: =IF(N28<60,"Below 60"," ") | CH28: =IF(T28 = 0, "Not 50%", IF(T28 >= 0.5 * N28, "Business Achieved 50%", "Not 50%")) -> Business Achieved 50% | CI28: =IFERROR((T28/N28),) -> 0.78504673 | CJ28: =IFERROR(__xludf.DUMMYFUNCTION("""COMPUTED_VALUE"""),1183) -> 1183 | CK28: =IFERROR(__xludf.DUMMYFUNCTION("""COMPUTED_VALUE"""),134) -> 134 | CL28: =IFERROR(__xludf.DUMMYFUNCTION("""COMPUTED_VALUE"""),0) -> 0 | CM28: =AE28-SUM(CJ28:CL28) -> 0 | CT28: =COUNTIFS(A:A,CS28,BA:BA,"Active") -> 0
A29: Sandeep Dadheech | B29: Odisha | C29: Sasikant Prasad | D29: ODISHA | E29: Raurkela | F29: 43710 | G29: 0 | H29: 24000000 | I29: 17570627 | J29: 1385954.1 | K29: 52 | L29: 54 | M29: 4 | N29: 56 | O29: 2 | P29: 16263606 | Q29: 1307020.9 | R29: 47 | S29: 4 | T29: 51 | U29: 2 | V29: 13 | W29: 32 | X29: 25 | Y29: 2 | Z29: 10 | AA29: 3 | AB29: 124 | AC29: 0 | AD29: 0 | AE29: 1130 | AF29: 1296 | AG29: 284 | AH29: =IFERROR(SUM(I29:J29)/AG29,"") -> 66748.525 | AI29: =IFERROR(AF29/AG29,"") -> 4.5633803 | AJ29: 50950 | AK29: =AJ29*BD29 -> 611400 | AL29: 202283 | AM29: =IFERROR(SUM(AK29:AL29)/SUM(I29:J29),"") -> 0.04292351 | AN29: =IFERROR(I29/T29,"") -> 344522.1 | AO29: =IFERROR(SUM(I29:J29)/SUM(G29:H29),"") -> 0.78985755 | AP29: 0 | AQ29: 562 | AR29: 3079 | AS29: 5370.53 | AT29: 4 | AU29: 99 | AV29: 51 | AW29: 3 | AX29: 2 | AY29: =IFERROR(VLOOKUP(C29,#REF!,13,0),"") | BA29: =IF(ISBLANK(AZ29),"Active","LEFT" ) -> Active | BB29: =_xludf.ifs(F29<$BB$1,"Old",F29>$BB$1,"New") -> #NAME? | BC29: =_xludf.ifs(AO29<50%,"Below 50%",AO29<70%,"50%-70%",AO29<90%,"70%-90%",AO29<100%,"90%-100%",AO29>100%,"Above 100%") -> #NAME? | BD29: =MATCH($BD$2,{"Apr","May","Jun","Jul","Aug","Sep","Oct","Nov","Dec","Jan","Feb","Mar"},0) -> 12 | BF29: =M29-AT29 -> 0 | BG29: Secondary | BH29: =IFERROR(__xludf.DUMMYFUNCTION("""COMPUTED_VALUE"""),13753144.49) -> 13753144 | BI29: =IFERROR(__xludf.DUMMYFUNCTION("""COMPUTED_VALUE"""),17773415.72) -> 17773416 | BL29: =BK29*BD29 -> 0 | BM29: =H29+BL29 -> 24000000 | BO29: =IFERROR(__xludf.DUMMYFUNCTION("IFERROR(ArrayFormula(SUM(VLOOKUP($C29,importrange(""1MwNMVzWE3QBVOyJjKr3eFX-Sq1Ng0Q1sghWJbgbE_8g"",""ORDER BOOKING REPORT 2024-25!C:CV""),{16,23,30},0))))"),4783553.1) -> 4783553.1 | BP29: =IFERROR(__xludf.DUMMYFUNCTION("IFERROR(ArrayFormula(SUM(VLOOKUP($C29,importrange(""1MwNMVzWE3QBVOyJjKr3eFX-Sq1Ng0Q1sghWJbgbE_8g"",""ORDER BOOKING REPORT 2024-25!C:CV""),{37,44,51},0))))"),3565758.7) -> 3565758.7 | BQ29: =IFERROR(__xludf.DUMMYFUNCTION("IFERROR(ArrayFormula(SUM(VLOOKUP($C29,importrange(""1MwNMVzWE3QBVOyJjKr3eFX-Sq1Ng0Q1sghWJbgbE_8g"",""ORDER BOOKING REPORT 2024-25!C:CV""),{58,65,72},0))))"),4461508.06) -> 4461508.1 | BR29: =IFERROR(__xludf.DUMMYFUNCTION("IFERROR(ArrayFormula(SUM(VLOOKUP($C29,importrange(""1MwNMVzWE3QBVOyJjKr3eFX-Sq1Ng0Q1sghWJbgbE_8g"",""ORDER BOOKING REPORT 2024-25!C:CV""),{79,86,93},0))))"),4962595.86) -> 4962595.9 | BS29: =IFERROR(AY29/BM29,"") | BT29: =IFERROR(SUM(AK29:AL29)/AY29,"") | BU29: =BL29-G29 -> 0 | BV29: 50950 | BW29: Area Sales Manager | BX29: 555 | BY29: =BV29-AJ29 -> 0 | CG29: =IF(N29<60,"Below 60"," ") -> Below 60 | CH29: =IF(T29 = 0, "Not 50%", IF(T29 >= 0.5 * N29, "Business Achieved 50%", "Not 50%")) -> Business Achieved 50% | CI29: =IFERROR((T29/N29),) -> 0.91071429 | CJ29: =IFERROR(__xludf.DUMMYFUNCTION("""COMPUTED_VALUE"""),1121) -> 1121 | CK29: =IFERROR(__xludf.DUMMYFUNCTION("""COMPUTED_VALUE"""),9) -> 9 | CL29: =IFERROR(__xludf.DUMMYFUNCTION("""COMPUTED_VALUE"""),0) -> 0 | CM29: =AE29-SUM(CJ29:CL29) -> 0 | CT29: =COUNTIFS(A:A,CS29,BA:BA,"Active") -> 0
A30: Sandeep Dadheech | B30: North East | C30: Litan Saha | D30: ARUNACHAL PRADESH, ASSAM, MANIPUR, MEGHALAYA, MIZORAM, NAGALAND, SIKKIM, TRIPURA | E30: Agartala | F30: 43710 | G30: 0 | H30: 18000000 | I30: 12285580 | J30: 0 | K30: 77 | L30: 80 | M30: 11 | N30: 88 | O30: 8 | P30: 11144038 | Q30: 1141541.7 | R30: 43 | S30: 11 | T30: 54 | U30: 0 | V30: 15 | W30: 33 | X30: 62 | Y30: 3 | Z30: 104 | AA30: 0 | AB30: 0 | AC30: 1 | AD30: 1 | AE30: 1033 | AF30: 1171 | AG30: 290 | AH30: =IFERROR(SUM(I30:J30)/AG30,"") -> 42364.068 | AI30: =IFERROR(AF30/AG30,"") -> 4.037931 | AJ30: 28050 | AK30: =AJ30*BD30 -> 336600 | AL30: 194155 | AM30: =IFERROR(SUM(AK30:AL30)/SUM(I30:J30),"") -> 0.043201462 | AN30: =IFERROR(I30/T30,"") -> 227510.73 | AO30: =IFERROR(SUM(I30:J30)/SUM(G30:H30),"") -> 0.6825322 | AP30: 0 | AQ30: 321 | AR30: 2738 | AS30: 2247.55 | AT30: 11 | AU30: 28 | AV30: 54 | AW30: 26 | AX30: 8 | AY30: =IFERROR(VLOOKUP(C30,#REF!,13,0),"") | BA30: =IF(ISBLANK(AZ30),"Active","LEFT" ) -> Active | BB30: =_xludf.ifs(F30<$BB$1,"Old",F30>$BB$1,"New") -> #NAME? | BC30: =_xludf.ifs(AO30<50%,"Below 50%",AO30<70%,"50%-70%",AO30<90%,"70%-90%",AO30<100%,"90%-100%",AO30>100%,"Above 100%") -> #NAME? | BD30: =MATCH($BD$2,{"Apr","May","Jun","Jul","Aug","Sep","Oct","Nov","Dec","Jan","Feb","Mar"},0) -> 12 | BF30: =M30-AT30 -> 0 | BG30: Secondary | BH30: =IFERROR(__xludf.DUMMYFUNCTION("""COMPUTED_VALUE"""),10055911) -> 10055911 | BI30: =IFERROR(__xludf.DUMMYFUNCTION("""COMPUTED_VALUE"""),11534011.53) -> 11534012 | BL30: =BK30*BD30 -> 0 | BM30: =H30+BL30 -> 18000000 | BO30: =IFERROR(__xludf.DUMMYFUNCTION("IFERROR(ArrayFormula(SUM(VLOOKUP($C30,importrange(""1MwNMVzWE3QBVOyJjKr3eFX-Sq1Ng0Q1sghWJbgbE_8g"",""ORDER BOOKING REPORT 2024-25!C:CV""),{16,23,30},0))))"),2441215.57) -> 2441215.6 | BP30: =IFERROR(__xludf.DUMMYFUNCTION("IFERROR(ArrayFormula(SUM(VLOOKUP($C30,importrange(""1MwNMVzWE3QBVOyJjKr3eFX-Sq1Ng0Q1sghWJbgbE_8g"",""ORDER BOOKING REPORT 2024-25!C:CV""),{37,44,51},0))))"),2863210.46) -> 2863210.5 | BQ30: =IFERROR(__xludf.DUMMYFUNCTION("IFERROR(ArrayFormula(SUM(VLOOKUP($C30,importrange(""1MwNMVzWE3QBVOyJjKr3eFX-Sq1Ng0Q1sghWJbgbE_8g"",""ORDER BOOKING REPORT 2024-25!C:CV""),{58,65,72},0))))"),2871881.58) -> 2871881.6 | BR30: =IFERROR(__xludf.DUMMYFUNCTION("IFERROR(ArrayFormula(SUM(VLOOKUP($C30,importrange(""1MwNMVzWE3QBVOyJjKr3eFX-Sq1Ng0Q1sghWJbgbE_8g"",""ORDER BOOKING REPORT 2024-25!C:CV""),{79,86,93},0))))"),3357703.91999999) -> 3357703.9 | BS30: =IFERROR(AY30/BM30,"") | BT30: =IFERROR(SUM(AK30:AL30)/AY30,"") | BU30: =BL30-G30 -> 0 | BV30: 28050 | BW30: Executive - Sales & Mkt. | BX30: 708 | BY30: =BV30-AJ30 -> 0 | CG30: =IF(N30<60,"Below 60"," ") | CH30: =IF(T30 = 0, "Not 50%", IF(T30 >= 0.5 * N30, "Business Achieved 50%", "Not 50%")) -> Business Achieved 50% | CI30: =IFERROR((T30/N30),) -> 0.61363636 | CJ30: =IFERROR(__xludf.DUMMYFUNCTION("""COMPUTED_VALUE"""),853) -> 853 | CK30: =IFERROR(__xludf.DUMMYFUNCTION("""COMPUTED_VALUE"""),180) -> 180 | CL30: =IFERROR(__xludf.DUMMYFUNCTION("""COMPUTED_VALUE"""),0) -> 0 | CM30: =AE30-SUM(CJ30:CL30) -> 0
A31: Sandeep Dadheech | B31: Tamil Nadu | C31: K.V.THAMIZHSELVAN | D31: TAMIL NADU | E31: VELLORE | F31: 44046 | G31: 0 | H31: 23499996 | I31: 16007148 | J31: 0 | K31: 104 | L31: 115 | M31: 11 | N31: 115 | O31: 0 | P31: 14760705 | Q31: 1246442.4 | R31: 91 | S31: 11 | T31: 102 | U31: 0 | V31: 4 | W31: 11 | X31: 0 | Y31: 1 | Z31: 11 | AA31: 0 | AB31: 0 | AC31: 1 | AD31: 1 | AE31: 2005 | AF31: 2028 | AG31: 289 | AH31: =IFERROR(SUM(I31:J31)/AG31,"") -> 55388.055 | AI31: =IFERROR(AF31/AG31,"") -> 7.017301 | AJ31: =BV31 -> 40380 | AK31: =AJ31*BD31 -> 484560 | AL31: 225757 | AM31: =IFERROR(SUM(AK31:AL31)/SUM(I31:J31),"") -> 0.044374988 | AN31: =IFERROR(I31/T31,"") -> 156932.82 | AO31: =IFERROR(SUM(I31:J31)/SUM(G31:H31),"") -> 0.68115535 | AP31: 0 | AQ31: 677 | AR31: 3260 | AS31: 5215.62 | AT31: 11 | AU31: 45 | AV31: 102 | AW31: 13 | AX31: 0 | AY31: =IFERROR(VLOOKUP(C31,#REF!,13,0),"") | BA31: =IF(ISBLANK(AZ31),"Active","LEFT" ) -> Active | BB31: =_xludf.ifs(F31<$BB$1,"Old",F31>$BB$1,"New") -> #NAME? | BC31: =_xludf.ifs(AO31<50%,"Below 50%",AO31<70%,"50%-70%",AO31<90%,"70%-90%",AO31<100%,"90%-100%",AO31>100%,"Above 100%") -> #NAME? | BD31: =MATCH($BD$2,{"Apr","May","Jun","Jul","Aug","Sep","Oct","Nov","Dec","Jan","Feb","Mar"},0) -> 12 | BF31: =M31-AT31 -> 0 | BG31: Secondary | BH31: =IFERROR(__xludf.DUMMYFUNCTION("""COMPUTED_VALUE"""),16241492.24) -> 16241492 | BI31: =IFERROR(__xludf.DUMMYFUNCTION("""COMPUTED_VALUE"""),13214504.4) -> 13214504 | BL31: =BK31*BD31 -> 0 | BM31: =H31+BL31 -> 23499996 | BO31: =IFERROR(__xludf.DUMMYFUNCTION("IFERROR(ArrayFormula(SUM(VLOOKUP($C31,importrange(""1MwNMVzWE3QBVOyJjKr3eFX-Sq1Ng0Q1sghWJbgbE_8g"",""ORDER BOOKING REPORT 2024-25!C:CV""),{16,23,30},0))))"),2974825.3) -> 2974825.3 | BP31: =IFERROR(__xludf.DUMMYFUNCTION("IFERROR(ArrayFormula(SUM(VLOOKUP($C31,importrange(""1MwNMVzWE3QBVOyJjKr3eFX-Sq1Ng0Q1sghWJbgbE_8g"",""ORDER BOOKING REPORT 2024-25!C:CV""),{37,44,51},0))))"),3160124) -> 3160124 | BQ31: =IFERROR(__xludf.DUMMYFUNCTION("IFERROR(ArrayFormula(SUM(VLOOKUP($C31,importrange(""1MwNMVzWE3QBVOyJjKr3eFX-Sq1Ng0Q1sghWJbgbE_8g"",""ORDER BOOKING REPORT 2024-25!C:CV""),{58,65,72},0))))"),3342748.4) -> 3342748.4 | BR31: =IFERROR(__xludf.DUMMYFUNCTION("IFERROR(ArrayFormula(SUM(VLOOKUP($C31,importrange(""1MwNMVzWE3QBVOyJjKr3eFX-Sq1Ng0Q1sghWJbgbE_8g"",""ORDER BOOKING REPORT 2024-25!C:CV""),{79,86,93},0))))"),3736806.7) -> 3736806.7 | BS31: =IFERROR(AY31/BM31,"") | BT31: =IFERROR(SUM(AK31:AL31)/AY31,"") | BU31: =BL31-G31 -> 0 | BV31: 40380 | BW31: Sr. Executive | BX31: 601 | BY31: =BV31-AJ31 -> 0 | CG31: =IF(N31<60,"Below 60"," ") | CH31: =IF(T31 = 0, "Not 50%", IF(T31 >= 0.5 * N31, "Business Achieved 50%", "Not 50%")) -> Business Achieved 50% | CI31: =IFERROR((T31/N31),) -> 0.88695652 | CJ31: =IFERROR(__xludf.DUMMYFUNCTION("""COMPUTED_VALUE"""),1846) -> 1846 | CK31: =IFERROR(__xludf.DUMMYFUNCTION("""COMPUTED_VALUE"""),159) -> 159 | CL31: =IFERROR(__xludf.DUMMYFUNCTION("""COMPUTED_VALUE"""),0) -> 0 | CM31: =AE31-SUM(CJ31:CL31) -> 0
A32: Sandeep Dadheech | B32: Bihar | C32: Pradeep Kumar | D32: BIHAR | E32: Aurangabad | F32: 44166 | G32: 0 | H32: 18000000 | I32: 9992477.8 | J32: 0 | K32: 42 | L32: 47 | M32: 5 | N32: 47 | O32: 0 | P32: 7806266.2 | Q32: 2186211.6 | R32: 24 | S32: 5 | T32: 29 | U32: 0 | V32: 16 | W32: 26 | X32: 18 | Y32: 2 | Z32: 79 | AA32: 0 | AB32: 0 | AC32: 0 | AD32: 0 | AE32: 881 | AF32: 986 | AG32: 293 | AH32: =IFERROR(SUM(I32:J32)/AG32,"") -> 34104.02 | AI32: =IFERROR(AF32/AG32,"") -> 3.3651877 | AJ32: 27200 | AK32: =AJ32*BD32 -> 326400 | AL32: 174096 | AM32: =IFERROR(SUM(AK32:AL32)/SUM(I32:J32),"") -> 0.050087277 | AN32: =IFERROR(I32/T32,"") -> 344568.2 | AO32: =IFERROR(SUM(I32:J32)/SUM(G32:H32),"") -> 0.55513765 | AP32: 0 | AQ32: 94 | AR32: 2375 | AS32: 1598.05 | AT32: 5 | AU32: 34 | AV32: 29 | AW32: 18 | AX32: 0 | AY32: =IFERROR(VLOOKUP(C32,#REF!,13,0),"") | BA32: =IF(ISBLANK(AZ32),"Active","LEFT" ) -> Active | BB32: =_xludf.ifs(F32<$BB$1,"Old",F32>$BB$1,"New") -> #NAME? | BC32: =_xludf.ifs(AO32<50%,"Below 50%",AO32<70%,"50%-70%",AO32<90%,"70%-90%",AO32<100%,"90%-100%",AO32>100%,"Above 100%") -> #NAME? | BD32: =MATCH($BD$2,{"Apr","May","Jun","Jul","Aug","Sep","Oct","Nov","Dec","Jan","Feb","Mar"},0) -> 12 | BF32: =M32-AT32 -> 0 | BG32: Secondary | BH32: =IFERROR(__xludf.DUMMYFUNCTION("""COMPUTED_VALUE"""),6083540) -> 6083540 | BI32: =IFERROR(__xludf.DUMMYFUNCTION("""COMPUTED_VALUE"""),2693150.7) -> 2693150.7 | BL32: =BK32*BD32 -> 0 | BM32: =H32+BL32 -> 18000000 | BO32: =IFERROR(__xludf.DUMMYFUNCTION("IFERROR(ArrayFormula(SUM(VLOOKUP($C32,importrange(""1MwNMVzWE3QBVOyJjKr3eFX-Sq1Ng0Q1sghWJbgbE_8g"",""ORDER BOOKING REPORT 2024-25!C:CV""),{16,23,30},0))))"),0) -> 0 | BP32: =IFERROR(__xludf.DUMMYFUNCTION("IFERROR(ArrayFormula(SUM(VLOOKUP($C32,importrange(""1MwNMVzWE3QBVOyJjKr3eFX-Sq1Ng0Q1sghWJbgbE_8g"",""ORDER BOOKING REPORT 2024-25!C:CV""),{37,44,51},0))))"),0) -> 0 | BQ32: =IFERROR(__xludf.DUMMYFUNCTION("IFERROR(ArrayFormula(SUM(VLOOKUP($C32,importrange(""1MwNMVzWE3QBVOyJjKr3eFX-Sq1Ng0Q1sghWJbgbE_8g"",""ORDER BOOKING REPORT 2024-25!C:CV""),{58,65,72},0))))"),1012125.9) -> 1012125.9 | BR32: =IFERROR(__xludf.DUMMYFUNCTION("IFERROR(ArrayFormula(SUM(VLOOKUP($C32,importrange(""1MwNMVzWE3QBVOyJjKr3eFX-Sq1Ng0Q1sghWJbgbE_8g"",""ORDER BOOKING REPORT 2024-25!C:CV""),{79,86,93},0))))"),1681024.8) -> 1681024.8 | BS32: =IFERROR(AY32/BM32,"") | BT32: =IFERROR(SUM(AK32:AL32)/AY32,"") | BU32: =BL32-G32 -> 0 | BV32: 27200 | BW32: Executive - Sales & Mkt. | BX32: 719 | BY32: =BV32-AJ32 -> 0 | CG32: =IF(N32<60,"Below 60"," ") -> Below 60 | CH32: =IF(T32 = 0, "Not 50%", IF(T32 >= 0.5 * N32, "Business Achieved 50%", "Not 50%")) -> Business Achieved 50% | CI32: =IFERROR((T32/N32),) -> 0.61702128 | CJ32: =IFERROR(__xludf.DUMMYFUNCTION("""COMPUTED_VALUE"""),575) -> 575 | CK32: =IFERROR(__xludf.DUMMYFUNCTION("""COMPUTED_VALUE"""),306) -> 306 | CL32: =IFERROR(__xludf.DUMMYFUNCTION("""COMPUTED_VALUE"""),0) -> 0 | CM32: =AE32-SUM(CJ32:CL32) -> 0
A33: Syed Aqil Rizvi | B33: Chattisgarh | C33: Akash kumar gulhare | D33: CHATTISGARH | E33: Bilaspur | F33: 44207 | G33: 0 | H33: 0 | I33: 306632.08 | J33: 0 | K33: 70 | L33: 44 | M33: 3 | N33: 73 | O33: 29 | P33: 306632.08 | Q33: 0 | R33: 13 | S33: 0 | T33: 13 | U33: 0 | V33: 3 | W33: 4 | X33: 69 | Y33: 1 | Z33: 1 | AA33: 0 | AB33: 0 | AC33: 0 | AD33: 0 | AE33: 74 | AF33: 79 | AG33: 23 | AH33: =IFERROR(SUM(I33:J33)/AG33,"") -> 13331.83 | AI33: =IFERROR(AF33/AG33,"") -> 3.4347826 | AJ33: 40085 | AK33: =AJ33*BD33 -> 40085 | AL33: 10260 | AM33: =IFERROR(SUM(AK33:AL33)/SUM(I33:J33),"") -> 0.164187 | AN33: =IFERROR(I33/T33,"") -> 23587.083 | AO33: No Target | AP33: 0 | AQ33: 19 | AR33: 196 | AS33: 0 | AT33: 0 | AU33: 0 | AV33: 13 | AW33: 35 | AX33: 25 | AY33: =IFERROR(VLOOKUP(C33,#REF!,13,0),"") | AZ33: 45777 | BA33: =IF(ISBLANK(AZ33),"Active","LEFT" ) -> LEFT | BB33: =_xludf.ifs(F33<$BB$1,"Old",F33>$BB$1,"New") -> #NAME? | BC33: No Target | BD33: 1 | BF33: =M33-AT33 -> 3 | BG33: Secondary | BH33: =IFERROR(__xludf.DUMMYFUNCTION("""COMPUTED_VALUE"""),7509183) -> 7509183 | BI33: =IFERROR(__xludf.DUMMYFUNCTION("""COMPUTED_VALUE"""),8237376) -> 8237376 | BL33: =BK33*BD33 -> 0 | BM33: =H33+BL33 -> 0 | BO33: =IFERROR(__xludf.DUMMYFUNCTION("IFERROR(ArrayFormula(SUM(VLOOKUP($C33,importrange(""1MwNMVzWE3QBVOyJjKr3eFX-Sq1Ng0Q1sghWJbgbE_8g"",""ORDER BOOKING REPORT 2024-25!C:CV""),{16,23,30},0))))"),2321738.42) -> 2321738.4 | BP33: =IFERROR(__xludf.DUMMYFUNCTION("IFERROR(ArrayFormula(SUM(VLOOKUP($C33,importrange(""1MwNMVzWE3QBVOyJjKr3eFX-Sq1Ng0Q1sghWJbgbE_8g"",""ORDER BOOKING REPORT 2024-25!C:CV""),{37,44,51},0))))"),1906434.27999999) -> 1906434.3 | BQ33: =IFERROR(__xludf.DUMMYFUNCTION("IFERROR(ArrayFormula(SUM(VLOOKUP($C33,importrange(""1MwNMVzWE3QBVOyJjKr3eFX-Sq1Ng0Q1sghWJbgbE_8g"",""ORDER BOOKING REPORT 2024-25!C:CV""),{58,65,72},0))))"),1968845.5) -> 1968845.5 | BR33: =IFERROR(__xludf.DUMMYFUNCTION("IFERROR(ArrayFormula(SUM(VLOOKUP($C33,importrange(""1MwNMVzWE3QBVOyJjKr3eFX-Sq1Ng0Q1sghWJbgbE_8g"",""ORDER BOOKING REPORT 2024-25!C:CV""),{79,86,93},0))))"),2040357.79999999) -> 2040357.8 | BS33: =IFERROR(AY33/BM33,"") | BT33: =IFERROR(SUM(AK33:AL33)/AY33,"") | BU33: =BL33-G33 -> 0 | BY33: =BV33-AJ33 -> -40085 | CG33: =IF(N33<60,"Below 60"," ") | CH33: =IF(T33 = 0, "Not 50%", IF(T33 >= 0.5 * N33, "Business Achieved 50%", "Not 50%")) -> Not 50% | CI33: =IFERROR((T33/N33),) -> 0.17808219 | CJ33: =IFERROR(__xludf.DUMMYFUNCTION("""COMPUTED_VALUE"""),16) -> 16 | CK33: =IFERROR(__xludf.DUMMYFUNCTION("""COMPUTED_VALUE"""),58) -> 58 | CL33: =IFERROR(__xludf.DUMMYFUNCTION("""COMPUTED_VALUE"""),0) -> 0 | CM33: =AE33-SUM(CJ33:CL33) -> 0
A34: Biju C.O | B34: Kerala | C34: Rajesh NN | D34: KERALA | E34: Palakkad | F34: 44224 | G34: 0 | H34: 0 | I34: 0 | J34: 0 | K34: 147 | L34: 43 | M34: 6 | N34: 153 | O34: 110 | P34: 0 | Q34: 0 | R34: 0 | S34: 0 | T34: 0 | U34: 0 | V34: 2 | W34: 2 | X34: 43 | Y34: 1 | Z34: 1 | AA34: 0 | AB34: 0 | AC34: 0 | AD34: 0 | AE34: 76 | AF34: 79 | AG34: 18 | AH34: =IFERROR(SUM(I34:J34)/AG34,"") -> 0 | AI34: =IFERROR(AF34/AG34,"") -> 4.3888889 | AJ34: 35543 | AK34: =AJ34*BD34 -> 31988.7 | AL34: 9680 | AM34: =IFERROR(SUM(AK34:AL34)/SUM(I34:J34),"") | AN34: =IFERROR(I34/T34,"") | AO34: No Target | AP34: 0 | AQ34: 0 | AR34: 142 | AS34: 0 | AT34: 0 | AU34: 0 | AV34: 0 | AW34: 43 | AX34: 110 | AY34: =IFERROR(VLOOKUP(C34,#REF!,13,0),"") | AZ34: 45774 | BA34: =IF(ISBLANK(AZ34),"Active","LEFT" ) -> LEFT | BB34: =_xludf.ifs(F34<$BB$1,"Old",F34>$BB$1,"New") -> #NAME? | BC34: No Target | BD34: =(30-3)/30 -> 0.9 | BF34: =M34-AT34 -> 6 | BG34: Primary | BJ34: =27/30 -> 0.9 | BL34: =BK34*BD34 -> 0 | BM34: =H34+BL34 -> 0 | BO34: =IFERROR(__xludf.DUMMYFUNCTION("IFERROR(ArrayFormula(SUM(VLOOKUP($C34,importrange(""1MwNMVzWE3QBVOyJjKr3eFX-Sq1Ng0Q1sghWJbgbE_8g"",""ORDER BOOKING REPORT 2024-25!C:CV""),{16,23,30},0))))"),"") | BP34: =IFERROR(__xludf.DUMMYFUNCTION("IFERROR(ArrayFormula(SUM(VLOOKUP($C34,importrange(""1MwNMVzWE3QBVOyJjKr3eFX-Sq1Ng0Q1sghWJbgbE_8g"",""ORDER BOOKING REPORT 2024-25!C:CV""),{37,44,51},0))))"),"") | BQ34: =IFERROR(__xludf.DUMMYFUNCTION("IFERROR(ArrayFormula(SUM(VLOOKUP($C34,importrange(""1MwNMVzWE3QBVOyJjKr3eFX-Sq1Ng0Q1sghWJbgbE_8g"",""ORDER BOOKING REPORT 2024-25!C:CV""),{58,65,72},0))))"),"") | BR34: =IFERROR(__xludf.DUMMYFUNCTION("IFERROR(ArrayFormula(SUM(VLOOKUP($C34,importrange(""1MwNMVzWE3QBVOyJjKr3eFX-Sq1Ng0Q1sghWJbgbE_8g"",""ORDER BOOKING REPORT 2024-25!C:CV""),{79,86,93},0))))"),"") | BS34: =IFERROR(AY34/BM34,"") | BT34: =IFERROR(SUM(AK34:AL34)/AY34,"") | BU34: =BL34-G34 -> 0 | BY34: =BV34-AJ34 -> -35543 | CG34: =IF(N34<60,"Below 60"," ") | CH34: =IF(T34 = 0, "Not 50%", IF(T34 >= 0.5 * N34, "Business Achieved 50%", "Not 50%")) -> Not 50% | CI34: =IFERROR((T34/N34),) -> 0 | CM34: =AE34-SUM(CJ34:CL34) -> 76
A35: Sandeep Dadheech | B35: Jharkhand | C35: Ashutosh Kumar | D35: JHARKHAND | E35: Dhanbad | F35: 44228 | G35: 0 | H35: 42000000 | I35: 17398691 | J35: 0 | K35: 79 | L35: 79 | M35: 2 | N35: 81 | O35: 2 | P35: 17280609 | Q35: 118082.38 | R35: 50 | S35: 2 | T35: 52 | U35: 0 | V35: 57 | W35: 102 | X35: 93 | Y35: 1 | Z35: 233 | AA35: 0 | AB35: 0 | AC35: 0 | AD35: 0 | AE35: 602 | AF35: 937 | AG35: 292 | AH35: =IFERROR(SUM(I35:J35)/AG35,"") -> 59584.559 | AI35: =IFERROR(AF35/AG35,"") -> 3.2089041 | AJ35: 40500 | AK35: =AJ35*BD35 -> 486000 | AL35: 145405 | AM35: =IFERROR(SUM(AK35:AL35)/SUM(I35:J35),"") -> 0.036290373 | AN35: =IFERROR(I35/T35,"") -> 334590.22 | AO35: =IFERROR(SUM(I35:J35)/SUM(G35:H35),"") -> 0.41425455 | AP35: 0 | AQ35: 268 | AR35: 2896 | AS35: 1823.62 | AT35: 2 | AU35: 23 | AV35: 52 | AW35: 27 | AX35: 2 | AY35: =IFERROR(VLOOKUP(C35,#REF!,13,0),"") | BA35: =IF(ISBLANK(AZ35),"Active","LEFT" ) -> Active | BB35: =_xludf.ifs(F35<$BB$1,"Old",F35>$BB$1,"New") -> #NAME? | BC35: =_xludf.ifs(AO35<50%,"Below 50%",AO35<70%,"50%-70%",AO35<90%,"70%-90%",AO35<100%,"90%-100%",AO35>100%,"Above 100%") -> #NAME? | BD35: =MATCH($BD$2,{"Apr","May","Jun","Jul","Aug","Sep","Oct","Nov","Dec","Jan","Feb","Mar"},0) -> 12 | BF35: =M35-AT35 -> 0 | BG35: Secondary | BH35: =IFERROR(__xludf.DUMMYFUNCTION("""COMPUTED_VALUE"""),27236545) -> 27236545 | BI35: =IFERROR(__xludf.DUMMYFUNCTION("""COMPUTED_VALUE"""),21634877.9899999) -> 21634878 | BL35: =BK35*BD35 -> 0 | BM35: =H35+BL35 -> 42000000 | BO35: =IFERROR(__xludf.DUMMYFUNCTION("IFERROR(ArrayFormula(SUM(VLOOKUP($C35,importrange(""1MwNMVzWE3QBVOyJjKr3eFX-Sq1Ng0Q1sghWJbgbE_8g"",""ORDER BOOKING REPORT 2024-25!C:CV""),{16,23,30},0))))"),4144773.80999999) -> 4144773.8 | BP35: =IFERROR(__xludf.DUMMYFUNCTION("IFERROR(ArrayFormula(SUM(VLOOKUP($C35,importrange(""1MwNMVzWE3QBVOyJjKr3eFX-Sq1Ng0Q1sghWJbgbE_8g"",""ORDER BOOKING REPORT 2024-25!C:CV""),{37,44,51},0))))"),6555039.09999999) -> 6555039.1 | BQ35: =IFERROR(__xludf.DUMMYFUNCTION("IFERROR(ArrayFormula(SUM(VLOOKUP($C35,importrange(""1MwNMVzWE3QBVOyJjKr3eFX-Sq1Ng0Q1sghWJbgbE_8g"",""ORDER BOOKING REPORT 2024-25!C:CV""),{58,65,72},0))))"),6288589.79999999) -> 6288589.8 | BR35: =IFERROR(__xludf.DUMMYFUNCTION("IFERROR(ArrayFormula(SUM(VLOOKUP($C35,importrange(""1MwNMVzWE3QBVOyJjKr3eFX-Sq1Ng0Q1sghWJbgbE_8g"",""ORDER BOOKING REPORT 2024-25!C:CV""),{79,86,93},0))))"),4646475.28) -> 4646475.3 | BS35: =IFERROR(AY35/BM35,"") | BT35: =IFERROR(SUM(AK35:AL35)/AY35,"") | BU35: =BL35-G35 -> 0 | BV35: 40500 | BW35: Sr. Executive - Sales & Mktg. | BX35: 639 | BY35: =BV35-AJ35 -> 0 | CG35: =IF(N35<60,"Below 60"," ") | CH35: =IF(T35 = 0, "Not 50%", IF(T35 >= 0.5 * N35, "Business Achieved 50%", "Not 50%")) -> Business Achieved 50% | CI35: =IFERROR((T35/N35),) -> 0.64197531 | CJ35: =IFERROR(__xludf.DUMMYFUNCTION("""COMPUTED_VALUE"""),487) -> 487 | CK35: =IFERROR(__xludf.DUMMYFUNCTION("""COMPUTED_VALUE"""),115) -> 115 | CL35: =IFERROR(__xludf.DUMMYFUNCTION("""COMPUTED_VALUE"""),0) -> 0 | CM35: =AE35-SUM(CJ35:CL35) -> 0
A36: Syed Aqil Rizvi | B36: Chattisgarh | C36: Nitin prasad baghel | D36: CHATTISGARH | E36: Raipur | F36: 44245 | G36: 0 | H36: 27999996 | I36: 14192530 | J36: 0 | K36: 108 | L36: 120 | M36: 19 | N36: 127 | O36: 7 | P36: 12628643 | Q36: 1563887 | R36: 70 | S36: 19 | T36: 89 | U36: 0 | V36: 39 | W36: 62 | X36: 101 | Y36: 3 | Z36: 27 | AA36: 1 | AB36: 1 | AC36: 0 | AD36: 0 | AE36: 995 | AF36: 1085 | AG36: 287 | AH36: =IFERROR(SUM(I36:J36)/AG36,"") -> 49451.323 | AI36: =IFERROR(AF36/AG36,"") -> 3.7804878 | AJ36: =BV36 -> 41690 | AK36: =AJ36*BD36 -> 500280 | AL36: 209570 | AM36: =IFERROR(SUM(AK36:AL36)/SUM(I36:J36),"") -> 0.050015749 | AN36: =IFERROR(I36/T36,"") -> 159466.63 | AO36: =IFERROR(SUM(I36:J36)/SUM(G36:H36),"") -> 0.50687614 | AP36: 0 | AQ36: 369 | AR36: 2854 | AS36: 3976.47 | AT36: 19 | AU36: 33 | AV36: 89 | AW36: 34 | AX36: 4 | AY36: =IFERROR(VLOOKUP(C36,#REF!,13,0),"") | BA36: =IF(ISBLANK(AZ36),"Active","LEFT" ) -> Active | BB36: =_xludf.ifs(F36<$BB$1,"Old",F36>$BB$1,"New") -> #NAME? | BC36: =_xludf.ifs(AO36<50%,"Below 50%",AO36<70%,"50%-70%",AO36<90%,"70%-90%",AO36<100%,"90%-100%",AO36>100%,"Above 100%") -> #NAME? | BD36: =MATCH($BD$2,{"Apr","May","Jun","Jul","Aug","Sep","Oct","Nov","Dec","Jan","Feb","Mar"},0) -> 12 | BF36: =M36-AT36 -> 0 | BG36: Secondary | BH36: =IFERROR(__xludf.DUMMYFUNCTION("""COMPUTED_VALUE"""),15003664) -> 15003664 | BI36: =IFERROR(__xludf.DUMMYFUNCTION("""COMPUTED_VALUE"""),10527128.0899999) -> 10527128 | BL36: =BK36*BD36 -> 0 | BM36: =H36+BL36 -> 27999996 | BO36: =IFERROR(__xludf.DUMMYFUNCTION("IFERROR(ArrayFormula(SUM(VLOOKUP($C36,importrange(""1MwNMVzWE3QBVOyJjKr3eFX-Sq1Ng0Q1sghWJbgbE_8g"",""ORDER BOOKING REPORT 2024-25!C:CV""),{16,23,30},0))))"),1966032.9) -> 1966032.9 | BP36: =IFERROR(__xludf.DUMMYFUNCTION("IFERROR(ArrayFormula(SUM(VLOOKUP($C36,importrange(""1MwNMVzWE3QBVOyJjKr3eFX-Sq1Ng0Q1sghWJbgbE_8g"",""ORDER BOOKING REPORT 2024-25!C:CV""),{37,44,51},0))))"),1856083.57) -> 1856083.6 | BQ36: =IFERROR(__xludf.DUMMYFUNCTION("IFERROR(ArrayFormula(SUM(VLOOKUP($C36,importrange(""1MwNMVzWE3QBVOyJjKr3eFX-Sq1Ng0Q1sghWJbgbE_8g"",""ORDER BOOKING REPORT 2024-25!C:CV""),{58,65,72},0))))"),2460624.32) -> 2460624.3 | BR36: =IFERROR(__xludf.DUMMYFUNCTION("IFERROR(ArrayFormula(SUM(VLOOKUP($C36,importrange(""1MwNMVzWE3QBVOyJjKr3eFX-Sq1Ng0Q1sghWJbgbE_8g"",""ORDER BOOKING REPORT 2024-25!C:CV""),{79,86,93},0))))"),4244387.3) -> 4244387.3 | BS36: =IFERROR(AY36/BM36,"") | BT36: =IFERROR(SUM(AK36:AL36)/AY36,"") | BU36: =BL36-G36 -> 0 | BV36: 41690 | BW36: Sr. Executive - Sales & Mktg. | BX36: 644 | BY36: =BV36-AJ36 -> 0 | CG36: =IF(N36<60,"Below 60"," ") | CH36: =IF(T36 = 0, "Not 50%", IF(T36 >= 0.5 * N36, "Business Achieved 50%", "Not 50%")) -> Business Achieved 50% | CI36: =IFERROR((T36/N36),) -> 0.7007874 | CJ36: =IFERROR(__xludf.DUMMYFUNCTION("""COMPUTED_VALUE"""),801) -> 801 | CK36: =IFERROR(__xludf.DUMMYFUNCTION("""COMPUTED_VALUE"""),194) -> 194 | CL36: =IFERROR(__xludf.DUMMYFUNCTION("""COMPUTED_VALUE"""),0) -> 0 | CM36: =AE36-SUM(CJ36:CL36) -> 0
A37: Syed Aqil Rizvi | B37: East U.P | C37: Hemant kumar srivastava | D37: East U.P | E37: Gorakhpur | F37: 44247 | G37: 0 | H37: 39999996 | I37: 28197453 | J37: 0 | K37: 77 | L37: 82 | M37: 48 | N37: 125 | O37: 43 | P37: 17561713 | Q37: 10635740 | R37: 49 | S37: 46 | T37: 95 | U37: 0 | V37: 5 | W37: 6 | X37: 41 | Y37: 3 | Z37: 212 | AA37: 0 | AB37: 0 | AC37: 1 | AD37: 3 | AE37: 900 | AF37: 1121 | AG37: 290 | AH37: =IFERROR(SUM(I37:J37)/AG37,"") -> 97232.597 | AI37: =IFERROR(AF37/AG37,"") -> 3.8655172 | AJ37: =BV37 -> 45515 | AK37: =AJ37*BD37 -> 546180 | AL37: 191190 | AM37: =IFERROR(SUM(AK37:AL37)/SUM(I37:J37),"") -> 0.026150234 | AN37: =IFERROR(I37/T37,"") -> 296815.3 | AO37: =IFERROR(SUM(I37:J37)/SUM(G37:H37),"") -> 0.7049364 | AP37: 0 | AQ37: 834 | AR37: 3038 | AS37: 2401.63 | AT37: 46 | AU37: 29 | AV37: 95 | AW37: 9 | AX37: 21 | AY37: =IFERROR(VLOOKUP(C37,#REF!,13,0),"") | BA37: =IF(ISBLANK(AZ37),"Active","LEFT" ) -> Active | BB37: =_xludf.ifs(F37<$BB$1,"Old",F37>$BB$1,"New") -> #NAME? | BC37: =_xludf.ifs(AO37<50%,"Below 50%",AO37<70%,"50%-70%",AO37<90%,"70%-90%",AO37<100%,"90%-100%",AO37>100%,"Above 100%") -> #NAME? | BD37: =MATCH($BD$2,{"Apr","May","Jun","Jul","Aug","Sep","Oct","Nov","Dec","Jan","Feb","Mar"},0) -> 12 | BF37: =M37-AT37 -> 2 | BG37: Secondary | BH37: =IFERROR(__xludf.DUMMYFUNCTION("""COMPUTED_VALUE"""),18863938.54) -> 18863939 | BI37: =IFERROR(__xludf.DUMMYFUNCTION("""COMPUTED_VALUE"""),21204570.884) -> 21204571 | BL37: =BK37*BD37 -> 0 | BM37: =H37+BL37 -> 39999996 | BO37: =IFERROR(__xludf.DUMMYFUNCTION("IFERROR(ArrayFormula(SUM(VLOOKUP($C37,importrange(""1MwNMVzWE3QBVOyJjKr3eFX-Sq1Ng0Q1sghWJbgbE_8g"",""ORDER BOOKING REPORT 2024-25!C:CV""),{16,23,30},0))))"),6699760.354) -> 6699760.4 | BP37: =IFERROR(__xludf.DUMMYFUNCTION("IFERROR(ArrayFormula(SUM(VLOOKUP($C37,importrange(""1MwNMVzWE3QBVOyJjKr3eFX-Sq1Ng0Q1sghWJbgbE_8g"",""ORDER BOOKING REPORT 2024-25!C:CV""),{37,44,51},0))))"),5487978.79) -> 5487978.8 | BQ37: =IFERROR(__xludf.DUMMYFUNCTION("IFERROR(ArrayFormula(SUM(VLOOKUP($C37,importrange(""1MwNMVzWE3QBVOyJjKr3eFX-Sq1Ng0Q1sghWJbgbE_8g"",""ORDER BOOKING REPORT 2024-25!C:CV""),{58,65,72},0))))"),5054309.23999999) -> 5054309.2 | BR37: =IFERROR(__xludf.DUMMYFUNCTION("IFERROR(ArrayFormula(SUM(VLOOKUP($C37,importrange(""1MwNMVzWE3QBVOyJjKr3eFX-Sq1Ng0Q1sghWJbgbE_8g"",""ORDER BOOKING REPORT 2024-25!C:CV""),{79,86,93},0))))"),3962522.49999999) -> 3962522.5 | BS37: =IFERROR(AY37/BM37,"") | BT37: =IFERROR(SUM(AK37:AL37)/AY37,"") | BU37: =BL37-G37 -> 0 | BV37: 45515 | BW37: Assistant Area Sales Manager | BX37: 642 | BY37: =BV37-AJ37 -> 0 | CG37: =IF(N37<60,"Below 60"," ") | CH37: =IF(T37 = 0, "Not 50%", IF(T37 >= 0.5 * N37, "Business Achieved 50%", "Not 50%")) -> Business Achieved 50% | CI37: =IFERROR((T37/N37),) -> 0.76 | CJ37: =IFERROR(__xludf.DUMMYFUNCTION("""COMPUTED_VALUE"""),852) -> 852 | CK37: =IFERROR(__xludf.DUMMYFUNCTION("""COMPUTED_VALUE"""),48) -> 48 | CL37: =IFERROR(__xludf.DUMMYFUNCTION("""COMPUTED_VALUE"""),0) -> 0 | CM37: =AE37-SUM(CJ37:CL37) -> 0
A38: Sandeep Dadheech | B38: Bihar | C38: Prabhakar Pratap Singh | D38: BIHAR | E38: Patna | F38: 44396 | G38: 0 | H38: 30000000 | I38: 34762215 | J38: 0 | K38: 247 | L38: 172 | M38: 21 | N38: 268 | O38: 96 | P38: 32091155 | Q38: 2671059.7 | R38: 98 | S38: 19 | T38: 117 | U38: 0 | V38: 189 | W38: 283 | X38: 350 | Y38: 5 | Z38: 123 | AA38: 0 | AB38: 0 | AC38: 1 | AD38: 5 | AE38: 938 | AF38: 1349 | AG38: 287 | AH38: =IFERROR(SUM(I38:J38)/AG38,"") -> 121122.7 | AI38: =IFERROR(AF38/AG38,"") -> 4.7003484 | AJ38: 49690 | AK38: =AJ38*BD38 -> 596280 | AL38: 322644 | AM38: =IFERROR(SUM(AK38:AL38)/SUM(I38:J38),"") -> 0.026434564 | AN38: =IFERROR(I38/T38,"") -> 297112.95 | AO38: =IFERROR(SUM(I38:J38)/SUM(G38:H38),"") -> 1.1587405 | AP38: 0 | AQ38: 399 | AR38: 3017 | AS38: 2812.13 | AT38: 19 | AU38: 16 | AV38: 117 | AW38: 60 | AX38: 91 | AY38: =IFERROR(VLOOKUP(C38,#REF!,13,0),"") | BA38: =IF(ISBLANK(AZ38),"Active","LEFT" ) -> Active | BB38: =_xludf.ifs(F38<$BB$1,"Old",F38>$BB$1,"New") -> #NAME? | BC38: =_xludf.ifs(AO38<50%,"Below 50%",AO38<70%,"50%-70%",AO38<90%,"70%-90%",AO38<100%,"90%-100%",AO38>100%,"Above 100%") -> #NAME? | BD38: =MATCH($BD$2,{"Apr","May","Jun","Jul","Aug","Sep","Oct","Nov","Dec","Jan","Feb","Mar"},0) -> 12 | BF38: =M38-AT38 -> 2 | BG38: Secondary | BH38: =IFERROR(__xludf.DUMMYFUNCTION("""COMPUTED_VALUE"""),0) -> 0 | BI38: =IFERROR(__xludf.DUMMYFUNCTION("""COMPUTED_VALUE"""),23312185.9799999) -> 23312186 | BL38: =BK38*BD38 -> 0 | BM38: =H38+BL38 -> 30000000 | BO38: =IFERROR(__xludf.DUMMYFUNCTION("IFERROR(ArrayFormula(SUM(VLOOKUP($C38,importrange(""1MwNMVzWE3QBVOyJjKr3eFX-Sq1Ng0Q1sghWJbgbE_8g"",""ORDER BOOKING REPORT 2024-25!C:CV""),{16,23,30},0))))"),4294587.06999999) -> 4294587.1 | BP38: =IFERROR(__xludf.DUMMYFUNCTION("IFERROR(ArrayFormula(SUM(VLOOKUP($C38,importrange(""1MwNMVzWE3QBVOyJjKr3eFX-Sq1Ng0Q1sghWJbgbE_8g"",""ORDER BOOKING REPORT 2024-25!C:CV""),{37,44,51},0))))"),4143569.49) -> 4143569.5 | BQ38: =IFERROR(__xludf.DUMMYFUNCTION("IFERROR(ArrayFormula(SUM(VLOOKUP($C38,importrange(""1MwNMVzWE3QBVOyJjKr3eFX-Sq1Ng0Q1sghWJbgbE_8g"",""ORDER BOOKING REPORT 2024-25!C:CV""),{58,65,72},0))))"),6496208.18) -> 6496208.2 | BR38: =IFERROR(__xludf.DUMMYFUNCTION("IFERROR(ArrayFormula(SUM(VLOOKUP($C38,importrange(""1MwNMVzWE3QBVOyJjKr3eFX-Sq1Ng0Q1sghWJbgbE_8g"",""ORDER BOOKING REPORT 2024-25!C:CV""),{79,86,93},0))))"),8377821.23999999) -> 8377821.2 | BS38: =IFERROR(AY38/BM38,"") | BT38: =IFERROR(SUM(AK38:AL38)/AY38,"") | BU38: =BL38-G38 -> 0 | BV38: 49690 | BW38: Area Sales Manager | BX38: 666 | BY38: =BV38-AJ38 -> 0 | CG38: =IF(N38<60,"Below 60"," ") | CH38: =IF(T38 = 0, "Not 50%", IF(T38 >= 0.5 * N38, "Business Achieved 50%", "Not 50%")) -> Not 50% | CI38: =IFERROR((T38/N38),) -> 0.43656716 | CJ38: =IFERROR(__xludf.DUMMYFUNCTION("""COMPUTED_VALUE"""),752) -> 752 | CK38: =IFERROR(__xludf.DUMMYFUNCTION("""COMPUTED_VALUE"""),186) -> 186 | CL38: =IFERROR(__xludf.DUMMYFUNCTION("""COMPUTED_VALUE"""),0) -> 0 | CM38: =AE38-SUM(CJ38:CL38) -> 0
A39: Sandeep Dadheech | B39: Jharkhand | C39: Rakesh Kumar Sinha | D39: BIHAR, JHARKHAND | E39: Deoghar | F39: 44424 | G39: 0 | H39: 89000004 | I39: 52611904 | J39: 0 | K39: 78 | L39: 86 | M39: 10 | N39: 88 | O39: 2 | P39: 50009562 | Q39: 2602341.8 | R39: 58 | S39: 8 | T39: 66 | U39: 0 | V39: 16 | W39: 28 | X39: 37 | Y39: 1 | Z39: 155 | AA39: 0 | AB39: 0 | AC39: 0 | AD39: 0 | AE39: 1170 | AF39: 1353 | AG39: 280 | AH39: =IFERROR(SUM(I39:J39)/AG39,"") -> 187899.66 | AI39: =IFERROR(AF39/AG39,"") -> 4.8321429 | AJ39: 51393 | AK39: =AJ39*BD39 -> 616716 | AL39: 143314 | AM39: =IFERROR(SUM(AK39:AL39)/SUM(I39:J39),"") -> 0.01444597 | AN39: =IFERROR(I39/T39,"") -> 797150.05 | AO39: =IFERROR(SUM(I39:J39)/SUM(G39:H39),"") -> 0.59114496 | AP39: 0 | AQ39: 488 | AR39: 2862 | AS39: 2574.92 | AT39: 8 | AU39: 30 | AV39: 66 | AW39: 20 | AX39: 2 | AY39: =IFERROR(VLOOKUP(C39,#REF!,13,0),"") | BA39: =IF(ISBLANK(AZ39),"Active","LEFT" ) -> Active | BB39: =_xludf.ifs(F39<$BB$1,"Old",F39>$BB$1,"New") -> #NAME? | BC39: =_xludf.ifs(AO39<50%,"Below 50%",AO39<70%,"50%-70%",AO39<90%,"70%-90%",AO39<100%,"90%-100%",AO39>100%,"Above 100%") -> #NAME? | BD39: =MATCH($BD$2,{"Apr","May","Jun","Jul","Aug","Sep","Oct","Nov","Dec","Jan","Feb","Mar"},0) -> 12 | BF39: =M39-AT39 -> 2 | BG39: Secondary | BH39: =IFERROR(__xludf.DUMMYFUNCTION("""COMPUTED_VALUE"""),58277388) -> 58277388 | BI39: =IFERROR(__xludf.DUMMYFUNCTION("""COMPUTED_VALUE"""),30576639.0999999) -> 30576639 | BL39: =BK39*BD39 -> 0 | BM39: =H39+BL39 -> 89000004 | BO39: =IFERROR(__xludf.DUMMYFUNCTION("IFERROR(ArrayFormula(SUM(VLOOKUP($C39,importrange(""1MwNMVzWE3QBVOyJjKr3eFX-Sq1Ng0Q1sghWJbgbE_8g"",""ORDER BOOKING REPORT 2024-25!C:CV""),{16,23,30},0))))"),6657518) -> 6657518 | BP39: =IFERROR(__xludf.DUMMYFUNCTION("IFERROR(ArrayFormula(SUM(VLOOKUP($C39,importrange(""1MwNMVzWE3QBVOyJjKr3eFX-Sq1Ng0Q1sghWJbgbE_8g"",""ORDER BOOKING REPORT 2024-25!C:CV""),{37,44,51},0))))"),8985975.1) -> 8985975.1 | BQ39: =IFERROR(__xludf.DUMMYFUNCTION("IFERROR(ArrayFormula(SUM(VLOOKUP($C39,importrange(""1MwNMVzWE3QBVOyJjKr3eFX-Sq1Ng0Q1sghWJbgbE_8g"",""ORDER BOOKING REPORT 2024-25!C:CV""),{58,65,72},0))))"),7418264.69999999) -> 7418264.7 | BR39: =IFERROR(__xludf.DUMMYFUNCTION("IFERROR(ArrayFormula(SUM(VLOOKUP($C39,importrange(""1MwNMVzWE3QBVOyJjKr3eFX-Sq1Ng0Q1sghWJbgbE_8g"",""ORDER BOOKING REPORT 2024-25!C:CV""),{79,86,93},0))))"),7514881.3) -> 7514881.3 | BS39: =IFERROR(AY39/BM39,"") | BT39: =IFERROR(SUM(AK39:AL39)/AY39,"") | BU39: =BL39-G39 -> 0 | BV39: 51393 | BW39: Area Sales Manager | BX39: 671 | BY39: =BV39-AJ39 -> 0 | CG39: =IF(N39<60,"Below 60"," ") | CH39: =IF(T39 = 0, "Not 50%", IF(T39 >= 0.5 * N39, "Business Achieved 50%", "Not 50%")) -> Business Achieved 50% | CI39: =IFERROR((T39/N39),) -> 0.75 | CJ39: =IFERROR(__xludf.DUMMYFUNCTION("""COMPUTED_VALUE"""),1078) -> 1078 | CK39: =IFERROR(__xludf.DUMMYFUNCTION("""COMPUTED_VALUE"""),92) -> 92 | CL39: =IFERROR(__xludf.DUMMYFUNCTION("""COMPUTED_VALUE"""),0) -> 0 | CM39: =AE39-SUM(CJ39:CL39) -> 0
A40: Lalan Kumar | B40: Maharashtra | C40: Tejas Lunawat | D40: MAHARASHTRA | E40: Pune | F40: 44459 | G40: 0 | H40: 21600000 | I40: 18278834 | J40: 0 | K40: 106 | L40: 71 | M40: 5 | N40: 111 | O40: 40 | P40: 18278834 | Q40: 0 | R40: 43 | S40: 0 | T40: 43 | U40: 0 | V40: 16 | W40: 17 | X40: 60 | Y40: 13 | Z40: 240 | AA40: 0 | AB40: 0 | AC40: 7 | AD40: 17 | AE40: 254 | AF40: 528 | AG40: 288 | AH40: =IFERROR(SUM(I40:J40)/AG40,"") -> 63468.173 | AI40: =IFERROR(AF40/AG40,"") -> 1.8333333 | AJ40: 49585 | AK40: =AJ40*BD40 -> 595020 | AL40: 295608 | AM40: =IFERROR(SUM(AK40:AL40)/SUM(I40:J40),"") -> 0.048724553 | AN40: =IFERROR(I40/T40,"") -> 425089.16 | AO40: =IFERROR(SUM(I40:J40)/SUM(G40:H40),"") -> 0.8462423 | AP40: 0 | AQ40: 267 | AR40: 2877 | AS40: 2706.04 | AT40: 0 | AU40: 38 | AV40: 43 | AW40: 33 | AX40: 35 | AY40: =IFERROR(VLOOKUP(C40,#REF!,13,0),"") | BA40: =IF(ISBLANK(AZ40),"Active","LEFT" ) -> Active | BB40: =_xludf.ifs(F40<$BB$1,"Old",F40>$BB$1,"New") -> #NAME? | BC40: =_xludf.ifs(AO40<50%,"Below 50%",AO40<70%,"50%-70%",AO40<90%,"70%-90%",AO40<100%,"90%-100%",AO40>100%,"Above 100%") -> #NAME? | BD40: =MATCH($BD$2,{"Apr","May","Jun","Jul","Aug","Sep","Oct","Nov","Dec","Jan","Feb","Mar"},0) -> 12 | BF40: =M40-AT40 -> 5 | BG40: Secondary | BH40: =IFERROR(__xludf.DUMMYFUNCTION("""COMPUTED_VALUE"""),24878609) -> 24878609 | BI40: =IFERROR(__xludf.DUMMYFUNCTION("""COMPUTED_VALUE"""),18946895.5) -> 18946896 | BL40: =BK40*BD40 -> 0 | BM40: =H40+BL40 -> 21600000 | BO40: =IFERROR(__xludf.DUMMYFUNCTION("IFERROR(ArrayFormula(SUM(VLOOKUP($C40,importrange(""1MwNMVzWE3QBVOyJjKr3eFX-Sq1Ng0Q1sghWJbgbE_8g"",""ORDER BOOKING REPORT 2024-25!C:CV""),{16,23,30},0))))"),4850194.38) -> 4850194.4 | BP40: =IFERROR(__xludf.DUMMYFUNCTION("IFERROR(ArrayFormula(SUM(VLOOKUP($C40,importrange(""1MwNMVzWE3QBVOyJjKr3eFX-Sq1Ng0Q1sghWJbgbE_8g"",""ORDER BOOKING REPORT 2024-25!C:CV""),{37,44,51},0))))"),5196598.04) -> 5196598 | BQ40: =IFERROR(__xludf.DUMMYFUNCTION("IFERROR(ArrayFormula(SUM(VLOOKUP($C40,importrange(""1MwNMVzWE3QBVOyJjKr3eFX-Sq1Ng0Q1sghWJbgbE_8g"",""ORDER BOOKING REPORT 2024-25!C:CV""),{58,65,72},0))))"),3758401.72) -> 3758401.7 | BR40: =IFERROR(__xludf.DUMMYFUNCTION("IFERROR(ArrayFormula(SUM(VLOOKUP($C40,importrange(""1MwNMVzWE3QBVOyJjKr3eFX-Sq1Ng0Q1sghWJbgbE_8g"",""ORDER BOOKING REPORT 2024-25!C:CV""),{79,86,93},0))))"),5141701.35999999) -> 5141701.4 | BS40: =IFERROR(AY40/BM40,"") | BT40: =IFERROR(SUM(AK40:AL40)/AY40,"") | BU40: =BL40-G40 -> 0 | BV40: 49585 | BW40: Area Sales Manager | BX40: 678 | BY40: =BV40-AJ40 -> 0 | CG40: =IF(N40<60,"Below 60"," ") | CH40: =IF(T40 = 0, "Not 50%", IF(T40 >= 0.5 * N40, "Business Achieved 50%", "Not 50%")) -> Not 50% | CI40: =IFERROR((T40/N40),) -> 0.38738739 | CJ40: =IFERROR(__xludf.DUMMYFUNCTION("""COMPUTED_VALUE"""),213) -> 213 | CK40: =IFERROR(__xludf.DUMMYFUNCTION("""COMPUTED_VALUE"""),41) -> 41 | CL40: =IFERROR(__xludf.DUMMYFUNCTION("""COMPUTED_VALUE"""),0) -> 0 | CM40: =AE40-SUM(CJ40:CL40) -> 0
A41: Sandeep Dadheech | B41: North East | C41: Santanu Kalita | D41: ARUNACHAL PRADESH, ASSAM, MANIPUR, MEGHALAYA, MIZORAM, NAGALAND, SIKKIM, TRIPURA | E41: Tezpur | F41: 44501 | G41: 0 | H41: 54000000 | I41: 40902035 | J41: 0 | K41: 105 | L41: 105 | M41: 5 | N41: 110 | O41: 5 | P41: 36738275 | Q41: 4163759.5 | R41: 38 | S41: 5 | T41: 43 | U41: 0 | V41: 26 | W41: 41 | X41: 119 | Y41: 3 | Z41: 5 | AA41: 0 | AB41: 0 | AC41: 0 | AD41: 0 | AE41: 2058 | AF41: 2104 | AG41: 303 | AH41: =IFERROR(SUM(I41:J41)/AG41,"") -> 134990.21 | AI41: =IFERROR(AF41/AG41,"") -> 6.9438944 | AJ41: 58700 | AK41: =AJ41*BD41 -> 704400 | AL41: 401751 | AM41: =IFERROR(SUM(AK41:AL41)/SUM(I41:J41),"") -> 0.027043911 | AN41: =IFERROR(I41/T41,"") -> 951210.11 | AO41: =IFERROR(SUM(I41:J41)/SUM(G41:H41),"") -> 0.75744508 | AP41: 0 | AQ41: 289 | AR41: 2818 | AS41: 2037.18 | AT41: 5 | AU41: 19 | AV41: 43 | AW41: 62 | AX41: 5 | AY41: =IFERROR(VLOOKUP(C41,#REF!,13,0),"") | BA41: =IF(ISBLANK(AZ41),"Active","LEFT" ) -> Active | BB41: =_xludf.ifs(F41<$BB$1,"Old",F41>$BB$1,"New") -> #NAME? | BC41: =_xludf.ifs(AO41<50%,"Below 50%",AO41<70%,"50%-70%",AO41<90%,"70%-90%",AO41<100%,"90%-100%",AO41>100%,"Above 100%") -> #NAME? | BD41: =MATCH($BD$2,{"Apr","May","Jun","Jul","Aug","Sep","Oct","Nov","Dec","Jan","Feb","Mar"},0) -> 12 | BF41: =M41-AT41 -> 0 | BG41: Secondary | BH41: =IFERROR(__xludf.DUMMYFUNCTION("""COMPUTED_VALUE"""),35253240) -> 35253240 | BI41: =IFERROR(__xludf.DUMMYFUNCTION("""COMPUTED_VALUE"""),37620571.6) -> 37620572 | BL41: =BK41*BD41 -> 0 | BM41: =H41+BL41 -> 54000000 | BO41: =IFERROR(__xludf.DUMMYFUNCTION("IFERROR(ArrayFormula(SUM(VLOOKUP($C41,importrange(""1MwNMVzWE3QBVOyJjKr3eFX-Sq1Ng0Q1sghWJbgbE_8g"",""ORDER BOOKING REPORT 2024-25!C:CV""),{16,23,30},0))))"),8213529.7) -> 8213529.7 | BP41: =IFERROR(__xludf.DUMMYFUNCTION("IFERROR(ArrayFormula(SUM(VLOOKUP($C41,importrange(""1MwNMVzWE3QBVOyJjKr3eFX-Sq1Ng0Q1sghWJbgbE_8g"",""ORDER BOOKING REPORT 2024-25!C:CV""),{37,44,51},0))))"),9723700.9) -> 9723700.9 | BQ41: =IFERROR(__xludf.DUMMYFUNCTION("IFERROR(ArrayFormula(SUM(VLOOKUP($C41,importrange(""1MwNMVzWE3QBVOyJjKr3eFX-Sq1Ng0Q1sghWJbgbE_8g"",""ORDER BOOKING REPORT 2024-25!C:CV""),{58,65,72},0))))"),9452900.7) -> 9452900.7 | BR41: =IFERROR(__xludf.DUMMYFUNCTION("IFERROR(ArrayFormula(SUM(VLOOKUP($C41,importrange(""1MwNMVzWE3QBVOyJjKr3eFX-Sq1Ng0Q1sghWJbgbE_8g"",""ORDER BOOKING REPORT 2024-25!C:CV""),{79,86,93},0))))"),10230440.3) -> 10230440 | BS41: =IFERROR(AY41/BM41,"") | BT41: =IFERROR(SUM(AK41:AL41)/AY41,"") | BU41: =BL41-G41 -> 0 | BV41: 58700 | BW41: Area Sales Manager | BX41: 697 | BY41: =BV41-AJ41 -> 0 | CG41: =IF(N41<60,"Below 60"," ") | CH41: =IF(T41 = 0, "Not 50%", IF(T41 >= 0.5 * N41, "Business Achieved 50%", "Not 50%")) -> Not 50% | CI41: =IFERROR((T41/N41),) -> 0.39090909 | CJ41: =IFERROR(__xludf.DUMMYFUNCTION("""COMPUTED_VALUE"""),1256) -> 1256 | CK41: =IFERROR(__xludf.DUMMYFUNCTION("""COMPUTED_VALUE"""),802) -> 802 | CL41: =IFERROR(__xludf.DUMMYFUNCTION("""COMPUTED_VALUE"""),0) -> 0 | CM41: =AE41-SUM(CJ41:CL41) -> 0
A42: Syed Aqil Rizvi | B42: Maharashtra 2 | C42: Himanshu Sable | D42: MAHARASHTRA | E42: Amravati | F42: 44501 | G42: 0 | H42: 21120000 | I42: 9779119.5 | J42: 0 | K42: 77 | L42: 77 | M42: 8 | N42: 85 | O42: 8 | P42: 7750626 | Q42: 2028493.5 | R42: 41 | S42: 7 | T42: 48 | U42: 0 | V42: 86 | W42: 158 | X42: 222 | Y42: 2 | Z42: 9 | AA42: 0 | AB42: 0 | AC42: 0 | AD42: 0 | AE42: 984 | AF42: 1151 | AG42: 286 | AH42: =IFERROR(SUM(I42:J42)/AG42,"") -> 34192.725 | AI42: =IFERROR(AF42/AG42,"") -> 4.0244755 | AJ42: 28500 | AK42: =AJ42*BD42 -> 342000 | AL42: 186475 | AM42: =IFERROR(SUM(AK42:AL42)/SUM(I42:J42),"") -> 0.054041164 | AN42: =IFERROR(I42/T42,"") -> 203731.66 | AO42: =IFERROR(SUM(I42:J42)/SUM(G42:H42),"") -> 0.46302649 | AP42: 0 | AQ42: 398 | AR42: 3476 | AS42: 2594.82 | AT42: 7 | AU42: 34 | AV42: 48 | AW42: 31 | AX42: 6 | AY42: =IFERROR(VLOOKUP(C42,#REF!,13,0),"") | BA42: =IF(ISBLANK(AZ42),"Active","LEFT" ) -> Active | BB42: =_xludf.ifs(F42<$BB$1,"Old",F42>$BB$1,"New") -> #NAME? | BC42: =_xludf.ifs(AO42<50%,"Below 50%",AO42<70%,"50%-70%",AO42<90%,"70%-90%",AO42<100%,"90%-100%",AO42>100%,"Above 100%") -> #NAME? | BD42: =MATCH($BD$2,{"Apr","May","Jun","Jul","Aug","Sep","Oct","Nov","Dec","Jan","Feb","Mar"},0) -> 12 | BF42: =M42-AT42 -> 1 | BG42: Secondary | BH42: =IFERROR(__xludf.DUMMYFUNCTION("""COMPUTED_VALUE"""),6088405.5) -> 6088405.5 | BI42: =IFERROR(__xludf.DUMMYFUNCTION("""COMPUTED_VALUE"""),7365298.11999999) -> 7365298.1 | BL42: =BK42*BD42 -> 0 | BM42: =H42+BL42 -> 21120000 | BO42: =IFERROR(__xludf.DUMMYFUNCTION("IFERROR(ArrayFormula(SUM(VLOOKUP($C42,importrange(""1MwNMVzWE3QBVOyJjKr3eFX-Sq1Ng0Q1sghWJbgbE_8g"",""ORDER BOOKING REPORT 2024-25!C:CV""),{16,23,30},0))))"),1707943.24) -> 1707943.2 | BP42: =IFERROR(__xludf.DUMMYFUNCTION("IFERROR(ArrayFormula(SUM(VLOOKUP($C42,importrange(""1MwNMVzWE3QBVOyJjKr3eFX-Sq1Ng0Q1sghWJbgbE_8g"",""ORDER BOOKING REPORT 2024-25!C:CV""),{37,44,51},0))))"),1774440.33999999) -> 1774440.3 | BQ42: =IFERROR(__xludf.DUMMYFUNCTION("IFERROR(ArrayFormula(SUM(VLOOKUP($C42,importrange(""1MwNMVzWE3QBVOyJjKr3eFX-Sq1Ng0Q1sghWJbgbE_8g"",""ORDER BOOKING REPORT 2024-25!C:CV""),{58,65,72},0))))"),1817942.02) -> 1817942 | BR42: =IFERROR(__xludf.DUMMYFUNCTION("IFERROR(ArrayFormula(SUM(VLOOKUP($C42,importrange(""1MwNMVzWE3QBVOyJjKr3eFX-Sq1Ng0Q1sghWJbgbE_8g"",""ORDER BOOKING REPORT 2024-25!C:CV""),{79,86,93},0))))"),2064972.52) -> 2064972.5 | BS42: =IFERROR(AY42/BM42,"") | BT42: =IFERROR(SUM(AK42:AL42)/AY42,"") | BU42: =BL42-G42 -> 0 | BV42: 28500 | BW42: Sr. Executive - Sales & Mktg. | BX42: 696 | BY42: =BV42-AJ42 -> 0 | CG42: =IF(N42<60,"Below 60"," ") | CH42: =IF(T42 = 0, "Not 50%", IF(T42 >= 0.5 * N42, "Business Achieved 50%", "Not 50%")) -> Business Achieved 50% | CI42: =IFERROR((T42/N42),) -> 0.56470588 | CJ42: =IFERROR(__xludf.DUMMYFUNCTION("""COMPUTED_VALUE"""),763) -> 763 | CK42: =IFERROR(__xludf.DUMMYFUNCTION("""COMPUTED_VALUE"""),221) -> 221 | CL42: =IFERROR(__xludf.DUMMYFUNCTION("""COMPUTED_VALUE"""),0) -> 0 | CM42: =AE42-SUM(CJ42:CL42) -> 0
A43: Sandeep Dadheech | B43: Tamil Nadu | C43: Arun kumar.S | D43: TAMIL NADU | E43: Salem | F43: 44508 | G43: 0 | H43: 0 | I43: 44994.4 | J43: 0 | K43: 95 | L43: 40 | M43: 0 | N43: 95 | O43: 55 | P43: 44994.4 | Q43: 0 | R43: 7 | S43: 0 | T43: 7 | U43: 0 | V43: 14 | W43: 14 | X43: 82 | Y43: 1 | Z43: 1 | AA43: 0 | AB43: 0 | AC43: 0 | AD43: 0 | AE43: 47 | AF43: 62 | AG43: 10 | AH43: =IFERROR(SUM(I43:J43)/AG43,"") -> 4499.44 | AI43: =IFERROR(AF43/AG43,"") -> 6.2 | AJ43: 21667 | AK43: =AJ43*BD43 -> 8666.8 | AL43: 6357 | AM43: =IFERROR(SUM(AK43:AL43)/SUM(I43:J43),"") -> 0.33390377 | AN43: =IFERROR(I43/T43,"") -> 6427.7714 | AO43: No Target | AP43: 0 | AQ43: 7 | AR43: 126 | AS43: 0 | AT43: 0 | AU43: 0 | AV43: 7 | AW43: 33 | AX43: 55 | AY43: =IFERROR(VLOOKUP(C43,#REF!,13,0),"") | AZ43: 45759 | BA43: =IF(ISBLANK(AZ43),"Active","LEFT" ) -> LEFT | BB43: =_xludf.ifs(F43<$BB$1,"Old",F43>$BB$1,"New") -> #NAME? | BC43: No Target | BD43: =12/30 -> 0.4 | BF43: =M43-AT43 -> 0 | BG43: Secondary | BH43: =IFERROR(__xludf.DUMMYFUNCTION("""COMPUTED_VALUE"""),3914074) -> 3914074 | BI43: =IFERROR(__xludf.DUMMYFUNCTION("""COMPUTED_VALUE"""),4013186.29999999) -> 4013186.3 | BJ43: =12/30 -> 0.4 | BL43: =BK43*BD43 -> 0 | BM43: =H43+BL43 -> 0 | BO43: =IFERROR(__xludf.DUMMYFUNCTION("IFERROR(ArrayFormula(SUM(VLOOKUP($C43,importrange(""1MwNMVzWE3QBVOyJjKr3eFX-Sq1Ng0Q1sghWJbgbE_8g"",""ORDER BOOKING REPORT 2024-25!C:CV""),{16,23,30},0))))"),1184475.6) -> 1184475.6 | BP43: =IFERROR(__xludf.DUMMYFUNCTION("IFERROR(ArrayFormula(SUM(VLOOKUP($C43,importrange(""1MwNMVzWE3QBVOyJjKr3eFX-Sq1Ng0Q1sghWJbgbE_8g"",""ORDER BOOKING REPORT 2024-25!C:CV""),{37,44,51},0))))"),1095206.6) -> 1095206.6 | BQ43: =IFERROR(__xludf.DUMMYFUNCTION("IFERROR(ArrayFormula(SUM(VLOOKUP($C43,importrange(""1MwNMVzWE3QBVOyJjKr3eFX-Sq1Ng0Q1sghWJbgbE_8g"",""ORDER BOOKING REPORT 2024-25!C:CV""),{58,65,72},0))))"),949346.099999999) -> 949346.1 | BR43: =IFERROR(__xludf.DUMMYFUNCTION("IFERROR(ArrayFormula(SUM(VLOOKUP($C43,importrange(""1MwNMVzWE3QBVOyJjKr3eFX-Sq1Ng0Q1sghWJbgbE_8g"",""ORDER BOOKING REPORT 2024-25!C:CV""),{79,86,93},0))))"),784158) -> 784158 | BS43: =IFERROR(AY43/BM43,"") | BT43: =IFERROR(SUM(AK43:AL43)/AY43,"") | BU43: =BL43-G43 -> 0 | BY43: =BV43-AJ43 -> -21667 | CG43: =IF(N43<60,"Below 60"," ") | CH43: =IF(T43 = 0, "Not 50%", IF(T43 >= 0.5 * N43, "Business Achieved 50%", "Not 50%")) -> Not 50% | CI43: =IFERROR((T43/N43),) -> 0.073684211 | CJ43: =IFERROR(__xludf.DUMMYFUNCTION("""COMPUTED_VALUE"""),10) -> 10 | CK43: =IFERROR(__xludf.DUMMYFUNCTION("""COMPUTED_VALUE"""),37) -> 37 | CL43: =IFERROR(__xludf.DUMMYFUNCTION("""COMPUTED_VALUE"""),0) -> 0 | CM43: =AE43-SUM(CJ43:CL43) -> 0
A44: Syed Aqil Rizvi | B44: East U.P | C44: Siddharth Shanker Singh | D44: East U.P | E44: Prayagraj (Allahabad) | F44: 44511 | G44: 2400000 | H44: 23600004 | I44: 13066456 | J44: 4044018.9 | K44: 74 | L44: 76 | M44: 7 | N44: 81 | O44: 5 | P44: 12223539 | Q44: 842916.71 | R44: 55 | S44: 7 | T44: 62 | U44: 12 | V44: 8 | W44: 17 | X44: 63 | Y44: 5 | Z44: 67 | AA44: 12 | AB44: 117 | AC44: 3 | AD44: 7 | AE44: 819 | AF44: 1027 | AG44: 295 | AH44: =IFERROR(SUM(I44:J44)/AG44,"") -> 58001.609 | AI44: =IFERROR(AF44/AG44,"") -> 3.4813559 | AJ44: =BV44 -> 44000 | AK44: =AJ44*BD44 -> 528000 | AL44: 113069 | AM44: =IFERROR(SUM(AK44:AL44)/SUM(I44:J44),"") -> 0.037466465 | AN44: =IFERROR(I44/T44,"") -> 210749.29 | AO44: =IFERROR(SUM(I44:J44)/SUM(G44:H44),"") -> 0.65809508 | AP44: 1.68 | AQ44: 276 | AR44: 2203 | AS44: 1884.7 | AT44: 7 | AU44: 25 | AV44: 62 | AW44: 14 | AX44: 5 | AY44: =IFERROR(VLOOKUP(C44,#REF!,13,0),"") | BA44: =IF(ISBLANK(AZ44),"Active","LEFT" ) -> Active | BB44: =_xludf.ifs(F44<$BB$1,"Old",F44>$BB$1,"New") -> #NAME? | BC44: =_xludf.ifs(AO44<50%,"Below 50%",AO44<70%,"50%-70%",AO44<90%,"70%-90%",AO44<100%,"90%-100%",AO44>100%,"Above 100%") -> #NAME? | BD44: {=MATCH($BD$2,{"Apr","May","Jun","Jul","Aug","Sep","Oct","Nov","Dec","Jan","Feb","Mar"},0)} -> 12 | BF44: =M44-AT44 -> 0 | BG44: Secondary | BH44: =IFERROR(__xludf.DUMMYFUNCTION("""COMPUTED_VALUE"""),14942928.36) -> 14942928 | BI44: =IFERROR(__xludf.DUMMYFUNCTION("""COMPUTED_VALUE"""),16341216.93) -> 16341217 | BK44: 200000 | BL44: =BK44*BD44 -> 2400000 | BM44: =H44+BL44 -> 26000004 | BO44: =IFERROR(__xludf.DUMMYFUNCTION("IFERROR(ArrayFormula(SUM(VLOOKUP($C44,importrange(""1MwNMVzWE3QBVOyJjKr3eFX-Sq1Ng0Q1sghWJbgbE_8g"",""ORDER BOOKING REPORT 2024-25!C:CV""),{16,23,30},0))))"),4031753.8) -> 4031753.8 | BP44: =IFERROR(__xludf.DUMMYFUNCTION("IFERROR(ArrayFormula(SUM(VLOOKUP($C44,importrange(""1MwNMVzWE3QBVOyJjKr3eFX-Sq1Ng0Q1sghWJbgbE_8g"",""ORDER BOOKING REPORT 2024-25!C:CV""),{37,44,51},0))))"),3533634.17999999) -> 3533634.2 | BQ44: =IFERROR(__xludf.DUMMYFUNCTION("IFERROR(ArrayFormula(SUM(VLOOKUP($C44,importrange(""1MwNMVzWE3QBVOyJjKr3eFX-Sq1Ng0Q1sghWJbgbE_8g"",""ORDER BOOKING REPORT 2024-25!C:CV""),{58,65,72},0))))"),3887315.3) -> 3887315.3 | BR44: =IFERROR(__xludf.DUMMYFUNCTION("IFERROR(ArrayFormula(SUM(VLOOKUP($C44,importrange(""1MwNMVzWE3QBVOyJjKr3eFX-Sq1Ng0Q1sghWJbgbE_8g"",""ORDER BOOKING REPORT 2024-25!C:CV""),{79,86,93},0))))"),4888513.65) -> 4888513.7 | BS44: =IFERROR(AY44/BM44,"") | BT44: =IFERROR(SUM(AK44:AL44)/AY44,"") | BU44: =BL44-G44 -> 0 | BV44: 44000 | BW44: Sr. Executive - Sales & Mktg. | BX44: 700 | BY44: =BV44-AJ44 -> 0 | CG44: =IF(N44<60,"Below 60"," ") | CH44: =IF(T44 = 0, "Not 50%", IF(T44 >= 0.5 * N44, "Business Achieved 50%", "Not 50%")) -> Business Achieved 50% | CI44: =IFERROR((T44/N44),) -> 0.7654321 | CJ44: =IFERROR(__xludf.DUMMYFUNCTION("""COMPUTED_VALUE"""),745) -> 745 | CK44: =IFERROR(__xludf.DUMMYFUNCTION("""COMPUTED_VALUE"""),74) -> 74 | CL44: =IFERROR(__xludf.DUMMYFUNCTION("""COMPUTED_VALUE"""),0) -> 0 | CM44: =AE44-SUM(CJ44:CL44) -> 0
A45: Lalan Kumar | B45: Maharashtra | C45: Satish Shete | D45: MAHARASHTRA | E45: Latur | F45: 44635 | G45: 0 | H45: 0 | I45: 0 | J45: 0 | K45: 116 | L45: 6 | M45: 1 | N45: 117 | O45: 111 | P45: 0 | Q45: 0 | R45: 0 | S45: 0 | T45: 0 | U45: 0 | V45: 0 | W45: 0 | X45: 128 | Y45: 0 | Z45: 0 | AA45: 0 | AB45: 0 | AC45: 0 | AD45: 0 | AE45: 9 | AF45: 9 | AG45: 3 | AH45: =IFERROR(SUM(I45:J45)/AG45,"") -> 0 | AI45: =IFERROR(AF45/AG45,"") -> 3 | AJ45: 38000 | AK45: =AJ45*BD45 -> 8740 | AM45: =IFERROR(SUM(AK45:AL45)/SUM(I45:J45),"") | AN45: =IFERROR(I45/T45,"") | AO45: No Target | AP45: 0 | AQ45: 0 | AR45: 24 | AS45: 0 | AT45: 0 | AU45: 0 | AV45: 0 | AW45: 6 | AX45: 111 | AY45: =IFERROR(VLOOKUP(C45,#REF!,13,0),"") | AZ45: 45754 | BA45: =IF(ISBLANK(AZ45),"Active","LEFT" ) -> LEFT | BB45: =_xludf.ifs(F45<$BB$1,"Old",F45>$BB$1,"New") -> #NAME? | BC45: No Target | BD45: 0.23 | BF45: =M45-AT45 -> 1 | BG45: Secondary | BH45: =IFERROR(__xludf.DUMMYFUNCTION("""COMPUTED_VALUE"""),13608518) -> 13608518 | BI45: =IFERROR(__xludf.DUMMYFUNCTION("""COMPUTED_VALUE"""),4935260.5) -> 4935260.5 | BJ45: =7/30 -> 0.23333333 | BL45: =BK45*BD45 -> 0 | BM45: =H45+BL45 -> 0 | BO45: =IFERROR(__xludf.DUMMYFUNCTION("IFERROR(ArrayFormula(SUM(VLOOKUP($C45,importrange(""1MwNMVzWE3QBVOyJjKr3eFX-Sq1Ng0Q1sghWJbgbE_8g"",""ORDER BOOKING REPORT 2024-25!C:CV""),{16,23,30},0))))"),1488251) -> 1488251 | BP45: =IFERROR(__xludf.DUMMYFUNCTION("IFERROR(ArrayFormula(SUM(VLOOKUP($C45,importrange(""1MwNMVzWE3QBVOyJjKr3eFX-Sq1Ng0Q1sghWJbgbE_8g"",""ORDER BOOKING REPORT 2024-25!C:CV""),{37,44,51},0))))"),1013684.2) -> 1013684.2 | BQ45: =IFERROR(__xludf.DUMMYFUNCTION("IFERROR(ArrayFormula(SUM(VLOOKUP($C45,importrange(""1MwNMVzWE3QBVOyJjKr3eFX-Sq1Ng0Q1sghWJbgbE_8g"",""ORDER BOOKING REPORT 2024-25!C:CV""),{58,65,72},0))))"),1247674.6) -> 1247674.6 | BR45: =IFERROR(__xludf.DUMMYFUNCTION("IFERROR(ArrayFormula(SUM(VLOOKUP($C45,importrange(""1MwNMVzWE3QBVOyJjKr3eFX-Sq1Ng0Q1sghWJbgbE_8g"",""ORDER BOOKING REPORT 2024-25!C:CV""),{79,86,93},0))))"),1185650.7) -> 1185650.7 | BS45: =IFERROR(AY45/BM45,"") | BT45: =IFERROR(SUM(AK45:AL45)/AY45,"") | BU45: =BL45-G45 -> 0 | BY45: =BV45-AJ45 -> -38000 | CG45: =IF(N45<60,"Below 60"," ") | CH45: =IF(T45 = 0, "Not 50%", IF(T45 >= 0.5 * N45, "Business Achieved 50%", "Not 50%")) -> Not 50% | CI45: =IFERROR((T45/N45),) -> 0 | CM45: =AE45-SUM(CJ45:CL45) -> 9
A46: Syed Aqil Rizvi | B46: Madhya Pradesh | C46: Neel Kamal choure | D46: MADHYA PRADESH | E46: Jabalpur | F46: 44662 | G46: 1200000 | H46: 19599996 | I46: 10642240 | J46: 0 | K46: 52 | L46: 64 | M46: 16 | N46: 68 | O46: 4 | P46: 8957819.6 | Q46: 1684420.3 | R46: 29 | S46: 16 | T46: 45 | U46: 0 | V46: 240 | W46: 457 | X46: 259 | Y46: 1 | Z46: 44 | AA46: 1 | AB46: 2 | AC46: 2 | AD46: 7 | AE46: 710 | AF46: 1220 | AG46: 261 | AH46: =IFERROR(SUM(I46:J46)/AG46,"") -> 40774.865 | AI46: =IFERROR(AF46/AG46,"") -> 4.6743295 | AJ46: =BV46 -> 51950 | AK46: =AJ46*BD46 -> 623400 | AL46: 186006 | AM46: =IFERROR(SUM(AK46:AL46)/SUM(I46:J46),"") -> 0.076055982 | AN46: =IFERROR(I46/T46,"") -> 236494.22 | AO46: =IFERROR(SUM(I46:J46)/SUM(G46:H46),"") -> 0.51164624 | AP46: 0 | AQ46: 181 | AR46: 1967 | AS46: 2845.85 | AT46: 16 | AU46: 44 | AV46: 45 | AW46: 21 | AX46: 2 | AY46: =IFERROR(VLOOKUP(C46,#REF!,13,0),"") | BA46: =IF(ISBLANK(AZ46),"Active","LEFT" ) -> Active | BB46: =_xludf.ifs(F46<$BB$1,"Old",F46>$BB$1,"New") -> #NAME? | BC46: =_xludf.ifs(AO46<50%,"Below 50%",AO46<70%,"50%-70%",AO46<90%,"70%-90%",AO46<100%,"90%-100%",AO46>100%,"Above 100%") -> #NAME? | BD46: =MATCH($BD$2,{"Apr","May","Jun","Jul","Aug","Sep","Oct","Nov","Dec","Jan","Feb","Mar"},0) -> 12 | BF46: =M46-AT46 -> 0 | BG46: Secondary | BH46: =IFERROR(__xludf.DUMMYFUNCTION("""COMPUTED_VALUE"""),6008130) -> 6008130 | BI46: =IFERROR(__xludf.DUMMYFUNCTION("""COMPUTED_VALUE"""),8459044.12) -> 8459044.1 | BK46: 100000 | BL46: =BK46*BD46 -> 1200000 | BM46: =H46+BL46 -> 20799996 | BO46: =IFERROR(__xludf.DUMMYFUNCTION("IFERROR(ArrayFormula(SUM(VLOOKUP($C46,importrange(""1MwNMVzWE3QBVOyJjKr3eFX-Sq1Ng0Q1sghWJbgbE_8g"",""ORDER BOOKING REPORT 2024-25!C:CV""),{16,23,30},0))))"),1536224.85999999) -> 1536224.9 | BP46: =IFERROR(__xludf.DUMMYFUNCTION("IFERROR(ArrayFormula(SUM(VLOOKUP($C46,importrange(""1MwNMVzWE3QBVOyJjKr3eFX-Sq1Ng0Q1sghWJbgbE_8g"",""ORDER BOOKING REPORT 2024-25!C:CV""),{37,44,51},0))))"),1501268) -> 1501268 | BQ46: =IFERROR(__xludf.DUMMYFUNCTION("IFERROR(ArrayFormula(SUM(VLOOKUP($C46,importrange(""1MwNMVzWE3QBVOyJjKr3eFX-Sq1Ng0Q1sghWJbgbE_8g"",""ORDER BOOKING REPORT 2024-25!C:CV""),{58,65,72},0))))"),2335381.8) -> 2335381.8 | BR46: =IFERROR(__xludf.DUMMYFUNCTION("IFERROR(ArrayFormula(SUM(VLOOKUP($C46,importrange(""1MwNMVzWE3QBVOyJjKr3eFX-Sq1Ng0Q1sghWJbgbE_8g"",""ORDER BOOKING REPORT 2024-25!C:CV""),{79,86,93},0))))"),3086169.46) -> 3086169.5 | BS46: =IFERROR(AY46/BM46,"") | BT46: =IFERROR(SUM(AK46:AL46)/AY46,"") | BU46: =BL46-G46 -> 0 | BV46: 51950 | BW46: Area Sales Manager | BX46: 752 | BY46: =BV46-AJ46 -> 0 | CG46: =IF(N46<60,"Below 60"," ") | CH46: =IF(T46 = 0, "Not 50%", IF(T46 >= 0.5 * N46, "Business Achieved 50%", "Not 50%")) -> Business Achieved 50% | CI46: =IFERROR((T46/N46),) -> 0.66176471 | CJ46: =IFERROR(__xludf.DUMMYFUNCTION("""COMPUTED_VALUE"""),667) -> 667 | CK46: =IFERROR(__xludf.DUMMYFUNCTION("""COMPUTED_VALUE"""),43) -> 43 | CL46: =IFERROR(__xludf.DUMMYFUNCTION("""COMPUTED_VALUE"""),0) -> 0 | CM46: =AE46-SUM(CJ46:CL46) -> 0
A47: Nasir Hussain Khan | B47: JAMMU AND KASHMIR | C47: PAWAN KUMAR | D47: JAMMU AND KASHMIR | E47: JAMMU | F47: 44684 | G47: 3999996 | H47: 24000000 | I47: 12533560 | J47: 448818.22 | K47: 29 | L47: 26 | M47: 1 | N47: 30 | O47: 4 | P47: 12475110 | Q47: 58449.7 | R47: 17 | S47: 1 | T47: 18 | U47: 1 | V47: 6 | W47: 7 | X47: 106 | Y47: 5 | Z47: 123 | AA47: 1 | AB47: 30 | AC47: 0 | AD47: 0 | AE47: 825 | AF47: 985 | AG47: 276 | AH47: =IFERROR(SUM(I47:J47)/AG47,"") -> 47037.602 | AI47: =IFERROR(AF47/AG47,"") -> 3.5688406 | AJ47: =BV47 -> 43505 | AK47: =AJ47*BD47 -> 522060 | AL47: 182199 | AM47: =IFERROR(SUM(AK47:AL47)/SUM(I47:J47),"") -> 0.054247303 | AN47: =IFERROR(I47/T47,"") -> 696308.88 | AO47: =IFERROR(SUM(I47:J47)/SUM(G47:H47),"") -> 0.46365643 | AP47: 0.54 | AQ47: 92 | AR47: 21 | AS47: 0 | AT47: 1 | AU47: 0 | AV47: 18 | AW47: 2 | AX47: 12 | AY47: =IFERROR(VLOOKUP(C47,#REF!,13,0),"") | BA47: =IF(ISBLANK(AZ47),"Active","LEFT" ) -> Active | BB47: =_xludf.ifs(F47<$BB$1,"Old",F47>$BB$1,"New") -> #NAME? | BC47: =_xludf.ifs(AO47<50%,"Below 50%",AO47<70%,"50%-70%",AO47<90%,"70%-90%",AO47<100%,"90%-100%",AO47>100%,"Above 100%") -> #NAME? | BD47: =MATCH($BD$2,{"Apr","May","Jun","Jul","Aug","Sep","Oct","Nov","Dec","Jan","Feb","Mar"},0) -> 12 | BF47: =M47-AT47 -> 0 | BG47: Secondary | BH47: =IFERROR(__xludf.DUMMYFUNCTION("""COMPUTED_VALUE"""),12210958) -> 12210958 | BI47: =IFERROR(__xludf.DUMMYFUNCTION("""COMPUTED_VALUE"""),12159890.3) -> 12159890 | BK47: 333333 | BL47: =BK47*BD47 -> 3999996 | BM47: =H47+BL47 -> 27999996 | BO47: =IFERROR(__xludf.DUMMYFUNCTION("IFERROR(ArrayFormula(SUM(VLOOKUP($C47,importrange(""1MwNMVzWE3QBVOyJjKr3eFX-Sq1Ng0Q1sghWJbgbE_8g"",""ORDER BOOKING REPORT 2024-25!C:CV""),{16,23,30},0))))"),2259749.3) -> 2259749.3 | BP47: =IFERROR(__xludf.DUMMYFUNCTION("IFERROR(ArrayFormula(SUM(VLOOKUP($C47,importrange(""1MwNMVzWE3QBVOyJjKr3eFX-Sq1Ng0Q1sghWJbgbE_8g"",""ORDER BOOKING REPORT 2024-25!C:CV""),{37,44,51},0))))"),2851480.55) -> 2851480.5 | BQ47: =IFERROR(__xludf.DUMMYFUNCTION("IFERROR(ArrayFormula(SUM(VLOOKUP($C47,importrange(""1MwNMVzWE3QBVOyJjKr3eFX-Sq1Ng0Q1sghWJbgbE_8g"",""ORDER BOOKING REPORT 2024-25!C:CV""),{58,65,72},0))))"),3237314) -> 3237314 | BR47: =IFERROR(__xludf.DUMMYFUNCTION("IFERROR(ArrayFormula(SUM(VLOOKUP($C47,importrange(""1MwNMVzWE3QBVOyJjKr3eFX-Sq1Ng0Q1sghWJbgbE_8g"",""ORDER BOOKING REPORT 2024-25!C:CV""),{79,86,93},0))))"),3811346.44999999) -> 3811346.4 | BS47: =IFERROR(AY47/BM47,"") | BT47: =IFERROR(SUM(AK47:AL47)/AY47,"") | BU47: =BL47-G47 -> 0 | BV47: 43505 | BW47: Area Sales Manager | BX47: 761 | BY47: =BV47-AJ47 -> 0 | CG47: =IF(N47<60,"Below 60"," ") -> Below 60 | CH47: =IF(T47 = 0, "Not 50%", IF(T47 >= 0.5 * N47, "Business Achieved 50%", "Not 50%")) -> Business Achieved 50% | CI47: =IFERROR((T47/N47),) -> 0.6 | CJ47: =IFERROR(__xludf.DUMMYFUNCTION("""COMPUTED_VALUE"""),683) -> 683 | CK47: =IFERROR(__xludf.DUMMYFUNCTION("""COMPUTED_VALUE"""),142) -> 142 | CL47: =IFERROR(__xludf.DUMMYFUNCTION("""COMPUTED_VALUE"""),0) -> 0 | CM47: =AE47-SUM(CJ47:CL47) -> 0
A48: Biju C.O | B48: Kerala | C48: PRATHEESH CC | D48: KERALA | E48: PALAKKAD | F48: 44693 | G48: 0 | H48: 15860000 | I48: 11934783 | J48: 0 | K48: 74 | L48: 70 | M48: 8 | N48: 82 | O48: 12 | P48: 11592761 | Q48: 342022.8 | R48: 40 | S48: 3 | T48: 43 | U48: 0 | V48: 24 | W48: 84 | X48: 35 | Y48: 1 | Z48: 20 | AA48: 0 | AB48: 0 | AC48: 0 | AD48: 0 | AE48: 1284 | AF48: 1388 | AG48: 279 | AH48: =IFERROR(SUM(I48:J48)/AG48,"") -> 42777.001 | AI48: =IFERROR(AF48/AG48,"") -> 4.9749104 | AJ48: =BV48 -> 32890 | AK48: =AJ48*BD48 -> 394680 | AL48: 123742 | AM48: =IFERROR(SUM(AK48:AL48)/SUM(I48:J48),"") -> 0.043437906 | AN48: =IFERROR(I48/T48,"") -> 277553.1 | AO48: =IFERROR(SUM(I48:J48)/SUM(G48:H48),"") -> 0.75250841 | AP48: 0 | AQ48: 222 | AR48: 2641 | AS48: 2022.17 | AT48: 3 | AU48: 29 | AV48: 43 | AW48: 28 | AX48: 11 | AY48: =IFERROR(VLOOKUP(C48,#REF!,13,0),"") | BA48: =IF(ISBLANK(AZ48),"Active","LEFT" ) -> Active | BB48: =_xludf.ifs(F48<$BB$1,"Old",F48>$BB$1,"New") -> #NAME? | BC48: =_xludf.ifs(AO48<50%,"Below 50%",AO48<70%,"50%-70%",AO48<90%,"70%-90%",AO48<100%,"90%-100%",AO48>100%,"Above 100%") -> #NAME? | BD48: =MATCH($BD$2,{"Apr","May","Jun","Jul","Aug","Sep","Oct","Nov","Dec","Jan","Feb","Mar"},0) -> 12 | BF48: =M48-AT48 -> 5 | BG48: Secondary | BH48: =IFERROR(__xludf.DUMMYFUNCTION("""COMPUTED_VALUE"""),8046618) -> 8046618 | BI48: =IFERROR(__xludf.DUMMYFUNCTION("""COMPUTED_VALUE"""),9689618.05999999) -> 9689618.1 | BL48: =BK48*BD48 -> 0 | BM48: =H48+BL48 -> 15860000 | BO48: =IFERROR(__xludf.DUMMYFUNCTION("IFERROR(ArrayFormula(SUM(VLOOKUP($C48,importrange(""1MwNMVzWE3QBVOyJjKr3eFX-Sq1Ng0Q1sghWJbgbE_8g"",""ORDER BOOKING REPORT 2024-25!C:CV""),{16,23,30},0))))"),2632946.1) -> 2632946.1 | BP48: =IFERROR(__xludf.DUMMYFUNCTION("IFERROR(ArrayFormula(SUM(VLOOKUP($C48,importrange(""1MwNMVzWE3QBVOyJjKr3eFX-Sq1Ng0Q1sghWJbgbE_8g"",""ORDER BOOKING REPORT 2024-25!C:CV""),{37,44,51},0))))"),1873230.27999999) -> 1873230.3 | BQ48: =IFERROR(__xludf.DUMMYFUNCTION("IFERROR(ArrayFormula(SUM(VLOOKUP($C48,importrange(""1MwNMVzWE3QBVOyJjKr3eFX-Sq1Ng0Q1sghWJbgbE_8g"",""ORDER BOOKING REPORT 2024-25!C:CV""),{58,65,72},0))))"),1736982.26) -> 1736982.3 | BR48: =IFERROR(__xludf.DUMMYFUNCTION("IFERROR(ArrayFormula(SUM(VLOOKUP($C48,importrange(""1MwNMVzWE3QBVOyJjKr3eFX-Sq1Ng0Q1sghWJbgbE_8g"",""ORDER BOOKING REPORT 2024-25!C:CV""),{79,86,93},0))))"),3446459.42) -> 3446459.4 | BS48: =IFERROR(AY48/BM48,"") | BT48: =IFERROR(SUM(AK48:AL48)/AY48,"") | BU48: =BL48-G48 -> 0 | BV48: 32890 | BW48: Executive - Sales & Mkt. | BX48: 880 | BY48: =BV48-AJ48 -> 0 | CG48: =IF(N48<60,"Below 60"," ") | CH48: =IF(T48 = 0, "Not 50%", IF(T48 >= 0.5 * N48, "Business Achieved 50%", "Not 50%")) -> Business Achieved 50% | CI48: =IFERROR((T48/N48),) -> 0.52439024 | CJ48: =IFERROR(__xludf.DUMMYFUNCTION("""COMPUTED_VALUE"""),983) -> 983 | CK48: =IFERROR(__xludf.DUMMYFUNCTION("""COMPUTED_VALUE"""),301) -> 301 | CL48: =IFERROR(__xludf.DUMMYFUNCTION("""COMPUTED_VALUE"""),0) -> 0 | CM48: =AE48-SUM(CJ48:CL48) -> 0
A49: Lalan Kumar | B49: Maharashtra | C49: Sandeep Amrut Sonawane | D49: MAHARASHTRA | E49: Dhule | F49: 44697 | G49: 0 | H49: 14400000 | I49: 9167160.2 | J49: 0 | K49: 76 | L49: 71 | M49: 6 | N49: 82 | O49: 11 | P49: 8565519.1 | Q49: 601641.1 | R49: 36 | S49: 6 | T49: 42 | U49: 0 | V49: 51 | W49: 65 | X49: 244 | Y49: 3 | Z49: 6 | AA49: 0 | AB49: 0 | AC49: 0 | AD49: 0 | AE49: 1083 | AF49: 1154 | AG49: 276 | AH49: =IFERROR(SUM(I49:J49)/AG49,"") -> 33214.349 | AI49: =IFERROR(AF49/AG49,"") -> 4.1811594 | AJ49: 36720 | AK49: =AJ49*BD49 -> 440640 | AL49: 157232 | AM49: =IFERROR(SUM(AK49:AL49)/SUM(I49:J49),"") -> 0.065218888 | AN49: =IFERROR(I49/T49,"") -> 218265.72 | AO49: =IFERROR(SUM(I49:J49)/SUM(G49:H49),"") -> 0.63660835 | AP49: 0 | AQ49: 327 | AR49: 2376 | AS49: 3048.93 | AT49: 6 | AU49: 43 | AV49: 42 | AW49: 29 | AX49: 11 | AY49: =IFERROR(VLOOKUP(C49,#REF!,13,0),"") | BA49: =IF(ISBLANK(AZ49),"Active","LEFT" ) -> Active | BB49: =_xludf.ifs(F49<$BB$1,"Old",F49>$BB$1,"New") -> #NAME? | BC49: =_xludf.ifs(AO49<50%,"Below 50%",AO49<70%,"50%-70%",AO49<90%,"70%-90%",AO49<100%,"90%-100%",AO49>100%,"Above 100%") -> #NAME? | BD49: =MATCH($BD$2,{"Apr","May","Jun","Jul","Aug","Sep","Oct","Nov","Dec","Jan","Feb","Mar"},0) -> 12 | BF49: =M49-AT49 -> 0 | BG49: Secondary | BH49: =IFERROR(__xludf.DUMMYFUNCTION("""COMPUTED_VALUE"""),8307773) -> 8307773 | BI49: =IFERROR(__xludf.DUMMYFUNCTION("""COMPUTED_VALUE"""),8154818.76) -> 8154818.8 | BL49: =BK49*BD49 -> 0 | BM49: =H49+BL49 -> 14400000 | BO49: =IFERROR(__xludf.DUMMYFUNCTION("IFERROR(ArrayFormula(SUM(VLOOKUP($C49,importrange(""1MwNMVzWE3QBVOyJjKr3eFX-Sq1Ng0Q1sghWJbgbE_8g"",""ORDER BOOKING REPORT 2024-25!C:CV""),{16,23,30},0))))"),1859469.69) -> 1859469.7 | BP49: =IFERROR(__xludf.DUMMYFUNCTION("IFERROR(ArrayFormula(SUM(VLOOKUP($C49,importrange(""1MwNMVzWE3QBVOyJjKr3eFX-Sq1Ng0Q1sghWJbgbE_8g"",""ORDER BOOKING REPORT 2024-25!C:CV""),{37,44,51},0))))"),1864931.28) -> 1864931.3 | BQ49: =IFERROR(__xludf.DUMMYFUNCTION("IFERROR(ArrayFormula(SUM(VLOOKUP($C49,importrange(""1MwNMVzWE3QBVOyJjKr3eFX-Sq1Ng0Q1sghWJbgbE_8g"",""ORDER BOOKING REPORT 2024-25!C:CV""),{58,65,72},0))))"),1390198.27) -> 1390198.3 | BR49: =IFERROR(__xludf.DUMMYFUNCTION("IFERROR(ArrayFormula(SUM(VLOOKUP($C49,importrange(""1MwNMVzWE3QBVOyJjKr3eFX-Sq1Ng0Q1sghWJbgbE_8g"",""ORDER BOOKING REPORT 2024-25!C:CV""),{79,86,93},0))))"),3040219.51999999) -> 3040219.5 | BS49: =IFERROR(AY49/BM49,"") | BT49: =IFERROR(SUM(AK49:AL49)/AY49,"") | BU49: =BL49-G49 -> 0 | BV49: 36720 | BW49: Executive - Sales & Mkt. | BX49: 770 | BY49: =BV49-AJ49 -> 0 | CG49: =IF(N49<60,"Below 60"," ") | CH49: =IF(T49 = 0, "Not 50%", IF(T49 >= 0.5 * N49, "Business Achieved 50%", "Not 50%")) -> Business Achieved 50% | CI49: =IFERROR((T49/N49),) -> 0.51219512 | CJ49: =IFERROR(__xludf.DUMMYFUNCTION("""COMPUTED_VALUE"""),843) -> 843 | CK49: =IFERROR(__xludf.DUMMYFUNCTION("""COMPUTED_VALUE"""),240) -> 240 | CL49: =IFERROR(__xludf.DUMMYFUNCTION("""COMPUTED_VALUE"""),0) -> 0 | CM49: =AE49-SUM(CJ49:CL49) -> 0
A50: Sandeep Dadheech | B50: Andhra Pradesh | C50: Taninki Ramesh Babu | D50: ANDHRA PRADESH | E50: Kakinada | F50: 44743 | G50: 0 | H50: 14400000 | I50: 3864460 | J50: 0 | K50: 73 | L50: 72 | M50: 3 | N50: 76 | O50: 4 | P50: 3736785.2 | Q50: 127674.8 | R50: 44 | S50: 3 | T50: 47 | U50: 0 | V50: 31 | W50: 82 | X50: 142 | Y50: 3 | Z50: 25 | AA50: 0 | AB50: 0 | AC50: 0 | AD50: 0 | AE50: 1175 | AF50: 1282 | AG50: 299 | AH50: =IFERROR(SUM(I50:J50)/AG50,"") -> 12924.615 | AI50: =IFERROR(AF50/AG50,"") -> 4.2876254 | AJ50: =BV50 -> 24445 | AK50: =AJ50*BD50 -> 293340 | AL50: 124559 | AM50: =IFERROR(SUM(AK50:AL50)/SUM(I50:J50),"") -> 0.10813904 | AN50: =IFERROR(I50/T50,"") -> 82222.552 | AO50: =IFERROR(SUM(I50:J50)/SUM(G50:H50),"") -> 0.26836528 | AP50: 0 | AQ50: 220 | AR50: 3435 | AS50: 3035.69 | AT50: 3 | AU50: 42 | AV50: 47 | AW50: 26 | AX50: 3 | AY50: =IFERROR(VLOOKUP(C50,#REF!,13,0),"") | BA50: =IF(ISBLANK(AZ50),"Active","LEFT" ) -> Active | BB50: =_xludf.ifs(F50<$BB$1,"Old",F50>$BB$1,"New") -> #NAME? | BC50: =_xludf.ifs(AO50<50%,"Below 50%",AO50<70%,"50%-70%",AO50<90%,"70%-90%",AO50<100%,"90%-100%",AO50>100%,"Above 100%") -> #NAME? | BD50: =MATCH($BD$2,{"Apr","May","Jun","Jul","Aug","Sep","Oct","Nov","Dec","Jan","Feb","Mar"},0) -> 12 | BF50: =M50-AT50 -> 0 | BG50: Secondary | BH50: =IFERROR(__xludf.DUMMYFUNCTION("""COMPUTED_VALUE"""),4730158) -> 4730158 | BI50: =IFERROR(__xludf.DUMMYFUNCTION("""COMPUTED_VALUE"""),4785001.22) -> 4785001.2 | BL50: =BK50*BD50 -> 0 | BM50: =H50+BL50 -> 14400000 | BO50: =IFERROR(__xludf.DUMMYFUNCTION("IFERROR(ArrayFormula(SUM(VLOOKUP($C50,importrange(""1MwNMVzWE3QBVOyJjKr3eFX-Sq1Ng0Q1sghWJbgbE_8g"",""ORDER BOOKING REPORT 2024-25!C:CV""),{16,23,30},0))))"),1034616.6) -> 1034616.6 | BP50: =IFERROR(__xludf.DUMMYFUNCTION("IFERROR(ArrayFormula(SUM(VLOOKUP($C50,importrange(""1MwNMVzWE3QBVOyJjKr3eFX-Sq1Ng0Q1sghWJbgbE_8g"",""ORDER BOOKING REPORT 2024-25!C:CV""),{37,44,51},0))))"),1015304.79999999) -> 1015304.8 | BQ50: =IFERROR(__xludf.DUMMYFUNCTION("IFERROR(ArrayFormula(SUM(VLOOKUP($C50,importrange(""1MwNMVzWE3QBVOyJjKr3eFX-Sq1Ng0Q1sghWJbgbE_8g"",""ORDER BOOKING REPORT 2024-25!C:CV""),{58,65,72},0))))"),1347077.6) -> 1347077.6 | BR50: =IFERROR(__xludf.DUMMYFUNCTION("IFERROR(ArrayFormula(SUM(VLOOKUP($C50,importrange(""1MwNMVzWE3QBVOyJjKr3eFX-Sq1Ng0Q1sghWJbgbE_8g"",""ORDER BOOKING REPORT 2024-25!C:CV""),{79,86,93},0))))"),1388002.22) -> 1388002.2 | BS50: =IFERROR(AY50/BM50,"") | BT50: =IFERROR(SUM(AK50:AL50)/AY50,"") | BU50: =BL50-G50 -> 0 | BV50: 24445 | BW50: Executive - Sales & Mkt. | BX50: 784 | BY50: =BV50-AJ50 -> 0 | CG50: =IF(N50<60,"Below 60"," ") | CH50: =IF(T50 = 0, "Not 50%", IF(T50 >= 0.5 * N50, "Business Achieved 50%", "Not 50%")) -> Business Achieved 50% | CI50: =IFERROR((T50/N50),) -> 0.61842105 | CJ50: =IFERROR(__xludf.DUMMYFUNCTION("""COMPUTED_VALUE"""),743) -> 743 | CK50: =IFERROR(__xludf.DUMMYFUNCTION("""COMPUTED_VALUE"""),432) -> 432 | CL50: =IFERROR(__xludf.DUMMYFUNCTION("""COMPUTED_VALUE"""),0) -> 0 | CM50: =AE50-SUM(CJ50:CL50) -> 0
A51: Syed Aqil Rizvi | B51: Madhya Pradesh | C51: Shiv Kumar Patel | D51: MADHYA PRADESH | E51: Rewa | F51: 44805 | G51: 1200000 | H51: 8800002 | I51: 1115217.8 | J51: 773216.52 | K51: 77 | L51: 69 | M51: 15 | N51: 92 | O51: 23 | P51: 1057744.1 | Q51: 57473.7 | R51: 34 | S51: 2 | T51: 36 | U51: 2 | V51: 107 | W51: 138 | X51: 267 | Y51: 2 | Z51: 35 | AA51: 3 | AB51: 24 | AC51: 1 | AD51: 1 | AE51: 352 | AF51: 550 | AG51: 130 | AH51: =IFERROR(SUM(I51:J51)/AG51,"") -> 14526.417 | AI51: =IFERROR(AF51/AG51,"") -> 4.2307692 | AJ51: =BV51 -> 38834 | AK51: =AJ51*BD51 -> 210868.62 | AL51: 64931 | AM51: =IFERROR(SUM(AK51:AL51)/SUM(I51:J51),"") -> 0.14604671 | AN51: =IFERROR(I51/T51,"") -> 30978.271 | AO51: =IFERROR(SUM(I51:J51)/SUM(G51:H51),"") -> 0.18884339 | AP51: 0.64 | AQ51: 82 | AR51: 1062 | AS51: 0 | AT51: 2 | AU51: 0 | AV51: 36 | AW51: 33 | AX51: 23 | AY51: =IFERROR(VLOOKUP(C51,#REF!,13,0),"") | AZ51: 45913 | BA51: =IF(ISBLANK(AZ51),"Active","LEFT" ) -> LEFT | BB51: =_xludf.ifs(F51<$BB$1,"Old",F51>$BB$1,"New") -> #NAME? | BC51: =_xludf.ifs(AO51<50%,"Below 50%",AO51<70%,"50%-70%",AO51<90%,"70%-90%",AO51<100%,"90%-100%",AO51>100%,"Above 100%") -> #NAME? | BD51: 5.43 | BF51: =M51-AT51 -> 13 | BG51: Secondary | BH51: =IFERROR(__xludf.DUMMYFUNCTION("""COMPUTED_VALUE"""),3178281) -> 3178281 | BI51: =IFERROR(__xludf.DUMMYFUNCTION("""COMPUTED_VALUE"""),3968260.82) -> 3968260.8 | BK51: 200000 | BL51: =BK51*6 -> 1200000 | BM51: =H51+BL51 -> 10000002 | BO51: =IFERROR(__xludf.DUMMYFUNCTION("IFERROR(ArrayFormula(SUM(VLOOKUP($C51,importrange(""1MwNMVzWE3QBVOyJjKr3eFX-Sq1Ng0Q1sghWJbgbE_8g"",""ORDER BOOKING REPORT 2024-25!C:CV""),{16,23,30},0))))"),1449578.59999999) -> 1449578.6 | BP51: =IFERROR(__xludf.DUMMYFUNCTION("IFERROR(ArrayFormula(SUM(VLOOKUP($C51,importrange(""1MwNMVzWE3QBVOyJjKr3eFX-Sq1Ng0Q1sghWJbgbE_8g"",""ORDER BOOKING REPORT 2024-25!C:CV""),{37,44,51},0))))"),304601.7) -> 304601.7 | BQ51: =IFERROR(__xludf.DUMMYFUNCTION("IFERROR(ArrayFormula(SUM(VLOOKUP($C51,importrange(""1MwNMVzWE3QBVOyJjKr3eFX-Sq1Ng0Q1sghWJbgbE_8g"",""ORDER BOOKING REPORT 2024-25!C:CV""),{58,65,72},0))))"),597554) -> 597554 | BR51: =IFERROR(__xludf.DUMMYFUNCTION("IFERROR(ArrayFormula(SUM(VLOOKUP($C51,importrange(""1MwNMVzWE3QBVOyJjKr3eFX-Sq1Ng0Q1sghWJbgbE_8g"",""ORDER BOOKING REPORT 2024-25!C:CV""),{79,86,93},0))))"),1616526.52) -> 1616526.5 | BS51: =IFERROR(AY51/BM51,"") | BT51: =IFERROR(SUM(AK51:AL51)/AY51,"") | BU51: =BL51-G51 -> 0 | BV51: 38834 | BW51: Sr. Executive - Sales & Mktg. | BX51: 812 | BY51: =BV51-AJ51 -> 0 | CA51: =BE51*BD51 -> #VALUE! | CC51: =CA51-H51 -> #VALUE! | CG51: =IF(N51<60,"Below 60"," ") | CH51: =IF(T51 = 0, "Not 50%", IF(T51 >= 0.5 * N51, "Business Achieved 50%", "Not 50%")) -> Not 50% | CI51: =IFERROR((T51/N51),) -> 0.39130435 | CJ51: =IFERROR(__xludf.DUMMYFUNCTION("""COMPUTED_VALUE"""),233) -> 233 | CK51: =IFERROR(__xludf.DUMMYFUNCTION("""COMPUTED_VALUE"""),119) -> 119 | CL51: =IFERROR(__xludf.DUMMYFUNCTION("""COMPUTED_VALUE"""),0) -> 0 | CM51: =AE51-SUM(CJ51:CL51) -> 0
A52: Anant Singh | B52: West U.P | C52: Ravinder Puri | D52: West U.P | E52: Ghaziabad | F52: 44809 | G52: 0 | H52: 21600000 | I52: 20551333 | J52: 0 | K52: 97 | L52: 98 | M52: 12 | N52: 109 | O52: 11 | P52: 19313262 | Q52: 1238070.7 | R52: 81 | S52: 10 | T52: 91 | U52: 0 | V52: 47 | W52: 104 | X52: 172 | Y52: 7 | Z52: 239 | AA52: 0 | AB52: 0 | AC52: 3 | AD52: 3 | AE52: 1447 | AF52: 1793 | AG52: 289 | AH52: =IFERROR(SUM(I52:J52)/AG52,"") -> 71111.878 | AI52: =IFERROR(AF52/AG52,"") -> 6.2041522 | AJ52: =BV52 -> 32910 | AK52: =AJ52*BD52 -> 394920 | AL52: 128294 | AM52: =IFERROR(SUM(AK52:AL52)/SUM(I52:J52),"") -> 0.025458884 | AN52: =IFERROR(I52/T52,"") -> 225838.82 | AO52: =IFERROR(SUM(I52:J52)/SUM(G52:H52),"") -> 0.9514506 | AP52: 0 | AQ52: 936 | AR52: 2757 | AS52: 1794.08 | AT52: 10 | AU52: 18 | AV52: 91 | AW52: 13 | AX52: 5 | AY52: =IFERROR(VLOOKUP(C52,#REF!,13,0),"") | BA52: =IF(ISBLANK(AZ52),"Active","LEFT" ) -> Active | BB52: =_xludf.ifs(F52<$BB$1,"Old",F52>$BB$1,"New") -> #NAME? | BC52: =_xludf.ifs(AO52<50%,"Below 50%",AO52<70%,"50%-70%",AO52<90%,"70%-90%",AO52<100%,"90%-100%",AO52>100%,"Above 100%") -> #NAME? | BD52: =MATCH($BD$2,{"Apr","May","Jun","Jul","Aug","Sep","Oct","Nov","Dec","Jan","Feb","Mar"},0) -> 12 | BF52: =M52-AT52 -> 2 | BG52: Secondary | BH52: =IFERROR(__xludf.DUMMYFUNCTION("""COMPUTED_VALUE"""),21927090) -> 21927090 | BI52: =IFERROR(__xludf.DUMMYFUNCTION("""COMPUTED_VALUE"""),20056689.4599999) -> 20056689 | BL52: =BK52*BD52 -> 0 | BM52: =H52+BL52 -> 21600000 | BO52: =IFERROR(__xludf.DUMMYFUNCTION("IFERROR(ArrayFormula(SUM(VLOOKUP($C52,importrange(""1MwNMVzWE3QBVOyJjKr3eFX-Sq1Ng0Q1sghWJbgbE_8g"",""ORDER BOOKING REPORT 2024-25!C:CV""),{16,23,30},0))))"),5968719.90999999) -> 5968719.9 | BP52: =IFERROR(__xludf.DUMMYFUNCTION("IFERROR(ArrayFormula(SUM(VLOOKUP($C52,importrange(""1MwNMVzWE3QBVOyJjKr3eFX-Sq1Ng0Q1sghWJbgbE_8g"",""ORDER BOOKING REPORT 2024-25!C:CV""),{37,44,51},0))))"),4939521.6) -> 4939521.6 | BQ52: =IFERROR(__xludf.DUMMYFUNCTION("IFERROR(ArrayFormula(SUM(VLOOKUP($C52,importrange(""1MwNMVzWE3QBVOyJjKr3eFX-Sq1Ng0Q1sghWJbgbE_8g"",""ORDER BOOKING REPORT 2024-25!C:CV""),{58,65,72},0))))"),4573381.96) -> 4573382 | BR52: =IFERROR(__xludf.DUMMYFUNCTION("IFERROR(ArrayFormula(SUM(VLOOKUP($C52,importrange(""1MwNMVzWE3QBVOyJjKr3eFX-Sq1Ng0Q1sghWJbgbE_8g"",""ORDER BOOKING REPORT 2024-25!C:CV""),{79,86,93},0))))"),4575065.99) -> 4575066 | BS52: =IFERROR(AY52/BM52,"") | BT52: =IFERROR(SUM(AK52:AL52)/AY52,"") | BU52: =BL52-G52 -> 0 | BV52: 32910 | BW52: Executive - Sales & Mkt. | BX52: 806 | BY52: =BV52-AJ52 -> 0 | CG52: =IF(N52<60,"Below 60"," ") | CH52: =IF(T52 = 0, "Not 50%", IF(T52 >= 0.5 * N52, "Business Achieved 50%", "Not 50%")) -> Business Achieved 50% | CI52: =IFERROR((T52/N52),) -> 0.83486239 | CJ52: =IFERROR(__xludf.DUMMYFUNCTION("""COMPUTED_VALUE"""),1378) -> 1378 | CK52: =IFERROR(__xludf.DUMMYFUNCTION("""COMPUTED_VALUE"""),69) -> 69 | CL52: =IFERROR(__xludf.DUMMYFUNCTION("""COMPUTED_VALUE"""),0) -> 0 | CM52: =AE52-SUM(CJ52:CL52) -> 0
A53: Lalan Kumar | B53: Maharashtra | C53: Amit Damodhar Jadhav | D53: MAHARASHTRA | E53: Aurangabad | F53: 44825 | G53: 0 | H53: 21600000 | I53: 12341859 | J53: 0 | K53: 92 | L53: 95 | M53: 9 | N53: 101 | O53: 6 | P53: 12133874 | Q53: 207985.2 | R53: 48 | S53: 5 | T53: 53 | U53: 0 | V53: 46 | W53: 105 | X53: 136 | Y53: 1 | Z53: 89 | AA53: 1 | AB53: 3 | AC53: 0 | AD53: 0 | AE53: 1452 | AF53: 1649 | AG53: 295 | AH53: =IFERROR(SUM(I53:J53)/AG53,"") -> 41836.811 | AI53: =IFERROR(AF53/AG53,"") -> 5.5898305 | AJ53: 45000 | AK53: =AJ53*BD53 -> 540000 | AL53: 198284 | AM53: =IFERROR(SUM(AK53:AL53)/SUM(I53:J53),"") -> 0.059819512 | AN53: =IFERROR(I53/T53,"") -> 232865.27 | AO53: =IFERROR(SUM(I53:J53)/SUM(G53:H53),"") -> 0.57138238 | AP53: 0 | AQ53: 396 | AR53: 2928 | AS53: 3101.82 | AT53: 5 | AU53: 33 | AV53: 53 | AW53: 44 | AX53: 4 | AY53: =IFERROR(VLOOKUP(C53,#REF!,13,0),"") | BA53: =IF(ISBLANK(AZ53),"Active","LEFT" ) -> Active | BB53: =_xludf.ifs(F53<$BB$1,"Old",F53>$BB$1,"New") -> #NAME? | BC53: =_xludf.ifs(AO53<50%,"Below 50%",AO53<70%,"50%-70%",AO53<90%,"70%-90%",AO53<100%,"90%-100%",AO53>100%,"Above 100%") -> #NAME? | BD53: =MATCH($BD$2,{"Apr","May","Jun","Jul","Aug","Sep","Oct","Nov","Dec","Jan","Feb","Mar"},0) -> 12 | BF53: =M53-AT53 -> 4 | BG53: Secondary | BH53: =IFERROR(__xludf.DUMMYFUNCTION("""COMPUTED_VALUE"""),11046346) -> 11046346 | BI53: =IFERROR(__xludf.DUMMYFUNCTION("""COMPUTED_VALUE"""),11122377.62) -> 11122378 | BL53: =BK53*BD53 -> 0 | BM53: =H53+BL53 -> 21600000 | BO53: =IFERROR(__xludf.DUMMYFUNCTION("IFERROR(ArrayFormula(SUM(VLOOKUP($C53,importrange(""1MwNMVzWE3QBVOyJjKr3eFX-Sq1Ng0Q1sghWJbgbE_8g"",""ORDER BOOKING REPORT 2024-25!C:CV""),{16,23,30},0))))"),2627640.5) -> 2627640.5 | BP53: =IFERROR(__xludf.DUMMYFUNCTION("IFERROR(ArrayFormula(SUM(VLOOKUP($C53,importrange(""1MwNMVzWE3QBVOyJjKr3eFX-Sq1Ng0Q1sghWJbgbE_8g"",""ORDER BOOKING REPORT 2024-25!C:CV""),{37,44,51},0))))"),3015989.92) -> 3015989.9 | BQ53: =IFERROR(__xludf.DUMMYFUNCTION("IFERROR(ArrayFormula(SUM(VLOOKUP($C53,importrange(""1MwNMVzWE3QBVOyJjKr3eFX-Sq1Ng0Q1sghWJbgbE_8g"",""ORDER BOOKING REPORT 2024-25!C:CV""),{58,65,72},0))))"),2456046.3) -> 2456046.3 | BR53: =IFERROR(__xludf.DUMMYFUNCTION("IFERROR(ArrayFormula(SUM(VLOOKUP($C53,importrange(""1MwNMVzWE3QBVOyJjKr3eFX-Sq1Ng0Q1sghWJbgbE_8g"",""ORDER BOOKING REPORT 2024-25!C:CV""),{79,86,93},0))))"),3022700.9) -> 3022700.9 | BS53: =IFERROR(AY53/BM53,"") | BT53: =IFERROR(SUM(AK53:AL53)/AY53,"") | BU53: =BL53-G53 -> 0 | BV53: 45000 | BW53: Sr. Executive - Sales & Mktg. | BX53: 809 | BY53: =BV53-AJ53 -> 0 | CG53: =IF(N53<60,"Below 60"," ") | CH53: =IF(T53 = 0, "Not 50%", IF(T53 >= 0.5 * N53, "Business Achieved 50%", "Not 50%")) -> Business Achieved 50% | CI53: =IFERROR((T53/N53),) -> 0.52475248 | CJ53: =IFERROR(__xludf.DUMMYFUNCTION("""COMPUTED_VALUE"""),903) -> 903 | CK53: =IFERROR(__xludf.DUMMYFUNCTION("""COMPUTED_VALUE"""),549) -> 549 | CL53: =IFERROR(__xludf.DUMMYFUNCTION("""COMPUTED_VALUE"""),0) -> 0 | CM53: =AE53-SUM(CJ53:CL53) -> 0
A54: Sandeep Dadheech | B54: North East | C54: Dipak Sharma | D54: ARUNACHAL PRADESH, ASSAM, MANIPUR, MEGHALAYA, MIZORAM, NAGALAND, ODISHA, SIKKIM, TRIPURA | E54: Silchar | F54: 44868 | G54: 0 | H54: 18000000 | I54: 9855471.1 | J54: 0 | K54: 71 | L54: 73 | M54: 8 | N54: 79 | O54: 6 | P54: 8744673 | Q54: 1110798.1 | R54: 39 | S54: 8 | T54: 47 | U54: 0 | V54: 20 | W54: 39 | X54: 32 | Y54: 1 | Z54: 73 | AA54: 0 | AB54: 0 | AC54: 0 | AD54: 0 | AE54: 688 | AF54: 800 | AG54: 264 | AH54: =IFERROR(SUM(I54:J54)/AG54,"") -> 37331.33 | AI54: =IFERROR(AF54/AG54,"") -> 3.030303 | AJ54: 31625 | AK54: =AJ54*BD54 -> 379500 | AL54: 169733 | AM54: =IFERROR(SUM(AK54:AL54)/SUM(I54:J54),"") -> 0.055728741 | AN54: =IFERROR(I54/T54,"") -> 209690.88 | AO54: =IFERROR(SUM(I54:J54)/SUM(G54:H54),"") -> 0.54752617 | AP54: 0 | AQ54: 167 | AR54: 2310 | AS54: 1005.82 | AT54: 8 | AU54: 14 | AV54: 47 | AW54: 27 | AX54: 5 | AY54: =IFERROR(VLOOKUP(C54,#REF!,13,0),"") | BA54: =IF(ISBLANK(AZ54),"Active","LEFT" ) -> Active | BB54: =_xludf.ifs(F54<$BB$1,"Old",F54>$BB$1,"New") -> #NAME? | BC54: =_xludf.ifs(AO54<50%,"Below 50%",AO54<70%,"50%-70%",AO54<90%,"70%-90%",AO54<100%,"90%-100%",AO54>100%,"Above 100%") -> #NAME? | BD54: =MATCH($BD$2,{"Apr","May","Jun","Jul","Aug","Sep","Oct","Nov","Dec","Jan","Feb","Mar"},0) -> 12 | BF54: =M54-AT54 -> 0 | BG54: Secondary | BH54: =IFERROR(__xludf.DUMMYFUNCTION("""COMPUTED_VALUE"""),10577915.36) -> 10577915 | BI54: =IFERROR(__xludf.DUMMYFUNCTION("""COMPUTED_VALUE"""),10770987.2) -> 10770987 | BL54: =BK54*BD54 -> 0 | BM54: =H54+BL54 -> 18000000 | BO54: =IFERROR(__xludf.DUMMYFUNCTION("IFERROR(ArrayFormula(SUM(VLOOKUP($C54,importrange(""1MwNMVzWE3QBVOyJjKr3eFX-Sq1Ng0Q1sghWJbgbE_8g"",""ORDER BOOKING REPORT 2024-25!C:CV""),{16,23,30},0))))"),2474235.3) -> 2474235.3 | BP54: =IFERROR(__xludf.DUMMYFUNCTION("IFERROR(ArrayFormula(SUM(VLOOKUP($C54,importrange(""1MwNMVzWE3QBVOyJjKr3eFX-Sq1Ng0Q1sghWJbgbE_8g"",""ORDER BOOKING REPORT 2024-25!C:CV""),{37,44,51},0))))"),2816418.5) -> 2816418.5 | BQ54: =IFERROR(__xludf.DUMMYFUNCTION("IFERROR(ArrayFormula(SUM(VLOOKUP($C54,importrange(""1MwNMVzWE3QBVOyJjKr3eFX-Sq1Ng0Q1sghWJbgbE_8g"",""ORDER BOOKING REPORT 2024-25!C:CV""),{58,65,72},0))))"),2683364.7) -> 2683364.7 | BR54: =IFERROR(__xludf.DUMMYFUNCTION("IFERROR(ArrayFormula(SUM(VLOOKUP($C54,importrange(""1MwNMVzWE3QBVOyJjKr3eFX-Sq1Ng0Q1sghWJbgbE_8g"",""ORDER BOOKING REPORT 2024-25!C:CV""),{79,86,93},0))))"),2796968.7) -> 2796968.7 | BS54: =IFERROR(AY54/BM54,"") | BT54: =IFERROR(SUM(AK54:AL54)/AY54,"") | BU54: =BL54-G54 -> 0 | BV54: 31625 | BW54: Sr. Executive - Sales & Mktg. | BX54: 826 | BY54: =BV54-AJ54 -> 0 | CG54: =IF(N54<60,"Below 60"," ") | CH54: =IF(T54 = 0, "Not 50%", IF(T54 >= 0.5 * N54, "Business Achieved 50%", "Not 50%")) -> Business Achieved 50% | CI54: =IFERROR((T54/N54),) -> 0.59493671 | CJ54: =IFERROR(__xludf.DUMMYFUNCTION("""COMPUTED_VALUE"""),464) -> 464 | CK54: =IFERROR(__xludf.DUMMYFUNCTION("""COMPUTED_VALUE"""),224) -> 224 | CL54: =IFERROR(__xludf.DUMMYFUNCTION("""COMPUTED_VALUE"""),0) -> 0 | CM54: =AE54-SUM(CJ54:CL54) -> 0
A55: Syed Aqil Rizvi | B55: East U.P | C55: Om dutt Dwivedi | D55: East U.P | E55: Lucknow | F55: 44911 | G55: 0 | H55: 20000004 | I55: 20833738 | J55: 204300.69 | K55: 214 | L55: 240 | M55: 65 | N55: 279 | O55: 39 | P55: 17197014 | Q55: 3636723.9 | R55: 160 | S55: 57 | T55: 217 | U55: 1 | V55: 49 | W55: 80 | X55: 123 | Y55: 2 | Z55: 196 | AA55: 1 | AB55: 3 | AC55: 0 | AD55: 0 | AE55: 1715 | AF55: 1994 | AG55: 296 | AH55: =IFERROR(SUM(I55:J55)/AG55,"") -> 71074.454 | AI55: =IFERROR(AF55/AG55,"") -> 6.7364865 | AJ55: =BV55 -> 45935 | AK55: =AJ55*BD55 -> 551220 | AL55: 259890 | AM55: =IFERROR(SUM(AK55:AL55)/SUM(I55:J55),"") -> 0.03855445 | AN55: =IFERROR(I55/T55,"") -> 96008.008 | AO55: =IFERROR(SUM(I55:J55)/SUM(G55:H55),"") -> 1.0519017 | AP55: 0 | AQ55: 1159 | AR55: 2066 | AS55: 2387.63 | AT55: 57 | AU55: 10 | AV55: 217 | AW55: 32 | AX55: 30 | AY55: =IFERROR(VLOOKUP(C55,#REF!,13,0),"") | BA55: =IF(ISBLANK(AZ55),"Active","LEFT" ) -> Active | BB55: =_xludf.ifs(F55<$BB$1,"Old",F55>$BB$1,"New") -> #NAME? | BC55: =_xludf.ifs(AO55<50%,"Below 50%",AO55<70%,"50%-70%",AO55<90%,"70%-90%",AO55<100%,"90%-100%",AO55>100%,"Above 100%") -> #NAME? | BD55: =MATCH($BD$2,{"Apr","May","Jun","Jul","Aug","Sep","Oct","Nov","Dec","Jan","Feb","Mar"},0) -> 12 | BF55: =M55-AT55 -> 8 | BG55: Secondary | BH55: =IFERROR(__xludf.DUMMYFUNCTION("""COMPUTED_VALUE"""),13718152) -> 13718152 | BI55: =IFERROR(__xludf.DUMMYFUNCTION("""COMPUTED_VALUE"""),13038969.14) -> 13038969 | BL55: =BK55*BD55 -> 0 | BM55: =H55+BL55 -> 20000004 | BO55: =IFERROR(__xludf.DUMMYFUNCTION("IFERROR(ArrayFormula(SUM(VLOOKUP($C55,importrange(""1MwNMVzWE3QBVOyJjKr3eFX-Sq1Ng0Q1sghWJbgbE_8g"",""ORDER BOOKING REPORT 2024-25!C:CV""),{16,23,30},0))))"),2846643.75) -> 2846643.8 | BP55: =IFERROR(__xludf.DUMMYFUNCTION("IFERROR(ArrayFormula(SUM(VLOOKUP($C55,importrange(""1MwNMVzWE3QBVOyJjKr3eFX-Sq1Ng0Q1sghWJbgbE_8g"",""ORDER BOOKING REPORT 2024-25!C:CV""),{37,44,51},0))))"),3167477.67) -> 3167477.7 | BQ55: =IFERROR(__xludf.DUMMYFUNCTION("IFERROR(ArrayFormula(SUM(VLOOKUP($C55,importrange(""1MwNMVzWE3QBVOyJjKr3eFX-Sq1Ng0Q1sghWJbgbE_8g"",""ORDER BOOKING REPORT 2024-25!C:CV""),{58,65,72},0))))"),2622988.55) -> 2622988.5 | BR55: =IFERROR(__xludf.DUMMYFUNCTION("IFERROR(ArrayFormula(SUM(VLOOKUP($C55,importrange(""1MwNMVzWE3QBVOyJjKr3eFX-Sq1Ng0Q1sghWJbgbE_8g"",""ORDER BOOKING REPORT 2024-25!C:CV""),{79,86,93},0))))"),4401859.17) -> 4401859.2 | BS55: =IFERROR(AY55/BM55,"") | BT55: =IFERROR(SUM(AK55:AL55)/AY55,"") | BU55: =BL55-G55 -> 0 | BV55: 45935 | BW55: Area Sales Manager | BX55: 832 | BY55: =BV55-AJ55 -> 0 | CG55: =IF(N55<60,"Below 60"," ") | CH55: =IF(T55 = 0, "Not 50%", IF(T55 >= 0.5 * N55, "Business Achieved 50%", "Not 50%")) -> Business Achieved 50% | CI55: =IFERROR((T55/N55),) -> 0.77777778 | CJ55: =IFERROR(__xludf.DUMMYFUNCTION("""COMPUTED_VALUE"""),1647) -> 1647 | CK55: =IFERROR(__xludf.DUMMYFUNCTION("""COMPUTED_VALUE"""),68) -> 68 | CL55: =IFERROR(__xludf.DUMMYFUNCTION("""COMPUTED_VALUE"""),0) -> 0 | CM55: =AE55-SUM(CJ55:CL55) -> 0
A56: Sunil Patel | B56: Gujarat | C56: Jagdish Palani | D56: GUJARAT | E56: Palanpur | F56: 44928 | G56: 0 | H56: 5833331 | I56: 1788891.2 | J56: 0 | K56: 65 | L56: 80 | M56: 24 | N56: 89 | O56: 9 | P56: 1327703.3 | Q56: 461187.95 | R56: 43 | S56: 20 | T56: 63 | U56: 0 | V56: 92 | W56: 199 | X56: 134 | Y56: 3 | Z56: 64 | AA56: 0 | AB56: 0 | AC56: 1 | AD56: 1 | AE56: 458 | AF56: 722 | AG56: 174 | AH56: =IFERROR(SUM(I56:J56)/AG56,"") -> 10280.984 | AI56: =IFERROR(AF56/AG56,"") -> 4.1494253 | AJ56: 49500 | AK56: =AJ56*BD56 -> 351450 | AL56: 69684 | AM56: =IFERROR(SUM(AK56:AL56)/SUM(I56:J56),"") -> 0.23541621 | AN56: =IFERROR(I56/T56,"") -> 28395.099 | AO56: =IFERROR(SUM(I56:J56)/SUM(G56:H56),"") -> 0.30666719 | AP56: 0 | AQ56: 121 | AR56: 1629 | AS56: 0 | AT56: 20 | AU56: 0 | AV56: 63 | AW56: 19 | AX56: 7 | AY56: =IFERROR(VLOOKUP(C56,#REF!,13,0),"") | AZ56: 45971 | BA56: =IF(ISBLANK(AZ56),"Active","LEFT" ) -> LEFT | BB56: =_xludf.ifs(F56<$BB$1,"Old",F56>$BB$1,"New") -> #NAME? | BC56: =_xludf.ifs(AO56<50%,"Below 50%",AO56<70%,"50%-70%",AO56<90%,"70%-90%",AO56<100%,"90%-100%",AO56>100%,"Above 100%") -> #NAME? | BD56: 7.1 | BF56: =M56-AT56 -> 4 | BG56: Secondary | BH56: =IFERROR(__xludf.DUMMYFUNCTION("""COMPUTED_VALUE"""),3181012) -> 3181012 | BI56: =IFERROR(__xludf.DUMMYFUNCTION("""COMPUTED_VALUE"""),3306516.15) -> 3306516.1 | BL56: =BK56*BD56 -> 0 | BM56: =H56+BL56 -> 5833331 | BO56: =IFERROR(__xludf.DUMMYFUNCTION("IFERROR(ArrayFormula(SUM(VLOOKUP($C56,importrange(""1MwNMVzWE3QBVOyJjKr3eFX-Sq1Ng0Q1sghWJbgbE_8g"",""ORDER BOOKING REPORT 2024-25!C:CV""),{16,23,30},0))))"),652304.5) -> 652304.5 | BP56: =IFERROR(__xludf.DUMMYFUNCTION("IFERROR(ArrayFormula(SUM(VLOOKUP($C56,importrange(""1MwNMVzWE3QBVOyJjKr3eFX-Sq1Ng0Q1sghWJbgbE_8g"",""ORDER BOOKING REPORT 2024-25!C:CV""),{37,44,51},0))))"),395992.9) -> 395992.9 | BQ56: =IFERROR(__xludf.DUMMYFUNCTION("IFERROR(ArrayFormula(SUM(VLOOKUP($C56,importrange(""1MwNMVzWE3QBVOyJjKr3eFX-Sq1Ng0Q1sghWJbgbE_8g"",""ORDER BOOKING REPORT 2024-25!C:CV""),{58,65,72},0))))"),1407421.98) -> 1407422 | BR56: =IFERROR(__xludf.DUMMYFUNCTION("IFERROR(ArrayFormula(SUM(VLOOKUP($C56,importrange(""1MwNMVzWE3QBVOyJjKr3eFX-Sq1Ng0Q1sghWJbgbE_8g"",""ORDER BOOKING REPORT 2024-25!C:CV""),{79,86,93},0))))"),850796.77) -> 850796.77 | BS56: =IFERROR(AY56/BM56,"") | BT56: =IFERROR(SUM(AK56:AL56)/AY56,"") | BU56: =BL56-G56 -> 0 | BV56: 49500 | BW56: Area Sales Manager | BX56: 839 | BY56: =BV56-AJ56 -> 0 | CG56: =IF(N56<60,"Below 60"," ") | CH56: =IF(T56 = 0, "Not 50%", IF(T56 >= 0.5 * N56, "Business Achieved 50%", "Not 50%")) -> Business Achieved 50% | CI56: =IFERROR((T56/N56),) -> 0.70786517 | CJ56: =IFERROR(__xludf.DUMMYFUNCTION("""COMPUTED_VALUE"""),366) -> 366 | CK56: =IFERROR(__xludf.DUMMYFUNCTION("""COMPUTED_VALUE"""),92) -> 92 | CL56: =IFERROR(__xludf.DUMMYFUNCTION("""COMPUTED_VALUE"""),0) -> 0 | CM56: =AE56-SUM(CJ56:CL56) -> 0
A57: Sandeep Dadheech | B57: Andhra Pradesh | C57: J.Kamal Kishore | D57: ANDHRA PRADESH | E57: Tirupati | F57: 44953 | G57: 0 | H57: 16800000 | I57: 7713644.7 | J57: 0 | K57: 133 | L57: 132 | M57: 10 | N57: 143 | O57: 11 | P57: 6891808.3 | Q57: 821836.38 | R57: 110 | S57: 10 | T57: 120 | U57: 0 | V57: 4 | W57: 9 | X57: 41 | Y57: 1 | Z57: 3 | AA57: 0 | AB57: 0 | AC57: 0 | AD57: 0 | AE57: 2065 | AF57: 2077 | AG57: 284 | AH57: =IFERROR(SUM(I57:J57)/AG57,"") -> 27160.721 | AI57: =IFERROR(AF57/AG57,"") -> 7.3133803 | AJ57: =BV57 -> 34920 | AK57: =AJ57*BD57 -> 419040 | AL57: 163530 | AM57: =IFERROR(SUM(AK57:AL57)/SUM(I57:J57),"") -> 0.075524609 | AN57: =IFERROR(I57/T57,"") -> 64280.372 | AO57: =IFERROR(SUM(I57:J57)/SUM(G57:H57),"") -> 0.45914552 | AP57: 0 | AQ57: 672 | AR57: 3066 | AS57: 2280.11 | AT57: 10 | AU57: 17 | AV57: 120 | AW57: 12 | AX57: 11 | AY57: =IFERROR(VLOOKUP(C57,#REF!,13,0),"") | BA57: =IF(ISBLANK(AZ57),"Active","LEFT" ) -> Active | BB57: =_xludf.ifs(F57<$BB$1,"Old",F57>$BB$1,"New") -> #NAME? | BC57: =_xludf.ifs(AO57<50%,"Below 50%",AO57<70%,"50%-70%",AO57<90%,"70%-90%",AO57<100%,"90%-100%",AO57>100%,"Above 100%") -> #NAME? | BD57: =MATCH($BD$2,{"Apr","May","Jun","Jul","Aug","Sep","Oct","Nov","Dec","Jan","Feb","Mar"},0) -> 12 | BF57: =M57-AT57 -> 0 | BG57: Secondary | BH57: =IFERROR(__xludf.DUMMYFUNCTION("""COMPUTED_VALUE"""),11302117) -> 11302117 | BI57: =IFERROR(__xludf.DUMMYFUNCTION("""COMPUTED_VALUE"""),9604709.78899999) -> 9604709.8 | BL57: =BK57*BD57 -> 0 | BM57: =H57+BL57 -> 16800000 | BO57: =IFERROR(__xludf.DUMMYFUNCTION("IFERROR(ArrayFormula(SUM(VLOOKUP($C57,importrange(""1MwNMVzWE3QBVOyJjKr3eFX-Sq1Ng0Q1sghWJbgbE_8g"",""ORDER BOOKING REPORT 2024-25!C:CV""),{16,23,30},0))))"),2715875.46999999) -> 2715875.5 | BP57: =IFERROR(__xludf.DUMMYFUNCTION("IFERROR(ArrayFormula(SUM(VLOOKUP($C57,importrange(""1MwNMVzWE3QBVOyJjKr3eFX-Sq1Ng0Q1sghWJbgbE_8g"",""ORDER BOOKING REPORT 2024-25!C:CV""),{37,44,51},0))))"),2208224.897) -> 2208224.9 | BQ57: =IFERROR(__xludf.DUMMYFUNCTION("IFERROR(ArrayFormula(SUM(VLOOKUP($C57,importrange(""1MwNMVzWE3QBVOyJjKr3eFX-Sq1Ng0Q1sghWJbgbE_8g"",""ORDER BOOKING REPORT 2024-25!C:CV""),{58,65,72},0))))"),2091501.572) -> 2091501.6 | BR57: =IFERROR(__xludf.DUMMYFUNCTION("IFERROR(ArrayFormula(SUM(VLOOKUP($C57,importrange(""1MwNMVzWE3QBVOyJjKr3eFX-Sq1Ng0Q1sghWJbgbE_8g"",""ORDER BOOKING REPORT 2024-25!C:CV""),{79,86,93},0))))"),2589107.85) -> 2589107.9 | BS57: =IFERROR(AY57/BM57,"") | BT57: =IFERROR(SUM(AK57:AL57)/AY57,"") | BU57: =BL57-G57 -> 0 | BV57: 34920 | BW57: Sr. Executive - Sales & Mktg. | BX57: 849 | BY57: =BV57-AJ57 -> 0 | CG57: =IF(N57<60,"Below 60"," ") | CH57: =IF(T57 = 0, "Not 50%", IF(T57 >= 0.5 * N57, "Business Achieved 50%", "Not 50%")) -> Business Achieved 50% | CI57: =IFERROR((T57/N57),) -> 0.83916084 | CJ57: =IFERROR(__xludf.DUMMYFUNCTION("""COMPUTED_VALUE"""),1952) -> 1952 | CK57: =IFERROR(__xludf.DUMMYFUNCTION("""COMPUTED_VALUE"""),113) -> 113 | CL57: =IFERROR(__xludf.DUMMYFUNCTION("""COMPUTED_VALUE"""),0) -> 0 | CM57: =AE57-SUM(CJ57:CL57) -> 0
A58: Sandeep Dadheech | B58: West Bengal | C58: Subhajit Koley | D58: WEST BENGAL | E58: Mecheda | F58: 44958 | G58: 0 | H58: 48000000 | I58: 46129853 | J58: 0 | K58: 66 | L58: 71 | M58: 6 | N58: 72 | O58: 1 | P58: 45135384 | Q58: 994469.9 | R58: 63 | S58: 5 | T58: 68 | U58: 0 | V58: 1 | W58: 2 | X58: 60 | Y58: 2 | Z58: 32 | AA58: 0 | AB58: 0 | AC58: 0 | AD58: 0 | AE58: 1325 | AF58: 1359 | AG58: 294 | AH58: =IFERROR(SUM(I58:J58)/AG58,"") -> 156904.26 | AI58: =IFERROR(AF58/AG58,"") -> 4.622449 | AJ58: 24116 | AK58: =AJ58*BD58 -> 289392 | AL58: 122777 | AM58: =IFERROR(SUM(AK58:AL58)/SUM(I58:J58),"") -> 0.0089349731 | AN58: =IFERROR(I58/T58,"") -> 678380.2 | AO58: =IFERROR(SUM(I58:J58)/SUM(G58:H58),"") -> 0.96103861 | AP58: 0 | AQ58: 423 | AR58: 3304 | AS58: 2040.04 | AT58: 5 | AU58: 29 | AV58: 68 | AW58: 3 | AX58: 1 | AY58: =IFERROR(VLOOKUP(C58,#REF!,13,0),"") | BA58: =IF(ISBLANK(AZ58),"Active","LEFT" ) -> Active | BB58: =_xludf.ifs(F58<$BB$1,"Old",F58>$BB$1,"New") -> #NAME? | BC58: =_xludf.ifs(AO58<50%,"Below 50%",AO58<70%,"50%-70%",AO58<90%,"70%-90%",AO58<100%,"90%-100%",AO58>100%,"Above 100%") -> #NAME? | BD58: =MATCH($BD$2,{"Apr","May","Jun","Jul","Aug","Sep","Oct","Nov","Dec","Jan","Feb","Mar"},0) -> 12 | BF58: =M58-AT58 -> 1 | BG58: Secondary | BH58: =IFERROR(__xludf.DUMMYFUNCTION("""COMPUTED_VALUE"""),19406539.4) -> 19406539 | BI58: =IFERROR(__xludf.DUMMYFUNCTION("""COMPUTED_VALUE"""),19618329.56) -> 19618330 | BL58: =BK58*BD58 -> 0 | BM58: =H58+BL58 -> 48000000 | BO58: =IFERROR(__xludf.DUMMYFUNCTION("IFERROR(ArrayFormula(SUM(VLOOKUP($C58,importrange(""1MwNMVzWE3QBVOyJjKr3eFX-Sq1Ng0Q1sghWJbgbE_8g"",""ORDER BOOKING REPORT 2024-25!C:CV""),{16,23,30},0))))"),2335924.2) -> 2335924.2 | BP58: =IFERROR(__xludf.DUMMYFUNCTION("IFERROR(ArrayFormula(SUM(VLOOKUP($C58,importrange(""1MwNMVzWE3QBVOyJjKr3eFX-Sq1Ng0Q1sghWJbgbE_8g"",""ORDER BOOKING REPORT 2024-25!C:CV""),{37,44,51},0))))"),4923505.1) -> 4923505.1 | BQ58: =IFERROR(__xludf.DUMMYFUNCTION("IFERROR(ArrayFormula(SUM(VLOOKUP($C58,importrange(""1MwNMVzWE3QBVOyJjKr3eFX-Sq1Ng0Q1sghWJbgbE_8g"",""ORDER BOOKING REPORT 2024-25!C:CV""),{58,65,72},0))))"),5593617.82) -> 5593617.8 | BR58: =IFERROR(__xludf.DUMMYFUNCTION("IFERROR(ArrayFormula(SUM(VLOOKUP($C58,importrange(""1MwNMVzWE3QBVOyJjKr3eFX-Sq1Ng0Q1sghWJbgbE_8g"",""ORDER BOOKING REPORT 2024-25!C:CV""),{79,86,93},0))))"),6765282.44) -> 6765282.4 | BS58: =IFERROR(AY58/BM58,"") | BT58: =IFERROR(SUM(AK58:AL58)/AY58,"") | BU58: =BL58-G58 -> 0 | BV58: 24116 | BW58: Executive - Sales & Mkt. | BX58: 853 | BY58: =BV58-AJ58 -> 0 | CG58: =IF(N58<60,"Below 60"," ") | CH58: =IF(T58 = 0, "Not 50%", IF(T58 >= 0.5 * N58, "Business Achieved 50%", "Not 50%")) -> Business Achieved 50% | CI58: =IFERROR((T58/N58),) -> 0.94444444 | CJ58: =IFERROR(__xludf.DUMMYFUNCTION("""COMPUTED_VALUE"""),1278) -> 1278 | CK58: =IFERROR(__xludf.DUMMYFUNCTION("""COMPUTED_VALUE"""),47) -> 47 | CL58: =IFERROR(__xludf.DUMMYFUNCTION("""COMPUTED_VALUE"""),0) -> 0 | CM58: =AE58-SUM(CJ58:CL58) -> 0
A59: Anant Singh | B59: Delhi | C59: Prasun Chatterjee | D59: DELHI | E59: Delhi | F59: 44994 | G59: 2400000 | H59: 18000000 | I59: 8148003 | J59: 1522428.7 | K59: 85 | L59: 74 | M59: 3 | N59: 88 | O59: 14 | P59: 7726671.1 | Q59: 421331.85 | R59: 46 | S59: 3 | T59: 49 | U59: 4 | V59: 27 | W59: 53 | X59: 113 | Y59: 3 | Z59: 111 | AA59: 7 | AB59: 211 | AC59: 3 | AD59: 80 | AE59: 1228 | AF59: 1683 | AG59: 280 | AH59: =IFERROR(SUM(I59:J59)/AG59,"") -> 34537.256 | AI59: =IFERROR(AF59/AG59,"") -> 6.0107143 | AJ59: =BV59 -> 46390 | AK59: =AJ59*BD59 -> 556680 | AL59: 91472 | AM59: =IFERROR(SUM(AK59:AL59)/SUM(I59:J59),"") -> 0.067024102 | AN59: =IFERROR(I59/T59,"") -> 166285.77 | AO59: =IFERROR(SUM(I59:J59)/SUM(G59:H59),"") -> 0.47404077 | AP59: 0.63 | AQ59: 273 | AR59: 2918 | AS59: 1645.64 | AT59: 3 | AU59: 22 | AV59: 49 | AW59: 25 | AX59: 14 | AY59: =IFERROR(VLOOKUP(C59,#REF!,13,0),"") | BA59: =IF(ISBLANK(AZ59),"Active","LEFT" ) -> Active | BB59: =_xludf.ifs(F59<$BB$1,"Old",F59>$BB$1,"New") -> #NAME? | BC59: =_xludf.ifs(AO59<50%,"Below 50%",AO59<70%,"50%-70%",AO59<90%,"70%-90%",AO59<100%,"90%-100%",AO59>100%,"Above 100%") -> #NAME? | BD59: =MATCH($BD$2,{"Apr","May","Jun","Jul","Aug","Sep","Oct","Nov","Dec","Jan","Feb","Mar"},0) -> 12 | BF59: =M59-AT59 -> 0 | BG59: Secondary | BH59: =IFERROR(__xludf.DUMMYFUNCTION("""COMPUTED_VALUE"""),11621619) -> 11621619 | BI59: =IFERROR(__xludf.DUMMYFUNCTION("""COMPUTED_VALUE"""),11345861) -> 11345861 | BK59: 200000 | BL59: =BK59*BD59 -> 2400000 | BM59: =H59+BL59 -> 20400000 | BO59: =IFERROR(__xludf.DUMMYFUNCTION("IFERROR(ArrayFormula(SUM(VLOOKUP($C59,importrange(""1MwNMVzWE3QBVOyJjKr3eFX-Sq1Ng0Q1sghWJbgbE_8g"",""ORDER BOOKING REPORT 2024-25!C:CV""),{16,23,30},0))))"),2283050.9) -> 2283050.9 | BP59: =IFERROR(__xludf.DUMMYFUNCTION("IFERROR(ArrayFormula(SUM(VLOOKUP($C59,importrange(""1MwNMVzWE3QBVOyJjKr3eFX-Sq1Ng0Q1sghWJbgbE_8g"",""ORDER BOOKING REPORT 2024-25!C:CV""),{37,44,51},0))))"),1719727.1) -> 1719727.1 | BQ59: =IFERROR(__xludf.DUMMYFUNCTION("IFERROR(ArrayFormula(SUM(VLOOKUP($C59,importrange(""1MwNMVzWE3QBVOyJjKr3eFX-Sq1Ng0Q1sghWJbgbE_8g"",""ORDER BOOKING REPORT 2024-25!C:CV""),{58,65,72},0))))"),2356826.5) -> 2356826.5 | BR59: =IFERROR(__xludf.DUMMYFUNCTION("IFERROR(ArrayFormula(SUM(VLOOKUP($C59,importrange(""1MwNMVzWE3QBVOyJjKr3eFX-Sq1Ng0Q1sghWJbgbE_8g"",""ORDER BOOKING REPORT 2024-25!C:CV""),{79,86,93},0))))"),4986256.5) -> 4986256.5 | BS59: =IFERROR(AY59/BM59,"") | BT59: =IFERROR(SUM(AK59:AL59)/AY59,"") | BU59: =BL59-G59 -> 0 | BV59: 46390 | BW59: Area Sales Manager | BX59: 861 | BY59: =BV59-AJ59 -> 0 | CG59: =IF(N59<60,"Below 60"," ") | CH59: =IF(T59 = 0, "Not 50%", IF(T59 >= 0.5 * N59, "Business Achieved 50%", "Not 50%")) -> Business Achieved 50% | CI59: =IFERROR((T59/N59),) -> 0.55681818 | CJ59: =IFERROR(__xludf.DUMMYFUNCTION("""COMPUTED_VALUE"""),1046) -> 1046 | CK59: =IFERROR(__xludf.DUMMYFUNCTION("""COMPUTED_VALUE"""),182) -> 182 | CL59: =IFERROR(__xludf.DUMMYFUNCTION("""COMPUTED_VALUE"""),0) -> 0 | CM59: =AE59-SUM(CJ59:CL59) -> 0
A60: Syed Aqil Rizvi | B60: East U.P | C60: Santosh Kumar dixit | D60: East U.P | E60: Farrukhabad | F60: 45000 | G60: 0 | H60: 10416665 | I60: 1970484.1 | J60: 0 | K60: 30 | L60: 29 | M60: 4 | N60: 34 | O60: 5 | P60: 1733087.2 | Q60: 237396.94 | R60: 17 | S60: 4 | T60: 21 | U60: 0 | V60: 8 | W60: 9 | X60: 100 | Y60: 1 | Z60: 23 | AA60: 0 | AB60: 0 | AC60: 0 | AD60: 0 | AE60: 418 | AF60: 450 | AG60: 111 | AH60: =IFERROR(SUM(I60:J60)/AG60,"") -> 17752.109 | AI60: =IFERROR(AF60/AG60,"") -> 4.0540541 | AJ60: =BV60 -> 28360 | AK60: =AJ60*BD60 -> 141800 | AL60: 73560 | AM60: =IFERROR(SUM(AK60:AL60)/SUM(I60:J60),"") -> 0.10929294 | AN60: =IFERROR(I60/T60,"") -> 93832.577 | AO60: =IFERROR(SUM(I60:J60)/SUM(G60:H60),"") -> 0.18916651 | AP60: 0 | AQ60: 40 | AR60: 773 | AS60: 0 | AT60: 4 | AU60: 0 | AV60: 21 | AW60: 8 | AX60: 5 | AY60: =IFERROR(VLOOKUP(C60,#REF!,13,0),"") | AZ60: 45900 | BA60: =IF(ISBLANK(AZ60),"Active","LEFT" ) -> LEFT | BB60: =_xludf.ifs(F60<$BB$1,"Old",F60>$BB$1,"New") -> #NAME? | BC60: =_xludf.ifs(AO60<50%,"Below 50%",AO60<70%,"50%-70%",AO60<90%,"70%-90%",AO60<100%,"90%-100%",AO60>100%,"Above 100%") -> #NAME? | BD60: 5 | BF60: =M60-AT60 -> 0 | BG60: Secondary | BH60: =IFERROR(__xludf.DUMMYFUNCTION("""COMPUTED_VALUE"""),8973760) -> 8973760 | BI60: =IFERROR(__xludf.DUMMYFUNCTION("""COMPUTED_VALUE"""),8754061.92) -> 8754061.9 | BL60: =BK60*BD60 -> 0 | BM60: =H60+BL60 -> 10416665 | BO60: =IFERROR(__xludf.DUMMYFUNCTION("IFERROR(ArrayFormula(SUM(VLOOKUP($C60,importrange(""1MwNMVzWE3QBVOyJjKr3eFX-Sq1Ng0Q1sghWJbgbE_8g"",""ORDER BOOKING REPORT 2024-25!C:CV""),{16,23,30},0))))"),1706342.36) -> 1706342.4 | BP60: =IFERROR(__xludf.DUMMYFUNCTION("IFERROR(ArrayFormula(SUM(VLOOKUP($C60,importrange(""1MwNMVzWE3QBVOyJjKr3eFX-Sq1Ng0Q1sghWJbgbE_8g"",""ORDER BOOKING REPORT 2024-25!C:CV""),{37,44,51},0))))"),1948076.32) -> 1948076.3 | BQ60: =IFERROR(__xludf.DUMMYFUNCTION("IFERROR(ArrayFormula(SUM(VLOOKUP($C60,importrange(""1MwNMVzWE3QBVOyJjKr3eFX-Sq1Ng0Q1sghWJbgbE_8g"",""ORDER BOOKING REPORT 2024-25!C:CV""),{58,65,72},0))))"),2312552.24) -> 2312552.2 | BR60: =IFERROR(__xludf.DUMMYFUNCTION("IFERROR(ArrayFormula(SUM(VLOOKUP($C60,importrange(""1MwNMVzWE3QBVOyJjKr3eFX-Sq1Ng0Q1sghWJbgbE_8g"",""ORDER BOOKING REPORT 2024-25!C:CV""),{79,86,93},0))))"),2787091) -> 2787091 | BS60: =IFERROR(AY60/BM60,"") | BT60: =IFERROR(SUM(AK60:AL60)/AY60,"") | BU60: =BL60-G60 -> 0 | BV60: 28360 | BW60: Executive - Sales & Mkt. | BX60: 870 | BY60: =BV60-AJ60 -> 0 | CA60: =BE60*BD60 -> #VALUE! | CC60: =CA60-H60 -> #VALUE! | CG60: =IF(N60<60,"Below 60"," ") -> Below 60 | CH60: =IF(T60 = 0, "Not 50%", IF(T60 >= 0.5 * N60, "Business Achieved 50%", "Not 50%")) -> Business Achieved 50% | CI60: =IFERROR((T60/N60),) -> 0.61764706 | CJ60: =IFERROR(__xludf.DUMMYFUNCTION("""COMPUTED_VALUE"""),337) -> 337 | CK60: =IFERROR(__xludf.DUMMYFUNCTION("""COMPUTED_VALUE"""),81) -> 81 | CL60: =IFERROR(__xludf.DUMMYFUNCTION("""COMPUTED_VALUE"""),0) -> 0 | CM60: =AE60-SUM(CJ60:CL60) -> 0
A61: Sandeep Dadheech | B61: Jharkhand | C61: Vikash Kumar Singh | D61: JHARKHAND | E61: Palamu | F61: 45040 | G61: 0 | H61: 18000000 | I61: 13289263 | J61: 0 | K61: 27 | L61: 41 | M61: 14 | N61: 41 | O61: 0 | P61: 9077784.4 | Q61: 4211478.7 | R61: 17 | S61: 14 | T61: 31 | U61: 0 | V61: 60 | W61: 145 | X61: 61 | Y61: 1 | Z61: 12 | AA61: 0 | AB61: 0 | AC61: 0 | AD61: 0 | AE61: 1505 | AF61: 1662 | AG61: 294 | AH61: =IFERROR(SUM(I61:J61)/AG61,"") -> 45201.575 | AI61: =IFERROR(AF61/AG61,"") -> 5.6530612 | AJ61: 36400 | AK61: =AJ61*BD61 -> 436800 | AL61: 218741 | AM61: =IFERROR(SUM(AK61:AL61)/SUM(I61:J61),"") -> 0.049328619 | AN61: =IFERROR(I61/T61,"") -> 428685.91 | AO61: =IFERROR(SUM(I61:J61)/SUM(G61:H61),"") -> 0.7382924 | AP61: 0 | AQ61: 137 | AR61: 2400 | AS61: 2159.76 | AT61: 14 | AU61: 53 | AV61: 31 | AW61: 10 | AX61: 0 | AY61: =IFERROR(VLOOKUP(C61,#REF!,13,0),"") | BA61: =IF(ISBLANK(AZ61),"Active","LEFT" ) -> Active | BB61: =_xludf.ifs(F61<$BB$1,"Old",F61>$BB$1,"New") -> #NAME? | BC61: =_xludf.ifs(AO61<50%,"Below 50%",AO61<70%,"50%-70%",AO61<90%,"70%-90%",AO61<100%,"90%-100%",AO61>100%,"Above 100%") -> #NAME? | BD61: {=MATCH($BD$2,{"Apr","May","Jun","Jul","Aug","Sep","Oct","Nov","Dec","Jan","Feb","Mar"},0)} -> 12 | BF61: =M61-AT61 -> 0 | BG61: Secondary | BH61: =IFERROR(__xludf.DUMMYFUNCTION("""COMPUTED_VALUE"""),9731676) -> 9731676 | BI61: =IFERROR(__xludf.DUMMYFUNCTION("""COMPUTED_VALUE"""),12183395.24) -> 12183395 | BL61: =BK61*BD61 -> 0 | BM61: =H61+BL61 -> 18000000 | BO61: =IFERROR(__xludf.DUMMYFUNCTION("IFERROR(ArrayFormula(SUM(VLOOKUP($C61,importrange(""1MwNMVzWE3QBVOyJjKr3eFX-Sq1Ng0Q1sghWJbgbE_8g"",""ORDER BOOKING REPORT 2024-25!C:CV""),{16,23,30},0))))"),2317912.54) -> 2317912.5 | BP61: =IFERROR(__xludf.DUMMYFUNCTION("IFERROR(ArrayFormula(SUM(VLOOKUP($C61,importrange(""1MwNMVzWE3QBVOyJjKr3eFX-Sq1Ng0Q1sghWJbgbE_8g"",""ORDER BOOKING REPORT 2024-25!C:CV""),{37,44,51},0))))"),3111418.82) -> 3111418.8 | BQ61: =IFERROR(__xludf.DUMMYFUNCTION("IFERROR(ArrayFormula(SUM(VLOOKUP($C61,importrange(""1MwNMVzWE3QBVOyJjKr3eFX-Sq1Ng0Q1sghWJbgbE_8g"",""ORDER BOOKING REPORT 2024-25!C:CV""),{58,65,72},0))))"),3463379.28) -> 3463379.3 | BR61: =IFERROR(__xludf.DUMMYFUNCTION("IFERROR(ArrayFormula(SUM(VLOOKUP($C61,importrange(""1MwNMVzWE3QBVOyJjKr3eFX-Sq1Ng0Q1sghWJbgbE_8g"",""ORDER BOOKING REPORT 2024-25!C:CV""),{79,86,93},0))))"),3290684.59999999) -> 3290684.6 | BS61: =IFERROR(AY61/BM61,"") | BT61: =IFERROR(SUM(AK61:AL61)/AY61,"") | BU61: =BL61-G61 -> 0 | BV61: 36400 | BW61: Executive - Sales & Mkt. | BX61: 886 | BY61: =BV61-AJ61 -> 0 | CG61: =IF(N61<60,"Below 60"," ") -> Below 60 | CH61: =IF(T61 = 0, "Not 50%", IF(T61 >= 0.5 * N61, "Business Achieved 50%", "Not 50%")) -> Business Achieved 50% | CI61: =IFERROR((T61/N61),) -> 0.75609756 | CJ61: =IFERROR(__xludf.DUMMYFUNCTION("""COMPUTED_VALUE"""),1410) -> 1410 | CK61: =IFERROR(__xludf.DUMMYFUNCTION("""COMPUTED_VALUE"""),95) -> 95 | CL61: =IFERROR(__xludf.DUMMYFUNCTION("""COMPUTED_VALUE"""),0) -> 0 | CM61: =AE61-SUM(CJ61:CL61) -> 0
A62: Sandeep Dadheech | B62: West Bengal | C62: Akash Santra | D62: WEST BENGAL | E62: Andal | F62: 45040 | G62: 0 | H62: 10500000 | I62: 4573013.8 | J62: 0 | K62: 75 | L62: 65 | M62: 1 | N62: 76 | O62: 11 | P62: 4571337.3 | Q62: 1676.4 | R62: 28 | S62: 1 | T62: 29 | U62: 0 | V62: 6 | W62: 17 | X62: 45 | Y62: 2 | Z62: 2 | AA62: 0 | AB62: 0 | AC62: 0 | AD62: 0 | AE62: 770 | AF62: 789 | AG62: 162 | AH62: =IFERROR(SUM(I62:J62)/AG62,"") -> 28228.48 | AI62: =IFERROR(AF62/AG62,"") -> 4.8703704 | AJ62: 25690 | AK62: =AJ62*BD62 -> 179830 | AL62: 58731 | AM62: =IFERROR(SUM(AK62:AL62)/SUM(I62:J62),"") -> 0.052167129 | AN62: =IFERROR(I62/T62,"") -> 157690.13 | AO62: =IFERROR(SUM(I62:J62)/SUM(G62:H62),"") -> 0.43552512 | AP62: 0 | AQ62: 83 | AR62: 1345 | AS62: 0 | AT62: 1 | AU62: 0 | AV62: 29 | AW62: 36 | AX62: 11 | AY62: =IFERROR(VLOOKUP(C62,#REF!,13,0),"") | AZ62: 45961 | BA62: =IF(ISBLANK(AZ62),"Active","LEFT" ) -> LEFT | BB62: =_xludf.ifs(F62<$BB$1,"Old",F62>$BB$1,"New") -> #NAME? | BC62: =_xludf.ifs(AO62<50%,"Below 50%",AO62<70%,"50%-70%",AO62<90%,"70%-90%",AO62<100%,"90%-100%",AO62>100%,"Above 100%") -> #NAME? | BD62: 7 | BF62: =M62-AT62 -> 0 | BG62: Secondary | BH62: =IFERROR(__xludf.DUMMYFUNCTION("""COMPUTED_VALUE"""),2909376) -> 2909376 | BI62: =IFERROR(__xludf.DUMMYFUNCTION("""COMPUTED_VALUE"""),7745483.4) -> 7745483.4 | BL62: =BK62*BD62 -> 0 | BM62: =H62+BL62 -> 10500000 | BO62: =IFERROR(__xludf.DUMMYFUNCTION("IFERROR(ArrayFormula(SUM(VLOOKUP($C62,importrange(""1MwNMVzWE3QBVOyJjKr3eFX-Sq1Ng0Q1sghWJbgbE_8g"",""ORDER BOOKING REPORT 2024-25!C:CV""),{16,23,30},0))))"),932918.5) -> 932918.5 | BP62: =IFERROR(__xludf.DUMMYFUNCTION("IFERROR(ArrayFormula(SUM(VLOOKUP($C62,importrange(""1MwNMVzWE3QBVOyJjKr3eFX-Sq1Ng0Q1sghWJbgbE_8g"",""ORDER BOOKING REPORT 2024-25!C:CV""),{37,44,51},0))))"),1319700.9) -> 1319700.9 | BQ62: =IFERROR(__xludf.DUMMYFUNCTION("IFERROR(ArrayFormula(SUM(VLOOKUP($C62,importrange(""1MwNMVzWE3QBVOyJjKr3eFX-Sq1Ng0Q1sghWJbgbE_8g"",""ORDER BOOKING REPORT 2024-25!C:CV""),{58,65,72},0))))"),2373025.7) -> 2373025.7 | BR62: =IFERROR(__xludf.DUMMYFUNCTION("IFERROR(ArrayFormula(SUM(VLOOKUP($C62,importrange(""1MwNMVzWE3QBVOyJjKr3eFX-Sq1Ng0Q1sghWJbgbE_8g"",""ORDER BOOKING REPORT 2024-25!C:CV""),{79,86,93},0))))"),3119838.3) -> 3119838.3 | BS62: =IFERROR(AY62/BM62,"") | BT62: =IFERROR(SUM(AK62:AL62)/AY62,"") | BU62: =BL62-G62 -> 0 | BV62: 25690 | BW62: Executive - Sales & Mkt. | BX62: 884 | BY62: =BV62-AJ62 -> 0 | CG62: =IF(N62<60,"Below 60"," ") | CH62: =IF(T62 = 0, "Not 50%", IF(T62 >= 0.5 * N62, "Business Achieved 50%", "Not 50%")) -> Not 50% | CI62: =IFERROR((T62/N62),) -> 0.38157895 | CJ62: =IFERROR(__xludf.DUMMYFUNCTION("""COMPUTED_VALUE"""),495) -> 495 | CK62: =IFERROR(__xludf.DUMMYFUNCTION("""COMPUTED_VALUE"""),275) -> 275 | CL62: =IFERROR(__xludf.DUMMYFUNCTION("""COMPUTED_VALUE"""),0) -> 0 | CM62: =AE62-SUM(CJ62:CL62) -> 0
A63: Lalan Kumar | B63: Maharashtra | C63: Tushar Ravindra Kanthale | D63: MAHARASHTRA | E63: Pune | F63: 45047 | G63: 0 | H63: 14400000 | I63: 7163532.4 | J63: 0 | K63: 113 | L63: 105 | M63: 11 | N63: 124 | O63: 19 | P63: 6272949.1 | Q63: 890583.3 | R63: 72 | S63: 9 | T63: 81 | U63: 0 | V63: 10 | W63: 20 | X63: 157 | Y63: 3 | Z63: 51 | AA63: 0 | AB63: 0 | AC63: 0 | AD63: 0 | AE63: 1288 | AF63: 1359 | AG63: 290 | AH63: =IFERROR(SUM(I63:J63)/AG63,"") -> 24701.836 | AI63: =IFERROR(AF63/AG63,"") -> 4.6862069 | AJ63: 37990 | AK63: =AJ63*BD63 -> 455880 | AL63: 115985 | AM63: =IFERROR(SUM(AK63:AL63)/SUM(I63:J63),"") -> 0.079830029 | AN63: =IFERROR(I63/T63,"") -> 88438.671 | AO63: =IFERROR(SUM(I63:J63)/SUM(G63:H63),"") -> 0.49746753 | AP63: 0 | AQ63: 557 | AR63: 2892 | AS63: 1849.17 | AT63: 9 | AU63: 18 | AV63: 81 | AW63: 27 | AX63: 16 | AY63: =IFERROR(VLOOKUP(C63,#REF!,13,0),"") | BA63: =IF(ISBLANK(AZ63),"Active","LEFT" ) -> Active | BB63: =_xludf.ifs(F63<$BB$1,"Old",F63>$BB$1,"New") -> #NAME? | BC63: =_xludf.ifs(AO63<50%,"Below 50%",AO63<70%,"50%-70%",AO63<90%,"70%-90%",AO63<100%,"90%-100%",AO63>100%,"Above 100%") -> #NAME? | BD63: {=MATCH($BD$2,{"Apr","May","Jun","Jul","Aug","Sep","Oct","Nov","Dec","Jan","Feb","Mar"},0)} -> 12 | BF63: =M63-AT63 -> 2 | BG63: Secondary | BH63: =IFERROR(__xludf.DUMMYFUNCTION("""COMPUTED_VALUE"""),7311644) -> 7311644 | BI63: =IFERROR(__xludf.DUMMYFUNCTION("""COMPUTED_VALUE"""),7401315.19) -> 7401315.2 | BL63: =BK63*BD63 -> 0 | BM63: =H63+BL63 -> 14400000 | BO63: =IFERROR(__xludf.DUMMYFUNCTION("IFERROR(ArrayFormula(SUM(VLOOKUP($C63,importrange(""1MwNMVzWE3QBVOyJjKr3eFX-Sq1Ng0Q1sghWJbgbE_8g"",""ORDER BOOKING REPORT 2024-25!C:CV""),{16,23,30},0))))"),1692578.96) -> 1692579 | BP63: =IFERROR(__xludf.DUMMYFUNCTION("IFERROR(ArrayFormula(SUM(VLOOKUP($C63,importrange(""1MwNMVzWE3QBVOyJjKr3eFX-Sq1Ng0Q1sghWJbgbE_8g"",""ORDER BOOKING REPORT 2024-25!C:CV""),{37,44,51},0))))"),1715364.72) -> 1715364.7 | BQ63: =IFERROR(__xludf.DUMMYFUNCTION("IFERROR(ArrayFormula(SUM(VLOOKUP($C63,importrange(""1MwNMVzWE3QBVOyJjKr3eFX-Sq1Ng0Q1sghWJbgbE_8g"",""ORDER BOOKING REPORT 2024-25!C:CV""),{58,65,72},0))))"),1782553.12) -> 1782553.1 | BR63: =IFERROR(__xludf.DUMMYFUNCTION("IFERROR(ArrayFormula(SUM(VLOOKUP($C63,importrange(""1MwNMVzWE3QBVOyJjKr3eFX-Sq1Ng0Q1sghWJbgbE_8g"",""ORDER BOOKING REPORT 2024-25!C:CV""),{79,86,93},0))))"),2210818.39) -> 2210818.4 | BS63: =IFERROR(AY63/BM63,"") | BT63: =IFERROR(SUM(AK63:AL63)/AY63,"") | BU63: =BL63-G63 -> 0 | BV63: 37990 | BW63: Sr. Executive - Sales & Mktg. | BX63: 896 | BY63: =BV63-AJ63 -> 0 | CG63: =IF(N63<60,"Below 60"," ") | CH63: =IF(T63 = 0, "Not 50%", IF(T63 >= 0.5 * N63, "Business Achieved 50%", "Not 50%")) -> Business Achieved 50% | CI63: =IFERROR((T63/N63),) -> 0.65322581 | CJ63: =IFERROR(__xludf.DUMMYFUNCTION("""COMPUTED_VALUE"""),1167) -> 1167 | CK63: =IFERROR(__xludf.DUMMYFUNCTION("""COMPUTED_VALUE"""),121) -> 121 | CL63: =IFERROR(__xludf.DUMMYFUNCTION("""COMPUTED_VALUE"""),0) -> 0 | CM63: =AE63-SUM(CJ63:CL63) -> 0
A64: Lalan Kumar | B64: Maharashtra | C64: Vibhor Mathur | D64: MAHARASHTRA | E64: Mumbai | F64: 45047 | G64: 0 | H64: 0 | I64: 0 | J64: 0 | K64: 35 | L64: 28 | M64: 1 | N64: 36 | O64: 8 | P64: 0 | Q64: 0 | R64: 0 | S64: 0 | T64: 0 | U64: 0 | V64: 3 | W64: 4 | X64: 120 | Y64: 5 | Z64: 26 | AA64: 1 | AB64: 4 | AC64: 2 | AD64: 5 | AE64: 74 | AF64: 113 | AG64: 32 | AH64: =IFERROR(SUM(I64:J64)/AG64,"") -> 0 | AI64: =IFERROR(AF64/AG64,"") -> 3.53125 | AJ64: 37335 | AK64: =AJ64*BD64 -> 47042.1 | AL64: 11050 | AM64: =IFERROR(SUM(AK64:AL64)/SUM(I64:J64),"") | AN64: =IFERROR(I64/T64,"") | AO64: No Target | AP64: 0 | AQ64: 0 | AR64: 275 | AS64: 0 | AT64: 0 | AU64: 0 | AV64: 0 | AW64: 28 | AX64: 8 | AY64: =IFERROR(VLOOKUP(C64,#REF!,13,0),"") | AZ64: 45785 | BA64: =IF(ISBLANK(AZ64),"Active","LEFT" ) -> LEFT | BB64: =_xludf.ifs(F64<$BB$1,"Old",F64>$BB$1,"New") -> #NAME? | BC64: No Target | BD64: 1.26 | BF64: =M64-AT64 -> 1 | BG64: Secondary | BH64: =IFERROR(__xludf.DUMMYFUNCTION("""COMPUTED_VALUE"""),3836040) -> 3836040 | BI64: =IFERROR(__xludf.DUMMYFUNCTION("""COMPUTED_VALUE"""),4643794.6) -> 4643794.6 | BJ64: =8/31 -> 0.25806452 | BL64: =BK64*BD64 -> 0 | BM64: =H64+BL64 -> 0 | BO64: =IFERROR(__xludf.DUMMYFUNCTION("IFERROR(ArrayFormula(SUM(VLOOKUP($C64,importrange(""1MwNMVzWE3QBVOyJjKr3eFX-Sq1Ng0Q1sghWJbgbE_8g"",""ORDER BOOKING REPORT 2024-25!C:CV""),{16,23,30},0))))"),505157.6) -> 505157.6 | BP64: =IFERROR(__xludf.DUMMYFUNCTION("IFERROR(ArrayFormula(SUM(VLOOKUP($C64,importrange(""1MwNMVzWE3QBVOyJjKr3eFX-Sq1Ng0Q1sghWJbgbE_8g"",""ORDER BOOKING REPORT 2024-25!C:CV""),{37,44,51},0))))"),691492.2) -> 691492.2 | BQ64: =IFERROR(__xludf.DUMMYFUNCTION("IFERROR(ArrayFormula(SUM(VLOOKUP($C64,importrange(""1MwNMVzWE3QBVOyJjKr3eFX-Sq1Ng0Q1sghWJbgbE_8g"",""ORDER BOOKING REPORT 2024-25!C:CV""),{58,65,72},0))))"),1165454.2) -> 1165454.2 | BR64: =IFERROR(__xludf.DUMMYFUNCTION("IFERROR(ArrayFormula(SUM(VLOOKUP($C64,importrange(""1MwNMVzWE3QBVOyJjKr3eFX-Sq1Ng0Q1sghWJbgbE_8g"",""ORDER BOOKING REPORT 2024-25!C:CV""),{79,86,93},0))))"),2281690.6) -> 2281690.6 | BS64: =IFERROR(AY64/BM64,"") | BT64: =IFERROR(SUM(AK64:AL64)/AY64,"") | BU64: =BL64-G64 -> 0 | BY64: =BV64-AJ64 -> -37335 | CG64: =IF(N64<60,"Below 60"," ") -> Below 60 | CH64: =IF(T64 = 0, "Not 50%", IF(T64 >= 0.5 * N64, "Business Achieved 50%", "Not 50%")) -> Not 50% | CI64: =IFERROR((T64/N64),) -> 0 | CJ64: =IFERROR(__xludf.DUMMYFUNCTION("""COMPUTED_VALUE"""),0) -> 0 | CK64: =IFERROR(__xludf.DUMMYFUNCTION("""COMPUTED_VALUE"""),74) -> 74 | CL64: =IFERROR(__xludf.DUMMYFUNCTION("""COMPUTED_VALUE"""),0) -> 0 | CM64: =AE64-SUM(CJ64:CL64) -> 0
A65: Sandeep Dadheech | B65: West Bengal | C65: Gonesh Dey | D65: WEST BENGAL | E65: Burdwan | F65: 45047 | G65: 0 | H65: 18000000 | I65: 14450867 | J65: 0 | K65: 45 | L65: 51 | M65: 10 | N65: 55 | O65: 4 | P65: 12801151 | Q65: 1649715.9 | R65: 20 | S65: 6 | T65: 26 | U65: 0 | V65: 67 | W65: 187 | X65: 154 | Y65: 2 | Z65: 6 | AA65: 0 | AB65: 0 | AC65: 0 | AD65: 0 | AE65: 1555 | AF65: 1748 | AG65: 293 | AH65: =IFERROR(SUM(I65:J65)/AG65,"") -> 49320.364 | AI65: =IFERROR(AF65/AG65,"") -> 5.9658703 | AJ65: 31500 | AK65: =AJ65*BD65 -> 378000 | AL65: 142750 | AM65: =IFERROR(SUM(AK65:AL65)/SUM(I65:J65),"") -> 0.036035901 | AN65: =IFERROR(I65/T65,"") -> 555802.56 | AO65: =IFERROR(SUM(I65:J65)/SUM(G65:H65),"") -> 0.80282592 | AP65: 0 | AQ65: 102 | AR65: 2881 | AS65: 3418.73 | AT65: 6 | AU65: 67 | AV65: 26 | AW65: 25 | AX65: 4 | AY65: =IFERROR(VLOOKUP(C65,#REF!,13,0),"") | BA65: =IF(ISBLANK(AZ65),"Active","LEFT" ) -> Active | BB65: =_xludf.ifs(F65<$BB$1,"Old",F65>$BB$1,"New") -> #NAME? | BC65: =_xludf.ifs(AO65<50%,"Below 50%",AO65<70%,"50%-70%",AO65<90%,"70%-90%",AO65<100%,"90%-100%",AO65>100%,"Above 100%") -> #NAME? | BD65: =MATCH($BD$2,{"Apr","May","Jun","Jul","Aug","Sep","Oct","Nov","Dec","Jan","Feb","Mar"},0) -> 12 | BF65: =M65-AT65 -> 4 | BG65: Secondary | BH65: =IFERROR(__xludf.DUMMYFUNCTION("""COMPUTED_VALUE"""),7721539) -> 7721539 | BI65: =IFERROR(__xludf.DUMMYFUNCTION("""COMPUTED_VALUE"""),9094347.39999999) -> 9094347.4 | BL65: =BK65*BD65 -> 0 | BM65: =H65+BL65 -> 18000000 | BO65: =IFERROR(__xludf.DUMMYFUNCTION("IFERROR(ArrayFormula(SUM(VLOOKUP($C65,importrange(""1MwNMVzWE3QBVOyJjKr3eFX-Sq1Ng0Q1sghWJbgbE_8g"",""ORDER BOOKING REPORT 2024-25!C:CV""),{16,23,30},0))))"),1470412.5) -> 1470412.5 | BP65: =IFERROR(__xludf.DUMMYFUNCTION("IFERROR(ArrayFormula(SUM(VLOOKUP($C65,importrange(""1MwNMVzWE3QBVOyJjKr3eFX-Sq1Ng0Q1sghWJbgbE_8g"",""ORDER BOOKING REPORT 2024-25!C:CV""),{37,44,51},0))))"),2361463.3) -> 2361463.3 | BQ65: =IFERROR(__xludf.DUMMYFUNCTION("IFERROR(ArrayFormula(SUM(VLOOKUP($C65,importrange(""1MwNMVzWE3QBVOyJjKr3eFX-Sq1Ng0Q1sghWJbgbE_8g"",""ORDER BOOKING REPORT 2024-25!C:CV""),{58,65,72},0))))"),2574447.09999999) -> 2574447.1 | BR65: =IFERROR(__xludf.DUMMYFUNCTION("IFERROR(ArrayFormula(SUM(VLOOKUP($C65,importrange(""1MwNMVzWE3QBVOyJjKr3eFX-Sq1Ng0Q1sghWJbgbE_8g"",""ORDER BOOKING REPORT 2024-25!C:CV""),{79,86,93},0))))"),2688024.5) -> 2688024.5 | BS65: =IFERROR(AY65/BM65,"") | BT65: =IFERROR(SUM(AK65:AL65)/AY65,"") | BU65: =BL65-G65 -> 0 | BV65: 31500 | BW65: Executive - Sales & Mkt. | BX65: 899 | BY65: =BV65-AJ65 -> 0 | CG65: =IF(N65<60,"Below 60"," ") -> Below 60 | CH65: =IF(T65 = 0, "Not 50%", IF(T65 >= 0.5 * N65, "Business Achieved 50%", "Not 50%")) -> Not 50% | CI65: =IFERROR((T65/N65),) -> 0.47272727 | CJ65: =IFERROR(__xludf.DUMMYFUNCTION("""COMPUTED_VALUE"""),1050) -> 1050 | CK65: =IFERROR(__xludf.DUMMYFUNCTION("""COMPUTED_VALUE"""),505) -> 505 | CL65: =IFERROR(__xludf.DUMMYFUNCTION("""COMPUTED_VALUE"""),0) -> 0 | CM65: =AE65-SUM(CJ65:CL65) -> 0
