Workbook

Sheet ORDER BOOKING REPORT 2025-26
B1: ORDER BOOKING REPORT 2025-26 | M1: =sum(M3,N1)-sum('Summary 25-26'!M5:N5) -> 2309013868 | N1: 2735023
C3: TOTAL | I3: =SUM(I7:I225) -> 7860770 | J3: =SUM(J7:J225) -> 3.6643401e+08 | K3: =SUM(K7:K225) -> 17273 | L3: =SUM(L7:L225) -> 3797511503 | M3: =SUM(M7:M225) -> 2344243214 | N3: =iferror(O3/L3,"") -> 0.63235699 | O3: =SUM(O7:O225) -> 2401382930 | P3: =SUM(P7:P225) -> 2.6491977e+08 | Q3: =SUM(Q7:Q225) -> 7200 | R3: =SUM(R7:R225) -> 1.3199116e+08 | S3: =SUM(S7:S225) -> 2590 | T3: =iferror(R3/P3,"") -> 0.4982307 | U3: =SUM(U7:U225) -> 143975271 | V3: =SUM(V7:V225) -> 2877 | W3: =SUM(W7:W225) -> 2.7900015e+08 | X3: =SUM(X7:X225) -> 7448 | Y3: =SUM(Y7:Y225) -> 1.8800099e+08 | Z3: =SUM(Z7:Z225) -> 3118 | AA3: =iferror(Y3/W3,"") -> 0.67383832 | AB3: =SUM(AB7:AB225) -> 1.9194412e+08 | AC3: =SUM(AC7:AC225) -> 3405 | AD3: =SUM(AD7:AD225) -> 3.007814e+08 | AE3: =SUM(AE7:AE225) -> 7743 | AF3: =SUM(AF7:AF225) -> 2.0909692e+08 | AG3: =SUM(AG7:AG225) -> 3019 | AH3: =iferror(AF3/AD3,"") -> 0.69517902 | AI3: =SUM(AI7:AI225) -> 2.1790106e+08 | AJ3: =SUM(AJ7:AJ225) -> 3220 | AK3: =SUM(AK7:AK225) -> 2.9376451e+08 | AL3: =SUM(AL7:AL225) -> 7782 | AM3: =SUM(AM7:AM225) -> 1.9449774e+08 | AN3: =SUM(AN7:AN225) -> 3266 | AO3: =iferror(AM3/AK3,"") -> 0.66208726 | AP3: =SUM(AP7:AP225) -> 1.9185567e+08 | AQ3: =SUM(AQ7:AQ225) -> 3310 | AR3: =SUM(AR7:AR225) -> 2.8231115e+08 | AS3: =SUM(AS7:AS225) -> 7887 | AT3: =SUM(AT7:AT225) -> 1.9327481e+08 | AU3: =SUM(AU7:AU225) -> 3120 | AV3: =iferror(AT3/AR3,"") -> 0.68461629 | AW3: =SUM(AW7:AW225) -> 1.9483789e+08 | AX3: =SUM(AX7:AX225) -> 3260 | AY3: =SUM(AY7:AY225) -> 3.0258034e+08 | AZ3: =SUM(AZ7:AZ225) -> 8074 | BA3: =SUM(BA7:BA225) -> 2.0462143e+08 | BB3: =SUM(BB7:BB225) -> 3326 | BC3: =iferror(BA3/AY3,"") -> 0.67625487 | BD3: =SUM(BD7:BD225) -> 2.0385066e+08 | BE3: =SUM(BE7:BE225) -> 3424 | BF3: =SUM(BF7:BF225) -> 2.8846526e+08 | BG3: =SUM(BG7:BG225) -> 7874 | BH3: =SUM(BH7:BH225) -> 1.7662105e+08 | BI3: =SUM(BI7:BI225) -> 2886 | BJ3: =iferror(BH3/BF3,"") -> 0.6122784 | BK3: =SUM(BK7:BK225) -> 1.8054222e+08 | BL3: =SUM(BL7:BL225) -> 3087 | BM3: =SUM(BM7:BM225) -> 2.9090573e+08 | BN3: =SUM(BN7:BN225) -> 7908 | BO3: =SUM(BO7:BO225) -> 1.7189559e+08 | BP3: =SUM(BP7:BP225) -> 3005 | BQ3: =iferror(BO3/BM3,"") -> 0.5908979 | BR3: =SUM(BR7:BR225) -> 1.7585819e+08 | BS3: =SUM(BS7:BS225) -> 3146 | BT3: =SUM(BT7:BT225) -> 3.2391346e+08 | BU3: =SUM(BU7:BU225) -> 8155 | BV3: =SUM(BV7:BV225) -> 2.0831272e+08 | BW3: =SUM(BW7:BW225) -> 3245 | BX3: =iferror(BV3/BT3,"") -> 0.64311226 | BY3: =SUM(BY7:BY225) -> 2.1256178e+08 | BZ3: =SUM(BZ7:BZ225) -> 3440 | CA3: =SUM(CA7:CA225) -> 2.8735403e+08 | CB3: =SUM(CB7:CB225) -> 7878 | CC3: =SUM(CC7:CC225) -> 2.0746012e+08 | CD3: =SUM(CD7:CD225) -> 3107 | CE3: =iferror(CC3/CA3,"") -> 0.72196699 | CF3: =SUM(CF7:CF225) -> 2.0719789e+08 | CG3: =SUM(CG7:CG225) -> 3392 | CH3: =SUM(CH7:CH225) -> 2.9736784e+08 | CI3: =SUM(CI7:CI225) -> 7731 | CJ3: =SUM(CJ7:CJ225) -> 1.9305124e+08 | CK3: =SUM(CK7:CK225) -> 3001 | CL3: =iferror(CJ3/CH3,"") -> 0.64920012 | CM3: =SUM(CM7:CM225) -> 2.0244648e+08 | CN3: =SUM(CN7:CN225) -> 3331 | CO3: =SUM(CO7:CO225) -> 3.1409766e+08 | CP3: =SUM(CP7:CP225) -> 7531 | CQ3: =SUM(CQ7:CQ225) -> 2.6541946e+08 | CR3: =SUM(CR7:CR225) -> 2970 | CS3: =iferror(CQ3/CO3,"") -> 0.84502209 | CT3: =SUM(CT7:CT225) -> 2.784117e+08 | CU3: =SUM(CU7:CU225) -> 3167
B4: State Head | C4: Team Member | D4: H.Q | E4: Contact Number | F4: DOJ | G4: Week Off | H4: Market Hours | I4: Monthly CTC 25-26 | J4: Monthly Target 25-26 | K4: Total Dealer 25-26 | L4: Business Plan 25-26 | M4: Order Booked 25-26 | N4: Final Achievement | O4: Sales 25-26 | P4: 45748 | W4: 45778 | AD4: 45809 | AK4: 45839 | AR4: 45870 | AY4: 45901 | BF4: 45931 | BM4: 45962 | BT4: 45992 | CA4: 46023 | CH4: 46054 | CO4: 46082
P5: Plan | R5: Order Booked | T5: % of Achievement | U5: Sales Received | W5: Plan | Y5: Order Booked | AA5: % of Achievement | AB5: Sales Received | AD5: Plan | AF5: Order Booked | AH5: % of Achievement | AI5: Sales Received | AK5: Plan | AM5: Order Booked | AO5: % of Achievement | AP5: Sales Received | AR5: Plan | AT5: Order Booked | AV5: % of Achievement | AW5: Sales Received | AY5: Plan | BA5: Order Booked | BC5: % of Achievement | BD5: Sales Received | BF5: Plan | BH5: Order Booked | BJ5: % of Achievement | BK5: Sales Received | BM5: Plan | BO5: Order Booked | BQ5: % of Achievement | BR5: Sales Received | BT5: Plan | BV5: Order Booked | BX5: % of Achievement | BY5: Sales Received | CA5: Plan | CC5: Order Booked | CE5: % of Achievement | CF5: Sales Received | CH5: Plan | CJ5: Order Booked | CL5: % of Achievement | CM5: Sales Received | CO5: Plan | CQ5: Order Booked | CS5: % of Achievement | CT5: Sales Received
P6: Amount | Q6: Count | R6: Amount | S6: Count | U6: Amount | V6: Count | W6: Amount | X6: Count | Y6: Amount | Z6: Count | AB6: Amount | AC6: Count | AD6: Amount | AE6: Count | AF6: Amount | AG6: Count | AI6: Amount | AJ6: Count | AK6: Amount | AL6: Count | AM6: Amount | AN6: Count | AP6: Amount | AQ6: Count | AR6: Amount | AS6: Count | AT6: Amount | AU6: Count | AW6: Amount | AX6: Count | AY6: Amount | AZ6: Count | BA6: Amount | BB6: Count | BD6: Amount | BE6: Count | BF6: Amount | BG6: Count | BH6: Amount | BI6: Count | BK6: Amount | BL6: Count | BM6: Amount | BN6: Count | BO6: Amount | BP6: Count | BR6: Amount | BS6: Count | BT6: Amount | BU6: Count | BV6: Amount | BW6: Count | BY6: Amount | BZ6: Count | CA6: Amount | CB6: Count | CC6: Amount | CD6: Count | CF6: Amount | CG6: Count | CH6: Amount | CI6: Count | CJ6: Amount | CK6: Count | CM6: Amount | CN6: Count | CO6: Amount | CP6: Count | CQ6: Amount | CR6: Count | CT6: Amount | CU6: Count
A7: Anant Singh | B7: Anant Singh | C7: Ravinder Puri | D7: Ghaziabad | E7: 8802898600 | F7: 44809 | I7: =VLOOKUP($C7,Data!$C:$BV,72,0) -> 32910 | J7: 1800000 | K7: =IFERROR(__xludf.DUMMYFUNCTION("IMPORTRANGE(""1WowgCGTCOMmqanUXVQIbYWHbXi0cuGFxvrPe3CdSDpA"",""2025-26!A3"")"),106.0) -> 106 | L7: =IFERROR(__xludf.DUMMYFUNCTION("IMPORTRANGE(""1WowgCGTCOMmqanUXVQIbYWHbXi0cuGFxvrPe3CdSDpA"",""2025-26!G4"")"),2.13E7) -> 21300000 | M7: =R7+Y7+AF7+AM7+AT7+BA7+BH7+BO7+BV7+CC7+CJ7+CQ7 -> 20551333 | N7: =O7/L7 -> 1.0528726 | O7: =U7+AB7+AI7+AP7+AW7+BD7+BK7+BR7+BY7+CF7+CM7+CT7 -> 22426186 | P7: =IFERROR(__xludf.DUMMYFUNCTION("IMPORTRANGE(""1WowgCGTCOMmqanUXVQIbYWHbXi0cuGFxvrPe3CdSDpA"",""2025-26!J4"")"),1650000.0) -> 1650000 | Q7: =IFERROR(__xludf.DUMMYFUNCTION("IMPORTRANGE(""1WowgCGTCOMmqanUXVQIbYWHbXi0cuGFxvrPe3CdSDpA"",""2025-26!J3"")"),80.0) -> 80 | R7: =IFERROR(__xludf.DUMMYFUNCTION("IMPORTRANGE(""1WowgCGTCOMmqanUXVQIbYWHbXi0cuGFxvrPe3CdSDpA"",""2025-26!K4"")"),1636412.13) -> 1636412.1 | S7: =IFERROR(__xludf.DUMMYFUNCTION("IMPORTRANGE(""1WowgCGTCOMmqanUXVQIbYWHbXi0cuGFxvrPe3CdSDpA"",""2025-26!K3"")"),40.0) -> 40 | T7: =IFERROR((U7/P7),"") -> 1.0851794 | U7: =IFERROR(__xludf.DUMMYFUNCTION("IMPORTRANGE(""1WowgCGTCOMmqanUXVQIbYWHbXi0cuGFxvrPe3CdSDpA"",""2025-26!L4"")"),1790546.0) -> 1790546 | V7: =IFERROR(__xludf.DUMMYFUNCTION("IMPORTRANGE(""1WowgCGTCOMmqanUXVQIbYWHbXi0cuGFxvrPe3CdSDpA"",""2025-26!L3"")"),43.0) -> 43 | W7: =IFERROR(__xludf.DUMMYFUNCTION("IMPORTRANGE(""1WowgCGTCOMmqanUXVQIbYWHbXi0cuGFxvrPe3CdSDpA"",""2025-26!m4"")"),1800000.0) -> 1800000 | X7: =IFERROR(__xludf.DUMMYFUNCTION("IMPORTRANGE(""1WowgCGTCOMmqanUXVQIbYWHbXi0cuGFxvrPe3CdSDpA"",""2025-26!m3"")"),57.0) -> 57 | Y7: =IFERROR(__xludf.DUMMYFUNCTION("IMPORTRANGE(""1WowgCGTCOMmqanUXVQIbYWHbXi0cuGFxvrPe3CdSDpA"",""2025-26!N4"")"),1767294.6600000001) -> 1767294.7 | Z7: =IFERROR(__xludf.DUMMYFUNCTION("IMPORTRANGE(""1WowgCGTCOMmqanUXVQIbYWHbXi0cuGFxvrPe3CdSDpA"",""2025-26!N3"")"),56.0) -> 56 | AA7: =IFERROR((AB7/W7),"") -> 1.0165478 | AB7: =IFERROR(__xludf.DUMMYFUNCTION("IMPORTRANGE(""1WowgCGTCOMmqanUXVQIbYWHbXi0cuGFxvrPe3CdSDpA"",""2025-26!O4"")"),1829786.0) -> 1829786 | AC7: =IFERROR(__xludf.DUMMYFUNCTION("IMPORTRANGE(""1WowgCGTCOMmqanUXVQIbYWHbXi0cuGFxvrPe3CdSDpA"",""2025-26!O3"")"),60.0) -> 60 | AD7: =IFERROR(__xludf.DUMMYFUNCTION("IMPORTRANGE(""1WowgCGTCOMmqanUXVQIbYWHbXi0cuGFxvrPe3CdSDpA"",""2025-26!P4"")"),1800000.0) -> 1800000 | AE7: =IFERROR(__xludf.DUMMYFUNCTION("IMPORTRANGE(""1WowgCGTCOMmqanUXVQIbYWHbXi0cuGFxvrPe3CdSDpA"",""2025-26!P3"")"),92.0) -> 92 | AF7: =IFERROR(__xludf.DUMMYFUNCTION("IMPORTRANGE(""1WowgCGTCOMmqanUXVQIbYWHbXi0cuGFxvrPe3CdSDpA"",""2025-26!Q4"")"),1692838.3799999994) -> 1692838.4 | AG7: =IFERROR(__xludf.DUMMYFUNCTION("IMPORTRANGE(""1WowgCGTCOMmqanUXVQIbYWHbXi0cuGFxvrPe3CdSDpA"",""2025-26!Q3"")"),40.0) -> 40 | AH7: =IFERROR((AI7/AD7),"") -> 1.0018522 | AI7: =IFERROR(__xludf.DUMMYFUNCTION("IMPORTRANGE(""1WowgCGTCOMmqanUXVQIbYWHbXi0cuGFxvrPe3CdSDpA"",""2025-26!R4"")"),1803334.0) -> 1803334 | AJ7: =IFERROR(__xludf.DUMMYFUNCTION("IMPORTRANGE(""1WowgCGTCOMmqanUXVQIbYWHbXi0cuGFxvrPe3CdSDpA"",""2025-26!R3"")"),47.0) -> 47 | AK7: =IFERROR(__xludf.DUMMYFUNCTION("IMPORTRANGE(""1WowgCGTCOMmqanUXVQIbYWHbXi0cuGFxvrPe3CdSDpA"",""2025-26!S4"")"),1800000.0) -> 1800000 | AL7: =IFERROR(__xludf.DUMMYFUNCTION("IMPORTRANGE(""1WowgCGTCOMmqanUXVQIbYWHbXi0cuGFxvrPe3CdSDpA"",""2025-26!S3"")"),97.0) -> 97 | AM7: =IFERROR(__xludf.DUMMYFUNCTION("IMPORTRANGE(""1WowgCGTCOMmqanUXVQIbYWHbXi0cuGFxvrPe3CdSDpA"",""2025-26!T4"")"),1278357.0399999998) -> 1278357 | AN7: =IFERROR(__xludf.DUMMYFUNCTION("IMPORTRANGE(""1WowgCGTCOMmqanUXVQIbYWHbXi0cuGFxvrPe3CdSDpA"",""2025-26!T3"")"),37.0) -> 37 | AO7: =IFERROR((AP7/AK7),"") -> 0.74253333 | AP7: =IFERROR(__xludf.DUMMYFUNCTION("IMPORTRANGE(""1WowgCGTCOMmqanUXVQIbYWHbXi0cuGFxvrPe3CdSDpA"",""2025-26!U4"")"),1336560.0) -> 1336560 | AQ7: =IFERROR(__xludf.DUMMYFUNCTION("IMPORTRANGE(""1WowgCGTCOMmqanUXVQIbYWHbXi0cuGFxvrPe3CdSDpA"",""2025-26!U3"")"),39.0) -> 39 | AR7: =IFERROR(__xludf.DUMMYFUNCTION("IMPORTRANGE(""1WowgCGTCOMmqanUXVQIbYWHbXi0cuGFxvrPe3CdSDpA"",""2025-26!V4"")"),1800000.0) -> 1800000 | AS7: =IFERROR(__xludf.DUMMYFUNCTION("IMPORTRANGE(""1WowgCGTCOMmqanUXVQIbYWHbXi0cuGFxvrPe3CdSDpA"",""2025-26!V3"")"),92.0) -> 92 | AT7: =IFERROR(__xludf.DUMMYFUNCTION("IMPORTRANGE(""1WowgCGTCOMmqanUXVQIbYWHbXi0cuGFxvrPe3CdSDpA"",""2025-26!W4"")"),1498904.2899999998) -> 1498904.3 | AU7: =IFERROR(__xludf.DUMMYFUNCTION("IMPORTRANGE(""1WowgCGTCOMmqanUXVQIbYWHbXi0cuGFxvrPe3CdSDpA"",""2025-26!W3"")"),40.0) -> 40 | AV7: =IFERROR((AW7/AR7),"") -> 1.0169083 | AW7: =IFERROR(__xludf.DUMMYFUNCTION("IMPORTRANGE(""1WowgCGTCOMmqanUXVQIbYWHbXi0cuGFxvrPe3CdSDpA"",""2025-26!X4"")"),1830435.0) -> 1830435 | AX7: =IFERROR(__xludf.DUMMYFUNCTION("IMPORTRANGE(""1WowgCGTCOMmqanUXVQIbYWHbXi0cuGFxvrPe3CdSDpA"",""2025-26!X3"")"),55.0) -> 55 | AY7: =IFERROR(__xludf.DUMMYFUNCTION("IMPORTRANGE(""1WowgCGTCOMmqanUXVQIbYWHbXi0cuGFxvrPe3CdSDpA"",""2025-26!Y4"")"),1800000.0) -> 1800000 | AZ7: =IFERROR(__xludf.DUMMYFUNCTION("IMPORTRANGE(""1WowgCGTCOMmqanUXVQIbYWHbXi0cuGFxvrPe3CdSDpA"",""2025-26!Y3"")"),90.0) -> 90 | BA7: =IFERROR(__xludf.DUMMYFUNCTION("IMPORTRANGE(""1WowgCGTCOMmqanUXVQIbYWHbXi0cuGFxvrPe3CdSDpA"",""2025-26!Z4"")"),2039934.8599999999) -> 2039934.9 | BB7: =IFERROR(__xludf.DUMMYFUNCTION("IMPORTRANGE(""1WowgCGTCOMmqanUXVQIbYWHbXi0cuGFxvrPe3CdSDpA"",""2025-26!Z3"")"),48.0) -> 48 | BC7: =IFERROR((BD7/AY7),"") -> 1.2881567 | BD7: =IFERROR(__xludf.DUMMYFUNCTION("IMPORTRANGE(""1WowgCGTCOMmqanUXVQIbYWHbXi0cuGFxvrPe3CdSDpA"",""2025-26!AA4"")"),2318682.0) -> 2318682 | BE7: =IFERROR(__xludf.DUMMYFUNCTION("IMPORTRANGE(""1WowgCGTCOMmqanUXVQIbYWHbXi0cuGFxvrPe3CdSDpA"",""2025-26!AA3"")"),55.0) -> 55 | BF7: =IFERROR(__xludf.DUMMYFUNCTION("IMPORTRANGE(""1WowgCGTCOMmqanUXVQIbYWHbXi0cuGFxvrPe3CdSDpA"",""2025-26!AB4"")"),1800000.0) -> 1800000 | BG7: =IFERROR(__xludf.DUMMYFUNCTION("IMPORTRANGE(""1WowgCGTCOMmqanUXVQIbYWHbXi0cuGFxvrPe3CdSDpA"",""2025-26!AB3"")"),90.0) -> 90 | BH7: =IFERROR(__xludf.DUMMYFUNCTION("IMPORTRANGE(""1WowgCGTCOMmqanUXVQIbYWHbXi0cuGFxvrPe3CdSDpA"",""2025-26!AC4"")"),1299667.7899999996) -> 1299667.8 | BI7: =IFERROR(__xludf.DUMMYFUNCTION("IMPORTRANGE(""1WowgCGTCOMmqanUXVQIbYWHbXi0cuGFxvrPe3CdSDpA"",""2025-26!AC3"")"),44.0) -> 44 | BJ7: =IFERROR((BK7/BF7),"") -> 0.82467667 | BK7: =IFERROR(__xludf.DUMMYFUNCTION("IMPORTRANGE(""1WowgCGTCOMmqanUXVQIbYWHbXi0cuGFxvrPe3CdSDpA"",""2025-26!AD4"")"),1484418.0) -> 1484418 | BL7: =IFERROR(__xludf.DUMMYFUNCTION("IMPORTRANGE(""1WowgCGTCOMmqanUXVQIbYWHbXi0cuGFxvrPe3CdSDpA"",""2025-26!AD3"")"),44.0) -> 44 | BM7: =IFERROR(__xludf.DUMMYFUNCTION("IMPORTRANGE(""1WowgCGTCOMmqanUXVQIbYWHbXi0cuGFxvrPe3CdSDpA"",""2025-26!AE4"")"),1800000.0) -> 1800000 | BN7: =IFERROR(__xludf.DUMMYFUNCTION("IMPORTRANGE(""1WowgCGTCOMmqanUXVQIbYWHbXi0cuGFxvrPe3CdSDpA"",""2025-26!AE3"")"),91.0) -> 91 | BO7: =IFERROR(__xludf.DUMMYFUNCTION("IMPORTRANGE(""1WowgCGTCOMmqanUXVQIbYWHbXi0cuGFxvrPe3CdSDpA"",""2025-26!AF4"")"),1749611.6400000004) -> 1749611.6 | BP7: =IFERROR(__xludf.DUMMYFUNCTION("IMPORTRANGE(""1WowgCGTCOMmqanUXVQIbYWHbXi0cuGFxvrPe3CdSDpA"",""2025-26!AF3"")"),44.0) -> 44 | BQ7: =IFERROR((BR7/BM7),"") -> 1.2408344 | BR7: =IFERROR(__xludf.DUMMYFUNCTION("IMPORTRANGE(""1WowgCGTCOMmqanUXVQIbYWHbXi0cuGFxvrPe3CdSDpA"",""2025-26!AG4"")"),2233502.0) -> 2233502 | BS7: =IFERROR(__xludf.DUMMYFUNCTION("IMPORTRANGE(""1WowgCGTCOMmqanUXVQIbYWHbXi0cuGFxvrPe3CdSDpA"",""2025-26!AG3"")"),55.0) -> 55 | BT7: =IFERROR(__xludf.DUMMYFUNCTION("IMPORTRANGE(""1WowgCGTCOMmqanUXVQIbYWHbXi0cuGFxvrPe3CdSDpA"",""2025-26!AH4"")"),1800000.0) -> 1800000 | BU7: =IFERROR(__xludf.DUMMYFUNCTION("IMPORTRANGE(""1WowgCGTCOMmqanUXVQIbYWHbXi0cuGFxvrPe3CdSDpA"",""2025-26!AH3"")"),89.0) -> 89 | BV7: =IFERROR(__xludf.DUMMYFUNCTION("IMPORTRANGE(""1WowgCGTCOMmqanUXVQIbYWHbXi0cuGFxvrPe3CdSDpA"",""2025-26!AI4"")"),2078025.1699999997) -> 2078025.2 | BW7: =IFERROR(__xludf.DUMMYFUNCTION("IMPORTRANGE(""1WowgCGTCOMmqanUXVQIbYWHbXi0cuGFxvrPe3CdSDpA"",""2025-26!AI3"")"),54.0) -> 54 | BX7: =IFERROR((BY7/BT7),"") -> 1.1865744 | BY7: =IFERROR(__xludf.DUMMYFUNCTION("IMPORTRANGE(""1WowgCGTCOMmqanUXVQIbYWHbXi0cuGFxvrPe3CdSDpA"",""2025-26!AJ4"")"),2135834.0) -> 2135834 | BZ7: =IFERROR(__xludf.DUMMYFUNCTION("IMPORTRANGE(""1WowgCGTCOMmqanUXVQIbYWHbXi0cuGFxvrPe3CdSDpA"",""2025-26!AJ3"")"),55.0) -> 55 | CA7: =IFERROR(__xludf.DUMMYFUNCTION("IMPORTRANGE(""1WowgCGTCOMmqanUXVQIbYWHbXi0cuGFxvrPe3CdSDpA"",""2025-26!AK4"")"),1800000.0) -> 1800000 | CB7: =IFERROR(__xludf.DUMMYFUNCTION("IMPORTRANGE(""1WowgCGTCOMmqanUXVQIbYWHbXi0cuGFxvrPe3CdSDpA"",""2025-26!AK3"")"),90.0) -> 90 | CC7: =IFERROR(__xludf.DUMMYFUNCTION("IMPORTRANGE(""1WowgCGTCOMmqanUXVQIbYWHbXi0cuGFxvrPe3CdSDpA"",""2025-26!AL4"")"),1892383.69) -> 1892383.7 | CD7: =IFERROR(__xludf.DUMMYFUNCTION("IMPORTRANGE(""1WowgCGTCOMmqanUXVQIbYWHbXi0cuGFxvrPe3CdSDpA"",""2025-26!AL3"")"),45.0) -> 45 | CE7: =IFERROR((CF7/CA7),"") -> 1.0655617 | CF7: =IFERROR(__xludf.DUMMYFUNCTION("IMPORTRANGE(""1WowgCGTCOMmqanUXVQIbYWHbXi0cuGFxvrPe3CdSDpA"",""2025-26!AM4"")"),1918011.0) -> 1918011 | CG7: =IFERROR(__xludf.DUMMYFUNCTION("IMPORTRANGE(""1WowgCGTCOMmqanUXVQIbYWHbXi0cuGFxvrPe3CdSDpA"",""2025-26!AM3"")"),49.0) -> 49 | CH7: =IFERROR(__xludf.DUMMYFUNCTION("IMPORTRANGE(""1WowgCGTCOMmqanUXVQIbYWHbXi0cuGFxvrPe3CdSDpA"",""2025-26!AN4"")"),1800000.0) -> 1800000 | CI7: =IFERROR(__xludf.DUMMYFUNCTION("IMPORTRANGE(""1WowgCGTCOMmqanUXVQIbYWHbXi0cuGFxvrPe3CdSDpA"",""2025-26!AN3"")"),92.0) -> 92 | CJ7: =IFERROR(__xludf.DUMMYFUNCTION("IMPORTRANGE(""1WowgCGTCOMmqanUXVQIbYWHbXi0cuGFxvrPe3CdSDpA"",""2025-26!AO4"")"),1669928.2499999998) -> 1669928.2 | CK7: =IFERROR(__xludf.DUMMYFUNCTION("IMPORTRANGE(""1WowgCGTCOMmqanUXVQIbYWHbXi0cuGFxvrPe3CdSDpA"",""2025-26!AO3"")"),43.0) -> 43 | CL7: =IFERROR((CM7/CH7),"") -> 0.94717 | CM7: =IFERROR(__xludf.DUMMYFUNCTION("IMPORTRANGE(""1WowgCGTCOMmqanUXVQIbYWHbXi0cuGFxvrPe3CdSDpA"",""2025-26!AP4"")"),1704906.0) -> 1704906 | CN7: =IFERROR(__xludf.DUMMYFUNCTION("IMPORTRANGE(""1WowgCGTCOMmqanUXVQIbYWHbXi0cuGFxvrPe3CdSDpA"",""2025-26!AP3"")"),46.0) -> 46 | CO7: =IFERROR(__xludf.DUMMYFUNCTION("IMPORTRANGE(""1WowgCGTCOMmqanUXVQIbYWHbXi0cuGFxvrPe3CdSDpA"",""2025-26!AQ4"")"),1800000.0) -> 1800000 | CP7: =IFERROR(__xludf.DUMMYFUNCTION("IMPORTRANGE(""1WowgCGTCOMmqanUXVQIbYWHbXi0cuGFxvrPe3CdSDpA"",""2025-26!AQ3"")"),95.0) -> 95 | CQ7: =IFERROR(__xludf.DUMMYFUNCTION("IMPORTRANGE(""1WowgCGTCOMmqanUXVQIbYWHbXi0cuGFxvrPe3CdSDpA"",""2025-26!AR4"")"),1947975.5199999998) -> 1947975.5 | CR7: =IFERROR(__xludf.DUMMYFUNCTION("IMPORTRANGE(""1WowgCGTCOMmqanUXVQIbYWHbXi0cuGFxvrPe3CdSDpA"",""2025-26!AR3"")"),40.0) -> 40 | CS7: =IFERROR((CT7/CO7),"") -> 1.1334289 | CT7: =IFERROR(__xludf.DUMMYFUNCTION("IMPORTRANGE(""1WowgCGTCOMmqanUXVQIbYWHbXi0cuGFxvrPe3CdSDpA"",""2025-26!AS4"")"),2040172.0) -> 2040172 | CU7: =IFERROR(__xludf.DUMMYFUNCTION("IMPORTRANGE(""1WowgCGTCOMmqanUXVQIbYWHbXi0cuGFxvrPe3CdSDpA"",""2025-26!AS3"")"),42.0) -> 42 | CV7: {=vlookup(C7:C225,{Data!C:C,Data!B:B},2,0)} -> West U.P
A8: Anant Singh | C8: PRASUN CHATTERJEE | D8: Delhi | E8: 9810268300 | F8: 44994 | I8: =VLOOKUP($C8,Data!$C:$BV,72,0) -> 46390 | J8: =1500000+200000 -> 1700000 | K8: =IFERROR(__xludf.DUMMYFUNCTION("IMPORTRANGE(""1UEZK2L9OACV3t606hu8vkTn-5ekPDyqCYSBS2X6A5Jc"",""2025-26!A3"")"),94.0) -> 94 | L8: =IFERROR(__xludf.DUMMYFUNCTION("IMPORTRANGE(""1UEZK2L9OACV3t606hu8vkTn-5ekPDyqCYSBS2X6A5Jc"",""2025-26!G4"")"),1.74E7) -> 17400000 | M8: =R8+Y8+AF8+AM8+AT8+BA8+BH8+BO8+BV8+CC8+CJ8+CQ8 -> 9670433.2 | N8: =O8/L8 -> 0.5315596 | O8: =U8+AB8+AI8+AP8+AW8+BD8+BK8+BR8+BY8+CF8+CM8+CT8 -> 9249137 | P8: =IFERROR(__xludf.DUMMYFUNCTION("IMPORTRANGE(""1UEZK2L9OACV3t606hu8vkTn-5ekPDyqCYSBS2X6A5Jc"",""2025-26!J4"")"),1600000.0) -> 1600000 | Q8: =IFERROR(__xludf.DUMMYFUNCTION("IMPORTRANGE(""1UEZK2L9OACV3t606hu8vkTn-5ekPDyqCYSBS2X6A5Jc"",""2025-26!J3"")"),90.0) -> 90 | R8: =IFERROR(__xludf.DUMMYFUNCTION("IMPORTRANGE(""1UEZK2L9OACV3t606hu8vkTn-5ekPDyqCYSBS2X6A5Jc"",""2025-26!K4"")"),1462179.0) -> 1462179 | S8: =IFERROR(__xludf.DUMMYFUNCTION("IMPORTRANGE(""1UEZK2L9OACV3t606hu8vkTn-5ekPDyqCYSBS2X6A5Jc"",""2025-26!K3"")"),28.0) -> 28 | T8: =IFERROR((U8/P8),"") -> 0.99004313 | U8: =IFERROR(__xludf.DUMMYFUNCTION("IMPORTRANGE(""1UEZK2L9OACV3t606hu8vkTn-5ekPDyqCYSBS2X6A5Jc"",""2025-26!L4"")"),1584069.0) -> 1584069 | V8: =IFERROR(__xludf.DUMMYFUNCTION("IMPORTRANGE(""1UEZK2L9OACV3t606hu8vkTn-5ekPDyqCYSBS2X6A5Jc"",""2025-26!L3"")"),27.0) -> 27 | W8: =IFERROR(__xludf.DUMMYFUNCTION("IMPORTRANGE(""1UEZK2L9OACV3t606hu8vkTn-5ekPDyqCYSBS2X6A5Jc"",""2025-26!m4"")"),1590000.0) -> 1590000 | X8: =IFERROR(__xludf.DUMMYFUNCTION("IMPORTRANGE(""1UEZK2L9OACV3t606hu8vkTn-5ekPDyqCYSBS2X6A5Jc"",""2025-26!m3"")"),89.0) -> 89 | Y8: =IFERROR(__xludf.DUMMYFUNCTION("IMPORTRANGE(""1UEZK2L9OACV3t606hu8vkTn-5ekPDyqCYSBS2X6A5Jc"",""2025-26!N4"")"),1185329.9999999998) -> 1185330 | Z8: =IFERROR(__xludf.DUMMYFUNCTION("IMPORTRANGE(""1UEZK2L9OACV3t606hu8vkTn-5ekPDyqCYSBS2X6A5Jc"",""2025-26!N3"")"),29.0) -> 29 | AA8: =IFERROR((AB8/W8),"") -> 0.81574465 | AB8: =IFERROR(__xludf.DUMMYFUNCTION("IMPORTRANGE(""1UEZK2L9OACV3t606hu8vkTn-5ekPDyqCYSBS2X6A5Jc"",""2025-26!O4"")"),1297034.0) -> 1297034 | AC8: =IFERROR(__xludf.DUMMYFUNCTION("IMPORTRANGE(""1UEZK2L9OACV3t606hu8vkTn-5ekPDyqCYSBS2X6A5Jc"",""2025-26!O3"")"),29.0) -> 29 | AD8: =IFERROR(__xludf.DUMMYFUNCTION("IMPORTRANGE(""1UEZK2L9OACV3t606hu8vkTn-5ekPDyqCYSBS2X6A5Jc"",""2025-26!P4"")"),1590000.0) -> 1590000 | AE8: =IFERROR(__xludf.DUMMYFUNCTION("IMPORTRANGE(""1UEZK2L9OACV3t606hu8vkTn-5ekPDyqCYSBS2X6A5Jc"",""2025-26!P3"")"),89.0) -> 89 | AF8: =IFERROR(__xludf.DUMMYFUNCTION("IMPORTRANGE(""1UEZK2L9OACV3t606hu8vkTn-5ekPDyqCYSBS2X6A5Jc"",""2025-26!Q4"")"),778565.4) -> 778565.4 | AG8: =IFERROR(__xludf.DUMMYFUNCTION("IMPORTRANGE(""1UEZK2L9OACV3t606hu8vkTn-5ekPDyqCYSBS2X6A5Jc"",""2025-26!Q3"")"),23.0) -> 23 | AH8: =IFERROR((AI8/AD8),"") -> 0.50446415 | AI8: =IFERROR(__xludf.DUMMYFUNCTION("IMPORTRANGE(""1UEZK2L9OACV3t606hu8vkTn-5ekPDyqCYSBS2X6A5Jc"",""2025-26!R4"")"),802098.0) -> 802098 | AJ8: =IFERROR(__xludf.DUMMYFUNCTION("IMPORTRANGE(""1UEZK2L9OACV3t606hu8vkTn-5ekPDyqCYSBS2X6A5Jc"",""2025-26!R3"")"),23.0) -> 23 | AK8: =IFERROR(__xludf.DUMMYFUNCTION("IMPORTRANGE(""1UEZK2L9OACV3t606hu8vkTn-5ekPDyqCYSBS2X6A5Jc"",""2025-26!S4"")"),1590000.0) -> 1590000 | AL8: =IFERROR(__xludf.DUMMYFUNCTION("IMPORTRANGE(""1UEZK2L9OACV3t606hu8vkTn-5ekPDyqCYSBS2X6A5Jc"",""2025-26!S3"")"),89.0) -> 89 | AM8: =IFERROR(__xludf.DUMMYFUNCTION("IMPORTRANGE(""1UEZK2L9OACV3t606hu8vkTn-5ekPDyqCYSBS2X6A5Jc"",""2025-26!T4"")"),936504.3500000001) -> 936504.35 | AN8: =IFERROR(__xludf.DUMMYFUNCTION("IMPORTRANGE(""1UEZK2L9OACV3t606hu8vkTn-5ekPDyqCYSBS2X6A5Jc"",""2025-26!T3"")"),27.0) -> 27 | AO8: =IFERROR((AP8/AK8),"") -> 0.60073333 | AP8: =IFERROR(__xludf.DUMMYFUNCTION("IMPORTRANGE(""1UEZK2L9OACV3t606hu8vkTn-5ekPDyqCYSBS2X6A5Jc"",""2025-26!U4"")"),955166.0) -> 955166 | AQ8: =IFERROR(__xludf.DUMMYFUNCTION("IMPORTRANGE(""1UEZK2L9OACV3t606hu8vkTn-5ekPDyqCYSBS2X6A5Jc"",""2025-26!U3"")"),28.0) -> 28 | AR8: =IFERROR(__xludf.DUMMYFUNCTION("IMPORTRANGE(""1UEZK2L9OACV3t606hu8vkTn-5ekPDyqCYSBS2X6A5Jc"",""2025-26!V4"")"),1590000.0) -> 1590000 | AS8: =IFERROR(__xludf.DUMMYFUNCTION("IMPORTRANGE(""1UEZK2L9OACV3t606hu8vkTn-5ekPDyqCYSBS2X6A5Jc"",""2025-26!V3"")"),89.0) -> 89 | AT8: =IFERROR(__xludf.DUMMYFUNCTION("IMPORTRANGE(""1UEZK2L9OACV3t606hu8vkTn-5ekPDyqCYSBS2X6A5Jc"",""2025-26!W4"")"),955602.7500000001) -> 955602.75 | AU8: =IFERROR(__xludf.DUMMYFUNCTION("IMPORTRANGE(""1UEZK2L9OACV3t606hu8vkTn-5ekPDyqCYSBS2X6A5Jc"",""2025-26!W3"")"),29.0) -> 29 | AV8: =IFERROR((AW8/AR8),"") -> 0.55920566 | AW8: =IFERROR(__xludf.DUMMYFUNCTION("IMPORTRANGE(""1UEZK2L9OACV3t606hu8vkTn-5ekPDyqCYSBS2X6A5Jc"",""2025-26!X4"")"),889137.0) -> 889137 | AX8: =IFERROR(__xludf.DUMMYFUNCTION("IMPORTRANGE(""1UEZK2L9OACV3t606hu8vkTn-5ekPDyqCYSBS2X6A5Jc"",""2025-26!X3"")"),28.0) -> 28 | AY8: =IFERROR(__xludf.DUMMYFUNCTION("IMPORTRANGE(""1UEZK2L9OACV3t606hu8vkTn-5ekPDyqCYSBS2X6A5Jc"",""2025-26!Y4"")"),1590000.0) -> 1590000 | AZ8: =IFERROR(__xludf.DUMMYFUNCTION("IMPORTRANGE(""1UEZK2L9OACV3t606hu8vkTn-5ekPDyqCYSBS2X6A5Jc"",""2025-26!Y3"")"),89.0) -> 89 | BA8: =IFERROR(__xludf.DUMMYFUNCTION("IMPORTRANGE(""1UEZK2L9OACV3t606hu8vkTn-5ekPDyqCYSBS2X6A5Jc"",""2025-26!Z4"")"),906875.4299999999) -> 906875.43 | BB8: =IFERROR(__xludf.DUMMYFUNCTION("IMPORTRANGE(""1UEZK2L9OACV3t606hu8vkTn-5ekPDyqCYSBS2X6A5Jc"",""2025-26!Z3"")"),25.0) -> 25 | BC8: =IFERROR((BD8/AY8),"") -> 0.57211195 | BD8: =IFERROR(__xludf.DUMMYFUNCTION("IMPORTRANGE(""1UEZK2L9OACV3t606hu8vkTn-5ekPDyqCYSBS2X6A5Jc"",""2025-26!AA4"")"),909658.0) -> 909658 | BE8: =IFERROR(__xludf.DUMMYFUNCTION("IMPORTRANGE(""1UEZK2L9OACV3t606hu8vkTn-5ekPDyqCYSBS2X6A5Jc"",""2025-26!AA3"")"),25.0) -> 25 | BF8: =IFERROR(__xludf.DUMMYFUNCTION("IMPORTRANGE(""1UEZK2L9OACV3t606hu8vkTn-5ekPDyqCYSBS2X6A5Jc"",""2025-26!AB4"")"),1511000.0) -> 1511000 | BG8: =IFERROR(__xludf.DUMMYFUNCTION("IMPORTRANGE(""1UEZK2L9OACV3t606hu8vkTn-5ekPDyqCYSBS2X6A5Jc"",""2025-26!AB3"")"),67.0) -> 67 | BH8: =IFERROR(__xludf.DUMMYFUNCTION("IMPORTRANGE(""1UEZK2L9OACV3t606hu8vkTn-5ekPDyqCYSBS2X6A5Jc"",""2025-26!AC4"")"),844005.05) -> 844005.05 | BI8: =IFERROR(__xludf.DUMMYFUNCTION("IMPORTRANGE(""1UEZK2L9OACV3t606hu8vkTn-5ekPDyqCYSBS2X6A5Jc"",""2025-26!AC3"")"),18.0) -> 18 | BJ8: =IFERROR((BK8/BF8),"") -> 0.51032958 | BK8: =IFERROR(__xludf.DUMMYFUNCTION("IMPORTRANGE(""1UEZK2L9OACV3t606hu8vkTn-5ekPDyqCYSBS2X6A5Jc"",""2025-26!AD4"")"),771108.0) -> 771108 | BL8: =IFERROR(__xludf.DUMMYFUNCTION("IMPORTRANGE(""1UEZK2L9OACV3t606hu8vkTn-5ekPDyqCYSBS2X6A5Jc"",""2025-26!AD3"")"),17.0) -> 17 | BM8: =IFERROR(__xludf.DUMMYFUNCTION("IMPORTRANGE(""1UEZK2L9OACV3t606hu8vkTn-5ekPDyqCYSBS2X6A5Jc"",""2025-26!AE4"")"),1511000.0) -> 1511000 | BN8: =IFERROR(__xludf.DUMMYFUNCTION("IMPORTRANGE(""1UEZK2L9OACV3t606hu8vkTn-5ekPDyqCYSBS2X6A5Jc"",""2025-26!AE3"")"),67.0) -> 67 | BO8: =IFERROR(__xludf.DUMMYFUNCTION("IMPORTRANGE(""1UEZK2L9OACV3t606hu8vkTn-5ekPDyqCYSBS2X6A5Jc"",""2025-26!AF4"")"),322651.9) -> 322651.9 | BP8: =IFERROR(__xludf.DUMMYFUNCTION("IMPORTRANGE(""1UEZK2L9OACV3t606hu8vkTn-5ekPDyqCYSBS2X6A5Jc"",""2025-26!AF3"")"),12.0) -> 12 | BQ8: =IFERROR((BR8/BM8),"") -> 0.21962343 | BR8: =IFERROR(__xludf.DUMMYFUNCTION("IMPORTRANGE(""1UEZK2L9OACV3t606hu8vkTn-5ekPDyqCYSBS2X6A5Jc"",""2025-26!AG4"")"),331851.0) -> 331851 | BS8: =IFERROR(__xludf.DUMMYFUNCTION("IMPORTRANGE(""1UEZK2L9OACV3t606hu8vkTn-5ekPDyqCYSBS2X6A5Jc"",""2025-26!AG3"")"),12.0) -> 12 | BT8: =IFERROR(__xludf.DUMMYFUNCTION("IMPORTRANGE(""1UEZK2L9OACV3t606hu8vkTn-5ekPDyqCYSBS2X6A5Jc"",""2025-26!AH4"")"),1511000.0) -> 1511000 | BU8: =IFERROR(__xludf.DUMMYFUNCTION("IMPORTRANGE(""1UEZK2L9OACV3t606hu8vkTn-5ekPDyqCYSBS2X6A5Jc"",""2025-26!AH3"")"),67.0) -> 67 | BV8: =IFERROR(__xludf.DUMMYFUNCTION("IMPORTRANGE(""1UEZK2L9OACV3t606hu8vkTn-5ekPDyqCYSBS2X6A5Jc"",""2025-26!AI4"")"),537682.4) -> 537682.4 | BW8: =IFERROR(__xludf.DUMMYFUNCTION("IMPORTRANGE(""1UEZK2L9OACV3t606hu8vkTn-5ekPDyqCYSBS2X6A5Jc"",""2025-26!AI3"")"),21.0) -> 21 | BX8: =IFERROR((BY8/BT8),"") -> 0.36031635 | BY8: =IFERROR(__xludf.DUMMYFUNCTION("IMPORTRANGE(""1UEZK2L9OACV3t606hu8vkTn-5ekPDyqCYSBS2X6A5Jc"",""2025-26!AJ4"")"),544438.0) -> 544438 | BZ8: =IFERROR(__xludf.DUMMYFUNCTION("IMPORTRANGE(""1UEZK2L9OACV3t606hu8vkTn-5ekPDyqCYSBS2X6A5Jc"",""2025-26!AJ3"")"),21.0) -> 21 | CA8: =IFERROR(__xludf.DUMMYFUNCTION("IMPORTRANGE(""1UEZK2L9OACV3t606hu8vkTn-5ekPDyqCYSBS2X6A5Jc"",""2025-26!AK4"")"),1656000.0) -> 1656000 | CB8: =IFERROR(__xludf.DUMMYFUNCTION("IMPORTRANGE(""1UEZK2L9OACV3t606hu8vkTn-5ekPDyqCYSBS2X6A5Jc"",""2025-26!AK3"")"),72.0) -> 72 | CC8: =IFERROR(__xludf.DUMMYFUNCTION("IMPORTRANGE(""1UEZK2L9OACV3t606hu8vkTn-5ekPDyqCYSBS2X6A5Jc"",""2025-26!AL4"")"),563550.7) -> 563550.7 | CD8: =IFERROR(__xludf.DUMMYFUNCTION("IMPORTRANGE(""1UEZK2L9OACV3t606hu8vkTn-5ekPDyqCYSBS2X6A5Jc"",""2025-26!AL3"")"),21.0) -> 21 | CE8: =IFERROR((CF8/CA8),"") -> 0.33966546 | CF8: =IFERROR(__xludf.DUMMYFUNCTION("IMPORTRANGE(""1UEZK2L9OACV3t606hu8vkTn-5ekPDyqCYSBS2X6A5Jc"",""2025-26!AM4"")"),562486.0) -> 562486 | CG8: =IFERROR(__xludf.DUMMYFUNCTION("IMPORTRANGE(""1UEZK2L9OACV3t606hu8vkTn-5ekPDyqCYSBS2X6A5Jc"",""2025-26!AM3"")"),21.0) -> 21 | CH8: =IFERROR(__xludf.DUMMYFUNCTION("IMPORTRANGE(""1UEZK2L9OACV3t606hu8vkTn-5ekPDyqCYSBS2X6A5Jc"",""2025-26!AN4"")"),1656000.0) -> 1656000 | CI8: =IFERROR(__xludf.DUMMYFUNCTION("IMPORTRANGE(""1UEZK2L9OACV3t606hu8vkTn-5ekPDyqCYSBS2X6A5Jc"",""2025-26!AN3"")"),72.0) -> 72 | CJ8: =IFERROR(__xludf.DUMMYFUNCTION("IMPORTRANGE(""1UEZK2L9OACV3t606hu8vkTn-5ekPDyqCYSBS2X6A5Jc"",""2025-26!AO4"")"),463732.5) -> 463732.5 | CK8: =IFERROR(__xludf.DUMMYFUNCTION("IMPORTRANGE(""1UEZK2L9OACV3t606hu8vkTn-5ekPDyqCYSBS2X6A5Jc"",""2025-26!AO3"")"),21.0) -> 21 | CL8: =IFERROR((CM8/CH8),"") -> 0.30358937 | CM8: =IFERROR(__xludf.DUMMYFUNCTION("IMPORTRANGE(""1UEZK2L9OACV3t606hu8vkTn-5ekPDyqCYSBS2X6A5Jc"",""2025-26!AP4"")"),502744.0) -> 502744 | CN8: =IFERROR(__xludf.DUMMYFUNCTION("IMPORTRANGE(""1UEZK2L9OACV3t606hu8vkTn-5ekPDyqCYSBS2X6A5Jc"",""2025-26!AP3"")"),22.0) -> 22 | CO8: =IFERROR(__xludf.DUMMYFUNCTION("IMPORTRANGE(""1UEZK2L9OACV3t606hu8vkTn-5ekPDyqCYSBS2X6A5Jc"",""2025-26!AQ4"")"),1656000.0) -> 1656000 | CP8: =IFERROR(__xludf.DUMMYFUNCTION("IMPORTRANGE(""1UEZK2L9OACV3t606hu8vkTn-5ekPDyqCYSBS2X6A5Jc"",""2025-26!AQ3"")"),72.0) -> 72 | CQ8: =IFERROR(__xludf.DUMMYFUNCTION("IMPORTRANGE(""1UEZK2L9OACV3t606hu8vkTn-5ekPDyqCYSBS2X6A5Jc"",""2025-26!AR4"")"),713753.75) -> 713753.75 | CR8: =IFERROR(__xludf.DUMMYFUNCTION("IMPORTRANGE(""1UEZK2L9OACV3t606hu8vkTn-5ekPDyqCYSBS2X6A5Jc"",""2025-26!AR3"")"),21.0) -> 21 | CS8: =IFERROR((CT8/CO8),"") -> 0.059992754 | CT8: =IFERROR(__xludf.DUMMYFUNCTION("IMPORTRANGE(""1UEZK2L9OACV3t606hu8vkTn-5ekPDyqCYSBS2X6A5Jc"",""2025-26!AS4"")"),99348.0) -> 99348 | CU8: =IFERROR(__xludf.DUMMYFUNCTION("IMPORTRANGE(""1UEZK2L9OACV3t606hu8vkTn-5ekPDyqCYSBS2X6A5Jc"",""2025-26!AS3"")"),7.0) -> 7 | CV8: Delhi
A9: Anant Singh | C9: Jagdev | D9: Mathura | E9: 8448288693 | F9: 45261 | I9: =VLOOKUP($C9,Data!$C:$BV,72,0) -> 29360 | J9: =1200000+200000 -> 1400000 | K9: =IFERROR(__xludf.DUMMYFUNCTION("IMPORTRANGE(""1FQCfm55A8B3_aOo8e1xPQEUbQHYH85diG24OUoTRqnY"",""2025-26!A3"")"),105.0) -> 105 | L9: =IFERROR(__xludf.DUMMYFUNCTION("IMPORTRANGE(""1FQCfm55A8B3_aOo8e1xPQEUbQHYH85diG24OUoTRqnY"",""2025-26!G4"")"),1.6E7) -> 16000000 | M9: =R9+Y9+AF9+AM9+AT9+BA9+BH9+BO9+BV9+CC9+CJ9+CQ9 -> 12136399 | N9: =O9/L9 -> 0.77128669 | O9: =U9+AB9+AI9+AP9+AW9+BD9+BK9+BR9+BY9+CF9+CM9+CT9 -> 12340587 | P9: =IFERROR(__xludf.DUMMYFUNCTION("IMPORTRANGE(""1FQCfm55A8B3_aOo8e1xPQEUbQHYH85diG24OUoTRqnY"",""2025-26!J4"")"),1095310.0) -> 1095310 | Q9: =IFERROR(__xludf.DUMMYFUNCTION("IMPORTRANGE(""1FQCfm55A8B3_aOo8e1xPQEUbQHYH85diG24OUoTRqnY"",""2025-26!J3"")"),68.0) -> 68 | R9: =IFERROR(__xludf.DUMMYFUNCTION("IMPORTRANGE(""1FQCfm55A8B3_aOo8e1xPQEUbQHYH85diG24OUoTRqnY"",""2025-26!K4"")"),974002.74) -> 974002.74 | S9: =IFERROR(__xludf.DUMMYFUNCTION("IMPORTRANGE(""1FQCfm55A8B3_aOo8e1xPQEUbQHYH85diG24OUoTRqnY"",""2025-26!K3"")"),17.0) -> 17 | T9: =IFERROR((U9/P9),"") -> 0.90698889 | U9: =IFERROR(__xludf.DUMMYFUNCTION("IMPORTRANGE(""1FQCfm55A8B3_aOo8e1xPQEUbQHYH85diG24OUoTRqnY"",""2025-26!L4"")"),993434.0) -> 993434 | V9: =IFERROR(__xludf.DUMMYFUNCTION("IMPORTRANGE(""1FQCfm55A8B3_aOo8e1xPQEUbQHYH85diG24OUoTRqnY"",""2025-26!L3"")"),17.0) -> 17 | W9: =IFERROR(__xludf.DUMMYFUNCTION("IMPORTRANGE(""1FQCfm55A8B3_aOo8e1xPQEUbQHYH85diG24OUoTRqnY"",""2025-26!m4"")"),1069978.0) -> 1069978 | X9: =IFERROR(__xludf.DUMMYFUNCTION("IMPORTRANGE(""1FQCfm55A8B3_aOo8e1xPQEUbQHYH85diG24OUoTRqnY"",""2025-26!m3"")"),68.0) -> 68 | Y9: =IFERROR(__xludf.DUMMYFUNCTION("IMPORTRANGE(""1FQCfm55A8B3_aOo8e1xPQEUbQHYH85diG24OUoTRqnY"",""2025-26!N4"")"),1039828.85) -> 1039828.8 | Z9: =IFERROR(__xludf.DUMMYFUNCTION("IMPORTRANGE(""1FQCfm55A8B3_aOo8e1xPQEUbQHYH85diG24OUoTRqnY"",""2025-26!N3"")"),22.0) -> 22 | AA9: =IFERROR((AB9/W9),"") -> 0.99852707 | AB9: =IFERROR(__xludf.DUMMYFUNCTION("IMPORTRANGE(""1FQCfm55A8B3_aOo8e1xPQEUbQHYH85diG24OUoTRqnY"",""2025-26!O4"")"),1068402.0) -> 1068402 | AC9: =IFERROR(__xludf.DUMMYFUNCTION("IMPORTRANGE(""1FQCfm55A8B3_aOo8e1xPQEUbQHYH85diG24OUoTRqnY"",""2025-26!O3"")"),22.0) -> 22 | AD9: =IFERROR(__xludf.DUMMYFUNCTION("IMPORTRANGE(""1FQCfm55A8B3_aOo8e1xPQEUbQHYH85diG24OUoTRqnY"",""2025-26!P4"")"),1107000.0) -> 1107000 | AE9: =IFERROR(__xludf.DUMMYFUNCTION("IMPORTRANGE(""1FQCfm55A8B3_aOo8e1xPQEUbQHYH85diG24OUoTRqnY"",""2025-26!P3"")"),68.0) -> 68 | AF9: =IFERROR(__xludf.DUMMYFUNCTION("IMPORTRANGE(""1FQCfm55A8B3_aOo8e1xPQEUbQHYH85diG24OUoTRqnY"",""2025-26!Q4"")"),1124766.61) -> 1124766.6 | AG9: =IFERROR(__xludf.DUMMYFUNCTION("IMPORTRANGE(""1FQCfm55A8B3_aOo8e1xPQEUbQHYH85diG24OUoTRqnY"",""2025-26!Q3"")"),21.0) -> 21 | AH9: =IFERROR((AI9/AD9),"") -> 1.0365808 | AI9: =IFERROR(__xludf.DUMMYFUNCTION("IMPORTRANGE(""1FQCfm55A8B3_aOo8e1xPQEUbQHYH85diG24OUoTRqnY"",""2025-26!R4"")"),1147495.0) -> 1147495 | AJ9: =IFERROR(__xludf.DUMMYFUNCTION("IMPORTRANGE(""1FQCfm55A8B3_aOo8e1xPQEUbQHYH85diG24OUoTRqnY"",""2025-26!R3"")"),21.0) -> 21 | AK9: =IFERROR(__xludf.DUMMYFUNCTION("IMPORTRANGE(""1FQCfm55A8B3_aOo8e1xPQEUbQHYH85diG24OUoTRqnY"",""2025-26!S4"")"),1304000.0) -> 1304000 | AL9: =IFERROR(__xludf.DUMMYFUNCTION("IMPORTRANGE(""1FQCfm55A8B3_aOo8e1xPQEUbQHYH85diG24OUoTRqnY"",""2025-26!S3"")"),85.0) -> 85 | AM9: =IFERROR(__xludf.DUMMYFUNCTION("IMPORTRANGE(""1FQCfm55A8B3_aOo8e1xPQEUbQHYH85diG24OUoTRqnY"",""2025-26!T4"")"),1293629.32) -> 1293629.3 | AN9: =IFERROR(__xludf.DUMMYFUNCTION("IMPORTRANGE(""1FQCfm55A8B3_aOo8e1xPQEUbQHYH85diG24OUoTRqnY"",""2025-26!T3"")"),26.0) -> 26 | AO9: =IFERROR((AP9/AK9),"") -> 1.0053758 | AP9: =IFERROR(__xludf.DUMMYFUNCTION("IMPORTRANGE(""1FQCfm55A8B3_aOo8e1xPQEUbQHYH85diG24OUoTRqnY"",""2025-26!U4"")"),1311010.0) -> 1311010 | AQ9: =IFERROR(__xludf.DUMMYFUNCTION("IMPORTRANGE(""1FQCfm55A8B3_aOo8e1xPQEUbQHYH85diG24OUoTRqnY"",""2025-26!U3"")"),26.0) -> 26 | AR9: =IFERROR(__xludf.DUMMYFUNCTION("IMPORTRANGE(""1FQCfm55A8B3_aOo8e1xPQEUbQHYH85diG24OUoTRqnY"",""2025-26!V4"")"),1336000.0) -> 1336000 | AS9: =IFERROR(__xludf.DUMMYFUNCTION("IMPORTRANGE(""1FQCfm55A8B3_aOo8e1xPQEUbQHYH85diG24OUoTRqnY"",""2025-26!V3"")"),85.0) -> 85 | AT9: =IFERROR(__xludf.DUMMYFUNCTION("IMPORTRANGE(""1FQCfm55A8B3_aOo8e1xPQEUbQHYH85diG24OUoTRqnY"",""2025-26!W4"")"),1242011.89) -> 1242011.9 | AU9: =IFERROR(__xludf.DUMMYFUNCTION("IMPORTRANGE(""1FQCfm55A8B3_aOo8e1xPQEUbQHYH85diG24OUoTRqnY"",""2025-26!W3"")"),24.0) -> 24 | AV9: =IFERROR((AW9/AR9),"") -> 0.9320232 | AW9: =IFERROR(__xludf.DUMMYFUNCTION("IMPORTRANGE(""1FQCfm55A8B3_aOo8e1xPQEUbQHYH85diG24OUoTRqnY"",""2025-26!X4"")"),1245183.0) -> 1245183 | AX9: =IFERROR(__xludf.DUMMYFUNCTION("IMPORTRANGE(""1FQCfm55A8B3_aOo8e1xPQEUbQHYH85diG24OUoTRqnY"",""2025-26!X3"")"),24.0) -> 24 | AY9: =IFERROR(__xludf.DUMMYFUNCTION("IMPORTRANGE(""1FQCfm55A8B3_aOo8e1xPQEUbQHYH85diG24OUoTRqnY"",""2025-26!Y4"")"),1249000.0) -> 1249000 | AZ9: =IFERROR(__xludf.DUMMYFUNCTION("IMPORTRANGE(""1FQCfm55A8B3_aOo8e1xPQEUbQHYH85diG24OUoTRqnY"",""2025-26!Y3"")"),83.0) -> 83 | BA9: =IFERROR(__xludf.DUMMYFUNCTION("IMPORTRANGE(""1FQCfm55A8B3_aOo8e1xPQEUbQHYH85diG24OUoTRqnY"",""2025-26!Z4"")"),953132.9799999999) -> 953132.98 | BB9: =IFERROR(__xludf.DUMMYFUNCTION("IMPORTRANGE(""1FQCfm55A8B3_aOo8e1xPQEUbQHYH85diG24OUoTRqnY"",""2025-26!Z3"")"),34.0) -> 34 | BC9: =IFERROR((BD9/AY9),"") -> 0.76533707 | BD9: =IFERROR(__xludf.DUMMYFUNCTION("IMPORTRANGE(""1FQCfm55A8B3_aOo8e1xPQEUbQHYH85diG24OUoTRqnY"",""2025-26!AA4"")"),955906.0) -> 955906 | BE9: =IFERROR(__xludf.DUMMYFUNCTION("IMPORTRANGE(""1FQCfm55A8B3_aOo8e1xPQEUbQHYH85diG24OUoTRqnY"",""2025-26!AA3"")"),34.0) -> 34 | BF9: =IFERROR(__xludf.DUMMYFUNCTION("IMPORTRANGE(""1FQCfm55A8B3_aOo8e1xPQEUbQHYH85diG24OUoTRqnY"",""2025-26!AB4"")"),1360000.0) -> 1360000 | BG9: =IFERROR(__xludf.DUMMYFUNCTION("IMPORTRANGE(""1FQCfm55A8B3_aOo8e1xPQEUbQHYH85diG24OUoTRqnY"",""2025-26!AB3"")"),85.0) -> 85 | BH9: =IFERROR(__xludf.DUMMYFUNCTION("IMPORTRANGE(""1FQCfm55A8B3_aOo8e1xPQEUbQHYH85diG24OUoTRqnY"",""2025-26!AC4"")"),907255.3400000001) -> 907255.34 | BI9: =IFERROR(__xludf.DUMMYFUNCTION("IMPORTRANGE(""1FQCfm55A8B3_aOo8e1xPQEUbQHYH85diG24OUoTRqnY"",""2025-26!AC3"")"),22.0) -> 22 | BJ9: =IFERROR((BK9/BF9),"") -> 0.66986176 | BK9: =IFERROR(__xludf.DUMMYFUNCTION("IMPORTRANGE(""1FQCfm55A8B3_aOo8e1xPQEUbQHYH85diG24OUoTRqnY"",""2025-26!AD4"")"),911012.0) -> 911012 | BL9: =IFERROR(__xludf.DUMMYFUNCTION("IMPORTRANGE(""1FQCfm55A8B3_aOo8e1xPQEUbQHYH85diG24OUoTRqnY"",""2025-26!AD3"")"),22.0) -> 22 | BM9: =IFERROR(__xludf.DUMMYFUNCTION("IMPORTRANGE(""1FQCfm55A8B3_aOo8e1xPQEUbQHYH85diG24OUoTRqnY"",""2025-26!AE4"")"),1269000.0) -> 1269000 | BN9: =IFERROR(__xludf.DUMMYFUNCTION("IMPORTRANGE(""1FQCfm55A8B3_aOo8e1xPQEUbQHYH85diG24OUoTRqnY"",""2025-26!AE3"")"),85.0) -> 85 | BO9: =IFERROR(__xludf.DUMMYFUNCTION("IMPORTRANGE(""1FQCfm55A8B3_aOo8e1xPQEUbQHYH85diG24OUoTRqnY"",""2025-26!AF4"")"),1007490.22) -> 1007490.2 | BP9: =IFERROR(__xludf.DUMMYFUNCTION("IMPORTRANGE(""1FQCfm55A8B3_aOo8e1xPQEUbQHYH85diG24OUoTRqnY"",""2025-26!AF3"")"),31.0) -> 31 | BQ9: =IFERROR((BR9/BM9),"") -> 0.81714342 | BR9: =IFERROR(__xludf.DUMMYFUNCTION("IMPORTRANGE(""1FQCfm55A8B3_aOo8e1xPQEUbQHYH85diG24OUoTRqnY"",""2025-26!AG4"")"),1036955.0) -> 1036955 | BS9: =IFERROR(__xludf.DUMMYFUNCTION("IMPORTRANGE(""1FQCfm55A8B3_aOo8e1xPQEUbQHYH85diG24OUoTRqnY"",""2025-26!AG3"")"),33.0) -> 33 | BT9: =IFERROR(__xludf.DUMMYFUNCTION("IMPORTRANGE(""1FQCfm55A8B3_aOo8e1xPQEUbQHYH85diG24OUoTRqnY"",""2025-26!AH4"")"),1357000.0) -> 1357000 | BU9: =IFERROR(__xludf.DUMMYFUNCTION("IMPORTRANGE(""1FQCfm55A8B3_aOo8e1xPQEUbQHYH85diG24OUoTRqnY"",""2025-26!AH3"")"),99.0) -> 99 | BV9: =IFERROR(__xludf.DUMMYFUNCTION("IMPORTRANGE(""1FQCfm55A8B3_aOo8e1xPQEUbQHYH85diG24OUoTRqnY"",""2025-26!AI4"")"),906093.8200000001) -> 906093.82 | BW9: =IFERROR(__xludf.DUMMYFUNCTION("IMPORTRANGE(""1FQCfm55A8B3_aOo8e1xPQEUbQHYH85diG24OUoTRqnY"",""2025-26!AI3"")"),28.0) -> 28 | BX9: =IFERROR((BY9/BT9),"") -> 0.66091304 | BY9: =IFERROR(__xludf.DUMMYFUNCTION("IMPORTRANGE(""1FQCfm55A8B3_aOo8e1xPQEUbQHYH85diG24OUoTRqnY"",""2025-26!AJ4"")"),896859.0) -> 896859 | BZ9: =IFERROR(__xludf.DUMMYFUNCTION("IMPORTRANGE(""1FQCfm55A8B3_aOo8e1xPQEUbQHYH85diG24OUoTRqnY"",""2025-26!AJ3"")"),27.0) -> 27 | CA9: =IFERROR(__xludf.DUMMYFUNCTION("IMPORTRANGE(""1FQCfm55A8B3_aOo8e1xPQEUbQHYH85diG24OUoTRqnY"",""2025-26!AK4"")"),1321000.0) -> 1321000 | CB9: =IFERROR(__xludf.DUMMYFUNCTION("IMPORTRANGE(""1FQCfm55A8B3_aOo8e1xPQEUbQHYH85diG24OUoTRqnY"",""2025-26!AK3"")"),99.0) -> 99 | CC9: =IFERROR(__xludf.DUMMYFUNCTION("IMPORTRANGE(""1FQCfm55A8B3_aOo8e1xPQEUbQHYH85diG24OUoTRqnY"",""2025-26!AL4"")"),1006623.01) -> 1006623 | CD9: =IFERROR(__xludf.DUMMYFUNCTION("IMPORTRANGE(""1FQCfm55A8B3_aOo8e1xPQEUbQHYH85diG24OUoTRqnY"",""2025-26!AL3"")"),27.0) -> 27 | CE9: =IFERROR((CF9/CA9),"") -> 0.78368887 | CF9: =IFERROR(__xludf.DUMMYFUNCTION("IMPORTRANGE(""1FQCfm55A8B3_aOo8e1xPQEUbQHYH85diG24OUoTRqnY"",""2025-26!AM4"")"),1035253.0) -> 1035253 | CG9: =IFERROR(__xludf.DUMMYFUNCTION("IMPORTRANGE(""1FQCfm55A8B3_aOo8e1xPQEUbQHYH85diG24OUoTRqnY"",""2025-26!AM3"")"),27.0) -> 27 | CH9: =IFERROR(__xludf.DUMMYFUNCTION("IMPORTRANGE(""1FQCfm55A8B3_aOo8e1xPQEUbQHYH85diG24OUoTRqnY"",""2025-26!AN4"")"),1314000.0) -> 1314000 | CI9: =IFERROR(__xludf.DUMMYFUNCTION("IMPORTRANGE(""1FQCfm55A8B3_aOo8e1xPQEUbQHYH85diG24OUoTRqnY"",""2025-26!AN3"")"),99.0) -> 99 | CJ9: =IFERROR(__xludf.DUMMYFUNCTION("IMPORTRANGE(""1FQCfm55A8B3_aOo8e1xPQEUbQHYH85diG24OUoTRqnY"",""2025-26!AO4"")"),732687.57) -> 732687.57 | CK9: =IFERROR(__xludf.DUMMYFUNCTION("IMPORTRANGE(""1FQCfm55A8B3_aOo8e1xPQEUbQHYH85diG24OUoTRqnY"",""2025-26!AO3"")"),26.0) -> 26 | CL9: =IFERROR((CM9/CH9),"") -> 0.577293 | CM9: =IFERROR(__xludf.DUMMYFUNCTION("IMPORTRANGE(""1FQCfm55A8B3_aOo8e1xPQEUbQHYH85diG24OUoTRqnY"",""2025-26!AP4"")"),758563.0) -> 758563 | CN9: =IFERROR(__xludf.DUMMYFUNCTION("IMPORTRANGE(""1FQCfm55A8B3_aOo8e1xPQEUbQHYH85diG24OUoTRqnY"",""2025-26!AP3"")"),26.0) -> 26 | CO9: =IFERROR(__xludf.DUMMYFUNCTION("IMPORTRANGE(""1FQCfm55A8B3_aOo8e1xPQEUbQHYH85diG24OUoTRqnY"",""2025-26!AQ4"")"),1375000.0) -> 1375000 | CP9: =IFERROR(__xludf.DUMMYFUNCTION("IMPORTRANGE(""1FQCfm55A8B3_aOo8e1xPQEUbQHYH85diG24OUoTRqnY"",""2025-26!AQ3"")"),99.0) -> 99 | CQ9: =IFERROR(__xludf.DUMMYFUNCTION("IMPORTRANGE(""1FQCfm55A8B3_aOo8e1xPQEUbQHYH85diG24OUoTRqnY"",""2025-26!AR4"")"),948876.5699999998) -> 948876.57 | CR9: =IFERROR(__xludf.DUMMYFUNCTION("IMPORTRANGE(""1FQCfm55A8B3_aOo8e1xPQEUbQHYH85diG24OUoTRqnY"",""2025-26!AR3"")"),23.0) -> 23 | CS9: =IFERROR((CT9/CO9),"") -> 0.71310182 | CT9: =IFERROR(__xludf.DUMMYFUNCTION("IMPORTRANGE(""1FQCfm55A8B3_aOo8e1xPQEUbQHYH85diG24OUoTRqnY"",""2025-26!AS4"")"),980515.0) -> 980515 | CU9: =IFERROR(__xludf.DUMMYFUNCTION("IMPORTRANGE(""1FQCfm55A8B3_aOo8e1xPQEUbQHYH85diG24OUoTRqnY"",""2025-26!AS3"")"),23.0) -> 23 | CV9: West U.P
A10: Anant Singh | C10: Manish Gupta | D10: South East Delhi | E10: 9891552205 | F10: 45551 | I10: =VLOOKUP($C10,Data!$C:$BV,72,0) -> 28310 | J10: 1300000 | K10: =IFERROR(__xludf.DUMMYFUNCTION("IMPORTRANGE(""1Oujo8vUnwFLr-WkmYYfJwaGjmRsDy-q2Aq0vU4BlykA"",""2025-26!A3"")"),125.0) -> 125 | L10: =IFERROR(__xludf.DUMMYFUNCTION("IMPORTRANGE(""1Oujo8vUnwFLr-WkmYYfJwaGjmRsDy-q2Aq0vU4BlykA"",""2025-26!G4"")"),1.5445E7) -> 15445000 | M10: =R10+Y10+AF10+AM10+AT10+BA10+BH10+BO10+BV10+CC10+CJ10+CQ10 -> 11338113 | N10: =O10/L10 -> 0.73676536 | O10: =U10+AB10+AI10+AP10+AW10+BD10+BK10+BR10+BY10+CF10+CM10+CT10 -> 11379341 | P10: =IFERROR(__xludf.DUMMYFUNCTION("IMPORTRANGE(""1Oujo8vUnwFLr-WkmYYfJwaGjmRsDy-q2Aq0vU4BlykA"",""2025-26!J4"")"),1232000.0) -> 1232000 | Q10: =IFERROR(__xludf.DUMMYFUNCTION("IMPORTRANGE(""1Oujo8vUnwFLr-WkmYYfJwaGjmRsDy-q2Aq0vU4BlykA"",""2025-26!J3"")"),114.0) -> 114 | R10: =IFERROR(__xludf.DUMMYFUNCTION("IMPORTRANGE(""1Oujo8vUnwFLr-WkmYYfJwaGjmRsDy-q2Aq0vU4BlykA"",""2025-26!K4"")"),846489.8100000002) -> 846489.81 | S10: =IFERROR(__xludf.DUMMYFUNCTION("IMPORTRANGE(""1Oujo8vUnwFLr-WkmYYfJwaGjmRsDy-q2Aq0vU4BlykA"",""2025-26!K3"")"),43.0) -> 43 | T10: =IFERROR((U10/P10),"") -> 0.7011333 | U10: =IFERROR(__xludf.DUMMYFUNCTION("IMPORTRANGE(""1Oujo8vUnwFLr-WkmYYfJwaGjmRsDy-q2Aq0vU4BlykA"",""2025-26!L4"")"),863796.22) -> 863796.22 | V10: =IFERROR(__xludf.DUMMYFUNCTION("IMPORTRANGE(""1Oujo8vUnwFLr-WkmYYfJwaGjmRsDy-q2Aq0vU4BlykA"",""2025-26!L3"")"),43.0) -> 43 | W10: =IFERROR(__xludf.DUMMYFUNCTION("IMPORTRANGE(""1Oujo8vUnwFLr-WkmYYfJwaGjmRsDy-q2Aq0vU4BlykA"",""2025-26!m4"")"),1214000.0) -> 1214000 | X10: =IFERROR(__xludf.DUMMYFUNCTION("IMPORTRANGE(""1Oujo8vUnwFLr-WkmYYfJwaGjmRsDy-q2Aq0vU4BlykA"",""2025-26!m3"")"),114.0) -> 114 | Y10: =IFERROR(__xludf.DUMMYFUNCTION("IMPORTRANGE(""1Oujo8vUnwFLr-WkmYYfJwaGjmRsDy-q2Aq0vU4BlykA"",""2025-26!N4"")"),926964.65) -> 926964.65 | Z10: =IFERROR(__xludf.DUMMYFUNCTION("IMPORTRANGE(""1Oujo8vUnwFLr-WkmYYfJwaGjmRsDy-q2Aq0vU4BlykA"",""2025-26!N3"")"),42.0) -> 42 | AA10: =IFERROR((AB10/W10),"") -> 0.78115451 | AB10: =IFERROR(__xludf.DUMMYFUNCTION("IMPORTRANGE(""1Oujo8vUnwFLr-WkmYYfJwaGjmRsDy-q2Aq0vU4BlykA"",""2025-26!O4"")"),948321.58) -> 948321.58 | AC10: =IFERROR(__xludf.DUMMYFUNCTION("IMPORTRANGE(""1Oujo8vUnwFLr-WkmYYfJwaGjmRsDy-q2Aq0vU4BlykA"",""2025-26!O3"")"),43.0) -> 43 | AD10: =IFERROR(__xludf.DUMMYFUNCTION("IMPORTRANGE(""1Oujo8vUnwFLr-WkmYYfJwaGjmRsDy-q2Aq0vU4BlykA"",""2025-26!P4"")"),1327000.0) -> 1327000 | AE10: =IFERROR(__xludf.DUMMYFUNCTION("IMPORTRANGE(""1Oujo8vUnwFLr-WkmYYfJwaGjmRsDy-q2Aq0vU4BlykA"",""2025-26!P3"")"),116.0) -> 116 | AF10: =IFERROR(__xludf.DUMMYFUNCTION("IMPORTRANGE(""1Oujo8vUnwFLr-WkmYYfJwaGjmRsDy-q2Aq0vU4BlykA"",""2025-26!Q4"")"),867458.8000000002) -> 867458.8 | AG10: =IFERROR(__xludf.DUMMYFUNCTION("IMPORTRANGE(""1Oujo8vUnwFLr-WkmYYfJwaGjmRsDy-q2Aq0vU4BlykA"",""2025-26!Q3"")"),36.0) -> 36 | AH10: =IFERROR((AI10/AD10),"") -> 0.65871839 | AI10: =IFERROR(__xludf.DUMMYFUNCTION("IMPORTRANGE(""1Oujo8vUnwFLr-WkmYYfJwaGjmRsDy-q2Aq0vU4BlykA"",""2025-26!R4"")"),874119.3099999998) -> 874119.31 | AJ10: =IFERROR(__xludf.DUMMYFUNCTION("IMPORTRANGE(""1Oujo8vUnwFLr-WkmYYfJwaGjmRsDy-q2Aq0vU4BlykA"",""2025-26!R3"")"),36.0) -> 36 | AK10: =IFERROR(__xludf.DUMMYFUNCTION("IMPORTRANGE(""1Oujo8vUnwFLr-WkmYYfJwaGjmRsDy-q2Aq0vU4BlykA"",""2025-26!S4"")"),1312000.0) -> 1312000 | AL10: =IFERROR(__xludf.DUMMYFUNCTION("IMPORTRANGE(""1Oujo8vUnwFLr-WkmYYfJwaGjmRsDy-q2Aq0vU4BlykA"",""2025-26!S3"")"),116.0) -> 116 | AM10: =IFERROR(__xludf.DUMMYFUNCTION("IMPORTRANGE(""1Oujo8vUnwFLr-WkmYYfJwaGjmRsDy-q2Aq0vU4BlykA"",""2025-26!T4"")"),958979.1399999999) -> 958979.14 | AN10: =IFERROR(__xludf.DUMMYFUNCTION("IMPORTRANGE(""1Oujo8vUnwFLr-WkmYYfJwaGjmRsDy-q2Aq0vU4BlykA"",""2025-26!T3"")"),40.0) -> 40 | AO10: =IFERROR((AP10/AK10),"") -> 0.73267927 | AP10: =IFERROR(__xludf.DUMMYFUNCTION("IMPORTRANGE(""1Oujo8vUnwFLr-WkmYYfJwaGjmRsDy-q2Aq0vU4BlykA"",""2025-26!U4"")"),961275.2000000001) -> 961275.2 | AQ10: =IFERROR(__xludf.DUMMYFUNCTION("IMPORTRANGE(""1Oujo8vUnwFLr-WkmYYfJwaGjmRsDy-q2Aq0vU4BlykA"",""2025-26!U3"")"),40.0) -> 40 | AR10: =IFERROR(__xludf.DUMMYFUNCTION("IMPORTRANGE(""1Oujo8vUnwFLr-WkmYYfJwaGjmRsDy-q2Aq0vU4BlykA"",""2025-26!V4"")"),1330000.0) -> 1330000 | AS10: =IFERROR(__xludf.DUMMYFUNCTION("IMPORTRANGE(""1Oujo8vUnwFLr-WkmYYfJwaGjmRsDy-q2Aq0vU4BlykA"",""2025-26!V3"")"),122.0) -> 122 | AT10: =IFERROR(__xludf.DUMMYFUNCTION("IMPORTRANGE(""1Oujo8vUnwFLr-WkmYYfJwaGjmRsDy-q2Aq0vU4BlykA"",""2025-26!W4"")"),811098.1600000004) -> 811098.16 | AU10: =IFERROR(__xludf.DUMMYFUNCTION("IMPORTRANGE(""1Oujo8vUnwFLr-WkmYYfJwaGjmRsDy-q2Aq0vU4BlykA"",""2025-26!W3"")"),45.0) -> 45 | AV10: =IFERROR((AW10/AR10),"") -> 0.6162202 | AW10: =IFERROR(__xludf.DUMMYFUNCTION("IMPORTRANGE(""1Oujo8vUnwFLr-WkmYYfJwaGjmRsDy-q2Aq0vU4BlykA"",""2025-26!X4"")"),819572.8599999999) -> 819572.86 | AX10: =IFERROR(__xludf.DUMMYFUNCTION("IMPORTRANGE(""1Oujo8vUnwFLr-WkmYYfJwaGjmRsDy-q2Aq0vU4BlykA"",""2025-26!X3"")"),45.0) -> 45 | AY10: =IFERROR(__xludf.DUMMYFUNCTION("IMPORTRANGE(""1Oujo8vUnwFLr-WkmYYfJwaGjmRsDy-q2Aq0vU4BlykA"",""2025-26!Y4"")"),1319000.0) -> 1319000 | AZ10: =IFERROR(__xludf.DUMMYFUNCTION("IMPORTRANGE(""1Oujo8vUnwFLr-WkmYYfJwaGjmRsDy-q2Aq0vU4BlykA"",""2025-26!Y3"")"),122.0) -> 122 | BA10: =IFERROR(__xludf.DUMMYFUNCTION("IMPORTRANGE(""1Oujo8vUnwFLr-WkmYYfJwaGjmRsDy-q2Aq0vU4BlykA"",""2025-26!Z4"")"),1184994.7600000002) -> 1184994.8 | BB10: =IFERROR(__xludf.DUMMYFUNCTION("IMPORTRANGE(""1Oujo8vUnwFLr-WkmYYfJwaGjmRsDy-q2Aq0vU4BlykA"",""2025-26!Z3"")"),45.0) -> 45 | BC10: =IFERROR((BD10/AY10),"") -> 0.90426295 | BD10: =IFERROR(__xludf.DUMMYFUNCTION("IMPORTRANGE(""1Oujo8vUnwFLr-WkmYYfJwaGjmRsDy-q2Aq0vU4BlykA"",""2025-26!AA4"")"),1192722.8299999998) -> 1192722.8 | BE10: =IFERROR(__xludf.DUMMYFUNCTION("IMPORTRANGE(""1Oujo8vUnwFLr-WkmYYfJwaGjmRsDy-q2Aq0vU4BlykA"",""2025-26!AA3"")"),45.0) -> 45 | BF10: =IFERROR(__xludf.DUMMYFUNCTION("IMPORTRANGE(""1Oujo8vUnwFLr-WkmYYfJwaGjmRsDy-q2Aq0vU4BlykA"",""2025-26!AB4"")"),1316000.0) -> 1316000 | BG10: =IFERROR(__xludf.DUMMYFUNCTION("IMPORTRANGE(""1Oujo8vUnwFLr-WkmYYfJwaGjmRsDy-q2Aq0vU4BlykA"",""2025-26!AB3"")"),121.0) -> 121 | BH10: =IFERROR(__xludf.DUMMYFUNCTION("IMPORTRANGE(""1Oujo8vUnwFLr-WkmYYfJwaGjmRsDy-q2Aq0vU4BlykA"",""2025-26!AC4"")"),1080876.61) -> 1080876.6 | BI10: =IFERROR(__xludf.DUMMYFUNCTION("IMPORTRANGE(""1Oujo8vUnwFLr-WkmYYfJwaGjmRsDy-q2Aq0vU4BlykA"",""2025-26!AC3"")"),47.0) -> 47 | BJ10: =IFERROR((BK10/BF10),"") -> 0.88111743 | BK10: =IFERROR(__xludf.DUMMYFUNCTION("IMPORTRANGE(""1Oujo8vUnwFLr-WkmYYfJwaGjmRsDy-q2Aq0vU4BlykA"",""2025-26!AD4"")"),1159550.5399999998) -> 1159550.5 | BL10: =IFERROR(__xludf.DUMMYFUNCTION("IMPORTRANGE(""1Oujo8vUnwFLr-WkmYYfJwaGjmRsDy-q2Aq0vU4BlykA"",""2025-26!AD3"")"),48.0) -> 48 | BM10: =IFERROR(__xludf.DUMMYFUNCTION("IMPORTRANGE(""1Oujo8vUnwFLr-WkmYYfJwaGjmRsDy-q2Aq0vU4BlykA"",""2025-26!AE4"")"),1322000.0) -> 1322000 | BN10: =IFERROR(__xludf.DUMMYFUNCTION("IMPORTRANGE(""1Oujo8vUnwFLr-WkmYYfJwaGjmRsDy-q2Aq0vU4BlykA"",""2025-26!AE3"")"),121.0) -> 121 | BO10: =IFERROR(__xludf.DUMMYFUNCTION("IMPORTRANGE(""1Oujo8vUnwFLr-WkmYYfJwaGjmRsDy-q2Aq0vU4BlykA"",""2025-26!AF4"")"),916671.9600000001) -> 916671.96 | BP10: =IFERROR(__xludf.DUMMYFUNCTION("IMPORTRANGE(""1Oujo8vUnwFLr-WkmYYfJwaGjmRsDy-q2Aq0vU4BlykA"",""2025-26!AF3"")"),39.0) -> 39 | BQ10: =IFERROR((BR10/BM10),"") -> 0.64042607 | BR10: =IFERROR(__xludf.DUMMYFUNCTION("IMPORTRANGE(""1Oujo8vUnwFLr-WkmYYfJwaGjmRsDy-q2Aq0vU4BlykA"",""2025-26!AG4"")"),846643.2599999999) -> 846643.26 | BS10: =IFERROR(__xludf.DUMMYFUNCTION("IMPORTRANGE(""1Oujo8vUnwFLr-WkmYYfJwaGjmRsDy-q2Aq0vU4BlykA"",""2025-26!AG3"")"),38.0) -> 38 | BT10: =IFERROR(__xludf.DUMMYFUNCTION("IMPORTRANGE(""1Oujo8vUnwFLr-WkmYYfJwaGjmRsDy-q2Aq0vU4BlykA"",""2025-26!AH4"")"),1332000.0) -> 1332000 | BU10: =IFERROR(__xludf.DUMMYFUNCTION("IMPORTRANGE(""1Oujo8vUnwFLr-WkmYYfJwaGjmRsDy-q2Aq0vU4BlykA"",""2025-26!AH3"")"),104.0) -> 104 | BV10: =IFERROR(__xludf.DUMMYFUNCTION("IMPORTRANGE(""1Oujo8vUnwFLr-WkmYYfJwaGjmRsDy-q2Aq0vU4BlykA"",""2025-26!AI4"")"),942623.2599999997) -> 942623.26 | BW10: =IFERROR(__xludf.DUMMYFUNCTION("IMPORTRANGE(""1Oujo8vUnwFLr-WkmYYfJwaGjmRsDy-q2Aq0vU4BlykA"",""2025-26!AI3"")"),31.0) -> 31 | BX10: =IFERROR((BY10/BT10),"") -> 0.70997222 | BY10: =IFERROR(__xludf.DUMMYFUNCTION("IMPORTRANGE(""1Oujo8vUnwFLr-WkmYYfJwaGjmRsDy-q2Aq0vU4BlykA"",""2025-26!AJ4"")"),945683.0000000002) -> 945683 | BZ10: =IFERROR(__xludf.DUMMYFUNCTION("IMPORTRANGE(""1Oujo8vUnwFLr-WkmYYfJwaGjmRsDy-q2Aq0vU4BlykA"",""2025-26!AJ3"")"),31.0) -> 31 | CA10: =IFERROR(__xludf.DUMMYFUNCTION("IMPORTRANGE(""1Oujo8vUnwFLr-WkmYYfJwaGjmRsDy-q2Aq0vU4BlykA"",""2025-26!AK4"")"),1319000.0) -> 1319000 | CB10: =IFERROR(__xludf.DUMMYFUNCTION("IMPORTRANGE(""1Oujo8vUnwFLr-WkmYYfJwaGjmRsDy-q2Aq0vU4BlykA"",""2025-26!AK3"")"),102.0) -> 102 | CC10: =IFERROR(__xludf.DUMMYFUNCTION("IMPORTRANGE(""1Oujo8vUnwFLr-WkmYYfJwaGjmRsDy-q2Aq0vU4BlykA"",""2025-26!AL4"")"),926198.1900000001) -> 926198.19 | CD10: =IFERROR(__xludf.DUMMYFUNCTION("IMPORTRANGE(""1Oujo8vUnwFLr-WkmYYfJwaGjmRsDy-q2Aq0vU4BlykA"",""2025-26!AL3"")"),39.0) -> 39 | CE10: =IFERROR((CF10/CA10),"") -> 0.67615102 | CF10: =IFERROR(__xludf.DUMMYFUNCTION("IMPORTRANGE(""1Oujo8vUnwFLr-WkmYYfJwaGjmRsDy-q2Aq0vU4BlykA"",""2025-26!AM4"")"),891843.2000000001) -> 891843.2 | CG10: =IFERROR(__xludf.DUMMYFUNCTION("IMPORTRANGE(""1Oujo8vUnwFLr-WkmYYfJwaGjmRsDy-q2Aq0vU4BlykA"",""2025-26!AM3"")"),38.0) -> 38 | CH10: =IFERROR(__xludf.DUMMYFUNCTION("IMPORTRANGE(""1Oujo8vUnwFLr-WkmYYfJwaGjmRsDy-q2Aq0vU4BlykA"",""2025-26!AN4"")"),1323000.0) -> 1323000 | CI10: =IFERROR(__xludf.DUMMYFUNCTION("IMPORTRANGE(""1Oujo8vUnwFLr-WkmYYfJwaGjmRsDy-q2Aq0vU4BlykA"",""2025-26!AN3"")"),102.0) -> 102 | CJ10: =IFERROR(__xludf.DUMMYFUNCTION("IMPORTRANGE(""1Oujo8vUnwFLr-WkmYYfJwaGjmRsDy-q2Aq0vU4BlykA"",""2025-26!AO4"")"),842725.1900000004) -> 842725.19 | CK10: =IFERROR(__xludf.DUMMYFUNCTION("IMPORTRANGE(""1Oujo8vUnwFLr-WkmYYfJwaGjmRsDy-q2Aq0vU4BlykA"",""2025-26!AO3"")"),35.0) -> 35 | CL10: =IFERROR((CM10/CH10),"") -> 0.63824714 | CM10: =IFERROR(__xludf.DUMMYFUNCTION("IMPORTRANGE(""1Oujo8vUnwFLr-WkmYYfJwaGjmRsDy-q2Aq0vU4BlykA"",""2025-26!AP4"")"),844400.9599999998) -> 844400.96 | CN10: =IFERROR(__xludf.DUMMYFUNCTION("IMPORTRANGE(""1Oujo8vUnwFLr-WkmYYfJwaGjmRsDy-q2Aq0vU4BlykA"",""2025-26!AP3"")"),35.0) -> 35 | CO10: =IFERROR(__xludf.DUMMYFUNCTION("IMPORTRANGE(""1Oujo8vUnwFLr-WkmYYfJwaGjmRsDy-q2Aq0vU4BlykA"",""2025-26!AQ4"")"),1314000.0) -> 1314000 | CP10: =IFERROR(__xludf.DUMMYFUNCTION("IMPORTRANGE(""1Oujo8vUnwFLr-WkmYYfJwaGjmRsDy-q2Aq0vU4BlykA"",""2025-26!AQ3"")"),103.0) -> 103 | CQ10: =IFERROR(__xludf.DUMMYFUNCTION("IMPORTRANGE(""1Oujo8vUnwFLr-WkmYYfJwaGjmRsDy-q2Aq0vU4BlykA"",""2025-26!AR4"")"),1033032.84) -> 1033032.8 | CR10: =IFERROR(__xludf.DUMMYFUNCTION("IMPORTRANGE(""1Oujo8vUnwFLr-WkmYYfJwaGjmRsDy-q2Aq0vU4BlykA"",""2025-26!AR3"")"),37.0) -> 37 | CS10: =IFERROR((CT10/CO10),"") -> 0.78494067 | CT10: =IFERROR(__xludf.DUMMYFUNCTION("IMPORTRANGE(""1Oujo8vUnwFLr-WkmYYfJwaGjmRsDy-q2Aq0vU4BlykA"",""2025-26!AS4"")"),1031412.04) -> 1031412 | CU10: =IFERROR(__xludf.DUMMYFUNCTION("IMPORTRANGE(""1Oujo8vUnwFLr-WkmYYfJwaGjmRsDy-q2Aq0vU4BlykA"",""2025-26!AS3"")"),37.0) -> 37 | CV10: Delhi
A11: Anant Singh | C11: Rinku | D11: Moradabad | E11: 6398490183 | F11: 45568 | I11: =VLOOKUP($C11,Data!$C:$BV,72,0) -> 30405 | J11: =1200000+200000 -> 1400000 | K11: =IFERROR(__xludf.DUMMYFUNCTION("IMPORTRANGE(""1LJGS53NCp-odxIXkmSORKxH8_UeQo5bY4expBVdkFdk"",""2025-26!A3"")"),30.0) -> 30 | L11: =IFERROR(__xludf.DUMMYFUNCTION("IMPORTRANGE(""1LJGS53NCp-odxIXkmSORKxH8_UeQo5bY4expBVdkFdk"",""2025-26!G4"")"),1.56E7) -> 15600000 | M11: =R11+Y11+AF11+AM11+AT11+BA11+BH11+BO11+BV11+CC11+CJ11+CQ11 -> 10993607 | N11: =O11/L11 -> 0.72929481 | O11: =U11+AB11+AI11+AP11+AW11+BD11+BK11+BR11+BY11+CF11+CM11+CT11 -> 11376999 | P11: =IFERROR(__xludf.DUMMYFUNCTION("IMPORTRANGE(""1LJGS53NCp-odxIXkmSORKxH8_UeQo5bY4expBVdkFdk"",""2025-26!J4"")"),1165000.0) -> 1165000 | Q11: =IFERROR(__xludf.DUMMYFUNCTION("IMPORTRANGE(""1LJGS53NCp-odxIXkmSORKxH8_UeQo5bY4expBVdkFdk"",""2025-26!J3"")"),27.0) -> 27 | R11: =IFERROR(__xludf.DUMMYFUNCTION("IMPORTRANGE(""1LJGS53NCp-odxIXkmSORKxH8_UeQo5bY4expBVdkFdk"",""2025-26!K4"")"),491517.30000000005) -> 491517.3 | S11: =IFERROR(__xludf.DUMMYFUNCTION("IMPORTRANGE(""1LJGS53NCp-odxIXkmSORKxH8_UeQo5bY4expBVdkFdk"",""2025-26!K3"")"),6.0) -> 6 | T11: =IFERROR((U11/P11),"") -> 0.559103 | U11: =IFERROR(__xludf.DUMMYFUNCTION("IMPORTRANGE(""1LJGS53NCp-odxIXkmSORKxH8_UeQo5bY4expBVdkFdk"",""2025-26!L4"")"),651355.0) -> 651355 | V11: =IFERROR(__xludf.DUMMYFUNCTION("IMPORTRANGE(""1LJGS53NCp-odxIXkmSORKxH8_UeQo5bY4expBVdkFdk"",""2025-26!L3"")"),6.0) -> 6 | W11: =IFERROR(__xludf.DUMMYFUNCTION("IMPORTRANGE(""1LJGS53NCp-odxIXkmSORKxH8_UeQo5bY4expBVdkFdk"",""2025-26!m4"")"),1464000.0) -> 1464000 | X11: =IFERROR(__xludf.DUMMYFUNCTION("IMPORTRANGE(""1LJGS53NCp-odxIXkmSORKxH8_UeQo5bY4expBVdkFdk"",""2025-26!m3"")"),26.0) -> 26 | Y11: =IFERROR(__xludf.DUMMYFUNCTION("IMPORTRANGE(""1LJGS53NCp-odxIXkmSORKxH8_UeQo5bY4expBVdkFdk"",""2025-26!N4"")"),1229076.0000000002) -> 1229076 | Z11: =IFERROR(__xludf.DUMMYFUNCTION("IMPORTRANGE(""1LJGS53NCp-odxIXkmSORKxH8_UeQo5bY4expBVdkFdk"",""2025-26!N3"")"),19.0) -> 19 | AA11: =IFERROR((AB11/W11),"") -> 0.87387227 | AB11: =IFERROR(__xludf.DUMMYFUNCTION("IMPORTRANGE(""1LJGS53NCp-odxIXkmSORKxH8_UeQo5bY4expBVdkFdk"",""2025-26!O4"")"),1279349.0) -> 1279349 | AC11: =IFERROR(__xludf.DUMMYFUNCTION("IMPORTRANGE(""1LJGS53NCp-odxIXkmSORKxH8_UeQo5bY4expBVdkFdk"",""2025-26!O3"")"),19.0) -> 19 | AD11: =IFERROR(__xludf.DUMMYFUNCTION("IMPORTRANGE(""1LJGS53NCp-odxIXkmSORKxH8_UeQo5bY4expBVdkFdk"",""2025-26!P4"")"),1398000.0) -> 1398000 | AE11: =IFERROR(__xludf.DUMMYFUNCTION("IMPORTRANGE(""1LJGS53NCp-odxIXkmSORKxH8_UeQo5bY4expBVdkFdk"",""2025-26!P3"")"),27.0) -> 27 | AF11: =IFERROR(__xludf.DUMMYFUNCTION("IMPORTRANGE(""1LJGS53NCp-odxIXkmSORKxH8_UeQo5bY4expBVdkFdk"",""2025-26!Q4"")"),859214.5699999998) -> 859214.57 | AG11: =IFERROR(__xludf.DUMMYFUNCTION("IMPORTRANGE(""1LJGS53NCp-odxIXkmSORKxH8_UeQo5bY4expBVdkFdk"",""2025-26!Q3"")"),13.0) -> 13 | AH11: =IFERROR((AI11/AD11),"") -> 0.71505436 | AI11: =IFERROR(__xludf.DUMMYFUNCTION("IMPORTRANGE(""1LJGS53NCp-odxIXkmSORKxH8_UeQo5bY4expBVdkFdk"",""2025-26!R4"")"),999646.0) -> 999646 | AJ11: =IFERROR(__xludf.DUMMYFUNCTION("IMPORTRANGE(""1LJGS53NCp-odxIXkmSORKxH8_UeQo5bY4expBVdkFdk"",""2025-26!R3"")"),14.0) -> 14 | AK11: =IFERROR(__xludf.DUMMYFUNCTION("IMPORTRANGE(""1LJGS53NCp-odxIXkmSORKxH8_UeQo5bY4expBVdkFdk"",""2025-26!S4"")"),1355000.0) -> 1355000 | AL11: =IFERROR(__xludf.DUMMYFUNCTION("IMPORTRANGE(""1LJGS53NCp-odxIXkmSORKxH8_UeQo5bY4expBVdkFdk"",""2025-26!S3"")"),27.0) -> 27 | AM11: =IFERROR(__xludf.DUMMYFUNCTION("IMPORTRANGE(""1LJGS53NCp-odxIXkmSORKxH8_UeQo5bY4expBVdkFdk"",""2025-26!T4"")"),940606.2599999998) -> 940606.26 | AN11: =IFERROR(__xludf.DUMMYFUNCTION("IMPORTRANGE(""1LJGS53NCp-odxIXkmSORKxH8_UeQo5bY4expBVdkFdk"",""2025-26!T3"")"),16.0) -> 16 | AO11: =IFERROR((AP11/AK11),"") -> 0.7383107 | AP11: =IFERROR(__xludf.DUMMYFUNCTION("IMPORTRANGE(""1LJGS53NCp-odxIXkmSORKxH8_UeQo5bY4expBVdkFdk"",""2025-26!U4"")"),1000411.0) -> 1000411 | AQ11: =IFERROR(__xludf.DUMMYFUNCTION("IMPORTRANGE(""1LJGS53NCp-odxIXkmSORKxH8_UeQo5bY4expBVdkFdk"",""2025-26!U3"")"),16.0) -> 16 | AR11: =IFERROR(__xludf.DUMMYFUNCTION("IMPORTRANGE(""1LJGS53NCp-odxIXkmSORKxH8_UeQo5bY4expBVdkFdk"",""2025-26!V4"")"),1375000.0) -> 1375000 | AS11: =IFERROR(__xludf.DUMMYFUNCTION("IMPORTRANGE(""1LJGS53NCp-odxIXkmSORKxH8_UeQo5bY4expBVdkFdk"",""2025-26!V3"")"),27.0) -> 27 | AT11: =IFERROR(__xludf.DUMMYFUNCTION("IMPORTRANGE(""1LJGS53NCp-odxIXkmSORKxH8_UeQo5bY4expBVdkFdk"",""2025-26!W4"")"),942006.9800000001) -> 942006.98 | AU11: =IFERROR(__xludf.DUMMYFUNCTION("IMPORTRANGE(""1LJGS53NCp-odxIXkmSORKxH8_UeQo5bY4expBVdkFdk"",""2025-26!W3"")"),14.0) -> 14 | AV11: =IFERROR((AW11/AR11),"") -> 0.69005891 | AW11: =IFERROR(__xludf.DUMMYFUNCTION("IMPORTRANGE(""1LJGS53NCp-odxIXkmSORKxH8_UeQo5bY4expBVdkFdk"",""2025-26!X4"")"),948831.0) -> 948831 | AX11: =IFERROR(__xludf.DUMMYFUNCTION("IMPORTRANGE(""1LJGS53NCp-odxIXkmSORKxH8_UeQo5bY4expBVdkFdk"",""2025-26!X3"")"),14.0) -> 14 | AY11: =IFERROR(__xludf.DUMMYFUNCTION("IMPORTRANGE(""1LJGS53NCp-odxIXkmSORKxH8_UeQo5bY4expBVdkFdk"",""2025-26!Y4"")"),1298000.0) -> 1298000 | AZ11: =IFERROR(__xludf.DUMMYFUNCTION("IMPORTRANGE(""1LJGS53NCp-odxIXkmSORKxH8_UeQo5bY4expBVdkFdk"",""2025-26!Y3"")"),27.0) -> 27 | BA11: =IFERROR(__xludf.DUMMYFUNCTION("IMPORTRANGE(""1LJGS53NCp-odxIXkmSORKxH8_UeQo5bY4expBVdkFdk"",""2025-26!Z4"")"),859656.6700000002) -> 859656.67 | BB11: =IFERROR(__xludf.DUMMYFUNCTION("IMPORTRANGE(""1LJGS53NCp-odxIXkmSORKxH8_UeQo5bY4expBVdkFdk"",""2025-26!Z3"")"),14.0) -> 14 | BC11: =IFERROR((BD11/AY11),"") -> 0.66229584 | BD11: =IFERROR(__xludf.DUMMYFUNCTION("IMPORTRANGE(""1LJGS53NCp-odxIXkmSORKxH8_UeQo5bY4expBVdkFdk"",""2025-26!AA4"")"),859660.0) -> 859660 | BE11: =IFERROR(__xludf.DUMMYFUNCTION("IMPORTRANGE(""1LJGS53NCp-odxIXkmSORKxH8_UeQo5bY4expBVdkFdk"",""2025-26!AA3"")"),14.0) -> 14 | BF11: =IFERROR(__xludf.DUMMYFUNCTION("IMPORTRANGE(""1LJGS53NCp-odxIXkmSORKxH8_UeQo5bY4expBVdkFdk"",""2025-26!AB4"")"),1220000.0) -> 1220000 | BG11: =IFERROR(__xludf.DUMMYFUNCTION("IMPORTRANGE(""1LJGS53NCp-odxIXkmSORKxH8_UeQo5bY4expBVdkFdk"",""2025-26!AB3"")"),27.0) -> 27 | BH11: =IFERROR(__xludf.DUMMYFUNCTION("IMPORTRANGE(""1LJGS53NCp-odxIXkmSORKxH8_UeQo5bY4expBVdkFdk"",""2025-26!AC4"")"),804507.96) -> 804507.96 | BI11: =IFERROR(__xludf.DUMMYFUNCTION("IMPORTRANGE(""1LJGS53NCp-odxIXkmSORKxH8_UeQo5bY4expBVdkFdk"",""2025-26!AC3"")"),11.0) -> 11 | BJ11: =IFERROR((BK11/BF11),"") -> 0.69172787 | BK11: =IFERROR(__xludf.DUMMYFUNCTION("IMPORTRANGE(""1LJGS53NCp-odxIXkmSORKxH8_UeQo5bY4expBVdkFdk"",""2025-26!AD4"")"),843908.0) -> 843908 | BL11: =IFERROR(__xludf.DUMMYFUNCTION("IMPORTRANGE(""1LJGS53NCp-odxIXkmSORKxH8_UeQo5bY4expBVdkFdk"",""2025-26!AD3"")"),11.0) -> 11 | BM11: =IFERROR(__xludf.DUMMYFUNCTION("IMPORTRANGE(""1LJGS53NCp-odxIXkmSORKxH8_UeQo5bY4expBVdkFdk"",""2025-26!AE4"")"),1475000.0) -> 1475000 | BN11: =IFERROR(__xludf.DUMMYFUNCTION("IMPORTRANGE(""1LJGS53NCp-odxIXkmSORKxH8_UeQo5bY4expBVdkFdk"",""2025-26!AE3"")"),27.0) -> 27 | BO11: =IFERROR(__xludf.DUMMYFUNCTION("IMPORTRANGE(""1LJGS53NCp-odxIXkmSORKxH8_UeQo5bY4expBVdkFdk"",""2025-26!AF4"")"),896959.07) -> 896959.07 | BP11: =IFERROR(__xludf.DUMMYFUNCTION("IMPORTRANGE(""1LJGS53NCp-odxIXkmSORKxH8_UeQo5bY4expBVdkFdk"",""2025-26!AF3"")"),15.0) -> 15 | BQ11: =IFERROR((BR11/BM11),"") -> 0.57509424 | BR11: =IFERROR(__xludf.DUMMYFUNCTION("IMPORTRANGE(""1LJGS53NCp-odxIXkmSORKxH8_UeQo5bY4expBVdkFdk"",""2025-26!AG4"")"),848264.0) -> 848264 | BS11: =IFERROR(__xludf.DUMMYFUNCTION("IMPORTRANGE(""1LJGS53NCp-odxIXkmSORKxH8_UeQo5bY4expBVdkFdk"",""2025-26!AG3"")"),14.0) -> 14 | BT11: =IFERROR(__xludf.DUMMYFUNCTION("IMPORTRANGE(""1LJGS53NCp-odxIXkmSORKxH8_UeQo5bY4expBVdkFdk"",""2025-26!AH4"")"),1545000.0) -> 1545000 | BU11: =IFERROR(__xludf.DUMMYFUNCTION("IMPORTRANGE(""1LJGS53NCp-odxIXkmSORKxH8_UeQo5bY4expBVdkFdk"",""2025-26!AH3"")"),27.0) -> 27 | BV11: =IFERROR(__xludf.DUMMYFUNCTION("IMPORTRANGE(""1LJGS53NCp-odxIXkmSORKxH8_UeQo5bY4expBVdkFdk"",""2025-26!AI4"")"),880052.94) -> 880052.94 | BW11: =IFERROR(__xludf.DUMMYFUNCTION("IMPORTRANGE(""1LJGS53NCp-odxIXkmSORKxH8_UeQo5bY4expBVdkFdk"",""2025-26!AI3"")"),11.0) -> 11 | BX11: =IFERROR((BY11/BT11),"") -> 0.62162265 | BY11: =IFERROR(__xludf.DUMMYFUNCTION("IMPORTRANGE(""1LJGS53NCp-odxIXkmSORKxH8_UeQo5bY4expBVdkFdk"",""2025-26!AJ4"")"),960407.0) -> 960407 | BZ11: =IFERROR(__xludf.DUMMYFUNCTION("IMPORTRANGE(""1LJGS53NCp-odxIXkmSORKxH8_UeQo5bY4expBVdkFdk"",""2025-26!AJ3"")"),11.0) -> 11 | CA11: =IFERROR(__xludf.DUMMYFUNCTION("IMPORTRANGE(""1LJGS53NCp-odxIXkmSORKxH8_UeQo5bY4expBVdkFdk"",""2025-26!AK4"")"),1610000.0) -> 1610000 | CB11: =IFERROR(__xludf.DUMMYFUNCTION("IMPORTRANGE(""1LJGS53NCp-odxIXkmSORKxH8_UeQo5bY4expBVdkFdk"",""2025-26!AK3"")"),29.0) -> 29 | CC11: =IFERROR(__xludf.DUMMYFUNCTION("IMPORTRANGE(""1LJGS53NCp-odxIXkmSORKxH8_UeQo5bY4expBVdkFdk"",""2025-26!AL4"")"),982861.73) -> 982861.73 | CD11: =IFERROR(__xludf.DUMMYFUNCTION("IMPORTRANGE(""1LJGS53NCp-odxIXkmSORKxH8_UeQo5bY4expBVdkFdk"",""2025-26!AL3"")"),14.0) -> 14 | CE11: =IFERROR((CF11/CA11),"") -> 0.61835839 | CF11: =IFERROR(__xludf.DUMMYFUNCTION("IMPORTRANGE(""1LJGS53NCp-odxIXkmSORKxH8_UeQo5bY4expBVdkFdk"",""2025-26!AM4"")"),995557.0) -> 995557 | CG11: =IFERROR(__xludf.DUMMYFUNCTION("IMPORTRANGE(""1LJGS53NCp-odxIXkmSORKxH8_UeQo5bY4expBVdkFdk"",""2025-26!AM3"")"),14.0) -> 14 | CH11: =IFERROR(__xludf.DUMMYFUNCTION("IMPORTRANGE(""1LJGS53NCp-odxIXkmSORKxH8_UeQo5bY4expBVdkFdk"",""2025-26!AN4"")"),1709000.0) -> 1709000 | CI11: =IFERROR(__xludf.DUMMYFUNCTION("IMPORTRANGE(""1LJGS53NCp-odxIXkmSORKxH8_UeQo5bY4expBVdkFdk"",""2025-26!AN3"")"),29.0) -> 29 | CJ11: =IFERROR(__xludf.DUMMYFUNCTION("IMPORTRANGE(""1LJGS53NCp-odxIXkmSORKxH8_UeQo5bY4expBVdkFdk"",""2025-26!AO4"")"),888212.03) -> 888212.03 | CK11: =IFERROR(__xludf.DUMMYFUNCTION("IMPORTRANGE(""1LJGS53NCp-odxIXkmSORKxH8_UeQo5bY4expBVdkFdk"",""2025-26!AO3"")"),14.0) -> 14 | CL11: =IFERROR((CM11/CH11),"") -> 0.54021416 | CM11: =IFERROR(__xludf.DUMMYFUNCTION("IMPORTRANGE(""1LJGS53NCp-odxIXkmSORKxH8_UeQo5bY4expBVdkFdk"",""2025-26!AP4"")"),923226.0) -> 923226 | CN11: =IFERROR(__xludf.DUMMYFUNCTION("IMPORTRANGE(""1LJGS53NCp-odxIXkmSORKxH8_UeQo5bY4expBVdkFdk"",""2025-26!AP3"")"),14.0) -> 14 | CO11: =IFERROR(__xludf.DUMMYFUNCTION("IMPORTRANGE(""1LJGS53NCp-odxIXkmSORKxH8_UeQo5bY4expBVdkFdk"",""2025-26!AQ4"")"),1690000.0) -> 1690000 | CP11: =IFERROR(__xludf.DUMMYFUNCTION("IMPORTRANGE(""1LJGS53NCp-odxIXkmSORKxH8_UeQo5bY4expBVdkFdk"",""2025-26!AQ3"")"),29.0) -> 29 | CQ11: =IFERROR(__xludf.DUMMYFUNCTION("IMPORTRANGE(""1LJGS53NCp-odxIXkmSORKxH8_UeQo5bY4expBVdkFdk"",""2025-26!AR4"")"),1218935.5999999999) -> 1218935.6 | CR11: =IFERROR(__xludf.DUMMYFUNCTION("IMPORTRANGE(""1LJGS53NCp-odxIXkmSORKxH8_UeQo5bY4expBVdkFdk"",""2025-26!AR3"")"),17.0) -> 17 | CS11: =IFERROR((CT11/CO11),"") -> 0.63099704 | CT11: =IFERROR(__xludf.DUMMYFUNCTION("IMPORTRANGE(""1LJGS53NCp-odxIXkmSORKxH8_UeQo5bY4expBVdkFdk"",""2025-26!AS4"")"),1066385.0) -> 1066385 | CU11: =IFERROR(__xludf.DUMMYFUNCTION("IMPORTRANGE(""1LJGS53NCp-odxIXkmSORKxH8_UeQo5bY4expBVdkFdk"",""2025-26!AS3"")"),16.0) -> 16 | CV11: West U.P
A12: Anant Singh | C12: Ashutosh Kumar (Rudrapur) | D12: Rudrapur | E12: 9319865478 | F12: 45658 | I12: =VLOOKUP($C12,Data!$C:$BV,72,0) -> 31455 | J12: 1200000 | K12: =IFERROR(__xludf.DUMMYFUNCTION("IMPORTRANGE(""13EYfcAewqPPQ83PA3ta2L46h2GIwi9k-mw8zx8HuEws"",""2025-26!A3"")"),88.0) -> 88 | L12: =IFERROR(__xludf.DUMMYFUNCTION("IMPORTRANGE(""13EYfcAewqPPQ83PA3ta2L46h2GIwi9k-mw8zx8HuEws"",""2025-26!G4"")"),1.4E7) -> 14000000 | M12: =R12+Y12+AF12+AM12+AT12+BA12+BH12+BO12+BV12+CC12+CJ12+CQ12 -> 7218770.5 | N12: =O12/L12 -> 0.50876821 | O12: =U12+AB12+AI12+AP12+AW12+BD12+BK12+BR12+BY12+CF12+CM12+CT12 -> 7122755 | P12: =IFERROR(__xludf.DUMMYFUNCTION("IMPORTRANGE(""13EYfcAewqPPQ83PA3ta2L46h2GIwi9k-mw8zx8HuEws"",""2025-26!J4"")"),227000.0) -> 227000 | Q12: =IFERROR(__xludf.DUMMYFUNCTION("IMPORTRANGE(""13EYfcAewqPPQ83PA3ta2L46h2GIwi9k-mw8zx8HuEws"",""2025-26!J3"")"),6.0) -> 6 | R12: =IFERROR(__xludf.DUMMYFUNCTION("IMPORTRANGE(""13EYfcAewqPPQ83PA3ta2L46h2GIwi9k-mw8zx8HuEws"",""2025-26!K4"")"),70360.04000000001) -> 70360.04 | S12: =IFERROR(__xludf.DUMMYFUNCTION("IMPORTRANGE(""13EYfcAewqPPQ83PA3ta2L46h2GIwi9k-mw8zx8HuEws"",""2025-26!K3"")"),8.0) -> 8 | T12: =IFERROR((U12/P12),"") -> 0.34500881 | U12: =IFERROR(__xludf.DUMMYFUNCTION("IMPORTRANGE(""13EYfcAewqPPQ83PA3ta2L46h2GIwi9k-mw8zx8HuEws"",""2025-26!L4"")"),78317.0) -> 78317 | V12: =IFERROR(__xludf.DUMMYFUNCTION("IMPORTRANGE(""13EYfcAewqPPQ83PA3ta2L46h2GIwi9k-mw8zx8HuEws"",""2025-26!L3"")"),9.0) -> 9 | W12: =IFERROR(__xludf.DUMMYFUNCTION("IMPORTRANGE(""13EYfcAewqPPQ83PA3ta2L46h2GIwi9k-mw8zx8HuEws"",""2025-26!m4"")"),450000.0) -> 450000 | X12: =IFERROR(__xludf.DUMMYFUNCTION("IMPORTRANGE(""13EYfcAewqPPQ83PA3ta2L46h2GIwi9k-mw8zx8HuEws"",""2025-26!m3"")"),17.0) -> 17 | Y12: =IFERROR(__xludf.DUMMYFUNCTION("IMPORTRANGE(""13EYfcAewqPPQ83PA3ta2L46h2GIwi9k-mw8zx8HuEws"",""2025-26!N4"")"),104245.26) -> 104245.26 | Z12: =IFERROR(__xludf.DUMMYFUNCTION("IMPORTRANGE(""13EYfcAewqPPQ83PA3ta2L46h2GIwi9k-mw8zx8HuEws"",""2025-26!N3"")"),9.0) -> 9 | AA12: =IFERROR((AB12/W12),"") -> 0.43310667 | AB12: =IFERROR(__xludf.DUMMYFUNCTION("IMPORTRANGE(""13EYfcAewqPPQ83PA3ta2L46h2GIwi9k-mw8zx8HuEws"",""2025-26!O4"")"),194898.0) -> 194898 | AC12: =IFERROR(__xludf.DUMMYFUNCTION("IMPORTRANGE(""13EYfcAewqPPQ83PA3ta2L46h2GIwi9k-mw8zx8HuEws"",""2025-26!O3"")"),17.0) -> 17 | AD12: =IFERROR(__xludf.DUMMYFUNCTION("IMPORTRANGE(""13EYfcAewqPPQ83PA3ta2L46h2GIwi9k-mw8zx8HuEws"",""2025-26!P4"")"),1400000.0) -> 1400000 | AE12: =IFERROR(__xludf.DUMMYFUNCTION("IMPORTRANGE(""13EYfcAewqPPQ83PA3ta2L46h2GIwi9k-mw8zx8HuEws"",""2025-26!P3"")"),25.0) -> 25 | AF12: =IFERROR(__xludf.DUMMYFUNCTION("IMPORTRANGE(""13EYfcAewqPPQ83PA3ta2L46h2GIwi9k-mw8zx8HuEws"",""2025-26!Q4"")"),404471.44) -> 404471.44 | AG12: =IFERROR(__xludf.DUMMYFUNCTION("IMPORTRANGE(""13EYfcAewqPPQ83PA3ta2L46h2GIwi9k-mw8zx8HuEws"",""2025-26!Q3"")"),14.0) -> 14 | AH12: =IFERROR((AI12/AD12),"") -> 0.349225 | AI12: =IFERROR(__xludf.DUMMYFUNCTION("IMPORTRANGE(""13EYfcAewqPPQ83PA3ta2L46h2GIwi9k-mw8zx8HuEws"",""2025-26!R4"")"),488915.0) -> 488915 | AJ12: =IFERROR(__xludf.DUMMYFUNCTION("IMPORTRANGE(""13EYfcAewqPPQ83PA3ta2L46h2GIwi9k-mw8zx8HuEws"",""2025-26!R3"")"),22.0) -> 22 | AK12: =IFERROR(__xludf.DUMMYFUNCTION("IMPORTRANGE(""13EYfcAewqPPQ83PA3ta2L46h2GIwi9k-mw8zx8HuEws"",""2025-26!S4"")"),1335000.0) -> 1335000 | AL12: =IFERROR(__xludf.DUMMYFUNCTION("IMPORTRANGE(""13EYfcAewqPPQ83PA3ta2L46h2GIwi9k-mw8zx8HuEws"",""2025-26!S3"")"),29.0) -> 29 | AM12: =IFERROR(__xludf.DUMMYFUNCTION("IMPORTRANGE(""13EYfcAewqPPQ83PA3ta2L46h2GIwi9k-mw8zx8HuEws"",""2025-26!T4"")"),627452.26) -> 627452.26 | AN12: =IFERROR(__xludf.DUMMYFUNCTION("IMPORTRANGE(""13EYfcAewqPPQ83PA3ta2L46h2GIwi9k-mw8zx8HuEws"",""2025-26!T3"")"),19.0) -> 19 | AO12: =IFERROR((AP12/AK12),"") -> 0.27222172 | AP12: =IFERROR(__xludf.DUMMYFUNCTION("IMPORTRANGE(""13EYfcAewqPPQ83PA3ta2L46h2GIwi9k-mw8zx8HuEws"",""2025-26!U4"")"),363416.0) -> 363416 | AQ12: =IFERROR(__xludf.DUMMYFUNCTION("IMPORTRANGE(""13EYfcAewqPPQ83PA3ta2L46h2GIwi9k-mw8zx8HuEws"",""2025-26!U3"")"),19.0) -> 19 | AR12: =IFERROR(__xludf.DUMMYFUNCTION("IMPORTRANGE(""13EYfcAewqPPQ83PA3ta2L46h2GIwi9k-mw8zx8HuEws"",""2025-26!V4"")"),1345000.0) -> 1345000 | AS12: =IFERROR(__xludf.DUMMYFUNCTION("IMPORTRANGE(""13EYfcAewqPPQ83PA3ta2L46h2GIwi9k-mw8zx8HuEws"",""2025-26!V3"")"),37.0) -> 37 | AT12: =IFERROR(__xludf.DUMMYFUNCTION("IMPORTRANGE(""13EYfcAewqPPQ83PA3ta2L46h2GIwi9k-mw8zx8HuEws"",""2025-26!W4"")"),884241.92) -> 884241.92 | AU12: =IFERROR(__xludf.DUMMYFUNCTION("IMPORTRANGE(""13EYfcAewqPPQ83PA3ta2L46h2GIwi9k-mw8zx8HuEws"",""2025-26!W3"")"),16.0) -> 16 | AV12: =IFERROR((AW12/AR12),"") -> 0.68369665 | AW12: =IFERROR(__xludf.DUMMYFUNCTION("IMPORTRANGE(""13EYfcAewqPPQ83PA3ta2L46h2GIwi9k-mw8zx8HuEws"",""2025-26!X4"")"),919572.0) -> 919572 | AX12: =IFERROR(__xludf.DUMMYFUNCTION("IMPORTRANGE(""13EYfcAewqPPQ83PA3ta2L46h2GIwi9k-mw8zx8HuEws"",""2025-26!X3"")"),15.0) -> 15 | AY12: =IFERROR(__xludf.DUMMYFUNCTION("IMPORTRANGE(""13EYfcAewqPPQ83PA3ta2L46h2GIwi9k-mw8zx8HuEws"",""2025-26!Y4"")"),1580000.0) -> 1580000 | AZ12: =IFERROR(__xludf.DUMMYFUNCTION("IMPORTRANGE(""13EYfcAewqPPQ83PA3ta2L46h2GIwi9k-mw8zx8HuEws"",""2025-26!Y3"")"),41.0) -> 41 | BA12: =IFERROR(__xludf.DUMMYFUNCTION("IMPORTRANGE(""13EYfcAewqPPQ83PA3ta2L46h2GIwi9k-mw8zx8HuEws"",""2025-26!Z4"")"),791740.35) -> 791740.35 | BB12: =IFERROR(__xludf.DUMMYFUNCTION("IMPORTRANGE(""13EYfcAewqPPQ83PA3ta2L46h2GIwi9k-mw8zx8HuEws"",""2025-26!Z3"")"),19.0) -> 19 | BC12: =IFERROR((BD12/AY12),"") -> 0.44733038 | BD12: =IFERROR(__xludf.DUMMYFUNCTION("IMPORTRANGE(""13EYfcAewqPPQ83PA3ta2L46h2GIwi9k-mw8zx8HuEws"",""2025-26!AA4"")"),706782.0) -> 706782 | BE12: =IFERROR(__xludf.DUMMYFUNCTION("IMPORTRANGE(""13EYfcAewqPPQ83PA3ta2L46h2GIwi9k-mw8zx8HuEws"",""2025-26!AA3"")"),24.0) -> 24 | BF12: =IFERROR(__xludf.DUMMYFUNCTION("IMPORTRANGE(""13EYfcAewqPPQ83PA3ta2L46h2GIwi9k-mw8zx8HuEws"",""2025-26!AB4"")"),1175000.0) -> 1175000 | BG12: =IFERROR(__xludf.DUMMYFUNCTION("IMPORTRANGE(""13EYfcAewqPPQ83PA3ta2L46h2GIwi9k-mw8zx8HuEws"",""2025-26!AB3"")"),46.0) -> 46 | BH12: =IFERROR(__xludf.DUMMYFUNCTION("IMPORTRANGE(""13EYfcAewqPPQ83PA3ta2L46h2GIwi9k-mw8zx8HuEws"",""2025-26!AC4"")"),491959.2400000001) -> 491959.24 | BI12: =IFERROR(__xludf.DUMMYFUNCTION("IMPORTRANGE(""13EYfcAewqPPQ83PA3ta2L46h2GIwi9k-mw8zx8HuEws"",""2025-26!AC3"")"),23.0) -> 23 | BJ12: =IFERROR((BK12/BF12),"") -> 0.44130128 | BK12: =IFERROR(__xludf.DUMMYFUNCTION("IMPORTRANGE(""13EYfcAewqPPQ83PA3ta2L46h2GIwi9k-mw8zx8HuEws"",""2025-26!AD4"")"),518529.0) -> 518529 | BL12: =IFERROR(__xludf.DUMMYFUNCTION("IMPORTRANGE(""13EYfcAewqPPQ83PA3ta2L46h2GIwi9k-mw8zx8HuEws"",""2025-26!AD3"")"),21.0) -> 21 | BM12: =IFERROR(__xludf.DUMMYFUNCTION("IMPORTRANGE(""13EYfcAewqPPQ83PA3ta2L46h2GIwi9k-mw8zx8HuEws"",""2025-26!AE4"")"),1290000.0) -> 1290000 | BN12: =IFERROR(__xludf.DUMMYFUNCTION("IMPORTRANGE(""13EYfcAewqPPQ83PA3ta2L46h2GIwi9k-mw8zx8HuEws"",""2025-26!AE3"")"),60.0) -> 60 | BO12: =IFERROR(__xludf.DUMMYFUNCTION("IMPORTRANGE(""13EYfcAewqPPQ83PA3ta2L46h2GIwi9k-mw8zx8HuEws"",""2025-26!AF4"")"),604618.7) -> 604618.7 | BP12: =IFERROR(__xludf.DUMMYFUNCTION("IMPORTRANGE(""13EYfcAewqPPQ83PA3ta2L46h2GIwi9k-mw8zx8HuEws"",""2025-26!AF3"")"),28.0) -> 28 | BQ12: =IFERROR((BR12/BM12),"") -> 0.4700093 | BR12: =IFERROR(__xludf.DUMMYFUNCTION("IMPORTRANGE(""13EYfcAewqPPQ83PA3ta2L46h2GIwi9k-mw8zx8HuEws"",""2025-26!AG4"")"),606312.0) -> 606312 | BS12: =IFERROR(__xludf.DUMMYFUNCTION("IMPORTRANGE(""13EYfcAewqPPQ83PA3ta2L46h2GIwi9k-mw8zx8HuEws"",""2025-26!AG3"")"),28.0) -> 28 | BT12: =IFERROR(__xludf.DUMMYFUNCTION("IMPORTRANGE(""13EYfcAewqPPQ83PA3ta2L46h2GIwi9k-mw8zx8HuEws"",""2025-26!AH4"")"),1210000.0) -> 1210000 | BU12: =IFERROR(__xludf.DUMMYFUNCTION("IMPORTRANGE(""13EYfcAewqPPQ83PA3ta2L46h2GIwi9k-mw8zx8HuEws"",""2025-26!AH3"")"),67.0) -> 67 | BV12: =IFERROR(__xludf.DUMMYFUNCTION("IMPORTRANGE(""13EYfcAewqPPQ83PA3ta2L46h2GIwi9k-mw8zx8HuEws"",""2025-26!AI4"")"),908928.92) -> 908928.92 | BW12: =IFERROR(__xludf.DUMMYFUNCTION("IMPORTRANGE(""13EYfcAewqPPQ83PA3ta2L46h2GIwi9k-mw8zx8HuEws"",""2025-26!AI3"")"),17.0) -> 17 | BX12: =IFERROR((BY12/BT12),"") -> 0.7616 | BY12: =IFERROR(__xludf.DUMMYFUNCTION("IMPORTRANGE(""13EYfcAewqPPQ83PA3ta2L46h2GIwi9k-mw8zx8HuEws"",""2025-26!AJ4"")"),921536.0) -> 921536 | BZ12: =IFERROR(__xludf.DUMMYFUNCTION("IMPORTRANGE(""13EYfcAewqPPQ83PA3ta2L46h2GIwi9k-mw8zx8HuEws"",""2025-26!AJ3"")"),18.0) -> 18 | CA12: =IFERROR(__xludf.DUMMYFUNCTION("IMPORTRANGE(""13EYfcAewqPPQ83PA3ta2L46h2GIwi9k-mw8zx8HuEws"",""2025-26!AK4"")"),1210000.0) -> 1210000 | CB12: =IFERROR(__xludf.DUMMYFUNCTION("IMPORTRANGE(""13EYfcAewqPPQ83PA3ta2L46h2GIwi9k-mw8zx8HuEws"",""2025-26!AK3"")"),70.0) -> 70 | CC12: =IFERROR(__xludf.DUMMYFUNCTION("IMPORTRANGE(""13EYfcAewqPPQ83PA3ta2L46h2GIwi9k-mw8zx8HuEws"",""2025-26!AL4"")"),661496.65) -> 661496.65 | CD12: =IFERROR(__xludf.DUMMYFUNCTION("IMPORTRANGE(""13EYfcAewqPPQ83PA3ta2L46h2GIwi9k-mw8zx8HuEws"",""2025-26!AL3"")"),22.0) -> 22 | CE12: =IFERROR((CF12/CA12),"") -> 0.45844132 | CF12: =IFERROR(__xludf.DUMMYFUNCTION("IMPORTRANGE(""13EYfcAewqPPQ83PA3ta2L46h2GIwi9k-mw8zx8HuEws"",""2025-26!AM4"")"),554714.0) -> 554714 | CG12: =IFERROR(__xludf.DUMMYFUNCTION("IMPORTRANGE(""13EYfcAewqPPQ83PA3ta2L46h2GIwi9k-mw8zx8HuEws"",""2025-26!AM3"")"),18.0) -> 18 | CH12: =IFERROR(__xludf.DUMMYFUNCTION("IMPORTRANGE(""13EYfcAewqPPQ83PA3ta2L46h2GIwi9k-mw8zx8HuEws"",""2025-26!AN4"")"),1255000.0) -> 1255000 | CI12: =IFERROR(__xludf.DUMMYFUNCTION("IMPORTRANGE(""13EYfcAewqPPQ83PA3ta2L46h2GIwi9k-mw8zx8HuEws"",""2025-26!AN3"")"),70.0) -> 70 | CJ12: =IFERROR(__xludf.DUMMYFUNCTION("IMPORTRANGE(""13EYfcAewqPPQ83PA3ta2L46h2GIwi9k-mw8zx8HuEws"",""2025-26!AO4"")"),904055.73) -> 904055.73 | CK12: =IFERROR(__xludf.DUMMYFUNCTION("IMPORTRANGE(""13EYfcAewqPPQ83PA3ta2L46h2GIwi9k-mw8zx8HuEws"",""2025-26!AO3"")"),23.0) -> 23 | CL12: =IFERROR((CM12/CH12),"") -> 0.70224622 | CM12: =IFERROR(__xludf.DUMMYFUNCTION("IMPORTRANGE(""13EYfcAewqPPQ83PA3ta2L46h2GIwi9k-mw8zx8HuEws"",""2025-26!AP4"")"),881319.0) -> 881319 | CN12: =IFERROR(__xludf.DUMMYFUNCTION("IMPORTRANGE(""13EYfcAewqPPQ83PA3ta2L46h2GIwi9k-mw8zx8HuEws"",""2025-26!AP3"")"),19.0) -> 19 | CO12: =IFERROR(__xludf.DUMMYFUNCTION("IMPORTRANGE(""13EYfcAewqPPQ83PA3ta2L46h2GIwi9k-mw8zx8HuEws"",""2025-26!AQ4"")"),1445000.0) -> 1445000 | CP12: =IFERROR(__xludf.DUMMYFUNCTION("IMPORTRANGE(""13EYfcAewqPPQ83PA3ta2L46h2GIwi9k-mw8zx8HuEws"",""2025-26!AQ3"")"),83.0) -> 83 | CQ12: =IFERROR(__xludf.DUMMYFUNCTION("IMPORTRANGE(""13EYfcAewqPPQ83PA3ta2L46h2GIwi9k-mw8zx8HuEws"",""2025-26!AR4"")"),765200.01) -> 765200.01 | CR12: =IFERROR(__xludf.DUMMYFUNCTION("IMPORTRANGE(""13EYfcAewqPPQ83PA3ta2L46h2GIwi9k-mw8zx8HuEws"",""2025-26!AR3"")"),19.0) -> 19 | CS12: =IFERROR((CT12/CO12),"") -> 0.61484083 | CT12: =IFERROR(__xludf.DUMMYFUNCTION("IMPORTRANGE(""13EYfcAewqPPQ83PA3ta2L46h2GIwi9k-mw8zx8HuEws"",""2025-26!AS4"")"),888445.0) -> 888445 | CU12: =IFERROR(__xludf.DUMMYFUNCTION("IMPORTRANGE(""13EYfcAewqPPQ83PA3ta2L46h2GIwi9k-mw8zx8HuEws"",""2025-26!AS3"")"),18.0) -> 18 | CV12: Uttarakhand
A13: Anant Singh | C13: Ravi (Faridabad) | D13: Faridabad | E13: 8266009918 | F13: 45736 | I13: =VLOOKUP($C13,Data!$C:$BV,72,0) -> 27260 | J13: =1200000+50000 -> 1250000 | K13: =IFERROR(__xludf.DUMMYFUNCTION("IMPORTRANGE(""1jFDZ-XQ8Fuzz37_6c1Wi087O7eNCDVE8KbcMW9lSUac"",""2025-26!A3"")"),46.0) -> 46 | L13: =IFERROR(__xludf.DUMMYFUNCTION("IMPORTRANGE(""1jFDZ-XQ8Fuzz37_6c1Wi087O7eNCDVE8KbcMW9lSUac"",""2025-26!G4"")"),5800000.0) -> 5800000 | M13: =R13+Y13+AF13+AM13+AT13+BA13+BH13+BO13+BV13+CC13+CJ13+CQ13 -> 5077211.3 | N13: =O13/L13 -> 0.79193759 | O13: =U13+AB13+AI13+AP13+AW13+BD13+BK13+BR13+BY13+CF13+CM13+CT13 -> 4593238 | P13: =IFERROR(__xludf.DUMMYFUNCTION("IMPORTRANGE(""1jFDZ-XQ8Fuzz37_6c1Wi087O7eNCDVE8KbcMW9lSUac"",""2025-26!J4"")"),0.0) -> 0 | Q13: =IFERROR(__xludf.DUMMYFUNCTION("IMPORTRANGE(""1jFDZ-XQ8Fuzz37_6c1Wi087O7eNCDVE8KbcMW9lSUac"",""2025-26!J3"")"),0.0) -> 0 | R13: =IFERROR(__xludf.DUMMYFUNCTION("IMPORTRANGE(""1jFDZ-XQ8Fuzz37_6c1Wi087O7eNCDVE8KbcMW9lSUac"",""2025-26!K4"")"),95525.9) -> 95525.9 | S13: =IFERROR(__xludf.DUMMYFUNCTION("IMPORTRANGE(""1jFDZ-XQ8Fuzz37_6c1Wi087O7eNCDVE8KbcMW9lSUac"",""2025-26!K3"")"),1.0) -> 1 | T13: =IFERROR((U13/P13),"") | U13: =IFERROR(__xludf.DUMMYFUNCTION("IMPORTRANGE(""1jFDZ-XQ8Fuzz37_6c1Wi087O7eNCDVE8KbcMW9lSUac"",""2025-26!L4"")"),0.0) -> 0 | V13: =IFERROR(__xludf.DUMMYFUNCTION("IMPORTRANGE(""1jFDZ-XQ8Fuzz37_6c1Wi087O7eNCDVE8KbcMW9lSUac"",""2025-26!L3"")"),0.0) -> 0 | W13: =IFERROR(__xludf.DUMMYFUNCTION("IMPORTRANGE(""1jFDZ-XQ8Fuzz37_6c1Wi087O7eNCDVE8KbcMW9lSUac"",""2025-26!m4"")"),700000.0) -> 700000 | X13: =IFERROR(__xludf.DUMMYFUNCTION("IMPORTRANGE(""1jFDZ-XQ8Fuzz37_6c1Wi087O7eNCDVE8KbcMW9lSUac"",""2025-26!m3"")"),8.0) -> 8 | Y13: =IFERROR(__xludf.DUMMYFUNCTION("IMPORTRANGE(""1jFDZ-XQ8Fuzz37_6c1Wi087O7eNCDVE8KbcMW9lSUac"",""2025-26!N4"")"),434446.65) -> 434446.65 | Z13: =IFERROR(__xludf.DUMMYFUNCTION("IMPORTRANGE(""1jFDZ-XQ8Fuzz37_6c1Wi087O7eNCDVE8KbcMW9lSUac"",""2025-26!N3"")"),9.0) -> 9 | AA13: =IFERROR((AB13/W13),"") -> 0.62064143 | AB13: =IFERROR(__xludf.DUMMYFUNCTION("IMPORTRANGE(""1jFDZ-XQ8Fuzz37_6c1Wi087O7eNCDVE8KbcMW9lSUac"",""2025-26!O4"")"),434449.0) -> 434449 | AC13: =IFERROR(__xludf.DUMMYFUNCTION("IMPORTRANGE(""1jFDZ-XQ8Fuzz37_6c1Wi087O7eNCDVE8KbcMW9lSUac"",""2025-26!O3"")"),9.0) -> 9 | AD13: =IFERROR(__xludf.DUMMYFUNCTION("IMPORTRANGE(""1jFDZ-XQ8Fuzz37_6c1Wi087O7eNCDVE8KbcMW9lSUac"",""2025-26!P4"")"),800000.0) -> 800000 | AE13: =IFERROR(__xludf.DUMMYFUNCTION("IMPORTRANGE(""1jFDZ-XQ8Fuzz37_6c1Wi087O7eNCDVE8KbcMW9lSUac"",""2025-26!P3"")"),9.0) -> 9 | AF13: =IFERROR(__xludf.DUMMYFUNCTION("IMPORTRANGE(""1jFDZ-XQ8Fuzz37_6c1Wi087O7eNCDVE8KbcMW9lSUac"",""2025-26!Q4"")"),399885.78) -> 399885.78 | AG13: =IFERROR(__xludf.DUMMYFUNCTION("IMPORTRANGE(""1jFDZ-XQ8Fuzz37_6c1Wi087O7eNCDVE8KbcMW9lSUac"",""2025-26!Q3"")"),9.0) -> 9 | AH13: =IFERROR((AI13/AD13),"") -> 0.562365 | AI13: =IFERROR(__xludf.DUMMYFUNCTION("IMPORTRANGE(""1jFDZ-XQ8Fuzz37_6c1Wi087O7eNCDVE8KbcMW9lSUac"",""2025-26!R4"")"),449892.0) -> 449892 | AJ13: =IFERROR(__xludf.DUMMYFUNCTION("IMPORTRANGE(""1jFDZ-XQ8Fuzz37_6c1Wi087O7eNCDVE8KbcMW9lSUac"",""2025-26!R3"")"),9.0) -> 9 | AK13: =IFERROR(__xludf.DUMMYFUNCTION("IMPORTRANGE(""1jFDZ-XQ8Fuzz37_6c1Wi087O7eNCDVE8KbcMW9lSUac"",""2025-26!S4"")"),1300000.0) -> 1300000 | AL13: =IFERROR(__xludf.DUMMYFUNCTION("IMPORTRANGE(""1jFDZ-XQ8Fuzz37_6c1Wi087O7eNCDVE8KbcMW9lSUac"",""2025-26!S3"")"),12.0) -> 12 | AM13: =IFERROR(__xludf.DUMMYFUNCTION("IMPORTRANGE(""1jFDZ-XQ8Fuzz37_6c1Wi087O7eNCDVE8KbcMW9lSUac"",""2025-26!T4"")"),888460.8300000001) -> 888460.83 | AN13: =IFERROR(__xludf.DUMMYFUNCTION("IMPORTRANGE(""1jFDZ-XQ8Fuzz37_6c1Wi087O7eNCDVE8KbcMW9lSUac"",""2025-26!T3"")"),13.0) -> 13 | AO13: =IFERROR((AP13/AK13),"") -> 0.66476154 | AP13: =IFERROR(__xludf.DUMMYFUNCTION("IMPORTRANGE(""1jFDZ-XQ8Fuzz37_6c1Wi087O7eNCDVE8KbcMW9lSUac"",""2025-26!U4"")"),864190.0) -> 864190 | AQ13: =IFERROR(__xludf.DUMMYFUNCTION("IMPORTRANGE(""1jFDZ-XQ8Fuzz37_6c1Wi087O7eNCDVE8KbcMW9lSUac"",""2025-26!U3"")"),13.0) -> 13 | AR13: =IFERROR(__xludf.DUMMYFUNCTION("IMPORTRANGE(""1jFDZ-XQ8Fuzz37_6c1Wi087O7eNCDVE8KbcMW9lSUac"",""2025-26!V4"")"),1200000.0) -> 1200000 | AS13: =IFERROR(__xludf.DUMMYFUNCTION("IMPORTRANGE(""1jFDZ-XQ8Fuzz37_6c1Wi087O7eNCDVE8KbcMW9lSUac"",""2025-26!V3"")"),16.0) -> 16 | AT13: =IFERROR(__xludf.DUMMYFUNCTION("IMPORTRANGE(""1jFDZ-XQ8Fuzz37_6c1Wi087O7eNCDVE8KbcMW9lSUac"",""2025-26!W4"")"),746767.4299999999) -> 746767.43 | AU13: =IFERROR(__xludf.DUMMYFUNCTION("IMPORTRANGE(""1jFDZ-XQ8Fuzz37_6c1Wi087O7eNCDVE8KbcMW9lSUac"",""2025-26!W3"")"),7.0) -> 7 | AV13: =IFERROR((AW13/AR13),"") -> 0.60820667 | AW13: =IFERROR(__xludf.DUMMYFUNCTION("IMPORTRANGE(""1jFDZ-XQ8Fuzz37_6c1Wi087O7eNCDVE8KbcMW9lSUac"",""2025-26!X4"")"),729848.0) -> 729848 | AX13: =IFERROR(__xludf.DUMMYFUNCTION("IMPORTRANGE(""1jFDZ-XQ8Fuzz37_6c1Wi087O7eNCDVE8KbcMW9lSUac"",""2025-26!X3"")"),6.0) -> 6 | AY13: =IFERROR(__xludf.DUMMYFUNCTION("IMPORTRANGE(""1jFDZ-XQ8Fuzz37_6c1Wi087O7eNCDVE8KbcMW9lSUac"",""2025-26!Y4"")"),1200000.0) -> 1200000 | AZ13: =IFERROR(__xludf.DUMMYFUNCTION("IMPORTRANGE(""1jFDZ-XQ8Fuzz37_6c1Wi087O7eNCDVE8KbcMW9lSUac"",""2025-26!Y3"")"),14.0) -> 14 | BA13: =IFERROR(__xludf.DUMMYFUNCTION("IMPORTRANGE(""1jFDZ-XQ8Fuzz37_6c1Wi087O7eNCDVE8KbcMW9lSUac"",""2025-26!Z4"")"),827791.98) -> 827791.98 | BB13: =IFERROR(__xludf.DUMMYFUNCTION("IMPORTRANGE(""1jFDZ-XQ8Fuzz37_6c1Wi087O7eNCDVE8KbcMW9lSUac"",""2025-26!Z3"")"),9.0) -> 9 | BC13: =IFERROR((BD13/AY13),"") -> 0.6898275 | BD13: =IFERROR(__xludf.DUMMYFUNCTION("IMPORTRANGE(""1jFDZ-XQ8Fuzz37_6c1Wi087O7eNCDVE8KbcMW9lSUac"",""2025-26!AA4"")"),827793.0) -> 827793 | BE13: =IFERROR(__xludf.DUMMYFUNCTION("IMPORTRANGE(""1jFDZ-XQ8Fuzz37_6c1Wi087O7eNCDVE8KbcMW9lSUac"",""2025-26!AA3"")"),9.0) -> 9 | BF13: =IFERROR(__xludf.DUMMYFUNCTION("IMPORTRANGE(""1jFDZ-XQ8Fuzz37_6c1Wi087O7eNCDVE8KbcMW9lSUac"",""2025-26!AB4"")"),1200000.0) -> 1200000 | BG13: =IFERROR(__xludf.DUMMYFUNCTION("IMPORTRANGE(""1jFDZ-XQ8Fuzz37_6c1Wi087O7eNCDVE8KbcMW9lSUac"",""2025-26!AB3"")"),17.0) -> 17 | BH13: =IFERROR(__xludf.DUMMYFUNCTION("IMPORTRANGE(""1jFDZ-XQ8Fuzz37_6c1Wi087O7eNCDVE8KbcMW9lSUac"",""2025-26!AC4"")"),131286.49) -> 131286.49 | BI13: =IFERROR(__xludf.DUMMYFUNCTION("IMPORTRANGE(""1jFDZ-XQ8Fuzz37_6c1Wi087O7eNCDVE8KbcMW9lSUac"",""2025-26!AC3"")"),6.0) -> 6 | BJ13: =IFERROR((BK13/BF13),"") -> 0.022108333 | BK13: =IFERROR(__xludf.DUMMYFUNCTION("IMPORTRANGE(""1jFDZ-XQ8Fuzz37_6c1Wi087O7eNCDVE8KbcMW9lSUac"",""2025-26!AD4"")"),26530.0) -> 26530 | BL13: =IFERROR(__xludf.DUMMYFUNCTION("IMPORTRANGE(""1jFDZ-XQ8Fuzz37_6c1Wi087O7eNCDVE8KbcMW9lSUac"",""2025-26!AD3"")"),1.0) -> 1 | BM13: =IFERROR(__xludf.DUMMYFUNCTION("IMPORTRANGE(""1jFDZ-XQ8Fuzz37_6c1Wi087O7eNCDVE8KbcMW9lSUac"",""2025-26!AE4"")"),1200000.0) -> 1200000 | BN13: =IFERROR(__xludf.DUMMYFUNCTION("IMPORTRANGE(""1jFDZ-XQ8Fuzz37_6c1Wi087O7eNCDVE8KbcMW9lSUac"",""2025-26!AE3"")"),18.0) -> 18 | BO13: =IFERROR(__xludf.DUMMYFUNCTION("IMPORTRANGE(""1jFDZ-XQ8Fuzz37_6c1Wi087O7eNCDVE8KbcMW9lSUac"",""2025-26!AF4"")"),269022.36) -> 269022.36 | BP13: =IFERROR(__xludf.DUMMYFUNCTION("IMPORTRANGE(""1jFDZ-XQ8Fuzz37_6c1Wi087O7eNCDVE8KbcMW9lSUac"",""2025-26!AF3"")"),5.0) -> 5 | BQ13: =IFERROR((BR13/BM13),"") -> 0.22416 | BR13: =IFERROR(__xludf.DUMMYFUNCTION("IMPORTRANGE(""1jFDZ-XQ8Fuzz37_6c1Wi087O7eNCDVE8KbcMW9lSUac"",""2025-26!AG4"")"),268992.0) -> 268992 | BS13: =IFERROR(__xludf.DUMMYFUNCTION("IMPORTRANGE(""1jFDZ-XQ8Fuzz37_6c1Wi087O7eNCDVE8KbcMW9lSUac"",""2025-26!AG3"")"),5.0) -> 5 | BT13: =IFERROR(__xludf.DUMMYFUNCTION("IMPORTRANGE(""1jFDZ-XQ8Fuzz37_6c1Wi087O7eNCDVE8KbcMW9lSUac"",""2025-26!AH4"")"),1260000.0) -> 1260000 | BU13: =IFERROR(__xludf.DUMMYFUNCTION("IMPORTRANGE(""1jFDZ-XQ8Fuzz37_6c1Wi087O7eNCDVE8KbcMW9lSUac"",""2025-26!AH3"")"),17.0) -> 17 | BV13: =IFERROR(__xludf.DUMMYFUNCTION("IMPORTRANGE(""1jFDZ-XQ8Fuzz37_6c1Wi087O7eNCDVE8KbcMW9lSUac"",""2025-26!AI4"")"),648851.68) -> 648851.68 | BW13: =IFERROR(__xludf.DUMMYFUNCTION("IMPORTRANGE(""1jFDZ-XQ8Fuzz37_6c1Wi087O7eNCDVE8KbcMW9lSUac"",""2025-26!AI3"")"),9.0) -> 9 | BX13: =IFERROR((BY13/BT13),"") -> 0.51500952 | BY13: =IFERROR(__xludf.DUMMYFUNCTION("IMPORTRANGE(""1jFDZ-XQ8Fuzz37_6c1Wi087O7eNCDVE8KbcMW9lSUac"",""2025-26!AJ4"")"),648912.0) -> 648912 | BZ13: =IFERROR(__xludf.DUMMYFUNCTION("IMPORTRANGE(""1jFDZ-XQ8Fuzz37_6c1Wi087O7eNCDVE8KbcMW9lSUac"",""2025-26!AJ3"")"),9.0) -> 9 | CA13: =IFERROR(__xludf.DUMMYFUNCTION("IMPORTRANGE(""1jFDZ-XQ8Fuzz37_6c1Wi087O7eNCDVE8KbcMW9lSUac"",""2025-26!AK4"")"),1210000.0) -> 1210000 | CB13: =IFERROR(__xludf.DUMMYFUNCTION("IMPORTRANGE(""1jFDZ-XQ8Fuzz37_6c1Wi087O7eNCDVE8KbcMW9lSUac"",""2025-26!AK3"")"),17.0) -> 17 | CC13: =IFERROR(__xludf.DUMMYFUNCTION("IMPORTRANGE(""1jFDZ-XQ8Fuzz37_6c1Wi087O7eNCDVE8KbcMW9lSUac"",""2025-26!AL4"")"),356727.48) -> 356727.48 | CD13: =IFERROR(__xludf.DUMMYFUNCTION("IMPORTRANGE(""1jFDZ-XQ8Fuzz37_6c1Wi087O7eNCDVE8KbcMW9lSUac"",""2025-26!AL3"")"),6.0) -> 6 | CE13: =IFERROR((CF13/CA13),"") -> 0.17214215 | CF13: =IFERROR(__xludf.DUMMYFUNCTION("IMPORTRANGE(""1jFDZ-XQ8Fuzz37_6c1Wi087O7eNCDVE8KbcMW9lSUac"",""2025-26!AM4"")"),208292.0) -> 208292 | CG13: =IFERROR(__xludf.DUMMYFUNCTION("IMPORTRANGE(""1jFDZ-XQ8Fuzz37_6c1Wi087O7eNCDVE8KbcMW9lSUac"",""2025-26!AM3"")"),5.0) -> 5 | CH13: =IFERROR(__xludf.DUMMYFUNCTION("IMPORTRANGE(""1jFDZ-XQ8Fuzz37_6c1Wi087O7eNCDVE8KbcMW9lSUac"",""2025-26!AN4"")"),1205000.0) -> 1205000 | CI13: =IFERROR(__xludf.DUMMYFUNCTION("IMPORTRANGE(""1jFDZ-XQ8Fuzz37_6c1Wi087O7eNCDVE8KbcMW9lSUac"",""2025-26!AN3"")"),15.0) -> 15 | CJ13: =IFERROR(__xludf.DUMMYFUNCTION("IMPORTRANGE(""1jFDZ-XQ8Fuzz37_6c1Wi087O7eNCDVE8KbcMW9lSUac"",""2025-26!AO4"")"),208045.78) -> 208045.78 | CK13: =IFERROR(__xludf.DUMMYFUNCTION("IMPORTRANGE(""1jFDZ-XQ8Fuzz37_6c1Wi087O7eNCDVE8KbcMW9lSUac"",""2025-26!AO3"")"),5.0) -> 5 | CL13: =IFERROR((CM13/CH13),"") -> 0.069634855 | CM13: =IFERROR(__xludf.DUMMYFUNCTION("IMPORTRANGE(""1jFDZ-XQ8Fuzz37_6c1Wi087O7eNCDVE8KbcMW9lSUac"",""2025-26!AP4"")"),83910.0) -> 83910 | CN13: =IFERROR(__xludf.DUMMYFUNCTION("IMPORTRANGE(""1jFDZ-XQ8Fuzz37_6c1Wi087O7eNCDVE8KbcMW9lSUac"",""2025-26!AP3"")"),4.0) -> 4 | CO13: =IFERROR(__xludf.DUMMYFUNCTION("IMPORTRANGE(""1jFDZ-XQ8Fuzz37_6c1Wi087O7eNCDVE8KbcMW9lSUac"",""2025-26!AQ4"")"),330000.0) -> 330000 | CP13: =IFERROR(__xludf.DUMMYFUNCTION("IMPORTRANGE(""1jFDZ-XQ8Fuzz37_6c1Wi087O7eNCDVE8KbcMW9lSUac"",""2025-26!AQ3"")"),5.0) -> 5 | CQ13: =IFERROR(__xludf.DUMMYFUNCTION("IMPORTRANGE(""1jFDZ-XQ8Fuzz37_6c1Wi087O7eNCDVE8KbcMW9lSUac"",""2025-26!AR4"")"),70398.95) -> 70398.95 | CR13: =IFERROR(__xludf.DUMMYFUNCTION("IMPORTRANGE(""1jFDZ-XQ8Fuzz37_6c1Wi087O7eNCDVE8KbcMW9lSUac"",""2025-26!AR3"")"),3.0) -> 3 | CS13: =IFERROR((CT13/CO13),"") -> 0.15281818 | CT13: =IFERROR(__xludf.DUMMYFUNCTION("IMPORTRANGE(""1jFDZ-XQ8Fuzz37_6c1Wi087O7eNCDVE8KbcMW9lSUac"",""2025-26!AS4"")"),50430.0) -> 50430 | CU13: =IFERROR(__xludf.DUMMYFUNCTION("IMPORTRANGE(""1jFDZ-XQ8Fuzz37_6c1Wi087O7eNCDVE8KbcMW9lSUac"",""2025-26!AS3"")"),3.0) -> 3 | CV13: Delhi NCR
A14: Anant Singh | C14: Shivam Chauhan | D14: Haridwar | E14: 8006520839 | F14: 45887 | I14: =VLOOKUP($C14,Data!$C:$BV,72,0) -> 28835 | J14: 1200000 | K14: =IFERROR(__xludf.DUMMYFUNCTION("IMPORTRANGE(""132I0fvbfTDk_3h-QeYGrQ-F6z0A921MXbdqyLFsyN5Y"",""2025-26!A3"")"),169.0) -> 169 | L14: =IFERROR(__xludf.DUMMYFUNCTION("IMPORTRANGE(""132I0fvbfTDk_3h-QeYGrQ-F6z0A921MXbdqyLFsyN5Y"",""2025-26!G4"")"),1.1E7) -> 11000000 | M14: =R14+Y14+AF14+AM14+AT14+BA14+BH14+BO14+BV14+CC14+CJ14+CQ14 -> 6525450.8 | N14: =O14/L14 -> 0.58104227 | O14: =U14+AB14+AI14+AP14+AW14+BD14+BK14+BR14+BY14+CF14+CM14+CT14 -> 6391465 | P14: =IFERROR(__xludf.DUMMYFUNCTION("IMPORTRANGE(""132I0fvbfTDk_3h-QeYGrQ-F6z0A921MXbdqyLFsyN5Y"",""2025-26!J4"")"),0.0) -> 0 | Q14: =IFERROR(__xludf.DUMMYFUNCTION("IMPORTRANGE(""132I0fvbfTDk_3h-QeYGrQ-F6z0A921MXbdqyLFsyN5Y"",""2025-26!J3"")"),0.0) -> 0 | R14: =IFERROR(__xludf.DUMMYFUNCTION("IMPORTRANGE(""132I0fvbfTDk_3h-QeYGrQ-F6z0A921MXbdqyLFsyN5Y"",""2025-26!K4"")"),0.0) -> 0 | S14: =IFERROR(__xludf.DUMMYFUNCTION("IMPORTRANGE(""132I0fvbfTDk_3h-QeYGrQ-F6z0A921MXbdqyLFsyN5Y"",""2025-26!K3"")"),0.0) -> 0 | T14: =IFERROR((U14/P14),"") | U14: =IFERROR(__xludf.DUMMYFUNCTION("IMPORTRANGE(""132I0fvbfTDk_3h-QeYGrQ-F6z0A921MXbdqyLFsyN5Y"",""2025-26!L4"")"),0.0) -> 0 | V14: =IFERROR(__xludf.DUMMYFUNCTION("IMPORTRANGE(""132I0fvbfTDk_3h-QeYGrQ-F6z0A921MXbdqyLFsyN5Y"",""2025-26!L3"")"),0.0) -> 0 | W14: =IFERROR(__xludf.DUMMYFUNCTION("IMPORTRANGE(""132I0fvbfTDk_3h-QeYGrQ-F6z0A921MXbdqyLFsyN5Y"",""2025-26!m4"")"),0.0) -> 0 | X14: =IFERROR(__xludf.DUMMYFUNCTION("IMPORTRANGE(""132I0fvbfTDk_3h-QeYGrQ-F6z0A921MXbdqyLFsyN5Y"",""2025-26!m3"")"),0.0) -> 0 | Y14: =IFERROR(__xludf.DUMMYFUNCTION("IMPORTRANGE(""132I0fvbfTDk_3h-QeYGrQ-F6z0A921MXbdqyLFsyN5Y"",""2025-26!N4"")"),0.0) -> 0 | Z14: =IFERROR(__xludf.DUMMYFUNCTION("IMPORTRANGE(""132I0fvbfTDk_3h-QeYGrQ-F6z0A921MXbdqyLFsyN5Y"",""2025-26!N3"")"),0.0) -> 0 | AA14: =IFERROR((AB14/W14),"") | AB14: =IFERROR(__xludf.DUMMYFUNCTION("IMPORTRANGE(""132I0fvbfTDk_3h-QeYGrQ-F6z0A921MXbdqyLFsyN5Y"",""2025-26!O4"")"),0.0) -> 0 | AC14: =IFERROR(__xludf.DUMMYFUNCTION("IMPORTRANGE(""132I0fvbfTDk_3h-QeYGrQ-F6z0A921MXbdqyLFsyN5Y"",""2025-26!O3"")"),0.0) -> 0 | AD14: =IFERROR(__xludf.DUMMYFUNCTION("IMPORTRANGE(""132I0fvbfTDk_3h-QeYGrQ-F6z0A921MXbdqyLFsyN5Y"",""2025-26!P4"")"),0.0) -> 0 | AE14: =IFERROR(__xludf.DUMMYFUNCTION("IMPORTRANGE(""132I0fvbfTDk_3h-QeYGrQ-F6z0A921MXbdqyLFsyN5Y"",""2025-26!P3"")"),0.0) -> 0 | AF14: =IFERROR(__xludf.DUMMYFUNCTION("IMPORTRANGE(""132I0fvbfTDk_3h-QeYGrQ-F6z0A921MXbdqyLFsyN5Y"",""2025-26!Q4"")"),0.0) -> 0 | AG14: =IFERROR(__xludf.DUMMYFUNCTION("IMPORTRANGE(""132I0fvbfTDk_3h-QeYGrQ-F6z0A921MXbdqyLFsyN5Y"",""2025-26!Q3"")"),0.0) -> 0 | AH14: =IFERROR((AI14/AD14),"") | AI14: =IFERROR(__xludf.DUMMYFUNCTION("IMPORTRANGE(""132I0fvbfTDk_3h-QeYGrQ-F6z0A921MXbdqyLFsyN5Y"",""2025-26!R4"")"),0.0) -> 0 | AJ14: =IFERROR(__xludf.DUMMYFUNCTION("IMPORTRANGE(""132I0fvbfTDk_3h-QeYGrQ-F6z0A921MXbdqyLFsyN5Y"",""2025-26!R3"")"),0.0) -> 0 | AK14: =IFERROR(__xludf.DUMMYFUNCTION("IMPORTRANGE(""132I0fvbfTDk_3h-QeYGrQ-F6z0A921MXbdqyLFsyN5Y"",""2025-26!S4"")"),0.0) -> 0 | AL14: =IFERROR(__xludf.DUMMYFUNCTION("IMPORTRANGE(""132I0fvbfTDk_3h-QeYGrQ-F6z0A921MXbdqyLFsyN5Y"",""2025-26!S3"")"),0.0) -> 0 | AM14: =IFERROR(__xludf.DUMMYFUNCTION("IMPORTRANGE(""132I0fvbfTDk_3h-QeYGrQ-F6z0A921MXbdqyLFsyN5Y"",""2025-26!T4"")"),0.0) -> 0 | AN14: =IFERROR(__xludf.DUMMYFUNCTION("IMPORTRANGE(""132I0fvbfTDk_3h-QeYGrQ-F6z0A921MXbdqyLFsyN5Y"",""2025-26!T3"")"),0.0) -> 0 | AO14: =IFERROR((AP14/AK14),"") | AP14: =IFERROR(__xludf.DUMMYFUNCTION("IMPORTRANGE(""132I0fvbfTDk_3h-QeYGrQ-F6z0A921MXbdqyLFsyN5Y"",""2025-26!U4"")"),0.0) -> 0 | AQ14: =IFERROR(__xludf.DUMMYFUNCTION("IMPORTRANGE(""132I0fvbfTDk_3h-QeYGrQ-F6z0A921MXbdqyLFsyN5Y"",""2025-26!U3"")"),0.0) -> 0 | AR14: =IFERROR(__xludf.DUMMYFUNCTION("IMPORTRANGE(""132I0fvbfTDk_3h-QeYGrQ-F6z0A921MXbdqyLFsyN5Y"",""2025-26!V4"")"),0.0) -> 0 | AS14: =IFERROR(__xludf.DUMMYFUNCTION("IMPORTRANGE(""132I0fvbfTDk_3h-QeYGrQ-F6z0A921MXbdqyLFsyN5Y"",""2025-26!V3"")"),0.0) -> 0 | AT14: =IFERROR(__xludf.DUMMYFUNCTION("IMPORTRANGE(""132I0fvbfTDk_3h-QeYGrQ-F6z0A921MXbdqyLFsyN5Y"",""2025-26!W4"")"),473052.15) -> 473052.15 | AU14: =IFERROR(__xludf.DUMMYFUNCTION("IMPORTRANGE(""132I0fvbfTDk_3h-QeYGrQ-F6z0A921MXbdqyLFsyN5Y"",""2025-26!W3"")"),17.0) -> 17 | AV14: =IFERROR((AW14/AR14),"") | AW14: =IFERROR(__xludf.DUMMYFUNCTION("IMPORTRANGE(""132I0fvbfTDk_3h-QeYGrQ-F6z0A921MXbdqyLFsyN5Y"",""2025-26!X4"")"),578302.0) -> 578302 | AX14: =IFERROR(__xludf.DUMMYFUNCTION("IMPORTRANGE(""132I0fvbfTDk_3h-QeYGrQ-F6z0A921MXbdqyLFsyN5Y"",""2025-26!X3"")"),25.0) -> 25 | AY14: =IFERROR(__xludf.DUMMYFUNCTION("IMPORTRANGE(""132I0fvbfTDk_3h-QeYGrQ-F6z0A921MXbdqyLFsyN5Y"",""2025-26!Y4"")"),0.0) -> 0 | AZ14: =IFERROR(__xludf.DUMMYFUNCTION("IMPORTRANGE(""132I0fvbfTDk_3h-QeYGrQ-F6z0A921MXbdqyLFsyN5Y"",""2025-26!Y3"")"),0.0) -> 0 | BA14: =IFERROR(__xludf.DUMMYFUNCTION("IMPORTRANGE(""132I0fvbfTDk_3h-QeYGrQ-F6z0A921MXbdqyLFsyN5Y"",""2025-26!Z4"")"),826365.0800000001) -> 826365.08 | BB14: =IFERROR(__xludf.DUMMYFUNCTION("IMPORTRANGE(""132I0fvbfTDk_3h-QeYGrQ-F6z0A921MXbdqyLFsyN5Y"",""2025-26!Z3"")"),36.0) -> 36 | BC14: =IFERROR((BD14/AY14),"") | BD14: =IFERROR(__xludf.DUMMYFUNCTION("IMPORTRANGE(""132I0fvbfTDk_3h-QeYGrQ-F6z0A921MXbdqyLFsyN5Y"",""2025-26!AA4"")"),817479.0) -> 817479 | BE14: =IFERROR(__xludf.DUMMYFUNCTION("IMPORTRANGE(""132I0fvbfTDk_3h-QeYGrQ-F6z0A921MXbdqyLFsyN5Y"",""2025-26!AA3"")"),36.0) -> 36 | BF14: =IFERROR(__xludf.DUMMYFUNCTION("IMPORTRANGE(""132I0fvbfTDk_3h-QeYGrQ-F6z0A921MXbdqyLFsyN5Y"",""2025-26!AB4"")"),1200000.0) -> 1200000 | BG14: =IFERROR(__xludf.DUMMYFUNCTION("IMPORTRANGE(""132I0fvbfTDk_3h-QeYGrQ-F6z0A921MXbdqyLFsyN5Y"",""2025-26!AB3"")"),49.0) -> 49 | BH14: =IFERROR(__xludf.DUMMYFUNCTION("IMPORTRANGE(""132I0fvbfTDk_3h-QeYGrQ-F6z0A921MXbdqyLFsyN5Y"",""2025-26!AC4"")"),609920.0999999999) -> 609920.1 | BI14: =IFERROR(__xludf.DUMMYFUNCTION("IMPORTRANGE(""132I0fvbfTDk_3h-QeYGrQ-F6z0A921MXbdqyLFsyN5Y"",""2025-26!AC3"")"),30.0) -> 30 | BJ14: =IFERROR((BK14/BF14),"") -> 0.42274417 | BK14: =IFERROR(__xludf.DUMMYFUNCTION("IMPORTRANGE(""132I0fvbfTDk_3h-QeYGrQ-F6z0A921MXbdqyLFsyN5Y"",""2025-26!AD4"")"),507293.0) -> 507293 | BL14: =IFERROR(__xludf.DUMMYFUNCTION("IMPORTRANGE(""132I0fvbfTDk_3h-QeYGrQ-F6z0A921MXbdqyLFsyN5Y"",""2025-26!AD3"")"),28.0) -> 28 | BM14: =IFERROR(__xludf.DUMMYFUNCTION("IMPORTRANGE(""132I0fvbfTDk_3h-QeYGrQ-F6z0A921MXbdqyLFsyN5Y"",""2025-26!AE4"")"),1200000.0) -> 1200000 | BN14: =IFERROR(__xludf.DUMMYFUNCTION("IMPORTRANGE(""132I0fvbfTDk_3h-QeYGrQ-F6z0A921MXbdqyLFsyN5Y"",""2025-26!AE3"")"),58.0) -> 58 | BO14: =IFERROR(__xludf.DUMMYFUNCTION("IMPORTRANGE(""132I0fvbfTDk_3h-QeYGrQ-F6z0A921MXbdqyLFsyN5Y"",""2025-26!AF4"")"),622867.0) -> 622867 | BP14: =IFERROR(__xludf.DUMMYFUNCTION("IMPORTRANGE(""132I0fvbfTDk_3h-QeYGrQ-F6z0A921MXbdqyLFsyN5Y"",""2025-26!AF3"")"),33.0) -> 33 | BQ14: =IFERROR((BR14/BM14),"") -> 0.43821417 | BR14: =IFERROR(__xludf.DUMMYFUNCTION("IMPORTRANGE(""132I0fvbfTDk_3h-QeYGrQ-F6z0A921MXbdqyLFsyN5Y"",""2025-26!AG4"")"),525857.0) -> 525857 | BS14: =IFERROR(__xludf.DUMMYFUNCTION("IMPORTRANGE(""132I0fvbfTDk_3h-QeYGrQ-F6z0A921MXbdqyLFsyN5Y"",""2025-26!AG3"")"),31.0) -> 31 | BT14: =IFERROR(__xludf.DUMMYFUNCTION("IMPORTRANGE(""132I0fvbfTDk_3h-QeYGrQ-F6z0A921MXbdqyLFsyN5Y"",""2025-26!AH4"")"),1200000.0) -> 1200000 | BU14: =IFERROR(__xludf.DUMMYFUNCTION("IMPORTRANGE(""132I0fvbfTDk_3h-QeYGrQ-F6z0A921MXbdqyLFsyN5Y"",""2025-26!AH3"")"),64.0) -> 64 | BV14: =IFERROR(__xludf.DUMMYFUNCTION("IMPORTRANGE(""132I0fvbfTDk_3h-QeYGrQ-F6z0A921MXbdqyLFsyN5Y"",""2025-26!AI4"")"),902183.5) -> 902183.5 | BW14: =IFERROR(__xludf.DUMMYFUNCTION("IMPORTRANGE(""132I0fvbfTDk_3h-QeYGrQ-F6z0A921MXbdqyLFsyN5Y"",""2025-26!AI3"")"),45.0) -> 45 | BX14: =IFERROR((BY14/BT14),"") -> 0.64522 | BY14: =IFERROR(__xludf.DUMMYFUNCTION("IMPORTRANGE(""132I0fvbfTDk_3h-QeYGrQ-F6z0A921MXbdqyLFsyN5Y"",""2025-26!AJ4"")"),774264.0) -> 774264 | BZ14: =IFERROR(__xludf.DUMMYFUNCTION("IMPORTRANGE(""132I0fvbfTDk_3h-QeYGrQ-F6z0A921MXbdqyLFsyN5Y"",""2025-26!AJ3"")"),40.0) -> 40 | CA14: =IFERROR(__xludf.DUMMYFUNCTION("IMPORTRANGE(""132I0fvbfTDk_3h-QeYGrQ-F6z0A921MXbdqyLFsyN5Y"",""2025-26!AK4"")"),1200000.0) -> 1200000 | CB14: =IFERROR(__xludf.DUMMYFUNCTION("IMPORTRANGE(""132I0fvbfTDk_3h-QeYGrQ-F6z0A921MXbdqyLFsyN5Y"",""2025-26!AK3"")"),56.0) -> 56 | CC14: =IFERROR(__xludf.DUMMYFUNCTION("IMPORTRANGE(""132I0fvbfTDk_3h-QeYGrQ-F6z0A921MXbdqyLFsyN5Y"",""2025-26!AL4"")"),1202672.12) -> 1202672.1 | CD14: =IFERROR(__xludf.DUMMYFUNCTION("IMPORTRANGE(""132I0fvbfTDk_3h-QeYGrQ-F6z0A921MXbdqyLFsyN5Y"",""2025-26!AL3"")"),42.0) -> 42 | CE14: =IFERROR((CF14/CA14),"") -> 1.0166192 | CF14: =IFERROR(__xludf.DUMMYFUNCTION("IMPORTRANGE(""132I0fvbfTDk_3h-QeYGrQ-F6z0A921MXbdqyLFsyN5Y"",""2025-26!AM4"")"),1219943.0) -> 1219943 | CG14: =IFERROR(__xludf.DUMMYFUNCTION("IMPORTRANGE(""132I0fvbfTDk_3h-QeYGrQ-F6z0A921MXbdqyLFsyN5Y"",""2025-26!AM3"")"),41.0) -> 41 | CH14: =IFERROR(__xludf.DUMMYFUNCTION("IMPORTRANGE(""132I0fvbfTDk_3h-QeYGrQ-F6z0A921MXbdqyLFsyN5Y"",""2025-26!AN4"")"),1200000.0) -> 1200000 | CI14: =IFERROR(__xludf.DUMMYFUNCTION("IMPORTRANGE(""132I0fvbfTDk_3h-QeYGrQ-F6z0A921MXbdqyLFsyN5Y"",""2025-26!AN3"")"),35.0) -> 35 | CJ14: =IFERROR(__xludf.DUMMYFUNCTION("IMPORTRANGE(""132I0fvbfTDk_3h-QeYGrQ-F6z0A921MXbdqyLFsyN5Y"",""2025-26!AO4"")"),984451.1600000003) -> 984451.16 | CK14: =IFERROR(__xludf.DUMMYFUNCTION("IMPORTRANGE(""132I0fvbfTDk_3h-QeYGrQ-F6z0A921MXbdqyLFsyN5Y"",""2025-26!AO3"")"),41.0) -> 41 | CL14: =IFERROR((CM14/CH14),"") -> 0.82804083 | CM14: =IFERROR(__xludf.DUMMYFUNCTION("IMPORTRANGE(""132I0fvbfTDk_3h-QeYGrQ-F6z0A921MXbdqyLFsyN5Y"",""2025-26!AP4"")"),993649.0) -> 993649 | CN14: =IFERROR(__xludf.DUMMYFUNCTION("IMPORTRANGE(""132I0fvbfTDk_3h-QeYGrQ-F6z0A921MXbdqyLFsyN5Y"",""2025-26!AP3"")"),42.0) -> 42 | CO14: =IFERROR(__xludf.DUMMYFUNCTION("IMPORTRANGE(""132I0fvbfTDk_3h-QeYGrQ-F6z0A921MXbdqyLFsyN5Y"",""2025-26!AQ4"")"),1200000.0) -> 1200000 | CP14: =IFERROR(__xludf.DUMMYFUNCTION("IMPORTRANGE(""132I0fvbfTDk_3h-QeYGrQ-F6z0A921MXbdqyLFsyN5Y"",""2025-26!AQ3"")"),53.0) -> 53 | CQ14: =IFERROR(__xludf.DUMMYFUNCTION("IMPORTRANGE(""132I0fvbfTDk_3h-QeYGrQ-F6z0A921MXbdqyLFsyN5Y"",""2025-26!AR4"")"),903939.6999999998) -> 903939.7 | CR14: =IFERROR(__xludf.DUMMYFUNCTION("IMPORTRANGE(""132I0fvbfTDk_3h-QeYGrQ-F6z0A921MXbdqyLFsyN5Y"",""2025-26!AR3"")"),35.0) -> 35 | CS14: =IFERROR((CT14/CO14),"") -> 0.81223167 | CT14: =IFERROR(__xludf.DUMMYFUNCTION("IMPORTRANGE(""132I0fvbfTDk_3h-QeYGrQ-F6z0A921MXbdqyLFsyN5Y"",""2025-26!AS4"")"),974678.0) -> 974678 | CU14: =IFERROR(__xludf.DUMMYFUNCTION("IMPORTRANGE(""132I0fvbfTDk_3h-QeYGrQ-F6z0A921MXbdqyLFsyN5Y"",""2025-26!AS3"")"),35.0) -> 35 | CV14: Uttarakhand
A15: Anant Singh | C15: Ankit Kumar | D15: Aligarh | E15: 9720224041 | F15: 46002 | I15: 30405 | J15: 1200000 | K15: =IFERROR(__xludf.DUMMYFUNCTION("IMPORTRANGE(""1rYn_Flgp7jo7mcfA8eUDen14LV_dF62DRjmNbnJEK7k"",""2025-26!A3"")"),72.0) -> 72 | L15: =IFERROR(__xludf.DUMMYFUNCTION("IMPORTRANGE(""1rYn_Flgp7jo7mcfA8eUDen14LV_dF62DRjmNbnJEK7k"",""2025-26!G4"")"),3850000.0) -> 3850000 | M15: =R15+Y15+AF15+AM15+AT15+BA15+BH15+BO15+BV15+CC15+CJ15+CQ15 -> 2874423.3 | N15: =O15/L15 -> 0.77432727 | O15: =U15+AB15+AI15+AP15+AW15+BD15+BK15+BR15+BY15+CF15+CM15+CT15 -> 2981160 | P15: =IFERROR(__xludf.DUMMYFUNCTION("IMPORTRANGE(""1rYn_Flgp7jo7mcfA8eUDen14LV_dF62DRjmNbnJEK7k"",""2025-26!J4"")"),0.0) -> 0 | Q15: =IFERROR(__xludf.DUMMYFUNCTION("IMPORTRANGE(""1rYn_Flgp7jo7mcfA8eUDen14LV_dF62DRjmNbnJEK7k"",""2025-26!J3"")"),0.0) -> 0 | R15: =IFERROR(__xludf.DUMMYFUNCTION("IMPORTRANGE(""1rYn_Flgp7jo7mcfA8eUDen14LV_dF62DRjmNbnJEK7k"",""2025-26!K4"")"),0.0) -> 0 | S15: =IFERROR(__xludf.DUMMYFUNCTION("IMPORTRANGE(""1rYn_Flgp7jo7mcfA8eUDen14LV_dF62DRjmNbnJEK7k"",""2025-26!K3"")"),0.0) -> 0 | T15: =IFERROR((U15/P15),"") | U15: =IFERROR(__xludf.DUMMYFUNCTION("IMPORTRANGE(""1rYn_Flgp7jo7mcfA8eUDen14LV_dF62DRjmNbnJEK7k"",""2025-26!L4"")"),0.0) -> 0 | V15: =IFERROR(__xludf.DUMMYFUNCTION("IMPORTRANGE(""1rYn_Flgp7jo7mcfA8eUDen14LV_dF62DRjmNbnJEK7k"",""2025-26!L3"")"),0.0) -> 0 | W15: =IFERROR(__xludf.DUMMYFUNCTION("IMPORTRANGE(""1rYn_Flgp7jo7mcfA8eUDen14LV_dF62DRjmNbnJEK7k"",""2025-26!m4"")"),0.0) -> 0 | X15: =IFERROR(__xludf.DUMMYFUNCTION("IMPORTRANGE(""1rYn_Flgp7jo7mcfA8eUDen14LV_dF62DRjmNbnJEK7k"",""2025-26!m3"")"),0.0) -> 0 | Y15: =IFERROR(__xludf.DUMMYFUNCTION("IMPORTRANGE(""1rYn_Flgp7jo7mcfA8eUDen14LV_dF62DRjmNbnJEK7k"",""2025-26!N4"")"),0.0) -> 0 | Z15: =IFERROR(__xludf.DUMMYFUNCTION("IMPORTRANGE(""1rYn_Flgp7jo7mcfA8eUDen14LV_dF62DRjmNbnJEK7k"",""2025-26!N3"")"),0.0) -> 0 | AA15: =IFERROR((AB15/W15),"") | AB15: =IFERROR(__xludf.DUMMYFUNCTION("IMPORTRANGE(""1rYn_Flgp7jo7mcfA8eUDen14LV_dF62DRjmNbnJEK7k"",""2025-26!O4"")"),0.0) -> 0 | AC15: =IFERROR(__xludf.DUMMYFUNCTION("IMPORTRANGE(""1rYn_Flgp7jo7mcfA8eUDen14LV_dF62DRjmNbnJEK7k"",""2025-26!O3"")"),0.0) -> 0 | AD15: =IFERROR(__xludf.DUMMYFUNCTION("IMPORTRANGE(""1rYn_Flgp7jo7mcfA8eUDen14LV_dF62DRjmNbnJEK7k"",""2025-26!P4"")"),0.0) -> 0 | AE15: =IFERROR(__xludf.DUMMYFUNCTION("IMPORTRANGE(""1rYn_Flgp7jo7mcfA8eUDen14LV_dF62DRjmNbnJEK7k"",""2025-26!P3"")"),0.0) -> 0 | AF15: =IFERROR(__xludf.DUMMYFUNCTION("IMPORTRANGE(""1rYn_Flgp7jo7mcfA8eUDen14LV_dF62DRjmNbnJEK7k"",""2025-26!Q4"")"),0.0) -> 0 | AG15: =IFERROR(__xludf.DUMMYFUNCTION("IMPORTRANGE(""1rYn_Flgp7jo7mcfA8eUDen14LV_dF62DRjmNbnJEK7k"",""2025-26!Q3"")"),0.0) -> 0 | AH15: =IFERROR((AI15/AD15),"") | AI15: =IFERROR(__xludf.DUMMYFUNCTION("IMPORTRANGE(""1rYn_Flgp7jo7mcfA8eUDen14LV_dF62DRjmNbnJEK7k"",""2025-26!R4"")"),0.0) -> 0 | AJ15: =IFERROR(__xludf.DUMMYFUNCTION("IMPORTRANGE(""1rYn_Flgp7jo7mcfA8eUDen14LV_dF62DRjmNbnJEK7k"",""2025-26!R3"")"),0.0) -> 0 | AK15: =IFERROR(__xludf.DUMMYFUNCTION("IMPORTRANGE(""1rYn_Flgp7jo7mcfA8eUDen14LV_dF62DRjmNbnJEK7k"",""2025-26!S4"")"),0.0) -> 0 | AL15: =IFERROR(__xludf.DUMMYFUNCTION("IMPORTRANGE(""1rYn_Flgp7jo7mcfA8eUDen14LV_dF62DRjmNbnJEK7k"",""2025-26!S3"")"),0.0) -> 0 | AM15: =IFERROR(__xludf.DUMMYFUNCTION("IMPORTRANGE(""1rYn_Flgp7jo7mcfA8eUDen14LV_dF62DRjmNbnJEK7k"",""2025-26!T4"")"),0.0) -> 0 | AN15: =IFERROR(__xludf.DUMMYFUNCTION("IMPORTRANGE(""1rYn_Flgp7jo7mcfA8eUDen14LV_dF62DRjmNbnJEK7k"",""2025-26!T3"")"),0.0) -> 0 | AO15: =IFERROR((AP15/AK15),"") | AP15: =IFERROR(__xludf.DUMMYFUNCTION("IMPORTRANGE(""1rYn_Flgp7jo7mcfA8eUDen14LV_dF62DRjmNbnJEK7k"",""2025-26!U4"")"),0.0) -> 0 | AQ15: =IFERROR(__xludf.DUMMYFUNCTION("IMPORTRANGE(""1rYn_Flgp7jo7mcfA8eUDen14LV_dF62DRjmNbnJEK7k"",""2025-26!U3"")"),0.0) -> 0 | AR15: =IFERROR(__xludf.DUMMYFUNCTION("IMPORTRANGE(""1rYn_Flgp7jo7mcfA8eUDen14LV_dF62DRjmNbnJEK7k"",""2025-26!V4"")"),0.0) -> 0 | AS15: =IFERROR(__xludf.DUMMYFUNCTION("IMPORTRANGE(""1rYn_Flgp7jo7mcfA8eUDen14LV_dF62DRjmNbnJEK7k"",""2025-26!V3"")"),0.0) -> 0 | AT15: =IFERROR(__xludf.DUMMYFUNCTION("IMPORTRANGE(""1rYn_Flgp7jo7mcfA8eUDen14LV_dF62DRjmNbnJEK7k"",""2025-26!W4"")"),0.0) -> 0 | AU15: =IFERROR(__xludf.DUMMYFUNCTION("IMPORTRANGE(""1rYn_Flgp7jo7mcfA8eUDen14LV_dF62DRjmNbnJEK7k"",""2025-26!W3"")"),0.0) -> 0 | AV15: =IFERROR((AW15/AR15),"") | AW15: =IFERROR(__xludf.DUMMYFUNCTION("IMPORTRANGE(""1rYn_Flgp7jo7mcfA8eUDen14LV_dF62DRjmNbnJEK7k"",""2025-26!X4"")"),0.0) -> 0 | AX15: =IFERROR(__xludf.DUMMYFUNCTION("IMPORTRANGE(""1rYn_Flgp7jo7mcfA8eUDen14LV_dF62DRjmNbnJEK7k"",""2025-26!X3"")"),0.0) -> 0 | AY15: =IFERROR(__xludf.DUMMYFUNCTION("IMPORTRANGE(""1rYn_Flgp7jo7mcfA8eUDen14LV_dF62DRjmNbnJEK7k"",""2025-26!Y4"")"),0.0) -> 0 | AZ15: =IFERROR(__xludf.DUMMYFUNCTION("IMPORTRANGE(""1rYn_Flgp7jo7mcfA8eUDen14LV_dF62DRjmNbnJEK7k"",""2025-26!Y3"")"),0.0) -> 0 | BA15: =IFERROR(__xludf.DUMMYFUNCTION("IMPORTRANGE(""1rYn_Flgp7jo7mcfA8eUDen14LV_dF62DRjmNbnJEK7k"",""2025-26!Z4"")"),0.0) -> 0 | BB15: =IFERROR(__xludf.DUMMYFUNCTION("IMPORTRANGE(""1rYn_Flgp7jo7mcfA8eUDen14LV_dF62DRjmNbnJEK7k"",""2025-26!Z3"")"),0.0) -> 0 | BC15: =IFERROR((BD15/AY15),"") | BD15: =IFERROR(__xludf.DUMMYFUNCTION("IMPORTRANGE(""1rYn_Flgp7jo7mcfA8eUDen14LV_dF62DRjmNbnJEK7k"",""2025-26!AA4"")"),0.0) -> 0 | BE15: =IFERROR(__xludf.DUMMYFUNCTION("IMPORTRANGE(""1rYn_Flgp7jo7mcfA8eUDen14LV_dF62DRjmNbnJEK7k"",""2025-26!AA3"")"),0.0) -> 0 | BF15: =IFERROR(__xludf.DUMMYFUNCTION("IMPORTRANGE(""1rYn_Flgp7jo7mcfA8eUDen14LV_dF62DRjmNbnJEK7k"",""2025-26!AB4"")"),0.0) -> 0 | BG15: =IFERROR(__xludf.DUMMYFUNCTION("IMPORTRANGE(""1rYn_Flgp7jo7mcfA8eUDen14LV_dF62DRjmNbnJEK7k"",""2025-26!AB3"")"),0.0) -> 0 | BH15: =IFERROR(__xludf.DUMMYFUNCTION("IMPORTRANGE(""1rYn_Flgp7jo7mcfA8eUDen14LV_dF62DRjmNbnJEK7k"",""2025-26!AC4"")"),0.0) -> 0 | BI15: =IFERROR(__xludf.DUMMYFUNCTION("IMPORTRANGE(""1rYn_Flgp7jo7mcfA8eUDen14LV_dF62DRjmNbnJEK7k"",""2025-26!AC3"")"),0.0) -> 0 | BJ15: =IFERROR((BK15/BF15),"") | BK15: =IFERROR(__xludf.DUMMYFUNCTION("IMPORTRANGE(""1rYn_Flgp7jo7mcfA8eUDen14LV_dF62DRjmNbnJEK7k"",""2025-26!AD4"")"),0.0) -> 0 | BL15: =IFERROR(__xludf.DUMMYFUNCTION("IMPORTRANGE(""1rYn_Flgp7jo7mcfA8eUDen14LV_dF62DRjmNbnJEK7k"",""2025-26!AD3"")"),0.0) -> 0 | BM15: =IFERROR(__xludf.DUMMYFUNCTION("IMPORTRANGE(""1rYn_Flgp7jo7mcfA8eUDen14LV_dF62DRjmNbnJEK7k"",""2025-26!AE4"")"),0.0) -> 0 | BN15: =IFERROR(__xludf.DUMMYFUNCTION("IMPORTRANGE(""1rYn_Flgp7jo7mcfA8eUDen14LV_dF62DRjmNbnJEK7k"",""2025-26!AE3"")"),0.0) -> 0 | BO15: =IFERROR(__xludf.DUMMYFUNCTION("IMPORTRANGE(""1rYn_Flgp7jo7mcfA8eUDen14LV_dF62DRjmNbnJEK7k"",""2025-26!AF4"")"),0.0) -> 0 | BP15: =IFERROR(__xludf.DUMMYFUNCTION("IMPORTRANGE(""1rYn_Flgp7jo7mcfA8eUDen14LV_dF62DRjmNbnJEK7k"",""2025-26!AF3"")"),0.0) -> 0 | BQ15: =IFERROR((BR15/BM15),"") | BR15: =IFERROR(__xludf.DUMMYFUNCTION("IMPORTRANGE(""1rYn_Flgp7jo7mcfA8eUDen14LV_dF62DRjmNbnJEK7k"",""2025-26!AG4"")"),0.0) -> 0 | BS15: =IFERROR(__xludf.DUMMYFUNCTION("IMPORTRANGE(""1rYn_Flgp7jo7mcfA8eUDen14LV_dF62DRjmNbnJEK7k"",""2025-26!AG3"")"),0.0) -> 0 | BT15: =IFERROR(__xludf.DUMMYFUNCTION("IMPORTRANGE(""1rYn_Flgp7jo7mcfA8eUDen14LV_dF62DRjmNbnJEK7k"",""2025-26!AH4"")"),0.0) -> 0 | BU15: =IFERROR(__xludf.DUMMYFUNCTION("IMPORTRANGE(""1rYn_Flgp7jo7mcfA8eUDen14LV_dF62DRjmNbnJEK7k"",""2025-26!AH3"")"),0.0) -> 0 | BV15: =IFERROR(__xludf.DUMMYFUNCTION("IMPORTRANGE(""1rYn_Flgp7jo7mcfA8eUDen14LV_dF62DRjmNbnJEK7k"",""2025-26!AI4"")"),458961.05000000005) -> 458961.05 | BW15: =IFERROR(__xludf.DUMMYFUNCTION("IMPORTRANGE(""1rYn_Flgp7jo7mcfA8eUDen14LV_dF62DRjmNbnJEK7k"",""2025-26!AI3"")"),27.0) -> 27 | BX15: =IFERROR((BY15/BT15),"") | BY15: =IFERROR(__xludf.DUMMYFUNCTION("IMPORTRANGE(""1rYn_Flgp7jo7mcfA8eUDen14LV_dF62DRjmNbnJEK7k"",""2025-26!AJ4"")"),0.0) -> 0 | BZ15: =IFERROR(__xludf.DUMMYFUNCTION("IMPORTRANGE(""1rYn_Flgp7jo7mcfA8eUDen14LV_dF62DRjmNbnJEK7k"",""2025-26!AJ3"")"),0.0) -> 0 | CA15: =IFERROR(__xludf.DUMMYFUNCTION("IMPORTRANGE(""1rYn_Flgp7jo7mcfA8eUDen14LV_dF62DRjmNbnJEK7k"",""2025-26!AK4"")"),0.0) -> 0 | CB15: =IFERROR(__xludf.DUMMYFUNCTION("IMPORTRANGE(""1rYn_Flgp7jo7mcfA8eUDen14LV_dF62DRjmNbnJEK7k"",""2025-26!AK3"")"),0.0) -> 0 | CC15: =IFERROR(__xludf.DUMMYFUNCTION("IMPORTRANGE(""1rYn_Flgp7jo7mcfA8eUDen14LV_dF62DRjmNbnJEK7k"",""2025-26!AL4"")"),969316.7000000002) -> 969316.7 | CD15: =IFERROR(__xludf.DUMMYFUNCTION("IMPORTRANGE(""1rYn_Flgp7jo7mcfA8eUDen14LV_dF62DRjmNbnJEK7k"",""2025-26!AL3"")"),24.0) -> 24 | CE15: =IFERROR((CF15/CA15),"") | CF15: =IFERROR(__xludf.DUMMYFUNCTION("IMPORTRANGE(""1rYn_Flgp7jo7mcfA8eUDen14LV_dF62DRjmNbnJEK7k"",""2025-26!AM4"")"),1544500.0) -> 1544500 | CG15: =IFERROR(__xludf.DUMMYFUNCTION("IMPORTRANGE(""1rYn_Flgp7jo7mcfA8eUDen14LV_dF62DRjmNbnJEK7k"",""2025-26!AM3"")"),43.0) -> 43 | CH15: =IFERROR(__xludf.DUMMYFUNCTION("IMPORTRANGE(""1rYn_Flgp7jo7mcfA8eUDen14LV_dF62DRjmNbnJEK7k"",""2025-26!AN4"")"),1770000.0) -> 1770000 | CI15: =IFERROR(__xludf.DUMMYFUNCTION("IMPORTRANGE(""1rYn_Flgp7jo7mcfA8eUDen14LV_dF62DRjmNbnJEK7k"",""2025-26!AN3"")"),54.0) -> 54 | CJ15: =IFERROR(__xludf.DUMMYFUNCTION("IMPORTRANGE(""1rYn_Flgp7jo7mcfA8eUDen14LV_dF62DRjmNbnJEK7k"",""2025-26!AO4"")"),697269.6499999999) -> 697269.65 | CK15: =IFERROR(__xludf.DUMMYFUNCTION("IMPORTRANGE(""1rYn_Flgp7jo7mcfA8eUDen14LV_dF62DRjmNbnJEK7k"",""2025-26!AO3"")"),21.0) -> 21 | CL15: =IFERROR((CM15/CH15),"") -> 0.42053672 | CM15: =IFERROR(__xludf.DUMMYFUNCTION("IMPORTRANGE(""1rYn_Flgp7jo7mcfA8eUDen14LV_dF62DRjmNbnJEK7k"",""2025-26!AP4"")"),744350.0) -> 744350 | CN15: =IFERROR(__xludf.DUMMYFUNCTION("IMPORTRANGE(""1rYn_Flgp7jo7mcfA8eUDen14LV_dF62DRjmNbnJEK7k"",""2025-26!AP3"")"),24.0) -> 24 | CO15: =IFERROR(__xludf.DUMMYFUNCTION("IMPORTRANGE(""1rYn_Flgp7jo7mcfA8eUDen14LV_dF62DRjmNbnJEK7k"",""2025-26!AQ4"")"),1802000.0) -> 1802000 | CP15: =IFERROR(__xludf.DUMMYFUNCTION("IMPORTRANGE(""1rYn_Flgp7jo7mcfA8eUDen14LV_dF62DRjmNbnJEK7k"",""2025-26!AQ3"")"),55.0) -> 55 | CQ15: =IFERROR(__xludf.DUMMYFUNCTION("IMPORTRANGE(""1rYn_Flgp7jo7mcfA8eUDen14LV_dF62DRjmNbnJEK7k"",""2025-26!AR4"")"),748875.86) -> 748875.86 | CR15: =IFERROR(__xludf.DUMMYFUNCTION("IMPORTRANGE(""1rYn_Flgp7jo7mcfA8eUDen14LV_dF62DRjmNbnJEK7k"",""2025-26!AR3"")"),20.0) -> 20 | CS15: =IFERROR((CT15/CO15),"") -> 0.38418979 | CT15: =IFERROR(__xludf.DUMMYFUNCTION("IMPORTRANGE(""1rYn_Flgp7jo7mcfA8eUDen14LV_dF62DRjmNbnJEK7k"",""2025-26!AS4"")"),692310.0) -> 692310 | CU15: =IFERROR(__xludf.DUMMYFUNCTION("IMPORTRANGE(""1rYn_Flgp7jo7mcfA8eUDen14LV_dF62DRjmNbnJEK7k"",""2025-26!AS3"")"),19.0) -> 19 | CV15: West U.P
A16: Anant Singh | C16: Tarun Giri | D16: Meerut | E16: 7536014712 | F16: 46069 | I16: 31455 | J16: 1200000 | K16: =IFERROR(__xludf.DUMMYFUNCTION("IMPORTRANGE(""1K_te1jkI-iFfbgNObYuqxjJkg-GYMv3I58ZA0lOYHRg"",""2025-26!A3"")"),27.0) -> 27 | L16: =IFERROR(__xludf.DUMMYFUNCTION("IMPORTRANGE(""1K_te1jkI-iFfbgNObYuqxjJkg-GYMv3I58ZA0lOYHRg"",""2025-26!G4"")"),0.0) -> 0 | M16: =R16+Y16+AF16+AM16+AT16+BA16+BH16+BO16+BV16+CC16+CJ16+CQ16 -> 835665.65 | N16: =O16/L16 -> #DIV/0! | O16: =U16+AB16+AI16+AP16+AW16+BD16+BK16+BR16+BY16+CF16+CM16+CT16 -> 716782 | P16: =IFERROR(__xludf.DUMMYFUNCTION("IMPORTRANGE(""1K_te1jkI-iFfbgNObYuqxjJkg-GYMv3I58ZA0lOYHRg"",""2025-26!J4"")"),0.0) -> 0 | Q16: =IFERROR(__xludf.DUMMYFUNCTION("IMPORTRANGE(""1K_te1jkI-iFfbgNObYuqxjJkg-GYMv3I58ZA0lOYHRg"",""2025-26!J3"")"),0.0) -> 0 | R16: =IFERROR(__xludf.DUMMYFUNCTION("IMPORTRANGE(""1K_te1jkI-iFfbgNObYuqxjJkg-GYMv3I58ZA0lOYHRg"",""2025-26!K4"")"),0.0) -> 0 | S16: =IFERROR(__xludf.DUMMYFUNCTION("IMPORTRANGE(""1K_te1jkI-iFfbgNObYuqxjJkg-GYMv3I58ZA0lOYHRg"",""2025-26!K3"")"),0.0) -> 0 | T16: =IFERROR((U16/P16),"") | U16: =IFERROR(__xludf.DUMMYFUNCTION("IMPORTRANGE(""1K_te1jkI-iFfbgNObYuqxjJkg-GYMv3I58ZA0lOYHRg"",""2025-26!L4"")"),256170.0) -> 256170 | V16: =IFERROR(__xludf.DUMMYFUNCTION("IMPORTRANGE(""1K_te1jkI-iFfbgNObYuqxjJkg-GYMv3I58ZA0lOYHRg"",""2025-26!L3"")"),7.0) -> 7 | W16: =IFERROR(__xludf.DUMMYFUNCTION("IMPORTRANGE(""1K_te1jkI-iFfbgNObYuqxjJkg-GYMv3I58ZA0lOYHRg"",""2025-26!m4"")"),0.0) -> 0 | X16: =IFERROR(__xludf.DUMMYFUNCTION("IMPORTRANGE(""1K_te1jkI-iFfbgNObYuqxjJkg-GYMv3I58ZA0lOYHRg"",""2025-26!m3"")"),0.0) -> 0 | Y16: =IFERROR(__xludf.DUMMYFUNCTION("IMPORTRANGE(""1K_te1jkI-iFfbgNObYuqxjJkg-GYMv3I58ZA0lOYHRg"",""2025-26!N4"")"),0.0) -> 0 | Z16: =IFERROR(__xludf.DUMMYFUNCTION("IMPORTRANGE(""1K_te1jkI-iFfbgNObYuqxjJkg-GYMv3I58ZA0lOYHRg"",""2025-26!N3"")"),0.0) -> 0 | AA16: =IFERROR((AB16/W16),"") | AB16: =IFERROR(__xludf.DUMMYFUNCTION("IMPORTRANGE(""1K_te1jkI-iFfbgNObYuqxjJkg-GYMv3I58ZA0lOYHRg"",""2025-26!O4"")"),126829.0) -> 126829 | AC16: =IFERROR(__xludf.DUMMYFUNCTION("IMPORTRANGE(""1K_te1jkI-iFfbgNObYuqxjJkg-GYMv3I58ZA0lOYHRg"",""2025-26!O3"")"),2.0) -> 2 | AD16: =IFERROR(__xludf.DUMMYFUNCTION("IMPORTRANGE(""1K_te1jkI-iFfbgNObYuqxjJkg-GYMv3I58ZA0lOYHRg"",""2025-26!P4"")"),0.0) -> 0 | AE16: =IFERROR(__xludf.DUMMYFUNCTION("IMPORTRANGE(""1K_te1jkI-iFfbgNObYuqxjJkg-GYMv3I58ZA0lOYHRg"",""2025-26!P3"")"),0.0) -> 0 | AF16: =IFERROR(__xludf.DUMMYFUNCTION("IMPORTRANGE(""1K_te1jkI-iFfbgNObYuqxjJkg-GYMv3I58ZA0lOYHRg"",""2025-26!Q4"")"),0.0) -> 0 | AG16: =IFERROR(__xludf.DUMMYFUNCTION("IMPORTRANGE(""1K_te1jkI-iFfbgNObYuqxjJkg-GYMv3I58ZA0lOYHRg"",""2025-26!Q3"")"),0.0) -> 0 | AH16: =IFERROR((AI16/AD16),"") | AI16: =IFERROR(__xludf.DUMMYFUNCTION("IMPORTRANGE(""1K_te1jkI-iFfbgNObYuqxjJkg-GYMv3I58ZA0lOYHRg"",""2025-26!R4"")"),9668.0) -> 9668 | AJ16: =IFERROR(__xludf.DUMMYFUNCTION("IMPORTRANGE(""1K_te1jkI-iFfbgNObYuqxjJkg-GYMv3I58ZA0lOYHRg"",""2025-26!R3"")"),1.0) -> 1 | AK16: =IFERROR(__xludf.DUMMYFUNCTION("IMPORTRANGE(""1K_te1jkI-iFfbgNObYuqxjJkg-GYMv3I58ZA0lOYHRg"",""2025-26!S4"")"),0.0) -> 0 | AL16: =IFERROR(__xludf.DUMMYFUNCTION("IMPORTRANGE(""1K_te1jkI-iFfbgNObYuqxjJkg-GYMv3I58ZA0lOYHRg"",""2025-26!S3"")"),0.0) -> 0 | AM16: =IFERROR(__xludf.DUMMYFUNCTION("IMPORTRANGE(""1K_te1jkI-iFfbgNObYuqxjJkg-GYMv3I58ZA0lOYHRg"",""2025-26!T4"")"),0.0) -> 0 | AN16: =IFERROR(__xludf.DUMMYFUNCTION("IMPORTRANGE(""1K_te1jkI-iFfbgNObYuqxjJkg-GYMv3I58ZA0lOYHRg"",""2025-26!T3"")"),0.0) -> 0 | AO16: =IFERROR((AP16/AK16),"") | AP16: =IFERROR(__xludf.DUMMYFUNCTION("IMPORTRANGE(""1K_te1jkI-iFfbgNObYuqxjJkg-GYMv3I58ZA0lOYHRg"",""2025-26!U4"")"),324115.0) -> 324115 | AQ16: =IFERROR(__xludf.DUMMYFUNCTION("IMPORTRANGE(""1K_te1jkI-iFfbgNObYuqxjJkg-GYMv3I58ZA0lOYHRg"",""2025-26!U3"")"),5.0) -> 5 | AR16: =IFERROR(__xludf.DUMMYFUNCTION("IMPORTRANGE(""1K_te1jkI-iFfbgNObYuqxjJkg-GYMv3I58ZA0lOYHRg"",""2025-26!V4"")"),0.0) -> 0 | AS16: =IFERROR(__xludf.DUMMYFUNCTION("IMPORTRANGE(""1K_te1jkI-iFfbgNObYuqxjJkg-GYMv3I58ZA0lOYHRg"",""2025-26!V3"")"),0.0) -> 0 | AT16: =IFERROR(__xludf.DUMMYFUNCTION("IMPORTRANGE(""1K_te1jkI-iFfbgNObYuqxjJkg-GYMv3I58ZA0lOYHRg"",""2025-26!W4"")"),0.0) -> 0 | AU16: =IFERROR(__xludf.DUMMYFUNCTION("IMPORTRANGE(""1K_te1jkI-iFfbgNObYuqxjJkg-GYMv3I58ZA0lOYHRg"",""2025-26!W3"")"),0.0) -> 0 | AV16: =IFERROR((AW16/AR16),"") | AW16: =IFERROR(__xludf.DUMMYFUNCTION("IMPORTRANGE(""1K_te1jkI-iFfbgNObYuqxjJkg-GYMv3I58ZA0lOYHRg"",""2025-26!X4"")"),0.0) -> 0 | AX16: =IFERROR(__xludf.DUMMYFUNCTION("IMPORTRANGE(""1K_te1jkI-iFfbgNObYuqxjJkg-GYMv3I58ZA0lOYHRg"",""2025-26!X3"")"),0.0) -> 0 | AY16: =IFERROR(__xludf.DUMMYFUNCTION("IMPORTRANGE(""1K_te1jkI-iFfbgNObYuqxjJkg-GYMv3I58ZA0lOYHRg"",""2025-26!Y4"")"),0.0) -> 0 | AZ16: =IFERROR(__xludf.DUMMYFUNCTION("IMPORTRANGE(""1K_te1jkI-iFfbgNObYuqxjJkg-GYMv3I58ZA0lOYHRg"",""2025-26!Y3"")"),0.0) -> 0 | BA16: =IFERROR(__xludf.DUMMYFUNCTION("IMPORTRANGE(""1K_te1jkI-iFfbgNObYuqxjJkg-GYMv3I58ZA0lOYHRg"",""2025-26!Z4"")"),0.0) -> 0 | BB16: =IFERROR(__xludf.DUMMYFUNCTION("IMPORTRANGE(""1K_te1jkI-iFfbgNObYuqxjJkg-GYMv3I58ZA0lOYHRg"",""2025-26!Z3"")"),0.0) -> 0 | BC16: =IFERROR((BD16/AY16),"") | BD16: =IFERROR(__xludf.DUMMYFUNCTION("IMPORTRANGE(""1K_te1jkI-iFfbgNObYuqxjJkg-GYMv3I58ZA0lOYHRg"",""2025-26!AA4"")"),0.0) -> 0 | BE16: =IFERROR(__xludf.DUMMYFUNCTION("IMPORTRANGE(""1K_te1jkI-iFfbgNObYuqxjJkg-GYMv3I58ZA0lOYHRg"",""2025-26!AA3"")"),0.0) -> 0 | BF16: =IFERROR(__xludf.DUMMYFUNCTION("IMPORTRANGE(""1K_te1jkI-iFfbgNObYuqxjJkg-GYMv3I58ZA0lOYHRg"",""2025-26!AB4"")"),0.0) -> 0 | BG16: =IFERROR(__xludf.DUMMYFUNCTION("IMPORTRANGE(""1K_te1jkI-iFfbgNObYuqxjJkg-GYMv3I58ZA0lOYHRg"",""2025-26!AB3"")"),0.0) -> 0 | BH16: =IFERROR(__xludf.DUMMYFUNCTION("IMPORTRANGE(""1K_te1jkI-iFfbgNObYuqxjJkg-GYMv3I58ZA0lOYHRg"",""2025-26!AC4"")"),0.0) -> 0 | BI16: =IFERROR(__xludf.DUMMYFUNCTION("IMPORTRANGE(""1K_te1jkI-iFfbgNObYuqxjJkg-GYMv3I58ZA0lOYHRg"",""2025-26!AC3"")"),0.0) -> 0 | BJ16: =IFERROR((BK16/BF16),"") | BK16: =IFERROR(__xludf.DUMMYFUNCTION("IMPORTRANGE(""1K_te1jkI-iFfbgNObYuqxjJkg-GYMv3I58ZA0lOYHRg"",""2025-26!AD4"")"),0.0) -> 0 | BL16: =IFERROR(__xludf.DUMMYFUNCTION("IMPORTRANGE(""1K_te1jkI-iFfbgNObYuqxjJkg-GYMv3I58ZA0lOYHRg"",""2025-26!AD3"")"),0.0) -> 0 | BM16: =IFERROR(__xludf.DUMMYFUNCTION("IMPORTRANGE(""1K_te1jkI-iFfbgNObYuqxjJkg-GYMv3I58ZA0lOYHRg"",""2025-26!AE4"")"),0.0) -> 0 | BN16: =IFERROR(__xludf.DUMMYFUNCTION("IMPORTRANGE(""1K_te1jkI-iFfbgNObYuqxjJkg-GYMv3I58ZA0lOYHRg"",""2025-26!AE3"")"),0.0) -> 0 | BO16: =IFERROR(__xludf.DUMMYFUNCTION("IMPORTRANGE(""1K_te1jkI-iFfbgNObYuqxjJkg-GYMv3I58ZA0lOYHRg"",""2025-26!AF4"")"),0.0) -> 0 | BP16: =IFERROR(__xludf.DUMMYFUNCTION("IMPORTRANGE(""1K_te1jkI-iFfbgNObYuqxjJkg-GYMv3I58ZA0lOYHRg"",""2025-26!AF3"")"),0.0) -> 0 | BQ16: =IFERROR((BR16/BM16),"") | BR16: =IFERROR(__xludf.DUMMYFUNCTION("IMPORTRANGE(""1K_te1jkI-iFfbgNObYuqxjJkg-GYMv3I58ZA0lOYHRg"",""2025-26!AG4"")"),0.0) -> 0 | BS16: =IFERROR(__xludf.DUMMYFUNCTION("IMPORTRANGE(""1K_te1jkI-iFfbgNObYuqxjJkg-GYMv3I58ZA0lOYHRg"",""2025-26!AG3"")"),0.0) -> 0 | BT16: =IFERROR(__xludf.DUMMYFUNCTION("IMPORTRANGE(""1K_te1jkI-iFfbgNObYuqxjJkg-GYMv3I58ZA0lOYHRg"",""2025-26!AH4"")"),0.0) -> 0 | BU16: =IFERROR(__xludf.DUMMYFUNCTION("IMPORTRANGE(""1K_te1jkI-iFfbgNObYuqxjJkg-GYMv3I58ZA0lOYHRg"",""2025-26!AH3"")"),0.0) -> 0 | BV16: =IFERROR(__xludf.DUMMYFUNCTION("IMPORTRANGE(""1K_te1jkI-iFfbgNObYuqxjJkg-GYMv3I58ZA0lOYHRg"",""2025-26!AI4"")"),0.0) -> 0 | BW16: =IFERROR(__xludf.DUMMYFUNCTION("IMPORTRANGE(""1K_te1jkI-iFfbgNObYuqxjJkg-GYMv3I58ZA0lOYHRg"",""2025-26!AI3"")"),0.0) -> 0 | BX16: =IFERROR((BY16/BT16),"") | BY16: =IFERROR(__xludf.DUMMYFUNCTION("IMPORTRANGE(""1K_te1jkI-iFfbgNObYuqxjJkg-GYMv3I58ZA0lOYHRg"",""2025-26!AJ4"")"),0.0) -> 0 | BZ16: =IFERROR(__xludf.DUMMYFUNCTION("IMPORTRANGE(""1K_te1jkI-iFfbgNObYuqxjJkg-GYMv3I58ZA0lOYHRg"",""2025-26!AJ3"")"),0.0) -> 0 | CA16: =IFERROR(__xludf.DUMMYFUNCTION("IMPORTRANGE(""1K_te1jkI-iFfbgNObYuqxjJkg-GYMv3I58ZA0lOYHRg"",""2025-26!AK4"")"),0.0) -> 0 | CB16: =IFERROR(__xludf.DUMMYFUNCTION("IMPORTRANGE(""1K_te1jkI-iFfbgNObYuqxjJkg-GYMv3I58ZA0lOYHRg"",""2025-26!AK3"")"),0.0) -> 0 | CC16: =IFERROR(__xludf.DUMMYFUNCTION("IMPORTRANGE(""1K_te1jkI-iFfbgNObYuqxjJkg-GYMv3I58ZA0lOYHRg"",""2025-26!AL4"")"),0.0) -> 0 | CD16: =IFERROR(__xludf.DUMMYFUNCTION("IMPORTRANGE(""1K_te1jkI-iFfbgNObYuqxjJkg-GYMv3I58ZA0lOYHRg"",""2025-26!AL3"")"),0.0) -> 0 | CE16: =IFERROR((CF16/CA16),"") | CF16: =IFERROR(__xludf.DUMMYFUNCTION("IMPORTRANGE(""1K_te1jkI-iFfbgNObYuqxjJkg-GYMv3I58ZA0lOYHRg"",""2025-26!AM4"")"),0.0) -> 0 | CG16: =IFERROR(__xludf.DUMMYFUNCTION("IMPORTRANGE(""1K_te1jkI-iFfbgNObYuqxjJkg-GYMv3I58ZA0lOYHRg"",""2025-26!AM3"")"),0.0) -> 0 | CH16: =IFERROR(__xludf.DUMMYFUNCTION("IMPORTRANGE(""1K_te1jkI-iFfbgNObYuqxjJkg-GYMv3I58ZA0lOYHRg"",""2025-26!AN4"")"),0.0) -> 0 | CI16: =IFERROR(__xludf.DUMMYFUNCTION("IMPORTRANGE(""1K_te1jkI-iFfbgNObYuqxjJkg-GYMv3I58ZA0lOYHRg"",""2025-26!AN3"")"),0.0) -> 0 | CJ16: =IFERROR(__xludf.DUMMYFUNCTION("IMPORTRANGE(""1K_te1jkI-iFfbgNObYuqxjJkg-GYMv3I58ZA0lOYHRg"",""2025-26!AO4"")"),118904.09999999999) -> 118904.1 | CK16: =IFERROR(__xludf.DUMMYFUNCTION("IMPORTRANGE(""1K_te1jkI-iFfbgNObYuqxjJkg-GYMv3I58ZA0lOYHRg"",""2025-26!AO3"")"),5.0) -> 5 | CL16: =IFERROR((CM16/CH16),"") | CM16: =IFERROR(__xludf.DUMMYFUNCTION("IMPORTRANGE(""1K_te1jkI-iFfbgNObYuqxjJkg-GYMv3I58ZA0lOYHRg"",""2025-26!AP4"")"),0.0) -> 0 | CN16: =IFERROR(__xludf.DUMMYFUNCTION("IMPORTRANGE(""1K_te1jkI-iFfbgNObYuqxjJkg-GYMv3I58ZA0lOYHRg"",""2025-26!AP3"")"),0.0) -> 0 | CO16: =IFERROR(__xludf.DUMMYFUNCTION("IMPORTRANGE(""1K_te1jkI-iFfbgNObYuqxjJkg-GYMv3I58ZA0lOYHRg"",""2025-26!AQ4"")"),0.0) -> 0 | CP16: =IFERROR(__xludf.DUMMYFUNCTION("IMPORTRANGE(""1K_te1jkI-iFfbgNObYuqxjJkg-GYMv3I58ZA0lOYHRg"",""2025-26!AQ3"")"),0.0) -> 0 | CQ16: =IFERROR(__xludf.DUMMYFUNCTION("IMPORTRANGE(""1K_te1jkI-iFfbgNObYuqxjJkg-GYMv3I58ZA0lOYHRg"",""2025-26!AR4"")"),716761.5499999999) -> 716761.55 | CR16: =IFERROR(__xludf.DUMMYFUNCTION("IMPORTRANGE(""1K_te1jkI-iFfbgNObYuqxjJkg-GYMv3I58ZA0lOYHRg"",""2025-26!AR3"")"),13.0) -> 13 | CS16: =IFERROR((CT16/CO16),"") | CT16: =IFERROR(__xludf.DUMMYFUNCTION("IMPORTRANGE(""1K_te1jkI-iFfbgNObYuqxjJkg-GYMv3I58ZA0lOYHRg"",""2025-26!AS4"")"),0.0) -> 0 | CU16: =IFERROR(__xludf.DUMMYFUNCTION("IMPORTRANGE(""1K_te1jkI-iFfbgNObYuqxjJkg-GYMv3I58ZA0lOYHRg"",""2025-26!AS3"")"),0.0) -> 0 | CV16: West U.P
A17: Sulinder Pal | B17: Sulinder Pal | C17: Ranjit Kumar | D17: Abohar | E17: 7428099946 | F17: 45311 | I17: =VLOOKUP($C17,Data!$C:$BV,72,0) -> 28835 | J17: 833333 | K17: =IFERROR(__xludf.DUMMYFUNCTION("IMPORTRANGE(""1IoSPGtbL4ygnaTCF1Ct5WGA347GvBvKfaHJjalIvqh4"",""2025-26!A3"")"),76.0) -> 76 | L17: =IFERROR(__xludf.DUMMYFUNCTION("IMPORTRANGE(""1IoSPGtbL4ygnaTCF1Ct5WGA347GvBvKfaHJjalIvqh4"",""2025-26!G4"")"),8750000.0) -> 8750000 | M17: =R17+Y17+AF17+AM17+AT17+BA17+BH17+BO17+BV17+CC17+CJ17+CQ17 -> 6639185.6 | N17: =O17/L17 -> 0.78705646 | O17: =U17+AB17+AI17+AP17+AW17+BD17+BK17+BR17+BY17+CF17+CM17+CT17 -> 6886744 | P17: =IFERROR(__xludf.DUMMYFUNCTION("IMPORTRANGE(""1IoSPGtbL4ygnaTCF1Ct5WGA347GvBvKfaHJjalIvqh4"",""2025-26!J4"")"),675900.0) -> 675900 | Q17: =IFERROR(__xludf.DUMMYFUNCTION("IMPORTRANGE(""1IoSPGtbL4ygnaTCF1Ct5WGA347GvBvKfaHJjalIvqh4"",""2025-26!J3"")"),69.0) -> 69 | R17: =IFERROR(__xludf.DUMMYFUNCTION("IMPORTRANGE(""1IoSPGtbL4ygnaTCF1Ct5WGA347GvBvKfaHJjalIvqh4"",""2025-26!K4"")"),730928.8799999999) -> 730928.88 | S17: =IFERROR(__xludf.DUMMYFUNCTION("IMPORTRANGE(""1IoSPGtbL4ygnaTCF1Ct5WGA347GvBvKfaHJjalIvqh4"",""2025-26!K3"")"),59.0) -> 59 | T17: =IFERROR((U17/P17),"") -> 1.1183814 | U17: =IFERROR(__xludf.DUMMYFUNCTION("IMPORTRANGE(""1IoSPGtbL4ygnaTCF1Ct5WGA347GvBvKfaHJjalIvqh4"",""2025-26!L4"")"),755914.0) -> 755914 | V17: =IFERROR(__xludf.DUMMYFUNCTION("IMPORTRANGE(""1IoSPGtbL4ygnaTCF1Ct5WGA347GvBvKfaHJjalIvqh4"",""2025-26!L3"")"),59.0) -> 59 | W17: =IFERROR(__xludf.DUMMYFUNCTION("IMPORTRANGE(""1IoSPGtbL4ygnaTCF1Ct5WGA347GvBvKfaHJjalIvqh4"",""2025-26!m4"")"),691900.0) -> 691900 | X17: =IFERROR(__xludf.DUMMYFUNCTION("IMPORTRANGE(""1IoSPGtbL4ygnaTCF1Ct5WGA347GvBvKfaHJjalIvqh4"",""2025-26!m3"")"),71.0) -> 71 | Y17: =IFERROR(__xludf.DUMMYFUNCTION("IMPORTRANGE(""1IoSPGtbL4ygnaTCF1Ct5WGA347GvBvKfaHJjalIvqh4"",""2025-26!N4"")"),645506.9300000002) -> 645506.93 | Z17: =IFERROR(__xludf.DUMMYFUNCTION("IMPORTRANGE(""1IoSPGtbL4ygnaTCF1Ct5WGA347GvBvKfaHJjalIvqh4"",""2025-26!N3"")"),55.0) -> 55 | AA17: =IFERROR((AB17/W17),"") -> 0.99927302 | AB17: =IFERROR(__xludf.DUMMYFUNCTION("IMPORTRANGE(""1IoSPGtbL4ygnaTCF1Ct5WGA347GvBvKfaHJjalIvqh4"",""2025-26!O4"")"),691397.0) -> 691397 | AC17: =IFERROR(__xludf.DUMMYFUNCTION("IMPORTRANGE(""1IoSPGtbL4ygnaTCF1Ct5WGA347GvBvKfaHJjalIvqh4"",""2025-26!O3"")"),55.0) -> 55 | AD17: =IFERROR(__xludf.DUMMYFUNCTION("IMPORTRANGE(""1IoSPGtbL4ygnaTCF1Ct5WGA347GvBvKfaHJjalIvqh4"",""2025-26!P4"")"),633800.0) -> 633800 | AE17: =IFERROR(__xludf.DUMMYFUNCTION("IMPORTRANGE(""1IoSPGtbL4ygnaTCF1Ct5WGA347GvBvKfaHJjalIvqh4"",""2025-26!P3"")"),64.0) -> 64 | AF17: =IFERROR(__xludf.DUMMYFUNCTION("IMPORTRANGE(""1IoSPGtbL4ygnaTCF1Ct5WGA347GvBvKfaHJjalIvqh4"",""2025-26!Q4"")"),436145.14) -> 436145.14 | AG17: =IFERROR(__xludf.DUMMYFUNCTION("IMPORTRANGE(""1IoSPGtbL4ygnaTCF1Ct5WGA347GvBvKfaHJjalIvqh4"",""2025-26!Q3"")"),43.0) -> 43 | AH17: =IFERROR((AI17/AD17),"") -> 0.70551594 | AI17: =IFERROR(__xludf.DUMMYFUNCTION("IMPORTRANGE(""1IoSPGtbL4ygnaTCF1Ct5WGA347GvBvKfaHJjalIvqh4"",""2025-26!R4"")"),447156.0) -> 447156 | AJ17: =IFERROR(__xludf.DUMMYFUNCTION("IMPORTRANGE(""1IoSPGtbL4ygnaTCF1Ct5WGA347GvBvKfaHJjalIvqh4"",""2025-26!R3"")"),43.0) -> 43 | AK17: =IFERROR(__xludf.DUMMYFUNCTION("IMPORTRANGE(""1IoSPGtbL4ygnaTCF1Ct5WGA347GvBvKfaHJjalIvqh4"",""2025-26!S4"")"),604400.0) -> 604400 | AL17: =IFERROR(__xludf.DUMMYFUNCTION("IMPORTRANGE(""1IoSPGtbL4ygnaTCF1Ct5WGA347GvBvKfaHJjalIvqh4"",""2025-26!S3"")"),64.0) -> 64 | AM17: =IFERROR(__xludf.DUMMYFUNCTION("IMPORTRANGE(""1IoSPGtbL4ygnaTCF1Ct5WGA347GvBvKfaHJjalIvqh4"",""2025-26!T4"")"),395739.72) -> 395739.72 | AN17: =IFERROR(__xludf.DUMMYFUNCTION("IMPORTRANGE(""1IoSPGtbL4ygnaTCF1Ct5WGA347GvBvKfaHJjalIvqh4"",""2025-26!T3"")"),50.0) -> 50 | AO17: =IFERROR((AP17/AK17),"") -> 0.5670268 | AP17: =IFERROR(__xludf.DUMMYFUNCTION("IMPORTRANGE(""1IoSPGtbL4ygnaTCF1Ct5WGA347GvBvKfaHJjalIvqh4"",""2025-26!U4"")"),342711.0) -> 342711 | AQ17: =IFERROR(__xludf.DUMMYFUNCTION("IMPORTRANGE(""1IoSPGtbL4ygnaTCF1Ct5WGA347GvBvKfaHJjalIvqh4"",""2025-26!U3"")"),41.0) -> 41 | AR17: =IFERROR(__xludf.DUMMYFUNCTION("IMPORTRANGE(""1IoSPGtbL4ygnaTCF1Ct5WGA347GvBvKfaHJjalIvqh4"",""2025-26!V4"")"),645800.0) -> 645800 | AS17: =IFERROR(__xludf.DUMMYFUNCTION("IMPORTRANGE(""1IoSPGtbL4ygnaTCF1Ct5WGA347GvBvKfaHJjalIvqh4"",""2025-26!V3"")"),65.0) -> 65 | AT17: =IFERROR(__xludf.DUMMYFUNCTION("IMPORTRANGE(""1IoSPGtbL4ygnaTCF1Ct5WGA347GvBvKfaHJjalIvqh4"",""2025-26!W4"")"),306528.89) -> 306528.89 | AU17: =IFERROR(__xludf.DUMMYFUNCTION("IMPORTRANGE(""1IoSPGtbL4ygnaTCF1Ct5WGA347GvBvKfaHJjalIvqh4"",""2025-26!W3"")"),40.0) -> 40 | AV17: =IFERROR((AW17/AR17),"") -> 0.48855218 | AW17: =IFERROR(__xludf.DUMMYFUNCTION("IMPORTRANGE(""1IoSPGtbL4ygnaTCF1Ct5WGA347GvBvKfaHJjalIvqh4"",""2025-26!X4"")"),315507.0) -> 315507 | AX17: =IFERROR(__xludf.DUMMYFUNCTION("IMPORTRANGE(""1IoSPGtbL4ygnaTCF1Ct5WGA347GvBvKfaHJjalIvqh4"",""2025-26!X3"")"),43.0) -> 43 | AY17: =IFERROR(__xludf.DUMMYFUNCTION("IMPORTRANGE(""1IoSPGtbL4ygnaTCF1Ct5WGA347GvBvKfaHJjalIvqh4"",""2025-26!Y4"")"),645800.0) -> 645800 | AZ17: =IFERROR(__xludf.DUMMYFUNCTION("IMPORTRANGE(""1IoSPGtbL4ygnaTCF1Ct5WGA347GvBvKfaHJjalIvqh4"",""2025-26!Y3"")"),65.0) -> 65 | BA17: =IFERROR(__xludf.DUMMYFUNCTION("IMPORTRANGE(""1IoSPGtbL4ygnaTCF1Ct5WGA347GvBvKfaHJjalIvqh4"",""2025-26!Z4"")"),390281.55999999994) -> 390281.56 | BB17: =IFERROR(__xludf.DUMMYFUNCTION("IMPORTRANGE(""1IoSPGtbL4ygnaTCF1Ct5WGA347GvBvKfaHJjalIvqh4"",""2025-26!Z3"")"),51.0) -> 51 | BC17: =IFERROR((BD17/AY17),"") -> 0.58888356 | BD17: =IFERROR(__xludf.DUMMYFUNCTION("IMPORTRANGE(""1IoSPGtbL4ygnaTCF1Ct5WGA347GvBvKfaHJjalIvqh4"",""2025-26!AA4"")"),380301.0) -> 380301 | BE17: =IFERROR(__xludf.DUMMYFUNCTION("IMPORTRANGE(""1IoSPGtbL4ygnaTCF1Ct5WGA347GvBvKfaHJjalIvqh4"",""2025-26!AA3"")"),48.0) -> 48 | BF17: =IFERROR(__xludf.DUMMYFUNCTION("IMPORTRANGE(""1IoSPGtbL4ygnaTCF1Ct5WGA347GvBvKfaHJjalIvqh4"",""2025-26!AB4"")"),722900.0) -> 722900 | BG17: =IFERROR(__xludf.DUMMYFUNCTION("IMPORTRANGE(""1IoSPGtbL4ygnaTCF1Ct5WGA347GvBvKfaHJjalIvqh4"",""2025-26!AB3"")"),66.0) -> 66 | BH17: =IFERROR(__xludf.DUMMYFUNCTION("IMPORTRANGE(""1IoSPGtbL4ygnaTCF1Ct5WGA347GvBvKfaHJjalIvqh4"",""2025-26!AC4"")"),490023.0999999999) -> 490023.1 | BI17: =IFERROR(__xludf.DUMMYFUNCTION("IMPORTRANGE(""1IoSPGtbL4ygnaTCF1Ct5WGA347GvBvKfaHJjalIvqh4"",""2025-26!AC3"")"),49.0) -> 49 | BJ17: =IFERROR((BK17/BF17),"") -> 0.75625813 | BK17: =IFERROR(__xludf.DUMMYFUNCTION("IMPORTRANGE(""1IoSPGtbL4ygnaTCF1Ct5WGA347GvBvKfaHJjalIvqh4"",""2025-26!AD4"")"),546699.0) -> 546699 | BL17: =IFERROR(__xludf.DUMMYFUNCTION("IMPORTRANGE(""1IoSPGtbL4ygnaTCF1Ct5WGA347GvBvKfaHJjalIvqh4"",""2025-26!AD3"")"),54.0) -> 54 | BM17: =IFERROR(__xludf.DUMMYFUNCTION("IMPORTRANGE(""1IoSPGtbL4ygnaTCF1Ct5WGA347GvBvKfaHJjalIvqh4"",""2025-26!AE4"")"),737900.0) -> 737900 | BN17: =IFERROR(__xludf.DUMMYFUNCTION("IMPORTRANGE(""1IoSPGtbL4ygnaTCF1Ct5WGA347GvBvKfaHJjalIvqh4"",""2025-26!AE3"")"),67.0) -> 67 | BO17: =IFERROR(__xludf.DUMMYFUNCTION("IMPORTRANGE(""1IoSPGtbL4ygnaTCF1Ct5WGA347GvBvKfaHJjalIvqh4"",""2025-26!AF4"")"),435227.79999999993) -> 435227.8 | BP17: =IFERROR(__xludf.DUMMYFUNCTION("IMPORTRANGE(""1IoSPGtbL4ygnaTCF1Ct5WGA347GvBvKfaHJjalIvqh4"",""2025-26!AF3"")"),49.0) -> 49 | BQ17: =IFERROR((BR17/BM17),"") -> 0.60925464 | BR17: =IFERROR(__xludf.DUMMYFUNCTION("IMPORTRANGE(""1IoSPGtbL4ygnaTCF1Ct5WGA347GvBvKfaHJjalIvqh4"",""2025-26!AG4"")"),449569.0) -> 449569 | BS17: =IFERROR(__xludf.DUMMYFUNCTION("IMPORTRANGE(""1IoSPGtbL4ygnaTCF1Ct5WGA347GvBvKfaHJjalIvqh4"",""2025-26!AG3"")"),48.0) -> 48 | BT17: =IFERROR(__xludf.DUMMYFUNCTION("IMPORTRANGE(""1IoSPGtbL4ygnaTCF1Ct5WGA347GvBvKfaHJjalIvqh4"",""2025-26!AH4"")"),737900.0) -> 737900 | BU17: =IFERROR(__xludf.DUMMYFUNCTION("IMPORTRANGE(""1IoSPGtbL4ygnaTCF1Ct5WGA347GvBvKfaHJjalIvqh4"",""2025-26!AH3"")"),67.0) -> 67 | BV17: =IFERROR(__xludf.DUMMYFUNCTION("IMPORTRANGE(""1IoSPGtbL4ygnaTCF1Ct5WGA347GvBvKfaHJjalIvqh4"",""2025-26!AI4"")"),661369.14) -> 661369.14 | BW17: =IFERROR(__xludf.DUMMYFUNCTION("IMPORTRANGE(""1IoSPGtbL4ygnaTCF1Ct5WGA347GvBvKfaHJjalIvqh4"",""2025-26!AI3"")"),51.0) -> 51 | BX17: =IFERROR((BY17/BT17),"") -> 0.92527985 | BY17: =IFERROR(__xludf.DUMMYFUNCTION("IMPORTRANGE(""1IoSPGtbL4ygnaTCF1Ct5WGA347GvBvKfaHJjalIvqh4"",""2025-26!AJ4"")"),682764.0) -> 682764 | BZ17: =IFERROR(__xludf.DUMMYFUNCTION("IMPORTRANGE(""1IoSPGtbL4ygnaTCF1Ct5WGA347GvBvKfaHJjalIvqh4"",""2025-26!AJ3"")"),52.0) -> 52 | CA17: =IFERROR(__xludf.DUMMYFUNCTION("IMPORTRANGE(""1IoSPGtbL4ygnaTCF1Ct5WGA347GvBvKfaHJjalIvqh4"",""2025-26!AK4"")"),737900.0) -> 737900 | CB17: =IFERROR(__xludf.DUMMYFUNCTION("IMPORTRANGE(""1IoSPGtbL4ygnaTCF1Ct5WGA347GvBvKfaHJjalIvqh4"",""2025-26!AK3"")"),67.0) -> 67 | CC17: =IFERROR(__xludf.DUMMYFUNCTION("IMPORTRANGE(""1IoSPGtbL4ygnaTCF1Ct5WGA347GvBvKfaHJjalIvqh4"",""2025-26!AL4"")"),684869.2) -> 684869.2 | CD17: =IFERROR(__xludf.DUMMYFUNCTION("IMPORTRANGE(""1IoSPGtbL4ygnaTCF1Ct5WGA347GvBvKfaHJjalIvqh4"",""2025-26!AL3"")"),47.0) -> 47 | CE17: =IFERROR((CF17/CA17),"") -> 1.0419637 | CF17: =IFERROR(__xludf.DUMMYFUNCTION("IMPORTRANGE(""1IoSPGtbL4ygnaTCF1Ct5WGA347GvBvKfaHJjalIvqh4"",""2025-26!AM4"")"),768865.0) -> 768865 | CG17: =IFERROR(__xludf.DUMMYFUNCTION("IMPORTRANGE(""1IoSPGtbL4ygnaTCF1Ct5WGA347GvBvKfaHJjalIvqh4"",""2025-26!AM3"")"),48.0) -> 48 | CH17: =IFERROR(__xludf.DUMMYFUNCTION("IMPORTRANGE(""1IoSPGtbL4ygnaTCF1Ct5WGA347GvBvKfaHJjalIvqh4"",""2025-26!AN4"")"),737900.0) -> 737900 | CI17: =IFERROR(__xludf.DUMMYFUNCTION("IMPORTRANGE(""1IoSPGtbL4ygnaTCF1Ct5WGA347GvBvKfaHJjalIvqh4"",""2025-26!AN3"")"),67.0) -> 67 | CJ17: =IFERROR(__xludf.DUMMYFUNCTION("IMPORTRANGE(""1IoSPGtbL4ygnaTCF1Ct5WGA347GvBvKfaHJjalIvqh4"",""2025-26!AO4"")"),783677.82) -> 783677.82 | CK17: =IFERROR(__xludf.DUMMYFUNCTION("IMPORTRANGE(""1IoSPGtbL4ygnaTCF1Ct5WGA347GvBvKfaHJjalIvqh4"",""2025-26!AO3"")"),51.0) -> 51 | CL17: =IFERROR((CM17/CH17),"") -> 1.1126616 | CM17: =IFERROR(__xludf.DUMMYFUNCTION("IMPORTRANGE(""1IoSPGtbL4ygnaTCF1Ct5WGA347GvBvKfaHJjalIvqh4"",""2025-26!AP4"")"),821033.0) -> 821033 | CN17: =IFERROR(__xludf.DUMMYFUNCTION("IMPORTRANGE(""1IoSPGtbL4ygnaTCF1Ct5WGA347GvBvKfaHJjalIvqh4"",""2025-26!AP3"")"),53.0) -> 53 | CO17: =IFERROR(__xludf.DUMMYFUNCTION("IMPORTRANGE(""1IoSPGtbL4ygnaTCF1Ct5WGA347GvBvKfaHJjalIvqh4"",""2025-26!AQ4"")"),737900.0) -> 737900 | CP17: =IFERROR(__xludf.DUMMYFUNCTION("IMPORTRANGE(""1IoSPGtbL4ygnaTCF1Ct5WGA347GvBvKfaHJjalIvqh4"",""2025-26!AQ3"")"),67.0) -> 67 | CQ17: =IFERROR(__xludf.DUMMYFUNCTION("IMPORTRANGE(""1IoSPGtbL4ygnaTCF1Ct5WGA347GvBvKfaHJjalIvqh4"",""2025-26!AR4"")"),678887.4099999997) -> 678887.41 | CR17: =IFERROR(__xludf.DUMMYFUNCTION("IMPORTRANGE(""1IoSPGtbL4ygnaTCF1Ct5WGA347GvBvKfaHJjalIvqh4"",""2025-26!AR3"")"),48.0) -> 48 | CS17: =IFERROR((CT17/CO17),"") -> 0.92807698 | CT17: =IFERROR(__xludf.DUMMYFUNCTION("IMPORTRANGE(""1IoSPGtbL4ygnaTCF1Ct5WGA347GvBvKfaHJjalIvqh4"",""2025-26!AS4"")"),684828.0) -> 684828 | CU17: =IFERROR(__xludf.DUMMYFUNCTION("IMPORTRANGE(""1IoSPGtbL4ygnaTCF1Ct5WGA347GvBvKfaHJjalIvqh4"",""2025-26!AS3"")"),47.0) -> 47 | CV17: Punjab
A18: Sulinder Pal | C18: Amit Tangri | D18: Ludhiana | E18: 9914976557 | F18: 45393 | I18: =VLOOKUP($C18,Data!$C:$BV,72,0) -> 27000 | J18: 1250000 | K18: =IFERROR(__xludf.DUMMYFUNCTION("IMPORTRANGE(""1OCQdqqJIyWUmzr6sv4fbXUNAqVATScHotcGYSPP6YEs"",""2025-26!A3"")"),164.0) -> 164 | L18: =IFERROR(__xludf.DUMMYFUNCTION("IMPORTRANGE(""1OCQdqqJIyWUmzr6sv4fbXUNAqVATScHotcGYSPP6YEs"",""2025-26!G4"")"),8865000.0) -> 8865000 | M18: =R18+Y18+AF18+AM18+AT18+BA18+BH18+BO18+BV18+CC18+CJ18+CQ18 -> 6963246.2 | N18: =O18/L18 -> 0.75186999 | O18: =U18+AB18+AI18+AP18+AW18+BD18+BK18+BR18+BY18+CF18+CM18+CT18 -> 6665327.5 | P18: =IFERROR(__xludf.DUMMYFUNCTION("IMPORTRANGE(""1OCQdqqJIyWUmzr6sv4fbXUNAqVATScHotcGYSPP6YEs"",""2025-26!J4"")"),615000.0) -> 615000 | Q18: =IFERROR(__xludf.DUMMYFUNCTION("IMPORTRANGE(""1OCQdqqJIyWUmzr6sv4fbXUNAqVATScHotcGYSPP6YEs"",""2025-26!J3"")"),88.0) -> 88 | R18: =IFERROR(__xludf.DUMMYFUNCTION("IMPORTRANGE(""1OCQdqqJIyWUmzr6sv4fbXUNAqVATScHotcGYSPP6YEs"",""2025-26!K4"")"),537647.49) -> 537647.49 | S18: =IFERROR(__xludf.DUMMYFUNCTION("IMPORTRANGE(""1OCQdqqJIyWUmzr6sv4fbXUNAqVATScHotcGYSPP6YEs"",""2025-26!K3"")"),42.0) -> 42 | T18: =IFERROR((U18/P18),"") -> 0.81983577 | U18: =IFERROR(__xludf.DUMMYFUNCTION("IMPORTRANGE(""1OCQdqqJIyWUmzr6sv4fbXUNAqVATScHotcGYSPP6YEs"",""2025-26!L4"")"),504199.0) -> 504199 | V18: =IFERROR(__xludf.DUMMYFUNCTION("IMPORTRANGE(""1OCQdqqJIyWUmzr6sv4fbXUNAqVATScHotcGYSPP6YEs"",""2025-26!L3"")"),40.0) -> 40 | W18: =IFERROR(__xludf.DUMMYFUNCTION("IMPORTRANGE(""1OCQdqqJIyWUmzr6sv4fbXUNAqVATScHotcGYSPP6YEs"",""2025-26!m4"")"),633000.0) -> 633000 | X18: =IFERROR(__xludf.DUMMYFUNCTION("IMPORTRANGE(""1OCQdqqJIyWUmzr6sv4fbXUNAqVATScHotcGYSPP6YEs"",""2025-26!m3"")"),91.0) -> 91 | Y18: =IFERROR(__xludf.DUMMYFUNCTION("IMPORTRANGE(""1OCQdqqJIyWUmzr6sv4fbXUNAqVATScHotcGYSPP6YEs"",""2025-26!N4"")"),465790.64) -> 465790.64 | Z18: =IFERROR(__xludf.DUMMYFUNCTION("IMPORTRANGE(""1OCQdqqJIyWUmzr6sv4fbXUNAqVATScHotcGYSPP6YEs"",""2025-26!N3"")"),37.0) -> 37 | AA18: =IFERROR((AB18/W18),"") -> 0.6931169 | AB18: =IFERROR(__xludf.DUMMYFUNCTION("IMPORTRANGE(""1OCQdqqJIyWUmzr6sv4fbXUNAqVATScHotcGYSPP6YEs"",""2025-26!O4"")"),438743.0) -> 438743 | AC18: =IFERROR(__xludf.DUMMYFUNCTION("IMPORTRANGE(""1OCQdqqJIyWUmzr6sv4fbXUNAqVATScHotcGYSPP6YEs"",""2025-26!O3"")"),34.0) -> 34 | AD18: =IFERROR(__xludf.DUMMYFUNCTION("IMPORTRANGE(""1OCQdqqJIyWUmzr6sv4fbXUNAqVATScHotcGYSPP6YEs"",""2025-26!P4"")"),633000.0) -> 633000 | AE18: =IFERROR(__xludf.DUMMYFUNCTION("IMPORTRANGE(""1OCQdqqJIyWUmzr6sv4fbXUNAqVATScHotcGYSPP6YEs"",""2025-26!P3"")"),91.0) -> 91 | AF18: =IFERROR(__xludf.DUMMYFUNCTION("IMPORTRANGE(""1OCQdqqJIyWUmzr6sv4fbXUNAqVATScHotcGYSPP6YEs"",""2025-26!Q4"")"),349907.37000000005) -> 349907.37 | AG18: =IFERROR(__xludf.DUMMYFUNCTION("IMPORTRANGE(""1OCQdqqJIyWUmzr6sv4fbXUNAqVATScHotcGYSPP6YEs"",""2025-26!Q3"")"),38.0) -> 38 | AH18: =IFERROR((AI18/AD18),"") -> 0.57479542 | AI18: =IFERROR(__xludf.DUMMYFUNCTION("IMPORTRANGE(""1OCQdqqJIyWUmzr6sv4fbXUNAqVATScHotcGYSPP6YEs"",""2025-26!R4"")"),363845.5) -> 363845.5 | AJ18: =IFERROR(__xludf.DUMMYFUNCTION("IMPORTRANGE(""1OCQdqqJIyWUmzr6sv4fbXUNAqVATScHotcGYSPP6YEs"",""2025-26!R3"")"),39.0) -> 39 | AK18: =IFERROR(__xludf.DUMMYFUNCTION("IMPORTRANGE(""1OCQdqqJIyWUmzr6sv4fbXUNAqVATScHotcGYSPP6YEs"",""2025-26!S4"")"),756000.0) -> 756000 | AL18: =IFERROR(__xludf.DUMMYFUNCTION("IMPORTRANGE(""1OCQdqqJIyWUmzr6sv4fbXUNAqVATScHotcGYSPP6YEs"",""2025-26!S3"")"),93.0) -> 93 | AM18: =IFERROR(__xludf.DUMMYFUNCTION("IMPORTRANGE(""1OCQdqqJIyWUmzr6sv4fbXUNAqVATScHotcGYSPP6YEs"",""2025-26!T4"")"),309427.47) -> 309427.47 | AN18: =IFERROR(__xludf.DUMMYFUNCTION("IMPORTRANGE(""1OCQdqqJIyWUmzr6sv4fbXUNAqVATScHotcGYSPP6YEs"",""2025-26!T3"")"),28.0) -> 28 | AO18: =IFERROR((AP18/AK18),"") -> 0.32155952 | AP18: =IFERROR(__xludf.DUMMYFUNCTION("IMPORTRANGE(""1OCQdqqJIyWUmzr6sv4fbXUNAqVATScHotcGYSPP6YEs"",""2025-26!U4"")"),243099.0) -> 243099 | AQ18: =IFERROR(__xludf.DUMMYFUNCTION("IMPORTRANGE(""1OCQdqqJIyWUmzr6sv4fbXUNAqVATScHotcGYSPP6YEs"",""2025-26!U3"")"),22.0) -> 22 | AR18: =IFERROR(__xludf.DUMMYFUNCTION("IMPORTRANGE(""1OCQdqqJIyWUmzr6sv4fbXUNAqVATScHotcGYSPP6YEs"",""2025-26!V4"")"),776000.0) -> 776000 | AS18: =IFERROR(__xludf.DUMMYFUNCTION("IMPORTRANGE(""1OCQdqqJIyWUmzr6sv4fbXUNAqVATScHotcGYSPP6YEs"",""2025-26!V3"")"),94.0) -> 94 | AT18: =IFERROR(__xludf.DUMMYFUNCTION("IMPORTRANGE(""1OCQdqqJIyWUmzr6sv4fbXUNAqVATScHotcGYSPP6YEs"",""2025-26!W4"")"),416188.2699999999) -> 416188.27 | AU18: =IFERROR(__xludf.DUMMYFUNCTION("IMPORTRANGE(""1OCQdqqJIyWUmzr6sv4fbXUNAqVATScHotcGYSPP6YEs"",""2025-26!W3"")"),28.0) -> 28 | AV18: =IFERROR((AW18/AR18),"") -> 0.50584407 | AW18: =IFERROR(__xludf.DUMMYFUNCTION("IMPORTRANGE(""1OCQdqqJIyWUmzr6sv4fbXUNAqVATScHotcGYSPP6YEs"",""2025-26!X4"")"),392535.0) -> 392535 | AX18: =IFERROR(__xludf.DUMMYFUNCTION("IMPORTRANGE(""1OCQdqqJIyWUmzr6sv4fbXUNAqVATScHotcGYSPP6YEs"",""2025-26!X3"")"),26.0) -> 26 | AY18: =IFERROR(__xludf.DUMMYFUNCTION("IMPORTRANGE(""1OCQdqqJIyWUmzr6sv4fbXUNAqVATScHotcGYSPP6YEs"",""2025-26!Y4"")"),776000.0) -> 776000 | AZ18: =IFERROR(__xludf.DUMMYFUNCTION("IMPORTRANGE(""1OCQdqqJIyWUmzr6sv4fbXUNAqVATScHotcGYSPP6YEs"",""2025-26!Y3"")"),94.0) -> 94 | BA18: =IFERROR(__xludf.DUMMYFUNCTION("IMPORTRANGE(""1OCQdqqJIyWUmzr6sv4fbXUNAqVATScHotcGYSPP6YEs"",""2025-26!Z4"")"),406154.56000000006) -> 406154.56 | BB18: =IFERROR(__xludf.DUMMYFUNCTION("IMPORTRANGE(""1OCQdqqJIyWUmzr6sv4fbXUNAqVATScHotcGYSPP6YEs"",""2025-26!Z3"")"),35.0) -> 35 | BC18: =IFERROR((BD18/AY18),"") -> 0.47853479 | BD18: =IFERROR(__xludf.DUMMYFUNCTION("IMPORTRANGE(""1OCQdqqJIyWUmzr6sv4fbXUNAqVATScHotcGYSPP6YEs"",""2025-26!AA4"")"),371343.0) -> 371343 | BE18: =IFERROR(__xludf.DUMMYFUNCTION("IMPORTRANGE(""1OCQdqqJIyWUmzr6sv4fbXUNAqVATScHotcGYSPP6YEs"",""2025-26!AA3"")"),32.0) -> 32 | BF18: =IFERROR(__xludf.DUMMYFUNCTION("IMPORTRANGE(""1OCQdqqJIyWUmzr6sv4fbXUNAqVATScHotcGYSPP6YEs"",""2025-26!AB4"")"),1393000.0) -> 1393000 | BG18: =IFERROR(__xludf.DUMMYFUNCTION("IMPORTRANGE(""1OCQdqqJIyWUmzr6sv4fbXUNAqVATScHotcGYSPP6YEs"",""2025-26!AB3"")"),90.0) -> 90 | BH18: =IFERROR(__xludf.DUMMYFUNCTION("IMPORTRANGE(""1OCQdqqJIyWUmzr6sv4fbXUNAqVATScHotcGYSPP6YEs"",""2025-26!AC4"")"),562679.1) -> 562679.1 | BI18: =IFERROR(__xludf.DUMMYFUNCTION("IMPORTRANGE(""1OCQdqqJIyWUmzr6sv4fbXUNAqVATScHotcGYSPP6YEs"",""2025-26!AC3"")"),40.0) -> 40 | BJ18: =IFERROR((BK18/BF18),"") -> 0.39216009 | BK18: =IFERROR(__xludf.DUMMYFUNCTION("IMPORTRANGE(""1OCQdqqJIyWUmzr6sv4fbXUNAqVATScHotcGYSPP6YEs"",""2025-26!AD4"")"),546279.0) -> 546279 | BL18: =IFERROR(__xludf.DUMMYFUNCTION("IMPORTRANGE(""1OCQdqqJIyWUmzr6sv4fbXUNAqVATScHotcGYSPP6YEs"",""2025-26!AD3"")"),36.0) -> 36 | BM18: =IFERROR(__xludf.DUMMYFUNCTION("IMPORTRANGE(""1OCQdqqJIyWUmzr6sv4fbXUNAqVATScHotcGYSPP6YEs"",""2025-26!AE4"")"),1472000.0) -> 1472000 | BN18: =IFERROR(__xludf.DUMMYFUNCTION("IMPORTRANGE(""1OCQdqqJIyWUmzr6sv4fbXUNAqVATScHotcGYSPP6YEs"",""2025-26!AE3"")"),93.0) -> 93 | BO18: =IFERROR(__xludf.DUMMYFUNCTION("IMPORTRANGE(""1OCQdqqJIyWUmzr6sv4fbXUNAqVATScHotcGYSPP6YEs"",""2025-26!AF4"")"),598538.4899999999) -> 598538.49 | BP18: =IFERROR(__xludf.DUMMYFUNCTION("IMPORTRANGE(""1OCQdqqJIyWUmzr6sv4fbXUNAqVATScHotcGYSPP6YEs"",""2025-26!AF3"")"),41.0) -> 41 | BQ18: =IFERROR((BR18/BM18),"") -> 0.37808152 | BR18: =IFERROR(__xludf.DUMMYFUNCTION("IMPORTRANGE(""1OCQdqqJIyWUmzr6sv4fbXUNAqVATScHotcGYSPP6YEs"",""2025-26!AG4"")"),556536.0) -> 556536 | BS18: =IFERROR(__xludf.DUMMYFUNCTION("IMPORTRANGE(""1OCQdqqJIyWUmzr6sv4fbXUNAqVATScHotcGYSPP6YEs"",""2025-26!AG3"")"),40.0) -> 40 | BT18: =IFERROR(__xludf.DUMMYFUNCTION("IMPORTRANGE(""1OCQdqqJIyWUmzr6sv4fbXUNAqVATScHotcGYSPP6YEs"",""2025-26!AH4"")"),1500000.0) -> 1500000 | BU18: =IFERROR(__xludf.DUMMYFUNCTION("IMPORTRANGE(""1OCQdqqJIyWUmzr6sv4fbXUNAqVATScHotcGYSPP6YEs"",""2025-26!AH3"")"),94.0) -> 94 | BV18: =IFERROR(__xludf.DUMMYFUNCTION("IMPORTRANGE(""1OCQdqqJIyWUmzr6sv4fbXUNAqVATScHotcGYSPP6YEs"",""2025-26!AI4"")"),538137.9700000002) -> 538137.97 | BW18: =IFERROR(__xludf.DUMMYFUNCTION("IMPORTRANGE(""1OCQdqqJIyWUmzr6sv4fbXUNAqVATScHotcGYSPP6YEs"",""2025-26!AI3"")"),38.0) -> 38 | BX18: =IFERROR((BY18/BT18),"") -> 0.373404 | BY18: =IFERROR(__xludf.DUMMYFUNCTION("IMPORTRANGE(""1OCQdqqJIyWUmzr6sv4fbXUNAqVATScHotcGYSPP6YEs"",""2025-26!AJ4"")"),560106.0) -> 560106 | BZ18: =IFERROR(__xludf.DUMMYFUNCTION("IMPORTRANGE(""1OCQdqqJIyWUmzr6sv4fbXUNAqVATScHotcGYSPP6YEs"",""2025-26!AJ3"")"),38.0) -> 38 | CA18: =IFERROR(__xludf.DUMMYFUNCTION("IMPORTRANGE(""1OCQdqqJIyWUmzr6sv4fbXUNAqVATScHotcGYSPP6YEs"",""2025-26!AK4"")"),1500000.0) -> 1500000 | CB18: =IFERROR(__xludf.DUMMYFUNCTION("IMPORTRANGE(""1OCQdqqJIyWUmzr6sv4fbXUNAqVATScHotcGYSPP6YEs"",""2025-26!AK3"")"),95.0) -> 95 | CC18: =IFERROR(__xludf.DUMMYFUNCTION("IMPORTRANGE(""1OCQdqqJIyWUmzr6sv4fbXUNAqVATScHotcGYSPP6YEs"",""2025-26!AL4"")"),728160.13) -> 728160.13 | CD18: =IFERROR(__xludf.DUMMYFUNCTION("IMPORTRANGE(""1OCQdqqJIyWUmzr6sv4fbXUNAqVATScHotcGYSPP6YEs"",""2025-26!AL3"")"),35.0) -> 35 | CE18: =IFERROR((CF18/CA18),"") -> 0.47992067 | CF18: =IFERROR(__xludf.DUMMYFUNCTION("IMPORTRANGE(""1OCQdqqJIyWUmzr6sv4fbXUNAqVATScHotcGYSPP6YEs"",""2025-26!AM4"")"),719881.0) -> 719881 | CG18: =IFERROR(__xludf.DUMMYFUNCTION("IMPORTRANGE(""1OCQdqqJIyWUmzr6sv4fbXUNAqVATScHotcGYSPP6YEs"",""2025-26!AM3"")"),34.0) -> 34 | CH18: =IFERROR(__xludf.DUMMYFUNCTION("IMPORTRANGE(""1OCQdqqJIyWUmzr6sv4fbXUNAqVATScHotcGYSPP6YEs"",""2025-26!AN4"")"),1501000.0) -> 1501000 | CI18: =IFERROR(__xludf.DUMMYFUNCTION("IMPORTRANGE(""1OCQdqqJIyWUmzr6sv4fbXUNAqVATScHotcGYSPP6YEs"",""2025-26!AN3"")"),95.0) -> 95 | CJ18: =IFERROR(__xludf.DUMMYFUNCTION("IMPORTRANGE(""1OCQdqqJIyWUmzr6sv4fbXUNAqVATScHotcGYSPP6YEs"",""2025-26!AO4"")"),738976.2399999998) -> 738976.24 | CK18: =IFERROR(__xludf.DUMMYFUNCTION("IMPORTRANGE(""1OCQdqqJIyWUmzr6sv4fbXUNAqVATScHotcGYSPP6YEs"",""2025-26!AO3"")"),37.0) -> 37 | CL18: =IFERROR((CM18/CH18),"") -> 0.48731179 | CM18: =IFERROR(__xludf.DUMMYFUNCTION("IMPORTRANGE(""1OCQdqqJIyWUmzr6sv4fbXUNAqVATScHotcGYSPP6YEs"",""2025-26!AP4"")"),731455.0) -> 731455 | CN18: =IFERROR(__xludf.DUMMYFUNCTION("IMPORTRANGE(""1OCQdqqJIyWUmzr6sv4fbXUNAqVATScHotcGYSPP6YEs"",""2025-26!AP3"")"),37.0) -> 37 | CO18: =IFERROR(__xludf.DUMMYFUNCTION("IMPORTRANGE(""1OCQdqqJIyWUmzr6sv4fbXUNAqVATScHotcGYSPP6YEs"",""2025-26!AQ4"")"),1501000.0) -> 1501000 | CP18: =IFERROR(__xludf.DUMMYFUNCTION("IMPORTRANGE(""1OCQdqqJIyWUmzr6sv4fbXUNAqVATScHotcGYSPP6YEs"",""2025-26!AQ3"")"),95.0) -> 95 | CQ18: =IFERROR(__xludf.DUMMYFUNCTION("IMPORTRANGE(""1OCQdqqJIyWUmzr6sv4fbXUNAqVATScHotcGYSPP6YEs"",""2025-26!AR4"")"),1311638.4500000002) -> 1311638.4 | CR18: =IFERROR(__xludf.DUMMYFUNCTION("IMPORTRANGE(""1OCQdqqJIyWUmzr6sv4fbXUNAqVATScHotcGYSPP6YEs"",""2025-26!AR3"")"),48.0) -> 48 | CS18: =IFERROR((CT18/CO18),"") -> 0.82432112 | CT18: =IFERROR(__xludf.DUMMYFUNCTION("IMPORTRANGE(""1OCQdqqJIyWUmzr6sv4fbXUNAqVATScHotcGYSPP6YEs"",""2025-26!AS4"")"),1237306.0) -> 1237306 | CU18: =IFERROR(__xludf.DUMMYFUNCTION("IMPORTRANGE(""1OCQdqqJIyWUmzr6sv4fbXUNAqVATScHotcGYSPP6YEs"",""2025-26!AS3"")"),44.0) -> 44 | CV18: Punjab
A19: Pawan Sharma | B19: Pawan Sharma | C19: Dinesh Kumar Kaushik | D19: Bharatpur | E19: 7976699874 | F19: 45428 | I19: =VLOOKUP($C19,Data!$C:$BV,72,0) -> 26526 | J19: 1000000 | K19: =IFERROR(__xludf.DUMMYFUNCTION("IMPORTRANGE(""https://docs.google.com/spreadsheets/d/1WzUdmfnQDNkhWeXGDxfn71m4gjwTEw7ImG_HYmiR0VY/edit#gid=1361333659"",""2025-26!A3"")"),100.0) -> 100 | L19: =IFERROR(__xludf.DUMMYFUNCTION("IMPORTRANGE(""https://docs.google.com/spreadsheets/d/1WzUdmfnQDNkhWeXGDxfn71m4gjwTEw7ImG_HYmiR0VY/edit#gid=1361333659"",""2025-26!G4"")"),8850000.0) -> 8850000 | M19: =R19+Y19+AF19+AM19+AT19+BA19+BH19+BO19+BV19+CC19+CJ19+CQ19 -> 5898220.9 | N19: =iferror(O19/L19,"") -> 0.66868124 | O19: =SUM(U19,AB19,AI19,AP19,AW19,BD19,BK19,BR19,BY19,CF19,CM19,CT19) -> 5917829 | P19: =IFERROR(__xludf.DUMMYFUNCTION("IMPORTRANGE(""https://docs.google.com/spreadsheets/d/1WzUdmfnQDNkhWeXGDxfn71m4gjwTEw7ImG_HYmiR0VY/edit#gid=1361333659"",""2025-26!J4"")"),850832.0) -> 850832 | Q19: =IFERROR(__xludf.DUMMYFUNCTION("IMPORTRANGE(""https://docs.google.com/spreadsheets/d/1WzUdmfnQDNkhWeXGDxfn71m4gjwTEw7ImG_HYmiR0VY/edit#gid=1361333659"",""2025-26!J3"")"),78.0) -> 78 | R19: =IFERROR(__xludf.DUMMYFUNCTION("IMPORTRANGE(""https://docs.google.com/spreadsheets/d/1WzUdmfnQDNkhWeXGDxfn71m4gjwTEw7ImG_HYmiR0VY/edit#gid=1361333659"",""2025-26!K4"")"),312440.51999999996) -> 312440.52 | S19: =IFERROR(__xludf.DUMMYFUNCTION("IMPORTRANGE(""https://docs.google.com/spreadsheets/d/1WzUdmfnQDNkhWeXGDxfn71m4gjwTEw7ImG_HYmiR0VY/edit#gid=1361333659"",""2025-26!K3"")"),11.0) -> 11 | T19: =IFERROR((U19/P19),"") -> 0.36726522 | U19: =IFERROR(__xludf.DUMMYFUNCTION("IMPORTRANGE(""https://docs.google.com/spreadsheets/d/1WzUdmfnQDNkhWeXGDxfn71m4gjwTEw7ImG_HYmiR0VY/edit#gid=1361333659"",""2025-26!L4"")"),312481.0) -> 312481 | V19: =IFERROR(__xludf.DUMMYFUNCTION("IMPORTRANGE(""https://docs.google.com/spreadsheets/d/1WzUdmfnQDNkhWeXGDxfn71m4gjwTEw7ImG_HYmiR0VY/edit#gid=1361333659"",""2025-26!L3"")"),11.0) -> 11 | W19: =IFERROR(__xludf.DUMMYFUNCTION("IMPORTRANGE(""https://docs.google.com/spreadsheets/d/1WzUdmfnQDNkhWeXGDxfn71m4gjwTEw7ImG_HYmiR0VY/edit#gid=1361333659"",""2025-26!M4"")"),850832.0) -> 850832 | X19: =IFERROR(__xludf.DUMMYFUNCTION("IMPORTRANGE(""https://docs.google.com/spreadsheets/d/1WzUdmfnQDNkhWeXGDxfn71m4gjwTEw7ImG_HYmiR0VY/edit#gid=1361333659"",""2025-26!M3"")"),78.0) -> 78 | Y19: =IFERROR(__xludf.DUMMYFUNCTION("importrange(""https://docs.google.com/spreadsheets/d/1WzUdmfnQDNkhWeXGDxfn71m4gjwTEw7ImG_HYmiR0VY/edit#gid=1361333659"",""2025-26!n4"")"),431750.32000000007) -> 431750.32 | Z19: =IFERROR(__xludf.DUMMYFUNCTION("importrange(""https://docs.google.com/spreadsheets/d/1WzUdmfnQDNkhWeXGDxfn71m4gjwTEw7ImG_HYmiR0VY/edit#gid=1361333659"",""2025-26!n3"")"),15.0) -> 15 | AA19: =IFERROR((AB19/W19),"") -> 0.50744565 | AB19: =IFERROR(__xludf.DUMMYFUNCTION("importrange(""https://docs.google.com/spreadsheets/d/1WzUdmfnQDNkhWeXGDxfn71m4gjwTEw7ImG_HYmiR0VY/edit#gid=1361333659"",""2025-26!o4"")"),431751.0) -> 431751 | AC19: =IFERROR(__xludf.DUMMYFUNCTION("importrange(""https://docs.google.com/spreadsheets/d/1WzUdmfnQDNkhWeXGDxfn71m4gjwTEw7ImG_HYmiR0VY/edit#gid=1361333659"",""2025-26!o3"")"),15.0) -> 15 | AD19: =IFERROR(__xludf.DUMMYFUNCTION("importrange(""https://docs.google.com/spreadsheets/d/1WzUdmfnQDNkhWeXGDxfn71m4gjwTEw7ImG_HYmiR0VY/edit#gid=1361333659"",""2025-26!p4"")"),850832.0) -> 850832 | AE19: =IFERROR(__xludf.DUMMYFUNCTION("importrange(""https://docs.google.com/spreadsheets/d/1WzUdmfnQDNkhWeXGDxfn71m4gjwTEw7ImG_HYmiR0VY/edit#gid=1361333659"",""2025-26!p3"")"),78.0) -> 78 | AF19: =IFERROR(__xludf.DUMMYFUNCTION("importrange(""https://docs.google.com/spreadsheets/d/1WzUdmfnQDNkhWeXGDxfn71m4gjwTEw7ImG_HYmiR0VY/edit#gid=1361333659"",""2025-26!q4"")"),579055.84) -> 579055.84 | AG19: =IFERROR(__xludf.DUMMYFUNCTION("importrange(""https://docs.google.com/spreadsheets/d/1WzUdmfnQDNkhWeXGDxfn71m4gjwTEw7ImG_HYmiR0VY/edit#gid=1361333659"",""2025-26!q3"")"),16.0) -> 16 | AH19: =IFERROR((AI19/AD19),"") -> 0.71124264 | AI19: =IFERROR(__xludf.DUMMYFUNCTION("importrange(""https://docs.google.com/spreadsheets/d/1WzUdmfnQDNkhWeXGDxfn71m4gjwTEw7ImG_HYmiR0VY/edit#gid=1361333659"",""2025-26!r4"")"),605148.0) -> 605148 | AJ19: =IFERROR(__xludf.DUMMYFUNCTION("importrange(""https://docs.google.com/spreadsheets/d/1WzUdmfnQDNkhWeXGDxfn71m4gjwTEw7ImG_HYmiR0VY/edit#gid=1361333659"",""2025-26!r3"")"),17.0) -> 17 | AK19: =IFERROR(__xludf.DUMMYFUNCTION("importrange(""https://docs.google.com/spreadsheets/d/1WzUdmfnQDNkhWeXGDxfn71m4gjwTEw7ImG_HYmiR0VY/edit#gid=1361333659"",""2025-26!s4"")"),850832.0) -> 850832 | AL19: =IFERROR(__xludf.DUMMYFUNCTION("importrange(""https://docs.google.com/spreadsheets/d/1WzUdmfnQDNkhWeXGDxfn71m4gjwTEw7ImG_HYmiR0VY/edit#gid=1361333659"",""2025-26!s3"")"),78.0) -> 78 | AM19: =IFERROR(__xludf.DUMMYFUNCTION("importrange(""https://docs.google.com/spreadsheets/d/1WzUdmfnQDNkhWeXGDxfn71m4gjwTEw7ImG_HYmiR0VY/edit#gid=1361333659"",""2025-26!t4"")"),374506.54) -> 374506.54 | AN19: =IFERROR(__xludf.DUMMYFUNCTION("importrange(""https://docs.google.com/spreadsheets/d/1WzUdmfnQDNkhWeXGDxfn71m4gjwTEw7ImG_HYmiR0VY/edit#gid=1361333659"",""2025-26!t3"")"),14.0) -> 14 | AO19: =IFERROR((AP19/AK19),"") -> 0.436119 | AP19: =IFERROR(__xludf.DUMMYFUNCTION("importrange(""https://docs.google.com/spreadsheets/d/1WzUdmfnQDNkhWeXGDxfn71m4gjwTEw7ImG_HYmiR0VY/edit#gid=1361333659"",""2025-26!u4"")"),371064.0) -> 371064 | AQ19: =IFERROR(__xludf.DUMMYFUNCTION("importrange(""https://docs.google.com/spreadsheets/d/1WzUdmfnQDNkhWeXGDxfn71m4gjwTEw7ImG_HYmiR0VY/edit#gid=1361333659"",""2025-26!u3"")"),13.0) -> 13 | AR19: =IFERROR(__xludf.DUMMYFUNCTION("importrange(""https://docs.google.com/spreadsheets/d/1WzUdmfnQDNkhWeXGDxfn71m4gjwTEw7ImG_HYmiR0VY/edit#gid=1361333659"",""2025-26!v4"")"),850832.0) -> 850832 | AS19: =IFERROR(__xludf.DUMMYFUNCTION("importrange(""https://docs.google.com/spreadsheets/d/1WzUdmfnQDNkhWeXGDxfn71m4gjwTEw7ImG_HYmiR0VY/edit#gid=1361333659"",""2025-26!v3"")"),78.0) -> 78 | AT19: =IFERROR(__xludf.DUMMYFUNCTION("importrange(""https://docs.google.com/spreadsheets/d/1WzUdmfnQDNkhWeXGDxfn71m4gjwTEw7ImG_HYmiR0VY/edit#gid=1361333659"",""2025-26!w4"")"),488495.16000000003) -> 488495.16 | AU19: =IFERROR(__xludf.DUMMYFUNCTION("importrange(""https://docs.google.com/spreadsheets/d/1WzUdmfnQDNkhWeXGDxfn71m4gjwTEw7ImG_HYmiR0VY/edit#gid=1361333659"",""2025-26!w3"")"),15.0) -> 15 | AV19: =IFERROR((AW19/AR19),"") -> 0.57413802 | AW19: =IFERROR(__xludf.DUMMYFUNCTION("importrange(""https://docs.google.com/spreadsheets/d/1WzUdmfnQDNkhWeXGDxfn71m4gjwTEw7ImG_HYmiR0VY/edit#gid=1361333659"",""2025-26!x4"")"),488495.0) -> 488495 | AX19: =IFERROR(__xludf.DUMMYFUNCTION("importrange(""https://docs.google.com/spreadsheets/d/1WzUdmfnQDNkhWeXGDxfn71m4gjwTEw7ImG_HYmiR0VY/edit#gid=1361333659"",""2025-26!x3"")"),15.0) -> 15 | AY19: =IFERROR(__xludf.DUMMYFUNCTION("importrange(""https://docs.google.com/spreadsheets/d/1WzUdmfnQDNkhWeXGDxfn71m4gjwTEw7ImG_HYmiR0VY/edit#gid=1361333659"",""2025-26!y4"")"),850832.0) -> 850832 | AZ19: =IFERROR(__xludf.DUMMYFUNCTION("importrange(""https://docs.google.com/spreadsheets/d/1WzUdmfnQDNkhWeXGDxfn71m4gjwTEw7ImG_HYmiR0VY/edit#gid=1361333659"",""2025-26!y3"")"),78.0) -> 78 | BA19: =IFERROR(__xludf.DUMMYFUNCTION("importrange(""https://docs.google.com/spreadsheets/d/1WzUdmfnQDNkhWeXGDxfn71m4gjwTEw7ImG_HYmiR0VY/edit#gid=1361333659"",""2025-26!z4"")"),485726.26999999996) -> 485726.27 | BB19: =IFERROR(__xludf.DUMMYFUNCTION("importrange(""https://docs.google.com/spreadsheets/d/1WzUdmfnQDNkhWeXGDxfn71m4gjwTEw7ImG_HYmiR0VY/edit#gid=1361333659"",""2025-26!z3"")"),13.0) -> 13 | BC19: =IFERROR((BD19/AY19),"") -> 0.57088591 | BD19: =IFERROR(__xludf.DUMMYFUNCTION("importrange(""https://docs.google.com/spreadsheets/d/1WzUdmfnQDNkhWeXGDxfn71m4gjwTEw7ImG_HYmiR0VY/edit#gid=1361333659"",""2025-26!aa4"")"),485728.0) -> 485728 | BE19: =IFERROR(__xludf.DUMMYFUNCTION("importrange(""https://docs.google.com/spreadsheets/d/1WzUdmfnQDNkhWeXGDxfn71m4gjwTEw7ImG_HYmiR0VY/edit#gid=1361333659"",""2025-26!aa3"")"),13.0) -> 13 | BF19: =IFERROR(__xludf.DUMMYFUNCTION("importrange(""https://docs.google.com/spreadsheets/d/1WzUdmfnQDNkhWeXGDxfn71m4gjwTEw7ImG_HYmiR0VY/edit#gid=1361333659"",""2025-26!ab4"")"),850832.0) -> 850832 | BG19: =IFERROR(__xludf.DUMMYFUNCTION("importrange(""https://docs.google.com/spreadsheets/d/1WzUdmfnQDNkhWeXGDxfn71m4gjwTEw7ImG_HYmiR0VY/edit#gid=1361333659"",""2025-26!ab3"")"),78.0) -> 78 | BH19: =IFERROR(__xludf.DUMMYFUNCTION("importrange(""https://docs.google.com/spreadsheets/d/1WzUdmfnQDNkhWeXGDxfn71m4gjwTEw7ImG_HYmiR0VY/edit#gid=1361333659"",""2025-26!ac4"")"),533966.01) -> 533966.01 | BI19: =IFERROR(__xludf.DUMMYFUNCTION("importrange(""https://docs.google.com/spreadsheets/d/1WzUdmfnQDNkhWeXGDxfn71m4gjwTEw7ImG_HYmiR0VY/edit#gid=1361333659"",""2025-26!ac3"")"),9.0) -> 9 | BJ19: =IFERROR((BK19/BF19),"") -> 0.62758218 | BK19: =IFERROR(__xludf.DUMMYFUNCTION("importrange(""https://docs.google.com/spreadsheets/d/1WzUdmfnQDNkhWeXGDxfn71m4gjwTEw7ImG_HYmiR0VY/edit#gid=1361333659"",""2025-26!ad4"")"),533967.0) -> 533967 | BL19: =IFERROR(__xludf.DUMMYFUNCTION("importrange(""https://docs.google.com/spreadsheets/d/1WzUdmfnQDNkhWeXGDxfn71m4gjwTEw7ImG_HYmiR0VY/edit#gid=1361333659"",""2025-26!ad3"")"),9.0) -> 9 | BM19: =IFERROR(__xludf.DUMMYFUNCTION("importrange(""https://docs.google.com/spreadsheets/d/1WzUdmfnQDNkhWeXGDxfn71m4gjwTEw7ImG_HYmiR0VY/edit#gid=1361333659"",""2025-26!ae4"")"),850832.0) -> 850832 | BN19: =IFERROR(__xludf.DUMMYFUNCTION("importrange(""https://docs.google.com/spreadsheets/d/1WzUdmfnQDNkhWeXGDxfn71m4gjwTEw7ImG_HYmiR0VY/edit#gid=1361333659"",""2025-26!ae3"")"),78.0) -> 78 | BO19: =IFERROR(__xludf.DUMMYFUNCTION("importrange(""https://docs.google.com/spreadsheets/d/1WzUdmfnQDNkhWeXGDxfn71m4gjwTEw7ImG_HYmiR0VY/edit#gid=1361333659"",""2025-26!af4"")"),453125.6500000001) -> 453125.65 | BP19: =IFERROR(__xludf.DUMMYFUNCTION("importrange(""https://docs.google.com/spreadsheets/d/1WzUdmfnQDNkhWeXGDxfn71m4gjwTEw7ImG_HYmiR0VY/edit#gid=1361333659"",""2025-26!af3"")"),16.0) -> 16 | BQ19: =IFERROR((BR19/BM19),"") -> 0.53256695 | BR19: =IFERROR(__xludf.DUMMYFUNCTION("importrange(""https://docs.google.com/spreadsheets/d/1WzUdmfnQDNkhWeXGDxfn71m4gjwTEw7ImG_HYmiR0VY/edit#gid=1361333659"",""2025-26!ag4"")"),453125.0) -> 453125 | BS19: =IFERROR(__xludf.DUMMYFUNCTION("importrange(""https://docs.google.com/spreadsheets/d/1WzUdmfnQDNkhWeXGDxfn71m4gjwTEw7ImG_HYmiR0VY/edit#gid=1361333659"",""2025-26!ag3"")"),16.0) -> 16 | BT19: =IFERROR(__xludf.DUMMYFUNCTION("importrange(""https://docs.google.com/spreadsheets/d/1WzUdmfnQDNkhWeXGDxfn71m4gjwTEw7ImG_HYmiR0VY/edit#gid=1361333659"",""2025-26!ah4"")"),850832.0) -> 850832 | BU19: =IFERROR(__xludf.DUMMYFUNCTION("importrange(""https://docs.google.com/spreadsheets/d/1WzUdmfnQDNkhWeXGDxfn71m4gjwTEw7ImG_HYmiR0VY/edit#gid=1361333659"",""2025-26!ah3"")"),78.0) -> 78 | BV19: =IFERROR(__xludf.DUMMYFUNCTION("importrange(""https://docs.google.com/spreadsheets/d/1WzUdmfnQDNkhWeXGDxfn71m4gjwTEw7ImG_HYmiR0VY/edit#gid=1361333659"",""2025-26!ai4"")"),558233.6900000001) -> 558233.69 | BW19: =IFERROR(__xludf.DUMMYFUNCTION("importrange(""https://docs.google.com/spreadsheets/d/1WzUdmfnQDNkhWeXGDxfn71m4gjwTEw7ImG_HYmiR0VY/edit#gid=1361333659"",""2025-26!ai3"")"),19.0) -> 19 | BX19: =IFERROR((BY19/BT19),"") -> 0.65632463 | BY19: =IFERROR(__xludf.DUMMYFUNCTION("importrange(""https://docs.google.com/spreadsheets/d/1WzUdmfnQDNkhWeXGDxfn71m4gjwTEw7ImG_HYmiR0VY/edit#gid=1361333659"",""2025-26!aj4"")"),558422.0) -> 558422 | BZ19: =IFERROR(__xludf.DUMMYFUNCTION("importrange(""https://docs.google.com/spreadsheets/d/1WzUdmfnQDNkhWeXGDxfn71m4gjwTEw7ImG_HYmiR0VY/edit#gid=1361333659"",""2025-26!aj3"")"),19.0) -> 19 | CA19: =IFERROR(__xludf.DUMMYFUNCTION("importrange(""https://docs.google.com/spreadsheets/d/1WzUdmfnQDNkhWeXGDxfn71m4gjwTEw7ImG_HYmiR0VY/edit#gid=1361333659"",""2025-26!ak4"")"),850832.0) -> 850832 | CB19: =IFERROR(__xludf.DUMMYFUNCTION("importrange(""https://docs.google.com/spreadsheets/d/1WzUdmfnQDNkhWeXGDxfn71m4gjwTEw7ImG_HYmiR0VY/edit#gid=1361333659"",""2025-26!ak3"")"),78.0) -> 78 | CC19: =IFERROR(__xludf.DUMMYFUNCTION("importrange(""https://docs.google.com/spreadsheets/d/1WzUdmfnQDNkhWeXGDxfn71m4gjwTEw7ImG_HYmiR0VY/edit#gid=1361333659"",""2025-26!al4"")"),611706.6699999999) -> 611706.67 | CD19: =IFERROR(__xludf.DUMMYFUNCTION("importrange(""https://docs.google.com/spreadsheets/d/1WzUdmfnQDNkhWeXGDxfn71m4gjwTEw7ImG_HYmiR0VY/edit#gid=1361333659"",""2025-26!ai3"")"),19.0) -> 19 | CE19: =IFERROR((CF19/CA19),"") -> 0.73613475 | CF19: =IFERROR(__xludf.DUMMYFUNCTION("importrange(""https://docs.google.com/spreadsheets/d/1WzUdmfnQDNkhWeXGDxfn71m4gjwTEw7ImG_HYmiR0VY/edit#gid=1361333659"",""2025-26!am4"")"),626327.0) -> 626327 | CG19: =IFERROR(__xludf.DUMMYFUNCTION("importrange(""https://docs.google.com/spreadsheets/d/1WzUdmfnQDNkhWeXGDxfn71m4gjwTEw7ImG_HYmiR0VY/edit#gid=1361333659"",""2025-26!am3"")"),16.0) -> 16 | CH19: =IFERROR(__xludf.DUMMYFUNCTION("importrange(""https://docs.google.com/spreadsheets/d/1WzUdmfnQDNkhWeXGDxfn71m4gjwTEw7ImG_HYmiR0VY/edit#gid=1361333659"",""2025-26!an4"")"),850832.0) -> 850832 | CI19: =IFERROR(__xludf.DUMMYFUNCTION("importrange(""https://docs.google.com/spreadsheets/d/1WzUdmfnQDNkhWeXGDxfn71m4gjwTEw7ImG_HYmiR0VY/edit#gid=1361333659"",""2025-26!an3"")"),78.0) -> 78 | CJ19: =IFERROR(__xludf.DUMMYFUNCTION("importrange(""https://docs.google.com/spreadsheets/d/1WzUdmfnQDNkhWeXGDxfn71m4gjwTEw7ImG_HYmiR0VY/edit#gid=1361333659"",""2025-26!ao4"")"),607860.8600000001) -> 607860.86 | CK19: =IFERROR(__xludf.DUMMYFUNCTION("importrange(""https://docs.google.com/spreadsheets/d/1WzUdmfnQDNkhWeXGDxfn71m4gjwTEw7ImG_HYmiR0VY/edit#gid=1361333659"",""2025-26!ao3"")"),23.0) -> 23 | CL19: =IFERROR((CM19/CH19),"") -> 0.69340011 | CM19: =IFERROR(__xludf.DUMMYFUNCTION("importrange(""https://docs.google.com/spreadsheets/d/1WzUdmfnQDNkhWeXGDxfn71m4gjwTEw7ImG_HYmiR0VY/edit#gid=1361333659"",""2025-26!ap4"")"),589967.0) -> 589967 | CN19: =IFERROR(__xludf.DUMMYFUNCTION("importrange(""https://docs.google.com/spreadsheets/d/1WzUdmfnQDNkhWeXGDxfn71m4gjwTEw7ImG_HYmiR0VY/edit#gid=1361333659"",""2025-26!ap3"")"),22.0) -> 22 | CO19: =IFERROR(__xludf.DUMMYFUNCTION("importrange(""https://docs.google.com/spreadsheets/d/1WzUdmfnQDNkhWeXGDxfn71m4gjwTEw7ImG_HYmiR0VY/edit#gid=1361333659"",""2025-26!aq4"")"),850832.0) -> 850832 | CP19: =IFERROR(__xludf.DUMMYFUNCTION("importrange(""https://docs.google.com/spreadsheets/d/1WzUdmfnQDNkhWeXGDxfn71m4gjwTEw7ImG_HYmiR0VY/edit#gid=1361333659"",""2025-26!aq3"")"),78.0) -> 78 | CQ19: =IFERROR(__xludf.DUMMYFUNCTION("importrange(""https://docs.google.com/spreadsheets/d/1WzUdmfnQDNkhWeXGDxfn71m4gjwTEw7ImG_HYmiR0VY/edit#gid=1361333659"",""2025-26!ar4"")"),461353.35) -> 461353.35 | CR19: =IFERROR(__xludf.DUMMYFUNCTION("importrange(""https://docs.google.com/spreadsheets/d/1WzUdmfnQDNkhWeXGDxfn71m4gjwTEw7ImG_HYmiR0VY/edit#gid=1361333659"",""2025-26!ar3"")"),12.0) -> 12 | CS19: =IFERROR((CT19/CO19),"") -> 0.54223866 | CT19: =IFERROR(__xludf.DUMMYFUNCTION("importrange(""https://docs.google.com/spreadsheets/d/1WzUdmfnQDNkhWeXGDxfn71m4gjwTEw7ImG_HYmiR0VY/edit#gid=1361333659"",""2025-26!as4"")"),461354.0) -> 461354 | CU19: =IFERROR(__xludf.DUMMYFUNCTION("importrange(""https://docs.google.com/spreadsheets/d/1WzUdmfnQDNkhWeXGDxfn71m4gjwTEw7ImG_HYmiR0VY/edit#gid=1361333659"",""2025-26!as3"")"),12.0) -> 12 | CV19: Rajasthan
A20: Pawan Sharma | C20: Kanhaiya Lal Salvi | D20: Chittorgarh | E20: 8432805343 | F20: 45518 | I20: =VLOOKUP($C20,Data!$C:$BV,72,0) -> 23570 | J20: 700000 | K20: =IFERROR(__xludf.DUMMYFUNCTION("IMPORTRANGE(""https://docs.google.com/spreadsheets/d/1zbKpAkjR5pwXNP3vlQNzKnZWdUfQd6EtmpoFtLBYJoY/edit?gid=1824619316#gid=1824619316"",""2025-26!A3"")"),88.0) -> 88 | L20: =IFERROR(__xludf.DUMMYFUNCTION("IMPORTRANGE(""https://docs.google.com/spreadsheets/d/1zbKpAkjR5pwXNP3vlQNzKnZWdUfQd6EtmpoFtLBYJoY/edit?gid=1824619316#gid=1824619316"",""2025-26!G4"")"),4265000.0) -> 4265000 | M20: =R20+Y20+AF20+AM20+AT20+BA20+BH20+BO20+BV20+CC20+CJ20+CQ20 -> 2887869.8 | N20: =iferror(O20/L20,"") -> 0.1208075 | O20: =SUM(U20,AB20,AI20,AP20,AW20,BD20,BK20,BR20,BY20,CF20,CM20,CT20) -> 515244 | P20: =IFERROR(__xludf.DUMMYFUNCTION("IMPORTRANGE(""https://docs.google.com/spreadsheets/d/1zbKpAkjR5pwXNP3vlQNzKnZWdUfQd6EtmpoFtLBYJoY/edit?gid=1824619316#gid=1824619316"",""2025-26!J4"")"),132339.0) -> 132339 | Q20: =IFERROR(__xludf.DUMMYFUNCTION("IMPORTRANGE(""https://docs.google.com/spreadsheets/d/1zbKpAkjR5pwXNP3vlQNzKnZWdUfQd6EtmpoFtLBYJoY/edit?gid=1824619316#gid=1824619316"",""2025-26!J3"")"),12.0) -> 12 | R20: =IFERROR(__xludf.DUMMYFUNCTION("IMPORTRANGE(""https://docs.google.com/spreadsheets/d/1zbKpAkjR5pwXNP3vlQNzKnZWdUfQd6EtmpoFtLBYJoY/edit?gid=1824619316#gid=1824619316"",""2025-26!K4"")"),179291.4) -> 179291.4 | S20: =IFERROR(__xludf.DUMMYFUNCTION("IMPORTRANGE(""https://docs.google.com/spreadsheets/d/1zbKpAkjR5pwXNP3vlQNzKnZWdUfQd6EtmpoFtLBYJoY/edit?gid=1824619316#gid=1824619316"",""2025-26!K3"")"),13.0) -> 13 | T20: =IFERROR((U20/P20),"") -> 0.47332986 | U20: =IFERROR(__xludf.DUMMYFUNCTION("IMPORTRANGE(""https://docs.google.com/spreadsheets/d/1zbKpAkjR5pwXNP3vlQNzKnZWdUfQd6EtmpoFtLBYJoY/edit?gid=1824619316#gid=1824619316"",""2025-26!L4"")"),62640.0) -> 62640 | V20: =IFERROR(__xludf.DUMMYFUNCTION("IMPORTRANGE(""https://docs.google.com/spreadsheets/d/1zbKpAkjR5pwXNP3vlQNzKnZWdUfQd6EtmpoFtLBYJoY/edit?gid=1824619316#gid=1824619316"",""2025-26!L3"")"),6.0) -> 6 | W20: =IFERROR(__xludf.DUMMYFUNCTION("IMPORTRANGE(""https://docs.google.com/spreadsheets/d/1zbKpAkjR5pwXNP3vlQNzKnZWdUfQd6EtmpoFtLBYJoY/edit?gid=1824619316#gid=1824619316"",""2025-26!M4"")"),206333.0) -> 206333 | X20: =IFERROR(__xludf.DUMMYFUNCTION("IMPORTRANGE(""https://docs.google.com/spreadsheets/d/1zbKpAkjR5pwXNP3vlQNzKnZWdUfQd6EtmpoFtLBYJoY/edit?gid=1824619316#gid=1824619316"",""2025-26!M3"")"),15.0) -> 15 | Y20: =IFERROR(__xludf.DUMMYFUNCTION("importrange(""https://docs.google.com/spreadsheets/d/1zbKpAkjR5pwXNP3vlQNzKnZWdUfQd6EtmpoFtLBYJoY/edit?gid=1824619316#gid=1824619316"",""2025-26!n4"")"),216147.13999999998) -> 216147.14 | Z20: =IFERROR(__xludf.DUMMYFUNCTION("importrange(""https://docs.google.com/spreadsheets/d/1zbKpAkjR5pwXNP3vlQNzKnZWdUfQd6EtmpoFtLBYJoY/edit?gid=1824619316#gid=1824619316"",""2025-26!n3"")"),16.0) -> 16 | AA20: =IFERROR((AB20/W20),"") -> 0.12269487 | AB20: =IFERROR(__xludf.DUMMYFUNCTION("importrange(""https://docs.google.com/spreadsheets/d/1zbKpAkjR5pwXNP3vlQNzKnZWdUfQd6EtmpoFtLBYJoY/edit?gid=1824619316#gid=1824619316"",""2025-26!o4"")"),25316.0) -> 25316 | AC20: =IFERROR(__xludf.DUMMYFUNCTION("importrange(""https://docs.google.com/spreadsheets/d/1zbKpAkjR5pwXNP3vlQNzKnZWdUfQd6EtmpoFtLBYJoY/edit?gid=1824619316#gid=1824619316"",""2025-26!o3"")"),2.0) -> 2 | AD20: =IFERROR(__xludf.DUMMYFUNCTION("importrange(""https://docs.google.com/spreadsheets/d/1zbKpAkjR5pwXNP3vlQNzKnZWdUfQd6EtmpoFtLBYJoY/edit?gid=1824619316#gid=1824619316"",""2025-26!p4"")"),172561.0) -> 172561 | AE20: =IFERROR(__xludf.DUMMYFUNCTION("importrange(""https://docs.google.com/spreadsheets/d/1zbKpAkjR5pwXNP3vlQNzKnZWdUfQd6EtmpoFtLBYJoY/edit?gid=1824619316#gid=1824619316"",""2025-26!p3"")"),14.0) -> 14 | AF20: =IFERROR(__xludf.DUMMYFUNCTION("importrange(""https://docs.google.com/spreadsheets/d/1zbKpAkjR5pwXNP3vlQNzKnZWdUfQd6EtmpoFtLBYJoY/edit?gid=1824619316#gid=1824619316"",""2025-26!q4"")"),281453.36) -> 281453.36 | AG20: =IFERROR(__xludf.DUMMYFUNCTION("importrange(""https://docs.google.com/spreadsheets/d/1zbKpAkjR5pwXNP3vlQNzKnZWdUfQd6EtmpoFtLBYJoY/edit?gid=1824619316#gid=1824619316"",""2025-26!q3"")"),19.0) -> 19 | AH20: =IFERROR((AI20/AD20),"") -> 0.50527639 | AI20: =IFERROR(__xludf.DUMMYFUNCTION("importrange(""https://docs.google.com/spreadsheets/d/1zbKpAkjR5pwXNP3vlQNzKnZWdUfQd6EtmpoFtLBYJoY/edit?gid=1824619316#gid=1824619316"",""2025-26!r4"")"),87191.0) -> 87191 | AJ20: =IFERROR(__xludf.DUMMYFUNCTION("importrange(""https://docs.google.com/spreadsheets/d/1zbKpAkjR5pwXNP3vlQNzKnZWdUfQd6EtmpoFtLBYJoY/edit?gid=1824619316#gid=1824619316"",""2025-26!r3"")"),6.0) -> 6 | AK20: =IFERROR(__xludf.DUMMYFUNCTION("importrange(""https://docs.google.com/spreadsheets/d/1zbKpAkjR5pwXNP3vlQNzKnZWdUfQd6EtmpoFtLBYJoY/edit?gid=1824619316#gid=1824619316"",""2025-26!s4"")"),87400.0) -> 87400 | AL20: =IFERROR(__xludf.DUMMYFUNCTION("importrange(""https://docs.google.com/spreadsheets/d/1zbKpAkjR5pwXNP3vlQNzKnZWdUfQd6EtmpoFtLBYJoY/edit?gid=1824619316#gid=1824619316"",""2025-26!s3"")"),7.0) -> 7 | AM20: =IFERROR(__xludf.DUMMYFUNCTION("importrange(""https://docs.google.com/spreadsheets/d/1zbKpAkjR5pwXNP3vlQNzKnZWdUfQd6EtmpoFtLBYJoY/edit?gid=1824619316#gid=1824619316"",""2025-26!t4"")"),286803.7) -> 286803.7 | AN20: =IFERROR(__xludf.DUMMYFUNCTION("importrange(""https://docs.google.com/spreadsheets/d/1zbKpAkjR5pwXNP3vlQNzKnZWdUfQd6EtmpoFtLBYJoY/edit?gid=1824619316#gid=1824619316"",""2025-26!t3"")"),19.0) -> 19 | AO20: =IFERROR((AP20/AK20),"") -> 0 | AP20: =IFERROR(__xludf.DUMMYFUNCTION("importrange(""https://docs.google.com/spreadsheets/d/1zbKpAkjR5pwXNP3vlQNzKnZWdUfQd6EtmpoFtLBYJoY/edit?gid=1824619316#gid=1824619316"",""2025-26!u4"")"),0.0) -> 0 | AQ20: =IFERROR(__xludf.DUMMYFUNCTION("importrange(""https://docs.google.com/spreadsheets/d/1zbKpAkjR5pwXNP3vlQNzKnZWdUfQd6EtmpoFtLBYJoY/edit?gid=1824619316#gid=1824619316"",""2025-26!u3"")"),0.0) -> 0 | AR20: =IFERROR(__xludf.DUMMYFUNCTION("importrange(""https://docs.google.com/spreadsheets/d/1zbKpAkjR5pwXNP3vlQNzKnZWdUfQd6EtmpoFtLBYJoY/edit?gid=1824619316#gid=1824619316"",""2025-26!v4"")"),210718.0) -> 210718 | AS20: =IFERROR(__xludf.DUMMYFUNCTION("importrange(""https://docs.google.com/spreadsheets/d/1zbKpAkjR5pwXNP3vlQNzKnZWdUfQd6EtmpoFtLBYJoY/edit?gid=1824619316#gid=1824619316"",""2025-26!v3"")"),10.0) -> 10 | AT20: =IFERROR(__xludf.DUMMYFUNCTION("importrange(""https://docs.google.com/spreadsheets/d/1zbKpAkjR5pwXNP3vlQNzKnZWdUfQd6EtmpoFtLBYJoY/edit?gid=1824619316#gid=1824619316"",""2025-26!w4"")"),360688.43999999994) -> 360688.44 | AU20: =IFERROR(__xludf.DUMMYFUNCTION("importrange(""https://docs.google.com/spreadsheets/d/1zbKpAkjR5pwXNP3vlQNzKnZWdUfQd6EtmpoFtLBYJoY/edit?gid=1824619316#gid=1824619316"",""2025-26!w3"")"),20.0) -> 20 | AV20: =IFERROR((AW20/AR20),"") -> 0.085650016 | AW20: =IFERROR(__xludf.DUMMYFUNCTION("importrange(""https://docs.google.com/spreadsheets/d/1zbKpAkjR5pwXNP3vlQNzKnZWdUfQd6EtmpoFtLBYJoY/edit?gid=1824619316#gid=1824619316"",""2025-26!x4"")"),18048.0) -> 18048 | AX20: =IFERROR(__xludf.DUMMYFUNCTION("importrange(""https://docs.google.com/spreadsheets/d/1zbKpAkjR5pwXNP3vlQNzKnZWdUfQd6EtmpoFtLBYJoY/edit?gid=1824619316#gid=1824619316"",""2025-26!x3"")"),2.0) -> 2 | AY20: =IFERROR(__xludf.DUMMYFUNCTION("importrange(""https://docs.google.com/spreadsheets/d/1zbKpAkjR5pwXNP3vlQNzKnZWdUfQd6EtmpoFtLBYJoY/edit?gid=1824619316#gid=1824619316"",""2025-26!y4"")"),144103.0) -> 144103 | AZ20: =IFERROR(__xludf.DUMMYFUNCTION("importrange(""https://docs.google.com/spreadsheets/d/1zbKpAkjR5pwXNP3vlQNzKnZWdUfQd6EtmpoFtLBYJoY/edit?gid=1824619316#gid=1824619316"",""2025-26!y3"")"),7.0) -> 7 | BA20: =IFERROR(__xludf.DUMMYFUNCTION("importrange(""https://docs.google.com/spreadsheets/d/1zbKpAkjR5pwXNP3vlQNzKnZWdUfQd6EtmpoFtLBYJoY/edit?gid=1824619316#gid=1824619316"",""2025-26!z4"")"),225811.19999999998) -> 225811.2 | BB20: =IFERROR(__xludf.DUMMYFUNCTION("importrange(""https://docs.google.com/spreadsheets/d/1zbKpAkjR5pwXNP3vlQNzKnZWdUfQd6EtmpoFtLBYJoY/edit?gid=1824619316#gid=1824619316"",""2025-26!z3"")"),11.0) -> 11 | BC20: =IFERROR((BD20/AY20),"") -> 0 | BD20: =IFERROR(__xludf.DUMMYFUNCTION("importrange(""https://docs.google.com/spreadsheets/d/1zbKpAkjR5pwXNP3vlQNzKnZWdUfQd6EtmpoFtLBYJoY/edit?gid=1824619316#gid=1824619316"",""2025-26!aa4"")"),0.0) -> 0 | BE20: =IFERROR(__xludf.DUMMYFUNCTION("importrange(""https://docs.google.com/spreadsheets/d/1zbKpAkjR5pwXNP3vlQNzKnZWdUfQd6EtmpoFtLBYJoY/edit?gid=1824619316#gid=1824619316"",""2025-26!aa3"")"),0.0) -> 0 | BF20: =IFERROR(__xludf.DUMMYFUNCTION("importrange(""https://docs.google.com/spreadsheets/d/1zbKpAkjR5pwXNP3vlQNzKnZWdUfQd6EtmpoFtLBYJoY/edit?gid=1824619316#gid=1824619316"",""2025-26!ab4"")"),200266.0) -> 200266 | BG20: =IFERROR(__xludf.DUMMYFUNCTION("importrange(""https://docs.google.com/spreadsheets/d/1zbKpAkjR5pwXNP3vlQNzKnZWdUfQd6EtmpoFtLBYJoY/edit?gid=1824619316#gid=1824619316"",""2025-26!ab3"")"),9.0) -> 9 | BH20: =IFERROR(__xludf.DUMMYFUNCTION("importrange(""https://docs.google.com/spreadsheets/d/1zbKpAkjR5pwXNP3vlQNzKnZWdUfQd6EtmpoFtLBYJoY/edit?gid=1824619316#gid=1824619316"",""2025-26!ac4"")"),128378.56000000001) -> 128378.56 | BI20: =IFERROR(__xludf.DUMMYFUNCTION("importrange(""https://docs.google.com/spreadsheets/d/1zbKpAkjR5pwXNP3vlQNzKnZWdUfQd6EtmpoFtLBYJoY/edit?gid=1824619316#gid=1824619316"",""2025-26!ac3"")"),9.0) -> 9 | BJ20: =IFERROR((BK20/BF20),"") -> 0.032396912 | BK20: =IFERROR(__xludf.DUMMYFUNCTION("importrange(""https://docs.google.com/spreadsheets/d/1zbKpAkjR5pwXNP3vlQNzKnZWdUfQd6EtmpoFtLBYJoY/edit?gid=1824619316#gid=1824619316"",""2025-26!ad4"")"),6488.0) -> 6488 | BL20: =IFERROR(__xludf.DUMMYFUNCTION("importrange(""https://docs.google.com/spreadsheets/d/1zbKpAkjR5pwXNP3vlQNzKnZWdUfQd6EtmpoFtLBYJoY/edit?gid=1824619316#gid=1824619316"",""2025-26!ad3"")"),1.0) -> 1 | BM20: =IFERROR(__xludf.DUMMYFUNCTION("importrange(""https://docs.google.com/spreadsheets/d/1zbKpAkjR5pwXNP3vlQNzKnZWdUfQd6EtmpoFtLBYJoY/edit?gid=1824619316#gid=1824619316"",""2025-26!ae4"")"),267248.0) -> 267248 | BN20: =IFERROR(__xludf.DUMMYFUNCTION("importrange(""https://docs.google.com/spreadsheets/d/1zbKpAkjR5pwXNP3vlQNzKnZWdUfQd6EtmpoFtLBYJoY/edit?gid=1824619316#gid=1824619316"",""2025-26!ae3"")"),16.0) -> 16 | BO20: =IFERROR(__xludf.DUMMYFUNCTION("importrange(""https://docs.google.com/spreadsheets/d/1zbKpAkjR5pwXNP3vlQNzKnZWdUfQd6EtmpoFtLBYJoY/edit?gid=1824619316#gid=1824619316"",""2025-26!af4"")"),315690.51999999996) -> 315690.52 | BP20: =IFERROR(__xludf.DUMMYFUNCTION("importrange(""https://docs.google.com/spreadsheets/d/1zbKpAkjR5pwXNP3vlQNzKnZWdUfQd6EtmpoFtLBYJoY/edit?gid=1824619316#gid=1824619316"",""2025-26!af3"")"),21.0) -> 21 | BQ20: =IFERROR((BR20/BM20),"") -> 0.2938095 | BR20: =IFERROR(__xludf.DUMMYFUNCTION("importrange(""https://docs.google.com/spreadsheets/d/1zbKpAkjR5pwXNP3vlQNzKnZWdUfQd6EtmpoFtLBYJoY/edit?gid=1824619316#gid=1824619316"",""2025-26!ag4"")"),78520.0) -> 78520 | BS20: =IFERROR(__xludf.DUMMYFUNCTION("importrange(""https://docs.google.com/spreadsheets/d/1zbKpAkjR5pwXNP3vlQNzKnZWdUfQd6EtmpoFtLBYJoY/edit?gid=1824619316#gid=1824619316"",""2025-26!ag3"")"),4.0) -> 4 | BT20: =IFERROR(__xludf.DUMMYFUNCTION("importrange(""https://docs.google.com/spreadsheets/d/1zbKpAkjR5pwXNP3vlQNzKnZWdUfQd6EtmpoFtLBYJoY/edit?gid=1824619316#gid=1824619316"",""2025-26!ah4"")"),57240.0) -> 57240 | BU20: =IFERROR(__xludf.DUMMYFUNCTION("importrange(""https://docs.google.com/spreadsheets/d/1zbKpAkjR5pwXNP3vlQNzKnZWdUfQd6EtmpoFtLBYJoY/edit?gid=1824619316#gid=1824619316"",""2025-26!ah3"")"),5.0) -> 5 | BV20: =IFERROR(__xludf.DUMMYFUNCTION("importrange(""https://docs.google.com/spreadsheets/d/1zbKpAkjR5pwXNP3vlQNzKnZWdUfQd6EtmpoFtLBYJoY/edit?gid=1824619316#gid=1824619316"",""2025-26!ai4"")"),273046.72000000003) -> 273046.72 | BW20: =IFERROR(__xludf.DUMMYFUNCTION("importrange(""https://docs.google.com/spreadsheets/d/1zbKpAkjR5pwXNP3vlQNzKnZWdUfQd6EtmpoFtLBYJoY/edit?gid=1824619316#gid=1824619316"",""2025-26!ai3"")"),14.0) -> 14 | BX20: =IFERROR((BY20/BT20),"") -> 3.2462614 | BY20: =IFERROR(__xludf.DUMMYFUNCTION("importrange(""https://docs.google.com/spreadsheets/d/1zbKpAkjR5pwXNP3vlQNzKnZWdUfQd6EtmpoFtLBYJoY/edit?gid=1824619316#gid=1824619316"",""2025-26!aj4"")"),185816.0) -> 185816 | BZ20: =IFERROR(__xludf.DUMMYFUNCTION("importrange(""https://docs.google.com/spreadsheets/d/1zbKpAkjR5pwXNP3vlQNzKnZWdUfQd6EtmpoFtLBYJoY/edit?gid=1824619316#gid=1824619316"",""2025-26!aj3"")"),9.0) -> 9 | CA20: =IFERROR(__xludf.DUMMYFUNCTION("importrange(""https://docs.google.com/spreadsheets/d/1zbKpAkjR5pwXNP3vlQNzKnZWdUfQd6EtmpoFtLBYJoY/edit?gid=1824619316#gid=1824619316"",""2025-26!ak4"")"),40100.0) -> 40100 | CB20: =IFERROR(__xludf.DUMMYFUNCTION("importrange(""https://docs.google.com/spreadsheets/d/1zbKpAkjR5pwXNP3vlQNzKnZWdUfQd6EtmpoFtLBYJoY/edit?gid=1824619316#gid=1824619316"",""2025-26!ak3"")"),5.0) -> 5 | CC20: =IFERROR(__xludf.DUMMYFUNCTION("importrange(""https://docs.google.com/spreadsheets/d/1zbKpAkjR5pwXNP3vlQNzKnZWdUfQd6EtmpoFtLBYJoY/edit?gid=1824619316#gid=1824619316"",""2025-26!al4"")"),209621.92) -> 209621.92 | CD20: =IFERROR(__xludf.DUMMYFUNCTION("importrange(""https://docs.google.com/spreadsheets/d/1zbKpAkjR5pwXNP3vlQNzKnZWdUfQd6EtmpoFtLBYJoY/edit?gid=1824619316#gid=1824619316"",""2025-26!ai3"")"),14.0) -> 14 | CE20: =IFERROR((CF20/CA20),"") -> 1.1527431 | CF20: =IFERROR(__xludf.DUMMYFUNCTION("importrange(""https://docs.google.com/spreadsheets/d/1zbKpAkjR5pwXNP3vlQNzKnZWdUfQd6EtmpoFtLBYJoY/edit?gid=1824619316#gid=1824619316"",""2025-26!am4"")"),46225.0) -> 46225 | CG20: =IFERROR(__xludf.DUMMYFUNCTION("importrange(""https://docs.google.com/spreadsheets/d/1zbKpAkjR5pwXNP3vlQNzKnZWdUfQd6EtmpoFtLBYJoY/edit?gid=1824619316#gid=1824619316"",""2025-26!am3"")"),4.0) -> 4 | CH20: =IFERROR(__xludf.DUMMYFUNCTION("importrange(""https://docs.google.com/spreadsheets/d/1zbKpAkjR5pwXNP3vlQNzKnZWdUfQd6EtmpoFtLBYJoY/edit?gid=1824619316#gid=1824619316"",""2025-26!an4"")"),21600.0) -> 21600 | CI20: =IFERROR(__xludf.DUMMYFUNCTION("importrange(""https://docs.google.com/spreadsheets/d/1zbKpAkjR5pwXNP3vlQNzKnZWdUfQd6EtmpoFtLBYJoY/edit?gid=1824619316#gid=1824619316"",""2025-26!an3"")"),3.0) -> 3 | CJ20: =IFERROR(__xludf.DUMMYFUNCTION("importrange(""https://docs.google.com/spreadsheets/d/1zbKpAkjR5pwXNP3vlQNzKnZWdUfQd6EtmpoFtLBYJoY/edit?gid=1824619316#gid=1824619316"",""2025-26!ao4"")"),164826.16000000003) -> 164826.16 | CK20: =IFERROR(__xludf.DUMMYFUNCTION("importrange(""https://docs.google.com/spreadsheets/d/1zbKpAkjR5pwXNP3vlQNzKnZWdUfQd6EtmpoFtLBYJoY/edit?gid=1824619316#gid=1824619316"",""2025-26!ao3"")"),8.0) -> 8 | CL20: =IFERROR((CM20/CH20),"") -> 0.23148148 | CM20: =IFERROR(__xludf.DUMMYFUNCTION("importrange(""https://docs.google.com/spreadsheets/d/1zbKpAkjR5pwXNP3vlQNzKnZWdUfQd6EtmpoFtLBYJoY/edit?gid=1824619316#gid=1824619316"",""2025-26!ap4"")"),5000.0) -> 5000 | CN20: =IFERROR(__xludf.DUMMYFUNCTION("importrange(""https://docs.google.com/spreadsheets/d/1zbKpAkjR5pwXNP3vlQNzKnZWdUfQd6EtmpoFtLBYJoY/edit?gid=1824619316#gid=1824619316"",""2025-26!ap3"")"),1.0) -> 1 | CO20: =IFERROR(__xludf.DUMMYFUNCTION("importrange(""https://docs.google.com/spreadsheets/d/1zbKpAkjR5pwXNP3vlQNzKnZWdUfQd6EtmpoFtLBYJoY/edit?gid=1824619316#gid=1824619316"",""2025-26!aq4"")"),0.0) -> 0 | CP20: =IFERROR(__xludf.DUMMYFUNCTION("importrange(""https://docs.google.com/spreadsheets/d/1zbKpAkjR5pwXNP3vlQNzKnZWdUfQd6EtmpoFtLBYJoY/edit?gid=1824619316#gid=1824619316"",""2025-26!aq3"")"),0.0) -> 0 | CQ20: =IFERROR(__xludf.DUMMYFUNCTION("importrange(""https://docs.google.com/spreadsheets/d/1zbKpAkjR5pwXNP3vlQNzKnZWdUfQd6EtmpoFtLBYJoY/edit?gid=1824619316#gid=1824619316"",""2025-26!ar4"")"),246110.72) -> 246110.72 | CR20: =IFERROR(__xludf.DUMMYFUNCTION("importrange(""https://docs.google.com/spreadsheets/d/1zbKpAkjR5pwXNP3vlQNzKnZWdUfQd6EtmpoFtLBYJoY/edit?gid=1824619316#gid=1824619316"",""2025-26!ar3"")"),9.0) -> 9 | CS20: =IFERROR((CT20/CO20),"") | CT20: =IFERROR(__xludf.DUMMYFUNCTION("importrange(""https://docs.google.com/spreadsheets/d/1zbKpAkjR5pwXNP3vlQNzKnZWdUfQd6EtmpoFtLBYJoY/edit?gid=1824619316#gid=1824619316"",""2025-26!as4"")"),0.0) -> 0 | CU20: =IFERROR(__xludf.DUMMYFUNCTION("importrange(""https://docs.google.com/spreadsheets/d/1zbKpAkjR5pwXNP3vlQNzKnZWdUfQd6EtmpoFtLBYJoY/edit?gid=1824619316#gid=1824619316"",""2025-26!as3"")"),0.0) -> 0 | CV20: Rajasthan
A21: Pawan Sharma | C21: Gulab SIngh | D21: Karnal | E21: 9068844200 | F21: 45061 | I21: =VLOOKUP($C21,Data!$C:$BV,72,0) -> 40590 | J21: 1500000 | K21: =IFERROR(__xludf.DUMMYFUNCTION("IMPORTRANGE(""1ix1-nYckIcOYO0crqDtE6JH1Dxftw4VAGpahfAnYGlk"",""2025-26!A3"")"),127.0) -> 127 | L21: =IFERROR(__xludf.DUMMYFUNCTION("IMPORTRANGE(""1ix1-nYckIcOYO0crqDtE6JH1Dxftw4VAGpahfAnYGlk"",""2025-26!G4"")"),2.82E7) -> 28200000 | M21: =R21+Y21+AF21+AM21+AT21+BA21+BH21+BO21+BV21+CC21+CJ21+CQ21 -> 12354769 | N21: =O21/L21 -> 0.4850772 | O21: =U21+AB21+AI21+AP21+AW21+BD21+BK21+BR21+BY21+CF21+CM21+CT21 -> 13679177 | P21: =IFERROR(__xludf.DUMMYFUNCTION("IMPORTRANGE(""1ix1-nYckIcOYO0crqDtE6JH1Dxftw4VAGpahfAnYGlk"",""2025-26!J4"")"),2460000.0) -> 2460000 | Q21: =IFERROR(__xludf.DUMMYFUNCTION("IMPORTRANGE(""1ix1-nYckIcOYO0crqDtE6JH1Dxftw4VAGpahfAnYGlk"",""2025-26!J3"")"),44.0) -> 44 | R21: =IFERROR(__xludf.DUMMYFUNCTION("IMPORTRANGE(""1ix1-nYckIcOYO0crqDtE6JH1Dxftw4VAGpahfAnYGlk"",""2025-26!K4"")"),801374.4600000001) -> 801374.46 | S21: =IFERROR(__xludf.DUMMYFUNCTION("IMPORTRANGE(""1ix1-nYckIcOYO0crqDtE6JH1Dxftw4VAGpahfAnYGlk"",""2025-26!K3"")"),22.0) -> 22 | T21: =IFERROR((U21/P21),"") -> 0.36827033 | U21: =IFERROR(__xludf.DUMMYFUNCTION("IMPORTRANGE(""1ix1-nYckIcOYO0crqDtE6JH1Dxftw4VAGpahfAnYGlk"",""2025-26!L4"")"),905945.0) -> 905945 | V21: =IFERROR(__xludf.DUMMYFUNCTION("IMPORTRANGE(""1ix1-nYckIcOYO0crqDtE6JH1Dxftw4VAGpahfAnYGlk"",""2025-26!L3"")"),22.0) -> 22 | W21: =IFERROR(__xludf.DUMMYFUNCTION("IMPORTRANGE(""1ix1-nYckIcOYO0crqDtE6JH1Dxftw4VAGpahfAnYGlk"",""2025-26!m4"")"),2460000.0) -> 2460000 | X21: =IFERROR(__xludf.DUMMYFUNCTION("IMPORTRANGE(""1ix1-nYckIcOYO0crqDtE6JH1Dxftw4VAGpahfAnYGlk"",""2025-26!m3"")"),44.0) -> 44 | Y21: =IFERROR(__xludf.DUMMYFUNCTION("IMPORTRANGE(""1ix1-nYckIcOYO0crqDtE6JH1Dxftw4VAGpahfAnYGlk"",""2025-26!N4"")"),1515213.4999999995) -> 1515213.5 | Z21: =IFERROR(__xludf.DUMMYFUNCTION("IMPORTRANGE(""1ix1-nYckIcOYO0crqDtE6JH1Dxftw4VAGpahfAnYGlk"",""2025-26!N3"")"),21.0) -> 21 | AA21: =IFERROR((AB21/W21),"") -> 0.62778415 | AB21: =IFERROR(__xludf.DUMMYFUNCTION("IMPORTRANGE(""1ix1-nYckIcOYO0crqDtE6JH1Dxftw4VAGpahfAnYGlk"",""2025-26!O4"")"),1544349.0) -> 1544349 | AC21: =IFERROR(__xludf.DUMMYFUNCTION("IMPORTRANGE(""1ix1-nYckIcOYO0crqDtE6JH1Dxftw4VAGpahfAnYGlk"",""2025-26!O3"")"),16.0) -> 16 | AD21: =IFERROR(__xludf.DUMMYFUNCTION("IMPORTRANGE(""1ix1-nYckIcOYO0crqDtE6JH1Dxftw4VAGpahfAnYGlk"",""2025-26!P4"")"),2460000.0) -> 2460000 | AE21: =IFERROR(__xludf.DUMMYFUNCTION("IMPORTRANGE(""1ix1-nYckIcOYO0crqDtE6JH1Dxftw4VAGpahfAnYGlk"",""2025-26!P3"")"),44.0) -> 44 | AF21: =IFERROR(__xludf.DUMMYFUNCTION("IMPORTRANGE(""1ix1-nYckIcOYO0crqDtE6JH1Dxftw4VAGpahfAnYGlk"",""2025-26!Q4"")"),1502934.2399999998) -> 1502934.2 | AG21: =IFERROR(__xludf.DUMMYFUNCTION("IMPORTRANGE(""1ix1-nYckIcOYO0crqDtE6JH1Dxftw4VAGpahfAnYGlk"",""2025-26!Q3"")"),11.0) -> 11 | AH21: =IFERROR((AI21/AD21),"") -> 0.61186423 | AI21: =IFERROR(__xludf.DUMMYFUNCTION("IMPORTRANGE(""1ix1-nYckIcOYO0crqDtE6JH1Dxftw4VAGpahfAnYGlk"",""2025-26!R4"")"),1505186.0) -> 1505186 | AJ21: =IFERROR(__xludf.DUMMYFUNCTION("IMPORTRANGE(""1ix1-nYckIcOYO0crqDtE6JH1Dxftw4VAGpahfAnYGlk"",""2025-26!R3"")"),9.0) -> 9 | AK21: =IFERROR(__xludf.DUMMYFUNCTION("IMPORTRANGE(""1ix1-nYckIcOYO0crqDtE6JH1Dxftw4VAGpahfAnYGlk"",""2025-26!S4"")"),2520000.0) -> 2520000 | AL21: =IFERROR(__xludf.DUMMYFUNCTION("IMPORTRANGE(""1ix1-nYckIcOYO0crqDtE6JH1Dxftw4VAGpahfAnYGlk"",""2025-26!S3"")"),37.0) -> 37 | AM21: =IFERROR(__xludf.DUMMYFUNCTION("IMPORTRANGE(""1ix1-nYckIcOYO0crqDtE6JH1Dxftw4VAGpahfAnYGlk"",""2025-26!T4"")"),1201433.8199999998) -> 1201433.8 | AN21: =IFERROR(__xludf.DUMMYFUNCTION("IMPORTRANGE(""1ix1-nYckIcOYO0crqDtE6JH1Dxftw4VAGpahfAnYGlk"",""2025-26!T3"")"),26.0) -> 26 | AO21: =IFERROR((AP21/AK21),"") -> 0.50260159 | AP21: =IFERROR(__xludf.DUMMYFUNCTION("IMPORTRANGE(""1ix1-nYckIcOYO0crqDtE6JH1Dxftw4VAGpahfAnYGlk"",""2025-26!U4"")"),1266556.0) -> 1266556 | AQ21: =IFERROR(__xludf.DUMMYFUNCTION("IMPORTRANGE(""1ix1-nYckIcOYO0crqDtE6JH1Dxftw4VAGpahfAnYGlk"",""2025-26!U3"")"),26.0) -> 26 | AR21: =IFERROR(__xludf.DUMMYFUNCTION("IMPORTRANGE(""1ix1-nYckIcOYO0crqDtE6JH1Dxftw4VAGpahfAnYGlk"",""2025-26!V4"")"),2560000.0) -> 2560000 | AS21: =IFERROR(__xludf.DUMMYFUNCTION("IMPORTRANGE(""1ix1-nYckIcOYO0crqDtE6JH1Dxftw4VAGpahfAnYGlk"",""2025-26!V3"")"),37.0) -> 37 | AT21: =IFERROR(__xludf.DUMMYFUNCTION("IMPORTRANGE(""1ix1-nYckIcOYO0crqDtE6JH1Dxftw4VAGpahfAnYGlk"",""2025-26!W4"")"),1301441.22) -> 1301441.2 | AU21: =IFERROR(__xludf.DUMMYFUNCTION("IMPORTRANGE(""1ix1-nYckIcOYO0crqDtE6JH1Dxftw4VAGpahfAnYGlk"",""2025-26!W3"")"),26.0) -> 26 | AV21: =IFERROR((AW21/AR21),"") -> 0.55179023 | AW21: =IFERROR(__xludf.DUMMYFUNCTION("IMPORTRANGE(""1ix1-nYckIcOYO0crqDtE6JH1Dxftw4VAGpahfAnYGlk"",""2025-26!X4"")"),1412583.0) -> 1412583 | AX21: =IFERROR(__xludf.DUMMYFUNCTION("IMPORTRANGE(""1ix1-nYckIcOYO0crqDtE6JH1Dxftw4VAGpahfAnYGlk"",""2025-26!X3"")"),22.0) -> 22 | AY21: =IFERROR(__xludf.DUMMYFUNCTION("IMPORTRANGE(""1ix1-nYckIcOYO0crqDtE6JH1Dxftw4VAGpahfAnYGlk"",""2025-26!Y4"")"),2560000.0) -> 2560000 | AZ21: =IFERROR(__xludf.DUMMYFUNCTION("IMPORTRANGE(""1ix1-nYckIcOYO0crqDtE6JH1Dxftw4VAGpahfAnYGlk"",""2025-26!Y3"")"),37.0) -> 37 | BA21: =IFERROR(__xludf.DUMMYFUNCTION("IMPORTRANGE(""1ix1-nYckIcOYO0crqDtE6JH1Dxftw4VAGpahfAnYGlk"",""2025-26!Z4"")"),1001928.1100000001) -> 1001928.1 | BB21: =IFERROR(__xludf.DUMMYFUNCTION("IMPORTRANGE(""1ix1-nYckIcOYO0crqDtE6JH1Dxftw4VAGpahfAnYGlk"",""2025-26!Z3"")"),20.0) -> 20 | BC21: =IFERROR((BD21/AY21),"") -> 0.47894727 | BD21: =IFERROR(__xludf.DUMMYFUNCTION("IMPORTRANGE(""1ix1-nYckIcOYO0crqDtE6JH1Dxftw4VAGpahfAnYGlk"",""2025-26!AA4"")"),1226105.0) -> 1226105 | BE21: =IFERROR(__xludf.DUMMYFUNCTION("IMPORTRANGE(""1ix1-nYckIcOYO0crqDtE6JH1Dxftw4VAGpahfAnYGlk"",""2025-26!AA3"")"),19.0) -> 19 | BF21: =IFERROR(__xludf.DUMMYFUNCTION("IMPORTRANGE(""1ix1-nYckIcOYO0crqDtE6JH1Dxftw4VAGpahfAnYGlk"",""2025-26!AB4"")"),2110000.0) -> 2110000 | BG21: =IFERROR(__xludf.DUMMYFUNCTION("IMPORTRANGE(""1ix1-nYckIcOYO0crqDtE6JH1Dxftw4VAGpahfAnYGlk"",""2025-26!AB3"")"),37.0) -> 37 | BH21: =IFERROR(__xludf.DUMMYFUNCTION("IMPORTRANGE(""1ix1-nYckIcOYO0crqDtE6JH1Dxftw4VAGpahfAnYGlk"",""2025-26!AC4"")"),864820.19) -> 864820.19 | BI21: =IFERROR(__xludf.DUMMYFUNCTION("IMPORTRANGE(""1ix1-nYckIcOYO0crqDtE6JH1Dxftw4VAGpahfAnYGlk"",""2025-26!AC3"")"),15.0) -> 15 | BJ21: =IFERROR((BK21/BF21),"") -> 0.4745782 | BK21: =IFERROR(__xludf.DUMMYFUNCTION("IMPORTRANGE(""1ix1-nYckIcOYO0crqDtE6JH1Dxftw4VAGpahfAnYGlk"",""2025-26!AD4"")"),1001360.0) -> 1001360 | BL21: =IFERROR(__xludf.DUMMYFUNCTION("IMPORTRANGE(""1ix1-nYckIcOYO0crqDtE6JH1Dxftw4VAGpahfAnYGlk"",""2025-26!AD3"")"),13.0) -> 13 | BM21: =IFERROR(__xludf.DUMMYFUNCTION("IMPORTRANGE(""1ix1-nYckIcOYO0crqDtE6JH1Dxftw4VAGpahfAnYGlk"",""2025-26!AE4"")"),2330000.0) -> 2330000 | BN21: =IFERROR(__xludf.DUMMYFUNCTION("IMPORTRANGE(""1ix1-nYckIcOYO0crqDtE6JH1Dxftw4VAGpahfAnYGlk"",""2025-26!AE3"")"),37.0) -> 37 | BO21: =IFERROR(__xludf.DUMMYFUNCTION("IMPORTRANGE(""1ix1-nYckIcOYO0crqDtE6JH1Dxftw4VAGpahfAnYGlk"",""2025-26!AF4"")"),1005073.72) -> 1005073.7 | BP21: =IFERROR(__xludf.DUMMYFUNCTION("IMPORTRANGE(""1ix1-nYckIcOYO0crqDtE6JH1Dxftw4VAGpahfAnYGlk"",""2025-26!AF3"")"),14.0) -> 14 | BQ21: =IFERROR((BR21/BM21),"") -> 0.46333133 | BR21: =IFERROR(__xludf.DUMMYFUNCTION("IMPORTRANGE(""1ix1-nYckIcOYO0crqDtE6JH1Dxftw4VAGpahfAnYGlk"",""2025-26!AG4"")"),1079562.0) -> 1079562 | BS21: =IFERROR(__xludf.DUMMYFUNCTION("IMPORTRANGE(""1ix1-nYckIcOYO0crqDtE6JH1Dxftw4VAGpahfAnYGlk"",""2025-26!AG3"")"),15.0) -> 15 | BT21: =IFERROR(__xludf.DUMMYFUNCTION("IMPORTRANGE(""1ix1-nYckIcOYO0crqDtE6JH1Dxftw4VAGpahfAnYGlk"",""2025-26!AH4"")"),2170000.0) -> 2170000 | BU21: =IFERROR(__xludf.DUMMYFUNCTION("IMPORTRANGE(""1ix1-nYckIcOYO0crqDtE6JH1Dxftw4VAGpahfAnYGlk"",""2025-26!AH3"")"),37.0) -> 37 | BV21: =IFERROR(__xludf.DUMMYFUNCTION("IMPORTRANGE(""1ix1-nYckIcOYO0crqDtE6JH1Dxftw4VAGpahfAnYGlk"",""2025-26!AI4"")"),1062752.66) -> 1062752.7 | BW21: =IFERROR(__xludf.DUMMYFUNCTION("IMPORTRANGE(""1ix1-nYckIcOYO0crqDtE6JH1Dxftw4VAGpahfAnYGlk"",""2025-26!AI3"")"),23.0) -> 23 | BX21: =IFERROR((BY21/BT21),"") -> 0.49542212 | BY21: =IFERROR(__xludf.DUMMYFUNCTION("IMPORTRANGE(""1ix1-nYckIcOYO0crqDtE6JH1Dxftw4VAGpahfAnYGlk"",""2025-26!AJ4"")"),1075066.0) -> 1075066 | BZ21: =IFERROR(__xludf.DUMMYFUNCTION("IMPORTRANGE(""1ix1-nYckIcOYO0crqDtE6JH1Dxftw4VAGpahfAnYGlk"",""2025-26!AJ3"")"),22.0) -> 22 | CA21: =IFERROR(__xludf.DUMMYFUNCTION("IMPORTRANGE(""1ix1-nYckIcOYO0crqDtE6JH1Dxftw4VAGpahfAnYGlk"",""2025-26!AK4"")"),1880000.0) -> 1880000 | CB21: =IFERROR(__xludf.DUMMYFUNCTION("IMPORTRANGE(""1ix1-nYckIcOYO0crqDtE6JH1Dxftw4VAGpahfAnYGlk"",""2025-26!AK3"")"),35.0) -> 35 | CC21: =IFERROR(__xludf.DUMMYFUNCTION("IMPORTRANGE(""1ix1-nYckIcOYO0crqDtE6JH1Dxftw4VAGpahfAnYGlk"",""2025-26!AL4"")"),877175.45) -> 877175.45 | CD21: =IFERROR(__xludf.DUMMYFUNCTION("IMPORTRANGE(""1ix1-nYckIcOYO0crqDtE6JH1Dxftw4VAGpahfAnYGlk"",""2025-26!AL3"")"),13.0) -> 13 | CE21: =IFERROR((CF21/CA21),"") -> 0.6087734 | CF21: =IFERROR(__xludf.DUMMYFUNCTION("IMPORTRANGE(""1ix1-nYckIcOYO0crqDtE6JH1Dxftw4VAGpahfAnYGlk"",""2025-26!AM4"")"),1144494.0) -> 1144494 | CG21: =IFERROR(__xludf.DUMMYFUNCTION("IMPORTRANGE(""1ix1-nYckIcOYO0crqDtE6JH1Dxftw4VAGpahfAnYGlk"",""2025-26!AM3"")"),13.0) -> 13 | CH21: =IFERROR(__xludf.DUMMYFUNCTION("IMPORTRANGE(""1ix1-nYckIcOYO0crqDtE6JH1Dxftw4VAGpahfAnYGlk"",""2025-26!AN4"")"),1940000.0) -> 1940000 | CI21: =IFERROR(__xludf.DUMMYFUNCTION("IMPORTRANGE(""1ix1-nYckIcOYO0crqDtE6JH1Dxftw4VAGpahfAnYGlk"",""2025-26!AN3"")"),37.0) -> 37 | CJ21: =IFERROR(__xludf.DUMMYFUNCTION("IMPORTRANGE(""1ix1-nYckIcOYO0crqDtE6JH1Dxftw4VAGpahfAnYGlk"",""2025-26!AO4"")"),443504.88) -> 443504.88 | CK21: =IFERROR(__xludf.DUMMYFUNCTION("IMPORTRANGE(""1ix1-nYckIcOYO0crqDtE6JH1Dxftw4VAGpahfAnYGlk"",""2025-26!AO3"")"),8.0) -> 8 | CL21: =IFERROR((CM21/CH21),"") -> 0.31040412 | CM21: =IFERROR(__xludf.DUMMYFUNCTION("IMPORTRANGE(""1ix1-nYckIcOYO0crqDtE6JH1Dxftw4VAGpahfAnYGlk"",""2025-26!AP4"")"),602184.0) -> 602184 | CN21: =IFERROR(__xludf.DUMMYFUNCTION("IMPORTRANGE(""1ix1-nYckIcOYO0crqDtE6JH1Dxftw4VAGpahfAnYGlk"",""2025-26!AP3"")"),13.0) -> 13 | CO21: =IFERROR(__xludf.DUMMYFUNCTION("IMPORTRANGE(""1ix1-nYckIcOYO0crqDtE6JH1Dxftw4VAGpahfAnYGlk"",""2025-26!AQ4"")"),2060000.0) -> 2060000 | CP21: =IFERROR(__xludf.DUMMYFUNCTION("IMPORTRANGE(""1ix1-nYckIcOYO0crqDtE6JH1Dxftw4VAGpahfAnYGlk"",""2025-26!AQ3"")"),37.0) -> 37 | CQ21: =IFERROR(__xludf.DUMMYFUNCTION("IMPORTRANGE(""1ix1-nYckIcOYO0crqDtE6JH1Dxftw4VAGpahfAnYGlk"",""2025-26!AR4"")"),777116.5599999999) -> 777116.56 | CR21: =IFERROR(__xludf.DUMMYFUNCTION("IMPORTRANGE(""1ix1-nYckIcOYO0crqDtE6JH1Dxftw4VAGpahfAnYGlk"",""2025-26!AR3"")"),12.0) -> 12 | CS21: =IFERROR((CT21/CO21),"") -> 0.4445568 | CT21: =IFERROR(__xludf.DUMMYFUNCTION("IMPORTRANGE(""1ix1-nYckIcOYO0crqDtE6JH1Dxftw4VAGpahfAnYGlk"",""2025-26!AS4"")"),915787.0) -> 915787 | CU21: =IFERROR(__xludf.DUMMYFUNCTION("IMPORTRANGE(""1ix1-nYckIcOYO0crqDtE6JH1Dxftw4VAGpahfAnYGlk"",""2025-26!AS3"")"),11.0) -> 11 | CV21: Haryana
A22: Pawan Sharma | C22: Vikash Gour | D22: Neemrana | E22: 6378870243 | F22: 45733 | I22: 33550 | J22: 1500000 | K22: =IFERROR(__xludf.DUMMYFUNCTION("IMPORTRANGE(""https://docs.google.com/spreadsheets/d/1LxLvfF01hkJjA82h3lUiStXhCiLi6vZmRH5Kc6hYsVY/edit?gid=162659938#gid=162659938"",""2025-26!A3"")"),93.0) -> 93 | L22: =IFERROR(__xludf.DUMMYFUNCTION("IMPORTRANGE(""https://docs.google.com/spreadsheets/d/1LxLvfF01hkJjA82h3lUiStXhCiLi6vZmRH5Kc6hYsVY/edit?gid=162659938#gid=162659938"",""2025-26!G4"")"),1.17E7) -> 11700000 | M22: =SUM(R22+Y22+AF22+AM22+AT22+BA22+BH22+BO22+BV22+CC22+CJ22+CQ22) -> 8305428.6 | N22: =iferror(O22/L22,"") -> 0.53340906 | O22: =SUM(U22,AB22,AI22,AP22,AW22,BD22,BK22,BR22,BY22,CF22,CM22,CT22) -> 6240886 | P22: =IFERROR(__xludf.DUMMYFUNCTION("IMPORTRANGE(""https://docs.google.com/spreadsheets/d/1LxLvfF01hkJjA82h3lUiStXhCiLi6vZmRH5Kc6hYsVY/edit?gid=162659938#gid=162659938"",""2025-26!J4"")"),974965.0) -> 974965 | Q22: =IFERROR(__xludf.DUMMYFUNCTION("IMPORTRANGE(""https://docs.google.com/spreadsheets/d/1LxLvfF01hkJjA82h3lUiStXhCiLi6vZmRH5Kc6hYsVY/edit?gid=162659938#gid=162659938"",""2025-26!J3"")"),88.0) -> 88 | R22: =IFERROR(__xludf.DUMMYFUNCTION("IMPORTRANGE(""https://docs.google.com/spreadsheets/d/1LxLvfF01hkJjA82h3lUiStXhCiLi6vZmRH5Kc6hYsVY/edit?gid=162659938#gid=162659938"",""2025-26!K4"")"),819244.6299999999) -> 819244.63 | S22: =IFERROR(__xludf.DUMMYFUNCTION("IMPORTRANGE(""https://docs.google.com/spreadsheets/d/1LxLvfF01hkJjA82h3lUiStXhCiLi6vZmRH5Kc6hYsVY/edit?gid=162659938#gid=162659938"",""2025-26!K3"")"),22.0) -> 22 | T22: =IFERROR((U22/P22),"") -> 0.39718964 | U22: =IFERROR(__xludf.DUMMYFUNCTION("IMPORTRANGE(""https://docs.google.com/spreadsheets/d/1LxLvfF01hkJjA82h3lUiStXhCiLi6vZmRH5Kc6hYsVY/edit?gid=162659938#gid=162659938"",""2025-26!L4"")"),387246.0) -> 387246 | V22: =IFERROR(__xludf.DUMMYFUNCTION("IMPORTRANGE(""https://docs.google.com/spreadsheets/d/1LxLvfF01hkJjA82h3lUiStXhCiLi6vZmRH5Kc6hYsVY/edit?gid=162659938#gid=162659938"",""2025-26!L3"")"),15.0) -> 15 | W22: =IFERROR(__xludf.DUMMYFUNCTION("IMPORTRANGE(""https://docs.google.com/spreadsheets/d/1LxLvfF01hkJjA82h3lUiStXhCiLi6vZmRH5Kc6hYsVY/edit?gid=162659938#gid=162659938"",""2025-26!M4"")"),927000.0) -> 927000 | X22: =IFERROR(__xludf.DUMMYFUNCTION("IMPORTRANGE(""https://docs.google.com/spreadsheets/d/1LxLvfF01hkJjA82h3lUiStXhCiLi6vZmRH5Kc6hYsVY/edit?gid=162659938#gid=162659938"",""2025-26!M3"")"),88.0) -> 88 | Y22: =IFERROR(__xludf.DUMMYFUNCTION("importrange(""https://docs.google.com/spreadsheets/d/1LxLvfF01hkJjA82h3lUiStXhCiLi6vZmRH5Kc6hYsVY/edit?gid=162659938#gid=162659938"",""2025-26!n4"")"),1149372.7900000003) -> 1149372.8 | Z22: =IFERROR(__xludf.DUMMYFUNCTION("importrange(""https://docs.google.com/spreadsheets/d/1LxLvfF01hkJjA82h3lUiStXhCiLi6vZmRH5Kc6hYsVY/edit?gid=162659938#gid=162659938"",""2025-26!n3"")"),30.0) -> 30 | AA22: =IFERROR((AB22/W22),"") -> 1.3951866 | AB22: =IFERROR(__xludf.DUMMYFUNCTION("importrange(""https://docs.google.com/spreadsheets/d/1LxLvfF01hkJjA82h3lUiStXhCiLi6vZmRH5Kc6hYsVY/edit?gid=162659938#gid=162659938"",""2025-26!o4"")"),1293338.0) -> 1293338 | AC22: =IFERROR(__xludf.DUMMYFUNCTION("importrange(""https://docs.google.com/spreadsheets/d/1LxLvfF01hkJjA82h3lUiStXhCiLi6vZmRH5Kc6hYsVY/edit?gid=162659938#gid=162659938"",""2025-26!o3"")"),28.0) -> 28 | AD22: =IFERROR(__xludf.DUMMYFUNCTION("importrange(""https://docs.google.com/spreadsheets/d/1LxLvfF01hkJjA82h3lUiStXhCiLi6vZmRH5Kc6hYsVY/edit?gid=162659938#gid=162659938"",""2025-26!p4"")"),956700.0) -> 956700 | AE22: =IFERROR(__xludf.DUMMYFUNCTION("importrange(""https://docs.google.com/spreadsheets/d/1LxLvfF01hkJjA82h3lUiStXhCiLi6vZmRH5Kc6hYsVY/edit?gid=162659938#gid=162659938"",""2025-26!p3"")"),88.0) -> 88 | AF22: =IFERROR(__xludf.DUMMYFUNCTION("importrange(""https://docs.google.com/spreadsheets/d/1LxLvfF01hkJjA82h3lUiStXhCiLi6vZmRH5Kc6hYsVY/edit?gid=162659938#gid=162659938"",""2025-26!q4"")"),1083369.0000000002) -> 1083369 | AG22: =IFERROR(__xludf.DUMMYFUNCTION("importrange(""https://docs.google.com/spreadsheets/d/1LxLvfF01hkJjA82h3lUiStXhCiLi6vZmRH5Kc6hYsVY/edit?gid=162659938#gid=162659938"",""2025-26!q3"")"),22.0) -> 22 | AH22: =IFERROR((AI22/AD22),"") -> 0.54906136 | AI22: =IFERROR(__xludf.DUMMYFUNCTION("importrange(""https://docs.google.com/spreadsheets/d/1LxLvfF01hkJjA82h3lUiStXhCiLi6vZmRH5Kc6hYsVY/edit?gid=162659938#gid=162659938"",""2025-26!r4"")"),525287.0) -> 525287 | AJ22: =IFERROR(__xludf.DUMMYFUNCTION("importrange(""https://docs.google.com/spreadsheets/d/1LxLvfF01hkJjA82h3lUiStXhCiLi6vZmRH5Kc6hYsVY/edit?gid=162659938#gid=162659938"",""2025-26!r3"")"),20.0) -> 20 | AK22: =IFERROR(__xludf.DUMMYFUNCTION("importrange(""https://docs.google.com/spreadsheets/d/1LxLvfF01hkJjA82h3lUiStXhCiLi6vZmRH5Kc6hYsVY/edit?gid=162659938#gid=162659938"",""2025-26!s4"")"),999000.0) -> 999000 | AL22: =IFERROR(__xludf.DUMMYFUNCTION("importrange(""https://docs.google.com/spreadsheets/d/1LxLvfF01hkJjA82h3lUiStXhCiLi6vZmRH5Kc6hYsVY/edit?gid=162659938#gid=162659938"",""2025-26!s3"")"),88.0) -> 88 | AM22: =IFERROR(__xludf.DUMMYFUNCTION("importrange(""https://docs.google.com/spreadsheets/d/1LxLvfF01hkJjA82h3lUiStXhCiLi6vZmRH5Kc6hYsVY/edit?gid=162659938#gid=162659938"",""2025-26!t4"")"),957045.2500000001) -> 957045.25 | AN22: =IFERROR(__xludf.DUMMYFUNCTION("importrange(""https://docs.google.com/spreadsheets/d/1LxLvfF01hkJjA82h3lUiStXhCiLi6vZmRH5Kc6hYsVY/edit?gid=162659938#gid=162659938"",""2025-26!t3"")"),19.0) -> 19 | AO22: =IFERROR((AP22/AK22),"") -> 0.77756456 | AP22: =IFERROR(__xludf.DUMMYFUNCTION("importrange(""https://docs.google.com/spreadsheets/d/1LxLvfF01hkJjA82h3lUiStXhCiLi6vZmRH5Kc6hYsVY/edit?gid=162659938#gid=162659938"",""2025-26!u4"")"),776787.0) -> 776787 | AQ22: =IFERROR(__xludf.DUMMYFUNCTION("importrange(""https://docs.google.com/spreadsheets/d/1LxLvfF01hkJjA82h3lUiStXhCiLi6vZmRH5Kc6hYsVY/edit?gid=162659938#gid=162659938"",""2025-26!u3"")"),17.0) -> 17 | AR22: =IFERROR(__xludf.DUMMYFUNCTION("importrange(""https://docs.google.com/spreadsheets/d/1LxLvfF01hkJjA82h3lUiStXhCiLi6vZmRH5Kc6hYsVY/edit?gid=162659938#gid=162659938"",""2025-26!v4"")"),957000.0) -> 957000 | AS22: =IFERROR(__xludf.DUMMYFUNCTION("importrange(""https://docs.google.com/spreadsheets/d/1LxLvfF01hkJjA82h3lUiStXhCiLi6vZmRH5Kc6hYsVY/edit?gid=162659938#gid=162659938"",""2025-26!v3"")"),88.0) -> 88 | AT22: =IFERROR(__xludf.DUMMYFUNCTION("importrange(""https://docs.google.com/spreadsheets/d/1LxLvfF01hkJjA82h3lUiStXhCiLi6vZmRH5Kc6hYsVY/edit?gid=162659938#gid=162659938"",""2025-26!w4"")"),440492.34) -> 440492.34 | AU22: =IFERROR(__xludf.DUMMYFUNCTION("importrange(""https://docs.google.com/spreadsheets/d/1LxLvfF01hkJjA82h3lUiStXhCiLi6vZmRH5Kc6hYsVY/edit?gid=162659938#gid=162659938"",""2025-26!w3"")"),16.0) -> 16 | AV22: =IFERROR((AW22/AR22),"") -> 0.527628 | AW22: =IFERROR(__xludf.DUMMYFUNCTION("importrange(""https://docs.google.com/spreadsheets/d/1LxLvfF01hkJjA82h3lUiStXhCiLi6vZmRH5Kc6hYsVY/edit?gid=162659938#gid=162659938"",""2025-26!x4"")"),504940.0) -> 504940 | AX22: =IFERROR(__xludf.DUMMYFUNCTION("importrange(""https://docs.google.com/spreadsheets/d/1LxLvfF01hkJjA82h3lUiStXhCiLi6vZmRH5Kc6hYsVY/edit?gid=162659938#gid=162659938"",""2025-26!x3"")"),14.0) -> 14 | AY22: =IFERROR(__xludf.DUMMYFUNCTION("importrange(""https://docs.google.com/spreadsheets/d/1LxLvfF01hkJjA82h3lUiStXhCiLi6vZmRH5Kc6hYsVY/edit?gid=162659938#gid=162659938"",""2025-26!y4"")"),968100.0) -> 968100 | AZ22: =IFERROR(__xludf.DUMMYFUNCTION("importrange(""https://docs.google.com/spreadsheets/d/1LxLvfF01hkJjA82h3lUiStXhCiLi6vZmRH5Kc6hYsVY/edit?gid=162659938#gid=162659938"",""2025-26!y3"")"),88.0) -> 88 | BA22: =IFERROR(__xludf.DUMMYFUNCTION("importrange(""https://docs.google.com/spreadsheets/d/1LxLvfF01hkJjA82h3lUiStXhCiLi6vZmRH5Kc6hYsVY/edit?gid=162659938#gid=162659938"",""2025-26!z4"")"),680793.54) -> 680793.54 | BB22: =IFERROR(__xludf.DUMMYFUNCTION("importrange(""https://docs.google.com/spreadsheets/d/1LxLvfF01hkJjA82h3lUiStXhCiLi6vZmRH5Kc6hYsVY/edit?gid=162659938#gid=162659938"",""2025-26!z3"")"),14.0) -> 14 | BC22: =IFERROR((BD22/AY22),"") -> 0.83959405 | BD22: =IFERROR(__xludf.DUMMYFUNCTION("importrange(""https://docs.google.com/spreadsheets/d/1LxLvfF01hkJjA82h3lUiStXhCiLi6vZmRH5Kc6hYsVY/edit?gid=162659938#gid=162659938"",""2025-26!aa4"")"),812811.0) -> 812811 | BE22: =IFERROR(__xludf.DUMMYFUNCTION("importrange(""https://docs.google.com/spreadsheets/d/1LxLvfF01hkJjA82h3lUiStXhCiLi6vZmRH5Kc6hYsVY/edit?gid=162659938#gid=162659938"",""2025-26!aa3"")"),22.0) -> 22 | BF22: =IFERROR(__xludf.DUMMYFUNCTION("importrange(""https://docs.google.com/spreadsheets/d/1LxLvfF01hkJjA82h3lUiStXhCiLi6vZmRH5Kc6hYsVY/edit?gid=162659938#gid=162659938"",""2025-26!ab4"")"),999000.0) -> 999000 | BG22: =IFERROR(__xludf.DUMMYFUNCTION("importrange(""https://docs.google.com/spreadsheets/d/1LxLvfF01hkJjA82h3lUiStXhCiLi6vZmRH5Kc6hYsVY/edit?gid=162659938#gid=162659938"",""2025-26!ab3"")"),88.0) -> 88 | BH22: =IFERROR(__xludf.DUMMYFUNCTION("importrange(""https://docs.google.com/spreadsheets/d/1LxLvfF01hkJjA82h3lUiStXhCiLi6vZmRH5Kc6hYsVY/edit?gid=162659938#gid=162659938"",""2025-26!ac4"")"),604116.9499999998) -> 604116.95 | BI22: =IFERROR(__xludf.DUMMYFUNCTION("importrange(""https://docs.google.com/spreadsheets/d/1LxLvfF01hkJjA82h3lUiStXhCiLi6vZmRH5Kc6hYsVY/edit?gid=162659938#gid=162659938"",""2025-26!ac3"")"),21.0) -> 21 | BJ22: =IFERROR((BK22/BF22),"") -> 0.09176977 | BK22: =IFERROR(__xludf.DUMMYFUNCTION("importrange(""https://docs.google.com/spreadsheets/d/1LxLvfF01hkJjA82h3lUiStXhCiLi6vZmRH5Kc6hYsVY/edit?gid=162659938#gid=162659938"",""2025-26!ad4"")"),91678.0) -> 91678 | BL22: =IFERROR(__xludf.DUMMYFUNCTION("importrange(""https://docs.google.com/spreadsheets/d/1LxLvfF01hkJjA82h3lUiStXhCiLi6vZmRH5Kc6hYsVY/edit?gid=162659938#gid=162659938"",""2025-26!ad3"")"),6.0) -> 6 | BM22: =IFERROR(__xludf.DUMMYFUNCTION("importrange(""https://docs.google.com/spreadsheets/d/1LxLvfF01hkJjA82h3lUiStXhCiLi6vZmRH5Kc6hYsVY/edit?gid=162659938#gid=162659938"",""2025-26!ae4"")"),957000.0) -> 957000 | BN22: =IFERROR(__xludf.DUMMYFUNCTION("importrange(""https://docs.google.com/spreadsheets/d/1LxLvfF01hkJjA82h3lUiStXhCiLi6vZmRH5Kc6hYsVY/edit?gid=162659938#gid=162659938"",""2025-26!ae3"")"),88.0) -> 88 | BO22: =IFERROR(__xludf.DUMMYFUNCTION("importrange(""https://docs.google.com/spreadsheets/d/1LxLvfF01hkJjA82h3lUiStXhCiLi6vZmRH5Kc6hYsVY/edit?gid=162659938#gid=162659938"",""2025-26!af4"")"),590286.44) -> 590286.44 | BP22: =IFERROR(__xludf.DUMMYFUNCTION("importrange(""https://docs.google.com/spreadsheets/d/1LxLvfF01hkJjA82h3lUiStXhCiLi6vZmRH5Kc6hYsVY/edit?gid=162659938#gid=162659938"",""2025-26!af3"")"),21.0) -> 21 | BQ22: =IFERROR((BR22/BM22),"") -> 0.66276907 | BR22: =IFERROR(__xludf.DUMMYFUNCTION("importrange(""https://docs.google.com/spreadsheets/d/1LxLvfF01hkJjA82h3lUiStXhCiLi6vZmRH5Kc6hYsVY/edit?gid=162659938#gid=162659938"",""2025-26!ag4"")"),634270.0) -> 634270 | BS22: =IFERROR(__xludf.DUMMYFUNCTION("importrange(""https://docs.google.com/spreadsheets/d/1LxLvfF01hkJjA82h3lUiStXhCiLi6vZmRH5Kc6hYsVY/edit?gid=162659938#gid=162659938"",""2025-26!ag3"")"),18.0) -> 18 | BT22: =IFERROR(__xludf.DUMMYFUNCTION("importrange(""https://docs.google.com/spreadsheets/d/1LxLvfF01hkJjA82h3lUiStXhCiLi6vZmRH5Kc6hYsVY/edit?gid=162659938#gid=162659938"",""2025-26!ah4"")"),968100.0) -> 968100 | BU22: =IFERROR(__xludf.DUMMYFUNCTION("importrange(""https://docs.google.com/spreadsheets/d/1LxLvfF01hkJjA82h3lUiStXhCiLi6vZmRH5Kc6hYsVY/edit?gid=162659938#gid=162659938"",""2025-26!ah3"")"),88.0) -> 88 | BV22: =IFERROR(__xludf.DUMMYFUNCTION("importrange(""https://docs.google.com/spreadsheets/d/1LxLvfF01hkJjA82h3lUiStXhCiLi6vZmRH5Kc6hYsVY/edit?gid=162659938#gid=162659938"",""2025-26!ai4"")"),539311.28) -> 539311.28 | BW22: =IFERROR(__xludf.DUMMYFUNCTION("importrange(""https://docs.google.com/spreadsheets/d/1LxLvfF01hkJjA82h3lUiStXhCiLi6vZmRH5Kc6hYsVY/edit?gid=162659938#gid=162659938"",""2025-26!ai3"")"),17.0) -> 17 | BX22: =IFERROR((BY22/BT22),"") -> 0.36060944 | BY22: =IFERROR(__xludf.DUMMYFUNCTION("importrange(""https://docs.google.com/spreadsheets/d/1LxLvfF01hkJjA82h3lUiStXhCiLi6vZmRH5Kc6hYsVY/edit?gid=162659938#gid=162659938"",""2025-26!aj4"")"),349106.0) -> 349106 | BZ22: =IFERROR(__xludf.DUMMYFUNCTION("importrange(""https://docs.google.com/spreadsheets/d/1LxLvfF01hkJjA82h3lUiStXhCiLi6vZmRH5Kc6hYsVY/edit?gid=162659938#gid=162659938"",""2025-26!aj3"")"),13.0) -> 13 | CA22: =IFERROR(__xludf.DUMMYFUNCTION("importrange(""https://docs.google.com/spreadsheets/d/1LxLvfF01hkJjA82h3lUiStXhCiLi6vZmRH5Kc6hYsVY/edit?gid=162659938#gid=162659938"",""2025-26!ak4"")"),999000.0) -> 999000 | CB22: =IFERROR(__xludf.DUMMYFUNCTION("importrange(""https://docs.google.com/spreadsheets/d/1LxLvfF01hkJjA82h3lUiStXhCiLi6vZmRH5Kc6hYsVY/edit?gid=162659938#gid=162659938"",""2025-26!ak3"")"),88.0) -> 88 | CC22: =IFERROR(__xludf.DUMMYFUNCTION("importrange(""https://docs.google.com/spreadsheets/d/1LxLvfF01hkJjA82h3lUiStXhCiLi6vZmRH5Kc6hYsVY/edit?gid=162659938#gid=162659938"",""2025-26!al4"")"),236006.34000000003) -> 236006.34 | CD22: =IFERROR(__xludf.DUMMYFUNCTION("importrange(""https://docs.google.com/spreadsheets/d/1LxLvfF01hkJjA82h3lUiStXhCiLi6vZmRH5Kc6hYsVY/edit?gid=162659938#gid=162659938"",""2025-26!ai3"")"),17.0) -> 17 | CE22: =IFERROR((CF22/CA22),"") -> 0.51516917 | CF22: =IFERROR(__xludf.DUMMYFUNCTION("importrange(""https://docs.google.com/spreadsheets/d/1LxLvfF01hkJjA82h3lUiStXhCiLi6vZmRH5Kc6hYsVY/edit?gid=162659938#gid=162659938"",""2025-26!am4"")"),514654.0) -> 514654 | CG22: =IFERROR(__xludf.DUMMYFUNCTION("importrange(""https://docs.google.com/spreadsheets/d/1LxLvfF01hkJjA82h3lUiStXhCiLi6vZmRH5Kc6hYsVY/edit?gid=162659938#gid=162659938"",""2025-26!am3"")"),14.0) -> 14 | CH22: =IFERROR(__xludf.DUMMYFUNCTION("importrange(""https://docs.google.com/spreadsheets/d/1LxLvfF01hkJjA82h3lUiStXhCiLi6vZmRH5Kc6hYsVY/edit?gid=162659938#gid=162659938"",""2025-26!an4"")"),957000.0) -> 957000 | CI22: =IFERROR(__xludf.DUMMYFUNCTION("importrange(""https://docs.google.com/spreadsheets/d/1LxLvfF01hkJjA82h3lUiStXhCiLi6vZmRH5Kc6hYsVY/edit?gid=162659938#gid=162659938"",""2025-26!an3"")"),88.0) -> 88 | CJ22: =IFERROR(__xludf.DUMMYFUNCTION("importrange(""https://docs.google.com/spreadsheets/d/1LxLvfF01hkJjA82h3lUiStXhCiLi6vZmRH5Kc6hYsVY/edit?gid=162659938#gid=162659938"",""2025-26!ao4"")"),682158.01) -> 682158.01 | CK22: =IFERROR(__xludf.DUMMYFUNCTION("importrange(""https://docs.google.com/spreadsheets/d/1LxLvfF01hkJjA82h3lUiStXhCiLi6vZmRH5Kc6hYsVY/edit?gid=162659938#gid=162659938"",""2025-26!ao3"")"),14.0) -> 14 | CL22: =IFERROR((CM22/CH22),"") -> 0.20056426 | CM22: =IFERROR(__xludf.DUMMYFUNCTION("importrange(""https://docs.google.com/spreadsheets/d/1LxLvfF01hkJjA82h3lUiStXhCiLi6vZmRH5Kc6hYsVY/edit?gid=162659938#gid=162659938"",""2025-26!ap4"")"),191940.0) -> 191940 | CN22: =IFERROR(__xludf.DUMMYFUNCTION("importrange(""https://docs.google.com/spreadsheets/d/1LxLvfF01hkJjA82h3lUiStXhCiLi6vZmRH5Kc6hYsVY/edit?gid=162659938#gid=162659938"",""2025-26!ap3"")"),6.0) -> 6 | CO22: =IFERROR(__xludf.DUMMYFUNCTION("importrange(""https://docs.google.com/spreadsheets/d/1LxLvfF01hkJjA82h3lUiStXhCiLi6vZmRH5Kc6hYsVY/edit?gid=162659938#gid=162659938"",""2025-26!aq4"")"),968100.0) -> 968100 | CP22: =IFERROR(__xludf.DUMMYFUNCTION("importrange(""https://docs.google.com/spreadsheets/d/1LxLvfF01hkJjA82h3lUiStXhCiLi6vZmRH5Kc6hYsVY/edit?gid=162659938#gid=162659938"",""2025-26!aq3"")"),88.0) -> 88 | CQ22: =IFERROR(__xludf.DUMMYFUNCTION("importrange(""https://docs.google.com/spreadsheets/d/1LxLvfF01hkJjA82h3lUiStXhCiLi6vZmRH5Kc6hYsVY/edit?gid=162659938#gid=162659938"",""2025-26!ar4"")"),523232.03) -> 523232.03 | CR22: =IFERROR(__xludf.DUMMYFUNCTION("importrange(""https://docs.google.com/spreadsheets/d/1LxLvfF01hkJjA82h3lUiStXhCiLi6vZmRH5Kc6hYsVY/edit?gid=162659938#gid=162659938"",""2025-26!ar3"")"),15.0) -> 15 | CS22: =IFERROR((CT22/CO22),"") -> 0.1640626 | CT22: =IFERROR(__xludf.DUMMYFUNCTION("importrange(""https://docs.google.com/spreadsheets/d/1LxLvfF01hkJjA82h3lUiStXhCiLi6vZmRH5Kc6hYsVY/edit?gid=162659938#gid=162659938"",""2025-26!as4"")"),158829.0) -> 158829 | CU22: =IFERROR(__xludf.DUMMYFUNCTION("importrange(""https://docs.google.com/spreadsheets/d/1LxLvfF01hkJjA82h3lUiStXhCiLi6vZmRH5Kc6hYsVY/edit?gid=162659938#gid=162659938"",""2025-26!as3"")"),7.0) -> 7 | CV22: Rajasthan
